{
  "type": "Feature",
  "properties": {
    "gn:admin1_code":"1.0",
    "gn:asciiname":"Kuakor",
    "gn:country_code":"SL",
    "gn:dem":314,
    "gn:feature_class":"P",
    "gn:feature_code":"PPL",
    "gn:name":"Kuakor",
    "gn:population":0,
    "gn:timezone":"Africa/Freetown",
    "iso:country":"SL",
    "name:eng_x_preferred":[
        "Kuakor"
    ],
    "wof:name":"Kuakor",
    "wof:placetype":"locality"
},
  "geometry": {"coordinates":[-11.2358,8.54815],"type":"Point"}
}