{
  "type": "Feature",
  "properties": {
    "gn:admin1_code":"2.0",
    "gn:asciiname":"Mafari",
    "gn:country_code":"SL",
    "gn:dem":118,
    "gn:feature_class":"P",
    "gn:feature_code":"PPL",
    "gn:name":"Mafari",
    "gn:population":0,
    "gn:timezone":"Africa/Freetown",
    "iso:country":"SL",
    "name:eng_x_preferred":[
        "Mafari"
    ],
    "wof:name":"Mafari",
    "wof:placetype":"locality"
},
  "geometry": {"coordinates":[-11.96519,8.95594],"type":"Point"}
}