{
  "type": "Feature",
  "properties": {
    "gn:admin1_code":"2.0",
    "gn:asciiname":"Yatia",
    "gn:country_code":"SL",
    "gn:dem":129,
    "gn:feature_class":"P",
    "gn:feature_code":"PPL",
    "gn:name":"Yatia",
    "gn:population":0,
    "gn:timezone":"Africa/Freetown",
    "iso:country":"SL",
    "name:eng_x_preferred":[
        "Yatia"
    ],
    "wof:name":"Yatia",
    "wof:placetype":"locality"
},
  "geometry": {"coordinates":[-12.05062,9.86286],"type":"Point"}
}