{
  "type": "Feature",
  "properties": {
    "gn:admin1_code":"3.0",
    "gn:asciiname":"Gandohun",
    "gn:country_code":"SL",
    "gn:dem":112,
    "gn:feature_class":"P",
    "gn:feature_code":"PPL",
    "gn:name":"Gandohun",
    "gn:population":0,
    "gn:timezone":"Africa/Freetown",
    "iso:country":"SL",
    "name:eng_x_preferred":[
        "Gandohun"
    ],
    "wof:name":"Gandohun",
    "wof:placetype":"locality"
},
  "geometry": {"coordinates":[-11.7073,8.02623],"type":"Point"}
}