{
  "type": "Feature",
  "properties": {
    "gn:admin1_code":"3.0",
    "gn:asciiname":"Ngerehun",
    "gn:country_code":"SL",
    "gn:dem":18,
    "gn:feature_class":"P",
    "gn:feature_code":"PPL",
    "gn:name":"Ngerehun",
    "gn:population":0,
    "gn:timezone":"Africa/Freetown",
    "iso:country":"SL",
    "name:und_x_variant":[
        "Ngesehun"
    ],
    "wof:name":"Ngerehun",
    "wof:placetype":"locality"
},
  "geometry": {"coordinates":[-11.94363,7.3706],"type":"Point"}
}