{
  "type": "Feature",
  "properties": {
    "gn:admin1_code":"3.0",
    "gn:asciiname":"Timidi",
    "gn:country_code":"SL",
    "gn:dem":56,
    "gn:feature_class":"P",
    "gn:feature_code":"PPL",
    "gn:name":"Timidi",
    "gn:population":0,
    "gn:timezone":"Africa/Freetown",
    "iso:country":"SL",
    "name:eng_x_preferred":[
        "Timidi"
    ],
    "wof:name":"Timidi",
    "wof:placetype":"locality"
},
  "geometry": {"coordinates":[-12.06026,7.94308],"type":"Point"}
}