{
  "type": "Feature",
  "properties": {
    "gn:admin1_code":"4.0",
    "gn:asciiname":"Jungalau",
    "gn:country_code":"SL",
    "gn:dem":12,
    "gn:feature_class":"P",
    "gn:feature_code":"PPL",
    "gn:name":"Jungalau",
    "gn:population":0,
    "gn:timezone":"Africa/Freetown",
    "iso:country":"SL",
    "name:eng_x_preferred":[
        "Jungalau"
    ],
    "wof:name":"Jungalau",
    "wof:placetype":"locality"
},
  "geometry": {"coordinates":[-13.05969,8.30298],"type":"Point"}
}