{
  "type": "Feature",
  "properties": {
    "gn:admin1_code":"2.0",
    "gn:asciiname":"Koya",
    "gn:country_code":"SL",
    "gn:dem":18,
    "gn:feature_class":"P",
    "gn:feature_code":"PPL",
    "gn:name":"Koya",
    "gn:population":0,
    "gn:timezone":"Africa/Freetown",
    "iso:country":"SL",
    "name:ceb_x_preferred":[
        "Koya"
    ],
    "name:deu_x_preferred":[
        "Koya"
    ],
    "name:eng_x_preferred":[
        "Koya"
    ],
    "name:swe_x_preferred":[
        "Koya"
    ],
    "wof:name":"Koya",
    "wof:placetype":"locality"
},
  "geometry": {"coordinates":[-13.03633,8.96586],"type":"Point"}
}