{
  "type": "Feature",
  "properties": {
    "gn:admin1_code":"1.0",
    "gn:asciiname":"Tomandu",
    "gn:country_code":"SL",
    "gn:dem":292,
    "gn:feature_class":"P",
    "gn:feature_code":"PPL",
    "gn:name":"Tomandu",
    "gn:population":0,
    "gn:timezone":"Africa/Freetown",
    "iso:country":"SL",
    "name:eng_x_preferred":[
        "Tomandu"
    ],
    "wof:name":"Tomandu",
    "wof:placetype":"locality"
},
  "geometry": {"coordinates":[-10.61235,8.32514],"type":"Point"}
}