{
  "type": "Feature",
  "properties": {
    "gn:admin1_code":"2.0",
    "gn:asciiname":"Kupr",
    "gn:country_code":"SL",
    "gn:dem":21,
    "gn:feature_class":"P",
    "gn:feature_code":"PPL",
    "gn:name":"Kupr",
    "gn:population":0,
    "gn:timezone":"Africa/Freetown",
    "iso:country":"SL",
    "name:eng_x_preferred":[
        "Kupr"
    ],
    "wof:name":"Kupr",
    "wof:placetype":"locality"
},
  "geometry": {"coordinates":[-12.93015,8.86804],"type":"Point"}
}