{
  "type": "Feature",
  "properties": {
    "gn:admin1_code":"2.0",
    "gn:asciiname":"Kunia",
    "gn:country_code":"SL",
    "gn:dem":484,
    "gn:feature_class":"P",
    "gn:feature_code":"PPL",
    "gn:name":"Kunia",
    "gn:population":0,
    "gn:timezone":"Africa/Freetown",
    "iso:country":"SL",
    "name:eng_x_preferred":[
        "Kunia"
    ],
    "wof:name":"Kunia",
    "wof:placetype":"locality"
},
  "geometry": {"coordinates":[-11.33105,9.0423],"type":"Point"}
}