{
  "type": "Feature",
  "properties": {
    "gn:admin1_code":"1.0",
    "gn:asciiname":"Bongema",
    "gn:country_code":"SL",
    "gn:dem":345,
    "gn:feature_class":"P",
    "gn:feature_code":"PPL",
    "gn:name":"Bongema",
    "gn:population":0,
    "gn:timezone":"Africa/Freetown",
    "iso:country":"SL",
    "name:eng_x_preferred":[
        "Bongema"
    ],
    "wof:name":"Bongema",
    "wof:placetype":"locality"
},
  "geometry": {"coordinates":[-11.22708,8.71954],"type":"Point"}
}