{
  "type": "Feature",
  "properties": {
    "gn:admin1_code":"3.0",
    "gn:asciiname":"Kpuawala",
    "gn:country_code":"SL",
    "gn:dem":71,
    "gn:feature_class":"P",
    "gn:feature_code":"PPL",
    "gn:name":"Kpuawala",
    "gn:population":0,
    "gn:timezone":"Africa/Freetown",
    "iso:country":"SL",
    "name:eng_x_preferred":[
        "Kpuawala"
    ],
    "wof:name":"Kpuawala",
    "wof:placetype":"locality"
},
  "geometry": {"coordinates":[-12.2839,8.20602],"type":"Point"}
}