{
  "type": "Feature",
  "properties": {
    "gn:admin1_code":"3.0",
    "gn:asciiname":"Motafe",
    "gn:country_code":"SL",
    "gn:dem":8,
    "gn:feature_class":"P",
    "gn:feature_code":"PPL",
    "gn:name":"Motafe",
    "gn:population":0,
    "gn:timezone":"Africa/Freetown",
    "iso:country":"SL",
    "name:eng_x_preferred":[
        "Motafe"
    ],
    "name:und_x_variant":[
        "Moteva"
    ],
    "wof:name":"Motafe",
    "wof:placetype":"locality"
},
  "geometry": {"coordinates":[-12.42889,7.68139],"type":"Point"}
}