{
  "type": "Feature",
  "properties": {
    "gn:admin1_code":"3.0",
    "gn:asciiname":"Giebu",
    "gn:country_code":"SL",
    "gn:dem":57,
    "gn:feature_class":"P",
    "gn:feature_code":"PPL",
    "gn:name":"Giebu",
    "gn:population":0,
    "gn:timezone":"Africa/Freetown",
    "iso:country":"SL",
    "name:eng_x_preferred":[
        "Giebu"
    ],
    "wof:name":"Giebu",
    "wof:placetype":"locality"
},
  "geometry": {"coordinates":[-11.93959,7.93289],"type":"Point"}
}