{
  "type": "Feature",
  "properties": {
    "gn:admin1_code":"3.0",
    "gn:asciiname":"Gbalehun",
    "gn:country_code":"SL",
    "gn:dem":78,
    "gn:feature_class":"P",
    "gn:feature_code":"PPL",
    "gn:name":"Gbalehun",
    "gn:population":0,
    "gn:timezone":"Africa/Freetown",
    "iso:country":"SL",
    "name:eng_x_preferred":[
        "Gbalehun"
    ],
    "wof:name":"Gbalehun",
    "wof:placetype":"locality"
},
  "geometry": {"coordinates":[-11.80945,7.83085],"type":"Point"}
}