{
  "type": "Feature",
  "properties": {
    "gn:admin1_code":"1.0",
    "gn:asciiname":"Fowaya",
    "gn:country_code":"SL",
    "gn:dem":211,
    "gn:feature_class":"P",
    "gn:feature_code":"PPL",
    "gn:name":"Fowaya",
    "gn:population":0,
    "gn:timezone":"Africa/Freetown",
    "iso:country":"SL",
    "name:eng_x_preferred":[
        "Fowaya"
    ],
    "wof:name":"Fowaya",
    "wof:placetype":"locality"
},
  "geometry": {"coordinates":[-10.71771,8.22243],"type":"Point"}
}