{
  "type": "Feature",
  "properties": {
    "gn:admin1_code":"3.0",
    "gn:asciiname":"Mondoko",
    "gn:country_code":"SL",
    "gn:dem":40,
    "gn:feature_class":"P",
    "gn:feature_code":"PPL",
    "gn:name":"Mondoko",
    "gn:population":0,
    "gn:timezone":"Africa/Freetown",
    "iso:country":"SL",
    "name:eng_x_preferred":[
        "Mondoko"
    ],
    "wof:name":"Mondoko",
    "wof:placetype":"locality"
},
  "geometry": {"coordinates":[-11.85228,7.59253],"type":"Point"}
}