{
  "type": "Feature",
  "properties": {
    "gn:admin1_code":"01",
    "gn:asciiname":"Siwaia",
    "gn:country_code":"SL",
    "gn:dem":391,
    "gn:feature_class":"P",
    "gn:feature_code":"PPL",
    "gn:name":"Siwaia",
    "gn:population":0,
    "gn:timezone":"Africa/Freetown",
    "iso:country":"SL",
    "name:eng_x_preferred":[
        "Siwaia"
    ],
    "name:und_x_variant":[
        "Sewaiw",
        "Sewaia"
    ],
    "wof:name":"Siwaia",
    "wof:placetype":"locality"
},
  "geometry": {"coordinates":[-11.15586,8.83102],"type":"Point"}
}