{
  "type": "Feature",
  "properties": {
    "gn:admin1_code":"2.0",
    "gn:asciiname":"Kasiri",
    "gn:country_code":"SL",
    "gn:dem":40,
    "gn:feature_class":"P",
    "gn:feature_code":"PPL",
    "gn:name":"Kasiri",
    "gn:population":0,
    "gn:timezone":"Africa/Freetown",
    "iso:country":"SL",
    "name:eng_x_preferred":[
        "Kasiri"
    ],
    "wof:name":"Kasiri",
    "wof:placetype":"locality"
},
  "geometry": {"coordinates":[-12.82426,8.78983],"type":"Point"}
}