{
  "type": "Feature",
  "properties": {
    "gn:admin1_code":"1.0",
    "gn:asciiname":"Gbunduru",
    "gn:country_code":"SL",
    "gn:dem":292,
    "gn:feature_class":"P",
    "gn:feature_code":"PPL",
    "gn:name":"Gbunduru",
    "gn:population":0,
    "gn:timezone":"Africa/Freetown",
    "iso:country":"SL",
    "name:eng_x_preferred":[
        "Gbunduru"
    ],
    "name:und_x_variant":[
        "Gbondoru"
    ],
    "wof:name":"Gbunduru",
    "wof:placetype":"locality"
},
  "geometry": {"coordinates":[-11.32657,8.52708],"type":"Point"}
}