{
  "type": "Feature",
  "properties": {
    "gn:admin1_code":"1.0",
    "gn:asciiname":"Massagbe",
    "gn:country_code":"SL",
    "gn:dem":334,
    "gn:feature_class":"P",
    "gn:feature_code":"PPL",
    "gn:name":"Massagbe",
    "gn:population":0,
    "gn:timezone":"Africa/Freetown",
    "iso:country":"SL",
    "name:eng_x_preferred":[
        "Massagbe"
    ],
    "wof:name":"Massagbe",
    "wof:placetype":"locality"
},
  "geometry": {"coordinates":[-11.25203,8.6959],"type":"Point"}
}