{
  "type": "Feature",
  "properties": {
    "gn:admin1_code":"3.0",
    "gn:asciiname":"Komala",
    "gn:country_code":"SL",
    "gn:dem":29,
    "gn:feature_class":"P",
    "gn:feature_code":"PPL",
    "gn:name":"Komala",
    "gn:population":0,
    "gn:timezone":"Africa/Freetown",
    "iso:country":"SL",
    "name:eng_x_preferred":[
        "Komala"
    ],
    "name:srp_x_preferred":[
        "\u041a\u043e\u043c\u0430\u043b\u0430"
    ],
    "wof:name":"Komala",
    "wof:placetype":"locality"
},
  "geometry": {"coordinates":[-11.44528,7.06425],"type":"Point"}
}