{
  "type": "Feature",
  "properties": {
    "gn:admin1_code":"03",
    "gn:asciiname":"Taninahun Boka",
    "gn:country_code":"SL",
    "gn:dem":43,
    "gn:feature_class":"P",
    "gn:feature_code":"PPL",
    "gn:name":"Taninahun Boka",
    "gn:population":0,
    "gn:timezone":"Africa/Freetown",
    "iso:country":"SL",
    "name:eng_x_preferred":[
        "Taninahun Boka"
    ],
    "name:und_x_variant":[
        "Taninahun"
    ],
    "wof:name":"Taninahun Boka",
    "wof:placetype":"locality"
},
  "geometry": {"coordinates":[-12.54413,8.10894],"type":"Point"}
}