{
  "type": "Feature",
  "properties": {
    "gn:admin1_code":"02",
    "gn:asciiname":"Ntiria",
    "gn:country_code":"SL",
    "gn:dem":451,
    "gn:feature_class":"P",
    "gn:feature_code":"PPL",
    "gn:name":"Ntiria",
    "gn:population":0,
    "gn:timezone":"Africa/Freetown",
    "iso:country":"SL",
    "name:eng_x_preferred":[
        "Ntiria"
    ],
    "name:und_x_variant":[
        "Tiria"
    ],
    "wof:name":"Ntiria",
    "wof:placetype":"locality"
},
  "geometry": {"coordinates":[-11.38552,9.58058],"type":"Point"}
}