{
  "type": "Feature",
  "properties": {
    "gn:admin1_code":"1.0",
    "gn:asciiname":"Kokoma",
    "gn:country_code":"SL",
    "gn:dem":364,
    "gn:feature_class":"P",
    "gn:feature_code":"PPL",
    "gn:name":"Kokoma",
    "gn:population":0,
    "gn:timezone":"Africa/Freetown",
    "iso:country":"SL",
    "name:eng_x_preferred":[
        "Kokoma"
    ],
    "wof:name":"Kokoma",
    "wof:placetype":"locality"
},
  "geometry": {"coordinates":[-10.42908,8.38919],"type":"Point"}
}