{
  "type": "Feature",
  "properties": {
    "gn:admin1_code":"3.0",
    "gn:asciiname":"Kasi",
    "gn:cc2":"SL",
    "gn:country_code":"SL",
    "gn:dem":13,
    "gn:feature_class":"P",
    "gn:feature_code":"PPL",
    "gn:name":"Kasi",
    "gn:population":0,
    "gn:timezone":"Africa/Freetown",
    "iso:country":"SL",
    "name:ceb_x_preferred":[
        "Kasi"
    ],
    "name:swe_x_preferred":[
        "Kasi"
    ],
    "name:und_x_variant":[
        "Kasse"
    ],
    "wof:name":"Kasi",
    "wof:placetype":"locality"
},
  "geometry": {"coordinates":[-11.73389,7.10139],"type":"Point"}
}