{
  "type": "Feature",
  "properties": {
    "gn:admin1_code":"03",
    "gn:asciiname":"Sogbehun",
    "gn:country_code":"SL",
    "gn:dem":87,
    "gn:feature_class":"P",
    "gn:feature_code":"PPL",
    "gn:name":"Sogbehun",
    "gn:population":0,
    "gn:timezone":"Africa/Freetown",
    "iso:country":"SL",
    "name:eng_x_preferred":[
        "Sogbehun"
    ],
    "wof:name":"Sogbehun",
    "wof:placetype":"locality"
},
  "geometry": {"coordinates":[-11.81481,7.86039],"type":"Point"}
}