{
  "type": "Feature",
  "properties": {
    "gn:admin1_code":"2.0",
    "gn:asciiname":"Basia",
    "gn:country_code":"SL",
    "gn:dem":70,
    "gn:feature_class":"P",
    "gn:feature_code":"PPL",
    "gn:name":"Basia",
    "gn:population":0,
    "gn:timezone":"Africa/Freetown",
    "iso:country":"SL",
    "name:bre_x_preferred":[
        "Basia"
    ],
    "name:deu_x_preferred":[
        "Basia Trzetrzelewska"
    ],
    "name:eng_x_preferred":[
        "Basia"
    ],
    "name:fra_x_preferred":[
        "Basia Trzetrzelewska"
    ],
    "name:ita_x_preferred":[
        "Basia Trzetrzelewska"
    ],
    "name:jpn_x_preferred":[
        "\u30d0\u30fc\u30b7\u30a2"
    ],
    "name:nld_x_preferred":[
        "Basia Trzetrzelewska"
    ],
    "name:pol_x_preferred":[
        "Basia"
    ],
    "name:por_x_preferred":[
        "Basia"
    ],
    "name:spa_x_preferred":[
        "Basia Trzetrzelewska"
    ],
    "name:zho_x_preferred":[
        "Basia"
    ],
    "wof:name":"Basia",
    "wof:placetype":"locality"
},
  "geometry": {"coordinates":[-12.71041,9.17782],"type":"Point"}
}