{
  "type": "Feature",
  "properties": {
    "gn:admin1_code":"03",
    "gn:asciiname":"Yawei",
    "gn:country_code":"SL",
    "gn:dem":36,
    "gn:feature_class":"P",
    "gn:feature_code":"PPL",
    "gn:name":"Yawei",
    "gn:population":0,
    "gn:timezone":"Africa/Freetown",
    "iso:country":"SL",
    "name:und_x_variant":[
        "Yawe"
    ],
    "wof:name":"Yawei",
    "wof:placetype":"locality"
},
  "geometry": {"coordinates":[-11.70922,7.41124],"type":"Point"}
}