{
  "type": "Feature",
  "properties": {
    "gn:admin1_code":"2.0",
    "gn:asciiname":"Laia",
    "gn:country_code":"SL",
    "gn:dem":80,
    "gn:feature_class":"P",
    "gn:feature_code":"PPL",
    "gn:name":"Laia",
    "gn:population":0,
    "gn:timezone":"Africa/Freetown",
    "iso:country":"SL",
    "name:cat_x_preferred":[
        "Laia"
    ],
    "name:ceb_x_preferred":[
        "Laia"
    ],
    "name:eng_x_preferred":[
        "Laia"
    ],
    "name:eus_x_preferred":[
        "Laia"
    ],
    "name:glg_x_preferred":[
        "Laia"
    ],
    "name:spa_x_preferred":[
        "Laia"
    ],
    "name:swe_x_preferred":[
        "Laia"
    ],
    "wof:name":"Laia",
    "wof:placetype":"locality"
},
  "geometry": {"coordinates":[-12.27588,9.25192],"type":"Point"}
}