{
  "type": "Feature",
  "properties": {
    "gn:admin1_code":"2.0",
    "gn:asciiname":"Mankene",
    "gn:country_code":"SL",
    "gn:dem":26,
    "gn:feature_class":"P",
    "gn:feature_code":"PPL",
    "gn:name":"Mankene",
    "gn:population":0,
    "gn:timezone":"Africa/Freetown",
    "iso:country":"SL",
    "name:eng_x_preferred":[
        "Mankene"
    ],
    "wof:name":"Mankene",
    "wof:placetype":"locality"
},
  "geometry": {"coordinates":[-12.96774,9.04096],"type":"Point"}
}