{
  "type": "Feature",
  "properties": {
    "gn:admin1_code":"2.0",
    "gn:asciiname":"Kulkos",
    "gn:country_code":"SL",
    "gn:dem":82,
    "gn:feature_class":"P",
    "gn:feature_code":"PPL",
    "gn:name":"Kulkos",
    "gn:population":0,
    "gn:timezone":"Africa/Freetown",
    "iso:country":"SL",
    "name:eng_x_preferred":[
        "Kulkos"
    ],
    "wof:name":"Kulkos",
    "wof:placetype":"locality"
},
  "geometry": {"coordinates":[-12.28091,8.45903],"type":"Point"}
}