{
  "type": "Feature",
  "properties": {
    "gn:admin1_code":"2.0",
    "gn:asciiname":"Laminaia",
    "gn:country_code":"SL",
    "gn:dem":76,
    "gn:feature_class":"P",
    "gn:feature_code":"PPL",
    "gn:name":"Laminaia",
    "gn:population":0,
    "gn:timezone":"Africa/Freetown",
    "iso:country":"SL",
    "name:eng_x_preferred":[
        "Laminaia"
    ],
    "wof:name":"Laminaia",
    "wof:placetype":"locality"
},
  "geometry": {"coordinates":[-12.29918,9.39376],"type":"Point"}
}