{
  "type": "Feature",
  "properties": {
    "gn:admin1_code":"2.0",
    "gn:asciiname":"Makurubulai",
    "gn:country_code":"SL",
    "gn:dem":16,
    "gn:feature_class":"P",
    "gn:feature_code":"PPL",
    "gn:name":"Makurubulai",
    "gn:population":0,
    "gn:timezone":"Africa/Freetown",
    "iso:country":"SL",
    "name:eng_x_preferred":[
        "Makurubulai"
    ],
    "wof:name":"Makurubulai",
    "wof:placetype":"locality"
},
  "geometry": {"coordinates":[-12.92973,8.59458],"type":"Point"}
}