{
  "type": "Feature",
  "properties": {
    "gn:admin1_code":"2.0",
    "gn:asciiname":"Molonkor",
    "gn:country_code":"SL",
    "gn:dem":407,
    "gn:feature_class":"P",
    "gn:feature_code":"PPL",
    "gn:name":"Molonkor",
    "gn:population":0,
    "gn:timezone":"Africa/Freetown",
    "iso:country":"SL",
    "name:eng_x_preferred":[
        "Molonkor"
    ],
    "wof:name":"Molonkor",
    "wof:placetype":"locality"
},
  "geometry": {"coordinates":[-11.62146,9.83834],"type":"Point"}
}