{
  "type": "Feature",
  "properties": {
    "gn:admin1_code":"4.0",
    "gn:asciiname":"Williams Town",
    "gn:country_code":"SL",
    "gn:dem":35,
    "gn:feature_class":"P",
    "gn:feature_code":"PPL",
    "gn:name":"Williams Town",
    "gn:population":0,
    "gn:timezone":"Africa/Freetown",
    "iso:country":"SL",
    "name:eng_x_preferred":[
        "Williams Town"
    ],
    "wof:name":"Williams Town",
    "wof:placetype":"locality"
},
  "geometry": {"coordinates":[-13.15308,8.24306],"type":"Point"}
}