{
  "type": "Feature",
  "properties": {
    "gn:admin1_code":"2.0",
    "gn:asciiname":"Gbungbuna",
    "gn:country_code":"SL",
    "gn:dem":160,
    "gn:feature_class":"P",
    "gn:feature_code":"PPL",
    "gn:name":"Gbungbuna",
    "gn:population":0,
    "gn:timezone":"Africa/Freetown",
    "iso:country":"SL",
    "name:eng_x_preferred":[
        "Gbungbuna"
    ],
    "wof:name":"Gbungbuna",
    "wof:placetype":"locality"
},
  "geometry": {"coordinates":[-11.80658,9.06892],"type":"Point"}
}