{
  "type": "Feature",
  "properties": {
    "gn:admin1_code":"3.0",
    "gn:asciiname":"Gbongan",
    "gn:country_code":"SL",
    "gn:dem":12,
    "gn:feature_class":"P",
    "gn:feature_code":"PPL",
    "gn:name":"Gbongan",
    "gn:population":0,
    "gn:timezone":"Africa/Freetown",
    "iso:country":"SL",
    "name:ceb_x_preferred":[
        "Gbongan"
    ],
    "name:eng_x_preferred":[
        "Gbongan"
    ],
    "name:mlg_x_preferred":[
        "Gbongan"
    ],
    "name:yor_x_preferred":[
        "Gb\u1ecd\u0300ng\u00e1n"
    ],
    "wof:name":"Gbongan",
    "wof:placetype":"locality"
},
  "geometry": {"coordinates":[-12.74665,7.56296],"type":"Point"}
}