{
  "type": "Feature",
  "properties": {
    "gn:admin1_code":"3.0",
    "gn:asciiname":"Mongeriwo",
    "gn:country_code":"SL",
    "gn:dem":46,
    "gn:feature_class":"P",
    "gn:feature_code":"PPL",
    "gn:name":"Mongeriwo",
    "gn:population":0,
    "gn:timezone":"Africa/Freetown",
    "iso:country":"SL",
    "name:und_x_variant":[
        "Mongeriworo",
        "Mongeriwo"
    ],
    "wof:name":"Mongeriwo",
    "wof:placetype":"locality"
},
  "geometry": {"coordinates":[-12.21415,7.70181],"type":"Point"}
}