{
  "type": "Feature",
  "properties": {
    "gn:admin1_code":"1.0",
    "gn:asciiname":"Kolobengu",
    "gn:country_code":"SL",
    "gn:dem":363,
    "gn:feature_class":"P",
    "gn:feature_code":"PPL",
    "gn:name":"Kolobengu",
    "gn:population":0,
    "gn:timezone":"Africa/Conakry",
    "iso:country":"SL",
    "name:eng_x_preferred":[
        "Kolobengu"
    ],
    "wof:name":"Kolobengu",
    "wof:placetype":"locality"
},
  "geometry": {"coordinates":[-10.49225,8.70408],"type":"Point"}
}