{
  "type": "Feature",
  "properties": {
    "gn:admin1_code":"3.0",
    "gn:asciiname":"Mokea",
    "gn:country_code":"SL",
    "gn:dem":38,
    "gn:feature_class":"P",
    "gn:feature_code":"PPL",
    "gn:name":"Mokea",
    "gn:population":0,
    "gn:timezone":"Africa/Freetown",
    "iso:country":"SL",
    "name:eng_x_preferred":[
        "Mokea"
    ],
    "wof:name":"Mokea",
    "wof:placetype":"locality"
},
  "geometry": {"coordinates":[-12.74465,8.31231],"type":"Point"}
}