{
  "type": "Feature",
  "properties": {
    "gn:admin1_code":"1.0",
    "gn:asciiname":"Masau",
    "gn:country_code":"SL",
    "gn:dem":197,
    "gn:feature_class":"P",
    "gn:feature_code":"PPL",
    "gn:name":"Masau",
    "gn:population":0,
    "gn:timezone":"Africa/Freetown",
    "iso:country":"SL",
    "name:eng_x_preferred":[
        "Masau"
    ],
    "wof:name":"Masau",
    "wof:placetype":"locality"
},
  "geometry": {"coordinates":[-10.86433,8.14381],"type":"Point"}
}