{
  "type": "Feature",
  "properties": {
    "gn:admin1_code":"3.0",
    "gn:asciiname":"Maka",
    "gn:country_code":"SL",
    "gn:dem":32,
    "gn:feature_class":"P",
    "gn:feature_code":"PPL",
    "gn:name":"Maka",
    "gn:population":0,
    "gn:timezone":"Africa/Freetown",
    "iso:country":"SL",
    "name:ceb_x_preferred":[
        "Maka"
    ],
    "name:deu_x_preferred":[
        "Maka"
    ],
    "name:eng_x_preferred":[
        "Maka"
    ],
    "name:fra_x_preferred":[
        "Maka"
    ],
    "name:ita_x_preferred":[
        "Maka"
    ],
    "name:jpn_x_preferred":[
        "\u30de\u30ab"
    ],
    "name:rus_x_preferred":[
        "\u041c\u0430\u043a\u0430"
    ],
    "name:slk_x_preferred":[
        "Maka"
    ],
    "name:swe_x_preferred":[
        "Maka"
    ],
    "wof:name":"Maka",
    "wof:placetype":"locality"
},
  "geometry": {"coordinates":[-11.82965,7.45001],"type":"Point"}
}