{
  "type": "Feature",
  "properties": {
    "gn:admin1_code":"3.0",
    "gn:asciiname":"Benkeh",
    "gn:country_code":"SL",
    "gn:dem":22,
    "gn:feature_class":"P",
    "gn:feature_code":"PPL",
    "gn:name":"Benkeh",
    "gn:population":0,
    "gn:timezone":"Africa/Freetown",
    "iso:country":"SL",
    "name:und_x_variant":[
        "Benge",
        "Benkeh"
    ],
    "wof:name":"Benkeh",
    "wof:placetype":"locality"
},
  "geometry": {"coordinates":[-12.53564,7.82868],"type":"Point"}
}