{
  "type": "Feature",
  "properties": {
    "gn:admin1_code":"01",
    "gn:asciiname":"Yambama",
    "gn:country_code":"SL",
    "gn:dem":536,
    "gn:feature_class":"P",
    "gn:feature_code":"PPL",
    "gn:name":"Yambama",
    "gn:population":0,
    "gn:timezone":"Africa/Freetown",
    "iso:country":"SL",
    "wof:name":"Yambama",
    "wof:placetype":"locality"
},
  "geometry": {"coordinates":[-10.78333,8.61667],"type":"Point"}
}