{
  "type": "Feature",
  "properties": {
    "gn:admin1_code":"02",
    "gn:asciiname":"Seradu",
    "gn:country_code":"SL",
    "gn:dem":627,
    "gn:feature_class":"P",
    "gn:feature_code":"PPL",
    "gn:name":"Seradu",
    "gn:population":0,
    "gn:timezone":"Africa/Freetown",
    "iso:country":"SL",
    "name:eng_x_preferred":[
        "Seradu"
    ],
    "wof:name":"Seradu",
    "wof:placetype":"locality"
},
  "geometry": {"coordinates":[-10.82161,9.16105],"type":"Point"}
}