{
  "type": "Feature",
  "properties": {
    "gn:admin1_code":"3.0",
    "gn:asciiname":"Malumpa",
    "gn:country_code":"SL",
    "gn:dem":47,
    "gn:feature_class":"P",
    "gn:feature_code":"PPL",
    "gn:name":"Malumpa",
    "gn:population":0,
    "gn:timezone":"Africa/Freetown",
    "iso:country":"SL",
    "name:eng_x_preferred":[
        "Malumpa"
    ],
    "wof:name":"Malumpa",
    "wof:placetype":"locality"
},
  "geometry": {"coordinates":[-12.64392,8.2349],"type":"Point"}
}