{
  "type": "Feature",
  "properties": {
    "gn:admin1_code":"1.0",
    "gn:asciiname":"Dumbelebu",
    "gn:country_code":"SL",
    "gn:dem":364,
    "gn:feature_class":"P",
    "gn:feature_code":"PPL",
    "gn:name":"Dumbelebu",
    "gn:population":0,
    "gn:timezone":"Africa/Freetown",
    "iso:country":"SL",
    "name:eng_x_preferred":[
        "Dumbelebu"
    ],
    "name:und_x_variant":[
        "Dumbilibu"
    ],
    "wof:name":"Dumbelebu",
    "wof:placetype":"locality"
},
  "geometry": {"coordinates":[-11.42292,8.44481],"type":"Point"}
}