{
  "type": "Feature",
  "properties": {
    "gn:admin1_code":"1.0",
    "gn:asciiname":"Maraka",
    "gn:country_code":"SL",
    "gn:dem":341,
    "gn:feature_class":"P",
    "gn:feature_code":"PPL",
    "gn:name":"Maraka",
    "gn:population":0,
    "gn:timezone":"Africa/Freetown",
    "iso:country":"SL",
    "name:eng_x_preferred":[
        "Maraka"
    ],
    "wof:name":"Maraka",
    "wof:placetype":"locality"
},
  "geometry": {"coordinates":[-11.58258,8.52775],"type":"Point"}
}