{
  "type": "Feature",
  "properties": {
    "gn:admin1_code":"3.0",
    "gn:asciiname":"Gisiwulo",
    "gn:country_code":"SL",
    "gn:dem":89,
    "gn:feature_class":"P",
    "gn:feature_code":"PPL",
    "gn:name":"Gisiwulo",
    "gn:population":0,
    "gn:timezone":"Africa/Freetown",
    "iso:country":"SL",
    "name:eng_x_preferred":[
        "Gisiwulo"
    ],
    "wof:name":"Gisiwulo",
    "wof:placetype":"locality"
},
  "geometry": {"coordinates":[-11.26935,7.27192],"type":"Point"}
}