{
  "type": "Feature",
  "properties": {
    "gn:admin1_code":"2.0",
    "gn:asciiname":"Setnyin",
    "gn:country_code":"SL",
    "gn:dem":62,
    "gn:feature_class":"P",
    "gn:feature_code":"PPL",
    "gn:name":"Setnyin",
    "gn:population":0,
    "gn:timezone":"Africa/Freetown",
    "iso:country":"SL",
    "name:eng_x_preferred":[
        "Setnyin"
    ],
    "wof:name":"Setnyin",
    "wof:placetype":"locality"
},
  "geometry": {"coordinates":[-12.30135,8.33865],"type":"Point"}
}