{
  "type": "Feature",
  "properties": {
    "gn:admin1_code":"1.0",
    "gn:asciiname":"Bogbema",
    "gn:country_code":"SL",
    "gn:dem":214,
    "gn:feature_class":"P",
    "gn:feature_code":"PPL",
    "gn:name":"Bogbema",
    "gn:population":0,
    "gn:timezone":"Africa/Freetown",
    "iso:country":"SL",
    "name:und_x_variant":[
        "Bogema"
    ],
    "wof:name":"Bogbema",
    "wof:placetype":"locality"
},
  "geometry": {"coordinates":[-10.65015,7.95497],"type":"Point"}
}