{
  "type": "Feature",
  "properties": {
    "gn:admin1_code":"03",
    "gn:asciiname":"Tempehlong",
    "gn:country_code":"SL",
    "gn:dem":16,
    "gn:feature_class":"P",
    "gn:feature_code":"PPL",
    "gn:name":"Tempehlong",
    "gn:population":0,
    "gn:timezone":"Africa/Freetown",
    "iso:country":"SL",
    "name:eng_x_preferred":[
        "Tempehlong"
    ],
    "name:und_x_variant":[
        "Tepron"
    ],
    "wof:name":"Tempehlong",
    "wof:placetype":"locality"
},
  "geometry": {"coordinates":[-12.87131,7.88696],"type":"Point"}
}