{
  "type": "Feature",
  "properties": {
    "gn:admin1_code":"2.0",
    "gn:asciiname":"Foria",
    "gn:country_code":"SL",
    "gn:dem":445,
    "gn:feature_class":"P",
    "gn:feature_code":"PPL",
    "gn:name":"Foria",
    "gn:population":0,
    "gn:timezone":"Africa/Freetown",
    "iso:country":"SL",
    "name:eng_x_preferred":[
        "Foria"
    ],
    "wof:name":"Foria",
    "wof:placetype":"locality"
},
  "geometry": {"coordinates":[-11.4559,9.24922],"type":"Point"}
}