{
  "type": "Feature",
  "properties": {
    "gn:admin1_code":"2.0",
    "gn:asciiname":"Kulioia",
    "gn:country_code":"SL",
    "gn:dem":339,
    "gn:feature_class":"P",
    "gn:feature_code":"PPL",
    "gn:name":"Kulioia",
    "gn:population":0,
    "gn:timezone":"Africa/Freetown",
    "iso:country":"SL",
    "name:eng_x_preferred":[
        "Kulioia"
    ],
    "wof:name":"Kulioia",
    "wof:placetype":"locality"
},
  "geometry": {"coordinates":[-11.34806,8.80316],"type":"Point"}
}