{
  "type": "Feature",
  "properties": {
    "gn:admin1_code":"1.0",
    "gn:asciiname":"Polima",
    "gn:country_code":"SL",
    "gn:dem":203,
    "gn:feature_class":"P",
    "gn:feature_code":"PPL",
    "gn:name":"Polima",
    "gn:population":0,
    "gn:timezone":"Africa/Freetown",
    "iso:country":"SL",
    "name:eng_x_preferred":[
        "Polima"
    ],
    "wof:name":"Polima",
    "wof:placetype":"locality"
},
  "geometry": {"coordinates":[-10.93784,8.00888],"type":"Point"}
}