{
  "type": "Feature",
  "properties": {
    "gn:admin1_code":"2.0",
    "gn:asciiname":"Matasandaia",
    "gn:country_code":"SL",
    "gn:dem":57,
    "gn:feature_class":"P",
    "gn:feature_code":"PPL",
    "gn:name":"Matasandaia",
    "gn:population":0,
    "gn:timezone":"Africa/Freetown",
    "iso:country":"SL",
    "name:eng_x_preferred":[
        "Matasandaia"
    ],
    "wof:name":"Matasandaia",
    "wof:placetype":"locality"
},
  "geometry": {"coordinates":[-12.83438,9.24761],"type":"Point"}
}