{
  "type": "Feature",
  "properties": {
    "gn:admin1_code":"2.0",
    "gn:asciiname":"Magbile",
    "gn:country_code":"SL",
    "gn:dem":22,
    "gn:feature_class":"P",
    "gn:feature_code":"PPL",
    "gn:name":"Magbile",
    "gn:population":0,
    "gn:timezone":"Africa/Freetown",
    "iso:country":"SL",
    "name:und_x_variant":[
        "Mabil\u00e9",
        "Magbile"
    ],
    "wof:name":"Magbile",
    "wof:placetype":"locality"
},
  "geometry": {"coordinates":[-12.69636,8.59665],"type":"Point"}
}