{
  "type": "Feature",
  "properties": {
    "gn:admin1_code":"03",
    "gn:asciiname":"Victoria",
    "gn:country_code":"SL",
    "gn:dem":24,
    "gn:feature_class":"P",
    "gn:feature_code":"PPL",
    "gn:name":"Victoria",
    "gn:population":0,
    "gn:timezone":"Africa/Freetown",
    "iso:country":"SL",
    "wof:name":"Victoria",
    "wof:placetype":"locality"
},
  "geometry": {"coordinates":[-12.33278,7.64917],"type":"Point"}
}