{
  "type": "Feature",
  "properties": {
    "gn:admin1_code":"3.0",
    "gn:asciiname":"Ngukpabu",
    "gn:country_code":"SL",
    "gn:dem":59,
    "gn:feature_class":"P",
    "gn:feature_code":"PPL",
    "gn:name":"Ngukpabu",
    "gn:population":0,
    "gn:timezone":"Africa/Freetown",
    "iso:country":"SL",
    "name:eng_x_preferred":[
        "Ngukpabu"
    ],
    "wof:name":"Ngukpabu",
    "wof:placetype":"locality"
},
  "geometry": {"coordinates":[-11.96306,7.92],"type":"Point"}
}