{
  "type": "Feature",
  "properties": {
    "gn:admin1_code":"3.0",
    "gn:asciiname":"Gordie",
    "gn:country_code":"SL",
    "gn:dem":11,
    "gn:feature_class":"P",
    "gn:feature_code":"PPL",
    "gn:name":"Gordie",
    "gn:population":0,
    "gn:timezone":"Africa/Freetown",
    "iso:country":"SL",
    "name:eng_x_preferred":[
        "Gordie"
    ],
    "wof:name":"Gordie",
    "wof:placetype":"locality"
},
  "geometry": {"coordinates":[-12.16205,7.42485],"type":"Point"}
}