{
  "type": "Feature",
  "properties": {
    "gn:admin1_code":"2.0",
    "gn:asciiname":"Robump",
    "gn:country_code":"SL",
    "gn:dem":26,
    "gn:feature_class":"P",
    "gn:feature_code":"PPL",
    "gn:name":"Robump",
    "gn:population":0,
    "gn:timezone":"Africa/Freetown",
    "iso:country":"SL",
    "name:eng_x_preferred":[
        "Robump"
    ],
    "wof:name":"Robump",
    "wof:placetype":"locality"
},
  "geometry": {"coordinates":[-12.98933,8.9091],"type":"Point"}
}