{
  "type": "Feature",
  "properties": {
    "gn:admin1_code":"2.0",
    "gn:asciiname":"Malal",
    "gn:country_code":"SL",
    "gn:dem":58,
    "gn:feature_class":"P",
    "gn:feature_code":"PPL",
    "gn:name":"Malal",
    "gn:population":0,
    "gn:timezone":"Africa/Freetown",
    "iso:country":"SL",
    "name:ceb_x_preferred":[
        "Malal"
    ],
    "name:eng_x_preferred":[
        "Malal"
    ],
    "name:swe_x_preferred":[
        "Malal"
    ],
    "name:ukr_x_preferred":[
        "\u041c\u0430\u043b\u0430\u043b\u044c"
    ],
    "wof:name":"Malal",
    "wof:placetype":"locality"
},
  "geometry": {"coordinates":[-12.81094,8.92913],"type":"Point"}
}