{
  "type": "Feature",
  "properties": {
    "gn:admin1_code":"2.0",
    "gn:asciiname":"Matanko",
    "gn:country_code":"SL",
    "gn:dem":26,
    "gn:feature_class":"P",
    "gn:feature_code":"PPL",
    "gn:name":"Matanko",
    "gn:population":0,
    "gn:timezone":"Africa/Freetown",
    "iso:country":"SL",
    "name:eng_x_preferred":[
        "Matanko"
    ],
    "wof:name":"Matanko",
    "wof:placetype":"locality"
},
  "geometry": {"coordinates":[-12.87816,8.38938],"type":"Point"}
}