{
  "type": "Feature",
  "properties": {
    "gn:admin1_code":"3.0",
    "gn:asciiname":"Sargoh",
    "gn:country_code":"SL",
    "gn:dem":18,
    "gn:feature_class":"P",
    "gn:feature_code":"PPL",
    "gn:name":"Sargoh",
    "gn:population":0,
    "gn:timezone":"Africa/Freetown",
    "iso:country":"SL",
    "name:eng_x_preferred":[
        "Sargoh"
    ],
    "wof:name":"Sargoh",
    "wof:placetype":"locality"
},
  "geometry": {"coordinates":[-12.0794,7.41519],"type":"Point"}
}