{
  "type": "Feature",
  "properties": {
    "gn:admin1_code":"03",
    "gn:asciiname":"Toloko",
    "gn:country_code":"SL",
    "gn:dem":20,
    "gn:feature_class":"P",
    "gn:feature_code":"PPL",
    "gn:name":"Toloko",
    "gn:population":0,
    "gn:timezone":"Africa/Freetown",
    "iso:country":"SL",
    "name:eng_x_preferred":[
        "Toloko"
    ],
    "name:eng_x_variant":[
        "Toroko"
    ],
    "wof:name":"Toloko",
    "wof:placetype":"locality"
},
  "geometry": {"coordinates":[-11.59417,7.06208],"type":"Point"}
}