{
  "type": "Feature",
  "properties": {
    "gn:admin1_code":"2.0",
    "gn:asciiname":"Momal",
    "gn:country_code":"SL",
    "gn:dem":62,
    "gn:feature_class":"P",
    "gn:feature_code":"PPL",
    "gn:name":"Momal",
    "gn:population":0,
    "gn:timezone":"Africa/Freetown",
    "iso:country":"SL",
    "name:eng_x_preferred":[
        "Momal"
    ],
    "wof:name":"Momal",
    "wof:placetype":"locality"
},
  "geometry": {"coordinates":[-12.49815,8.3202],"type":"Point"}
}