{
  "type": "Feature",
  "properties": {
    "gn:admin1_code":"1.0",
    "gn:asciiname":"Densembadu",
    "gn:country_code":"SL",
    "gn:dem":326,
    "gn:feature_class":"P",
    "gn:feature_code":"PPL",
    "gn:name":"Densembadu",
    "gn:population":0,
    "gn:timezone":"Africa/Freetown",
    "iso:country":"SL",
    "name:eng_x_preferred":[
        "Densembadu"
    ],
    "wof:name":"Densembadu",
    "wof:placetype":"locality"
},
  "geometry": {"coordinates":[-10.52624,8.65779],"type":"Point"}
}