{
  "type": "Feature",
  "properties": {
    "gn:admin1_code":"01",
    "gn:asciiname":"Poyama",
    "gn:country_code":"SL",
    "gn:dem":171,
    "gn:feature_class":"P",
    "gn:feature_code":"PPL",
    "gn:name":"Poyama",
    "gn:population":0,
    "gn:timezone":"Africa/Freetown",
    "iso:country":"SL",
    "name:eng_x_preferred":[
        "Poyama"
    ],
    "name:und_x_variant":[
        "Poiama",
        "Poyama-poya"
    ],
    "wof:name":"Poyama",
    "wof:placetype":"locality"
},
  "geometry": {"coordinates":[-11.40777,8.22165],"type":"Point"}
}