{
  "type": "Feature",
  "properties": {
    "iso:country":"SL",
    "name:eng_x_preferred":[
        "New England"
    ],
    "qs:gn_country":"SL",
    "qs:gn_fcode":"PPLX",
    "qs:gn_pop":0,
    "qs:name":"New England",
    "qs:name_adm0":"Sierra Leone",
    "qs:name_adm1":"Western Area",
    "qs:photos":246,
    "qs:photos_1k":50,
    "qs:photos_9k":1,
    "qs:photos_9r":4,
    "qs:photos_all":246,
    "qs:photos_sr":4,
    "qs:placetype":"Town",
    "qs:pop_sr":"0",
    "qs:woe_adm0":23424946,
    "wd:wordcount":12398,
    "wof:name":"New England",
    "wof:placetype":"locality"
},
  "geometry": {"coordinates":[-13.23333,8.46667],"type":"Point"}
}