{
  "type": "Feature",
  "properties": {
    "gn:admin1_code":"01",
    "gn:asciiname":"Tinsiko",
    "gn:country_code":"SL",
    "gn:dem":584,
    "gn:feature_class":"P",
    "gn:feature_code":"PPL",
    "gn:name":"Tinsiko",
    "gn:population":0,
    "gn:timezone":"Africa/Freetown",
    "iso:country":"SL",
    "name:eng_x_preferred":[
        "Tinsiko"
    ],
    "wof:name":"Tinsiko",
    "wof:placetype":"locality"
},
  "geometry": {"coordinates":[-10.62931,8.63432],"type":"Point"}
}