{
  "type": "Feature",
  "properties": {
    "gn:admin1_code":"2.0",
    "gn:asciiname":"Manjaga",
    "gn:country_code":"SL",
    "gn:dem":65,
    "gn:feature_class":"P",
    "gn:feature_code":"PPL",
    "gn:name":"Manjaga",
    "gn:population":0,
    "gn:timezone":"Africa/Freetown",
    "iso:country":"SL",
    "name:eng_x_preferred":[
        "Manjaga"
    ],
    "wof:name":"Manjaga",
    "wof:placetype":"locality"
},
  "geometry": {"coordinates":[-12.06948,8.98167],"type":"Point"}
}