{
  "type": "Feature",
  "properties": {
    "gn:admin1_code":"3.0",
    "gn:asciiname":"Bonday",
    "gn:country_code":"SL",
    "gn:dem":19,
    "gn:feature_class":"P",
    "gn:feature_code":"PPL",
    "gn:name":"Bonday",
    "gn:population":0,
    "gn:timezone":"Africa/Freetown",
    "iso:country":"SL",
    "name:eng_x_preferred":[
        "Bonday"
    ],
    "name:und_x_variant":[
        "Bunde"
    ],
    "wof:name":"Bonday",
    "wof:placetype":"locality"
},
  "geometry": {"coordinates":[-12.59752,7.80835],"type":"Point"}
}