{
  "type": "Feature",
  "properties": {
    "gn:admin1_code":"2.0",
    "gn:asciiname":"Farama",
    "gn:country_code":"SL",
    "gn:dem":360,
    "gn:feature_class":"P",
    "gn:feature_code":"PPL",
    "gn:name":"Farama",
    "gn:population":0,
    "gn:timezone":"Africa/Freetown",
    "iso:country":"SL",
    "name:eng_x_preferred":[
        "Farama"
    ],
    "wof:name":"Farama",
    "wof:placetype":"locality"
},
  "geometry": {"coordinates":[-11.60014,8.57981],"type":"Point"}
}