{
  "type": "Feature",
  "properties": {
    "gn:admin1_code":"3.0",
    "gn:asciiname":"Fernandopo",
    "gn:country_code":"SL",
    "gn:dem":33,
    "gn:feature_class":"P",
    "gn:feature_code":"PPL",
    "gn:name":"Fernandopo",
    "gn:population":0,
    "gn:timezone":"Africa/Freetown",
    "iso:country":"SL",
    "name:eng_x_preferred":[
        "Fernandopo"
    ],
    "wof:name":"Fernandopo",
    "wof:placetype":"locality"
},
  "geometry": {"coordinates":[-11.72951,7.36069],"type":"Point"}
}