{
  "type": "Feature",
  "properties": {
    "gn:admin1_code":"3.0",
    "gn:asciiname":"Lantibul",
    "gn:country_code":"SL",
    "gn:dem":17,
    "gn:feature_class":"P",
    "gn:feature_code":"PPL",
    "gn:name":"Lantibul",
    "gn:population":0,
    "gn:timezone":"Africa/Freetown",
    "iso:country":"SL",
    "name:eng_x_preferred":[
        "Lantibul"
    ],
    "wof:name":"Lantibul",
    "wof:placetype":"locality"
},
  "geometry": {"coordinates":[-12.7997,7.81865],"type":"Point"}
}