{
  "type": "Feature",
  "properties": {
    "gn:admin1_code":"01",
    "gn:asciiname":"Tedu",
    "gn:country_code":"SL",
    "gn:dem":531,
    "gn:feature_class":"P",
    "gn:feature_code":"PPL",
    "gn:name":"Tedu",
    "gn:population":0,
    "gn:timezone":"Africa/Freetown",
    "iso:country":"SL",
    "name:eng_x_preferred":[
        "Tedu"
    ],
    "wof:name":"Tedu",
    "wof:placetype":"locality"
},
  "geometry": {"coordinates":[-10.32663,8.36817],"type":"Point"}
}