{
  "type": "Feature",
  "properties": {
    "gn:admin1_code":"1.0",
    "gn:asciiname":"Mandahun",
    "gn:country_code":"SL",
    "gn:dem":238,
    "gn:feature_class":"P",
    "gn:feature_code":"PPL",
    "gn:name":"Mandahun",
    "gn:population":0,
    "gn:timezone":"Africa/Freetown",
    "iso:country":"SL",
    "name:eng_x_preferred":[
        "Mandahun"
    ],
    "wof:name":"Mandahun",
    "wof:placetype":"locality"
},
  "geometry": {"coordinates":[-11.08758,8.23297],"type":"Point"}
}