{
  "type": "Feature",
  "properties": {
    "gn:admin1_code":"03",
    "gn:asciiname":"Nyandehun",
    "gn:country_code":"SL",
    "gn:dem":47,
    "gn:feature_class":"P",
    "gn:feature_code":"PPL",
    "gn:name":"Nyandehun",
    "gn:population":0,
    "gn:timezone":"Africa/Freetown",
    "iso:country":"SL",
    "name:eng_x_preferred":[
        "Nyandehun"
    ],
    "wof:name":"Nyandehun",
    "wof:placetype":"locality"
},
  "geometry": {"coordinates":[-12.3556,7.87904],"type":"Point"}
}