{
  "type": "Feature",
  "properties": {
    "gn:admin1_code":"3.0",
    "gn:asciiname":"Kpalma",
    "gn:country_code":"SL",
    "gn:dem":14,
    "gn:feature_class":"P",
    "gn:feature_code":"PPL",
    "gn:name":"Kpalma",
    "gn:population":0,
    "gn:timezone":"Africa/Freetown",
    "iso:country":"SL",
    "name:eng_x_preferred":[
        "Kpalma"
    ],
    "wof:name":"Kpalma",
    "wof:placetype":"locality"
},
  "geometry": {"coordinates":[-11.78609,7.12368],"type":"Point"}
}