{
  "type": "Feature",
  "properties": {
    "gn:admin1_code":"2.0",
    "gn:asciiname":"Lungi",
    "gn:country_code":"SL",
    "gn:dem":58,
    "gn:feature_class":"P",
    "gn:feature_code":"PPL",
    "gn:name":"Lungi",
    "gn:population":0,
    "gn:timezone":"Africa/Freetown",
    "iso:country":"SL",
    "name:eng_x_preferred":[
        "Lungi"
    ],
    "wof:name":"Lungi",
    "wof:placetype":"locality"
},
  "geometry": {"coordinates":[-12.76966,9.1334],"type":"Point"}
}