{
  "type": "Feature",
  "properties": {
    "gn:admin1_code":"2.0",
    "gn:asciiname":"Masimera",
    "gn:country_code":"SL",
    "gn:dem":67,
    "gn:feature_class":"P",
    "gn:feature_code":"PPL",
    "gn:name":"Masimera",
    "gn:population":0,
    "gn:timezone":"Africa/Freetown",
    "iso:country":"SL",
    "name:eng_x_preferred":[
        "Masimera"
    ],
    "wof:name":"Masimera",
    "wof:placetype":"locality"
},
  "geometry": {"coordinates":[-12.45042,8.64515],"type":"Point"}
}