{
  "type": "Feature",
  "properties": {
    "gn:admin1_code":"2.0",
    "gn:asciiname":"Gbonkofol",
    "gn:country_code":"SL",
    "gn:dem":70,
    "gn:feature_class":"P",
    "gn:feature_code":"PPL",
    "gn:name":"Gbonkofol",
    "gn:population":0,
    "gn:timezone":"Africa/Freetown",
    "iso:country":"SL",
    "name:eng_x_preferred":[
        "Gbonkofol"
    ],
    "wof:name":"Gbonkofol",
    "wof:placetype":"locality"
},
  "geometry": {"coordinates":[-12.29951,9.3053],"type":"Point"}
}