{
  "type": "Feature",
  "properties": {
    "gn:admin1_code":"04",
    "gn:asciiname":"Samuel Town",
    "gn:country_code":"SL",
    "gn:dem":22,
    "gn:feature_class":"P",
    "gn:feature_code":"PPL",
    "gn:name":"Samuel Town",
    "gn:population":0,
    "gn:timezone":"Africa/Freetown",
    "iso:country":"SL",
    "name:eng_x_preferred":[
        "Samuel Town"
    ],
    "wof:name":"Samuel Town",
    "wof:placetype":"locality"
},
  "geometry": {"coordinates":[-13.07853,8.31131],"type":"Point"}
}