{
  "type": "Feature",
  "properties": {
    "gn:admin1_code":"2.0",
    "gn:asciiname":"Gbengbembu",
    "gn:country_code":"SL",
    "gn:dem":125,
    "gn:feature_class":"P",
    "gn:feature_code":"PPL",
    "gn:name":"Gbengbembu",
    "gn:population":0,
    "gn:timezone":"Africa/Freetown",
    "iso:country":"SL",
    "name:eng_x_preferred":[
        "Gbengbembu"
    ],
    "wof:name":"Gbengbembu",
    "wof:placetype":"locality"
},
  "geometry": {"coordinates":[-12.09063,9.31748],"type":"Point"}
}