{
  "type": "Feature",
  "properties": {
    "gn:admin1_code":"1.0",
    "gn:asciiname":"Ngokoma",
    "gn:country_code":"SL",
    "gn:dem":323,
    "gn:feature_class":"P",
    "gn:feature_code":"PPL",
    "gn:name":"Ngokoma",
    "gn:population":0,
    "gn:timezone":"Africa/Freetown",
    "iso:country":"SL",
    "name:eng_x_preferred":[
        "Ngokoma"
    ],
    "wof:name":"Ngokoma",
    "wof:placetype":"locality"
},
  "geometry": {"coordinates":[-11.12116,8.20345],"type":"Point"}
}