{
  "type": "Feature",
  "properties": {
    "gn:admin1_code":"2.0",
    "gn:asciiname":"Masampa",
    "gn:country_code":"SL",
    "gn:dem":36,
    "gn:feature_class":"P",
    "gn:feature_code":"PPL",
    "gn:name":"Masampa",
    "gn:population":0,
    "gn:timezone":"Africa/Freetown",
    "iso:country":"SL",
    "name:eng_x_preferred":[
        "Masampa"
    ],
    "wof:name":"Masampa",
    "wof:placetype":"locality"
},
  "geometry": {"coordinates":[-12.94721,8.8978],"type":"Point"}
}