{
  "type": "Feature",
  "properties": {
    "gn:admin1_code":"01",
    "gn:asciiname":"Yelendu",
    "gn:country_code":"SL",
    "gn:dem":402,
    "gn:feature_class":"P",
    "gn:feature_code":"PPL",
    "gn:name":"Yelendu",
    "gn:population":0,
    "gn:timezone":"Africa/Freetown",
    "iso:country":"SL",
    "name:und_x_variant":[
        "Yerendu"
    ],
    "wof:name":"Yelendu",
    "wof:placetype":"locality"
},
  "geometry": {"coordinates":[-10.34544,8.39073],"type":"Point"}
}