{
  "type": "Feature",
  "properties": {
    "gn:admin1_code":"2.0",
    "gn:asciiname":"Mabure",
    "gn:country_code":"SL",
    "gn:dem":51,
    "gn:feature_class":"P",
    "gn:feature_code":"PPL",
    "gn:name":"Mabure",
    "gn:population":0,
    "gn:timezone":"Africa/Freetown",
    "iso:country":"SL",
    "name:eng_x_preferred":[
        "Mabure"
    ],
    "wof:name":"Mabure",
    "wof:placetype":"locality"
},
  "geometry": {"coordinates":[-12.75469,8.91312],"type":"Point"}
}