{
  "type": "Feature",
  "properties": {
    "gn:admin1_code":"03",
    "gn:asciiname":"Rokai",
    "gn:country_code":"SL",
    "gn:dem":36,
    "gn:feature_class":"P",
    "gn:feature_code":"PPL",
    "gn:name":"Rokai",
    "gn:population":0,
    "gn:timezone":"Africa/Freetown",
    "iso:country":"SL",
    "name:eng_x_preferred":[
        "Rokai"
    ],
    "wof:name":"Rokai",
    "wof:placetype":"locality"
},
  "geometry": {"coordinates":[-12.62189,8.03712],"type":"Point"}
}