{
  "type": "Feature",
  "properties": {
    "gn:admin1_code":"3.0",
    "gn:asciiname":"Buma",
    "gn:country_code":"SL",
    "gn:dem":45,
    "gn:feature_class":"P",
    "gn:feature_code":"PPL",
    "gn:name":"Buma",
    "gn:population":0,
    "gn:timezone":"Africa/Freetown",
    "iso:country":"SL",
    "name:ceb_x_preferred":[
        "Buma"
    ],
    "name:eng_x_preferred":[
        "Buma"
    ],
    "name:nld_x_preferred":[
        "Buma"
    ],
    "name:swe_x_preferred":[
        "Buma"
    ],
    "wof:name":"Buma",
    "wof:placetype":"locality"
},
  "geometry": {"coordinates":[-11.9406,7.68918],"type":"Point"}
}