{
  "type": "Feature",
  "properties": {
    "gn:admin1_code":"02",
    "gn:asciiname":"Nyandankolia",
    "gn:country_code":"SL",
    "gn:dem":475,
    "gn:feature_class":"P",
    "gn:feature_code":"PPL",
    "gn:name":"Nyandankolia",
    "gn:population":0,
    "gn:timezone":"Africa/Freetown",
    "iso:country":"SL",
    "name:eng_x_preferred":[
        "Nyandankolia"
    ],
    "wof:name":"Nyandankolia",
    "wof:placetype":"locality"
},
  "geometry": {"coordinates":[-11.18092,8.99747],"type":"Point"}
}