{
  "type": "Feature",
  "properties": {
    "gn:admin1_code":"2.0",
    "gn:asciiname":"Dansadia",
    "gn:country_code":"SL",
    "gn:dem":513,
    "gn:feature_class":"P",
    "gn:feature_code":"PPL",
    "gn:name":"Dansadia",
    "gn:population":0,
    "gn:timezone":"Africa/Freetown",
    "iso:country":"SL",
    "name:eng_x_preferred":[
        "Dansadia"
    ],
    "wof:name":"Dansadia",
    "wof:placetype":"locality"
},
  "geometry": {"coordinates":[-11.23065,9.9909],"type":"Point"}
}