{
  "type": "Feature",
  "properties": {
    "gn:admin1_code":"3.0",
    "gn:asciiname":"Naiahun",
    "gn:country_code":"SL",
    "gn:dem":105,
    "gn:feature_class":"P",
    "gn:feature_code":"PPL",
    "gn:name":"Naiahun",
    "gn:population":0,
    "gn:timezone":"Africa/Freetown",
    "iso:country":"SL",
    "name:eng_x_preferred":[
        "Naiahun"
    ],
    "wof:name":"Naiahun",
    "wof:placetype":"locality"
},
  "geometry": {"coordinates":[-11.38205,7.52391],"type":"Point"}
}