{
  "type": "Feature",
  "properties": {
    "gn:admin1_code":"2.0",
    "gn:asciiname":"Yele",
    "gn:country_code":"SL",
    "gn:dem":21,
    "gn:feature_class":"P",
    "gn:feature_code":"PPL",
    "gn:name":"Yele",
    "gn:population":0,
    "gn:timezone":"Africa/Freetown",
    "iso:country":"SL",
    "name:ceb_x_preferred":[
        "Yele"
    ],
    "name:eng_x_preferred":[
        "Yele"
    ],
    "name:fra_x_preferred":[
        "Yele"
    ],
    "name:swe_x_preferred":[
        "Yele"
    ],
    "wof:name":"Yele",
    "wof:placetype":"locality"
},
  "geometry": {"coordinates":[-12.6968,8.5332],"type":"Point"}
}