{
  "type": "Feature",
  "properties": {
    "gn:admin1_code":"2.0",
    "gn:asciiname":"Karina",
    "gn:country_code":"SL",
    "gn:dem":107,
    "gn:feature_class":"P",
    "gn:feature_code":"PPL",
    "gn:name":"Karina",
    "gn:population":0,
    "gn:timezone":"Africa/Freetown",
    "iso:country":"SL",
    "name:ceb_x_preferred":[
        "Karina"
    ],
    "name:ces_x_preferred":[
        "Karina"
    ],
    "name:fra_x_preferred":[
        "Karina"
    ],
    "name:hun_x_preferred":[
        "Karina"
    ],
    "name:nld_x_preferred":[
        "Karina"
    ],
    "name:por_x_preferred":[
        "Karina"
    ],
    "name:rus_x_preferred":[
        "\u041a\u0430\u0440\u0438\u043d\u0430"
    ],
    "name:spa_x_preferred":[
        "Karina"
    ],
    "name:srp_x_preferred":[
        "\u041a\u0430\u0440\u0438\u043d\u0430"
    ],
    "name:swe_x_preferred":[
        "Karina"
    ],
    "name:tur_x_preferred":[
        "Karina"
    ],
    "name:und_x_variant":[
        "Karim",
        "Karima",
        "Karina"
    ],
    "wof:name":"Karina",
    "wof:placetype":"locality"
},
  "geometry": {"coordinates":[-12.01223,9.1721],"type":"Point"}
}