{
  "type": "Feature",
  "properties": {
    "gn:admin1_code":"2.0",
    "gn:asciiname":"Karina",
    "gn:country_code":"SL",
    "gn:dem":107,
    "gn:feature_class":"P",
    "gn:feature_code":"PPL",
    "gn:name":"Karina",
    "gn:population":0,
    "gn:timezone":"Africa/Freetown",
    "iso:country":"SL",
    "name:und_x_variant":[
        "Karim",
        "Karima",
        "Karina"
    ],
    "wof:name":"Karina",
    "wof:placetype":"locality"
},
  "geometry": {"coordinates":[-12.01223,9.1721],"type":"Point"}
}