{
  "type": "Feature",
  "properties": {
    "gn:admin1_code":"2.0",
    "gn:asciiname":"Mabonka",
    "gn:country_code":"SL",
    "gn:dem":76,
    "gn:feature_class":"P",
    "gn:feature_code":"PPL",
    "gn:name":"Mabonka",
    "gn:population":0,
    "gn:timezone":"Africa/Freetown",
    "iso:country":"SL",
    "name:eng_x_preferred":[
        "Mabonka"
    ],
    "wof:name":"Mabonka",
    "wof:placetype":"locality"
},
  "geometry": {"coordinates":[-12.58847,8.8689],"type":"Point"}
}