{
  "type": "Feature",
  "properties": {
    "gn:admin1_code":"2.0",
    "gn:asciiname":"Manewa",
    "gn:country_code":"SL",
    "gn:dem":80,
    "gn:feature_class":"P",
    "gn:feature_code":"PPL",
    "gn:name":"Manewa",
    "gn:population":0,
    "gn:timezone":"Africa/Freetown",
    "iso:country":"SL",
    "name:eng_x_preferred":[
        "Manewa"
    ],
    "wof:name":"Manewa",
    "wof:placetype":"locality"
},
  "geometry": {"coordinates":[-12.14269,8.70181],"type":"Point"}
}