{
  "type": "Feature",
  "properties": {
    "gn:admin1_code":"02",
    "gn:asciiname":"Polo",
    "gn:country_code":"SL",
    "gn:dem":109,
    "gn:feature_class":"P",
    "gn:feature_code":"PPL",
    "gn:name":"Polo",
    "gn:population":0,
    "gn:timezone":"Africa/Freetown",
    "iso:country":"SL",
    "name:eng_x_preferred":[
        "Polo"
    ],
    "wof:name":"Polo",
    "wof:placetype":"locality"
},
  "geometry": {"coordinates":[-11.93088,8.70881],"type":"Point"}
}