{
  "type": "Feature",
  "properties": {
    "gn:admin1_code":"2.0",
    "gn:asciiname":"Magbanda",
    "gn:country_code":"SL",
    "gn:dem":71,
    "gn:feature_class":"P",
    "gn:feature_code":"PPL",
    "gn:name":"Magbanda",
    "gn:population":0,
    "gn:timezone":"Africa/Freetown",
    "iso:country":"SL",
    "name:eng_x_preferred":[
        "Magbanda"
    ],
    "wof:name":"Magbanda",
    "wof:placetype":"locality"
},
  "geometry": {"coordinates":[-12.54338,8.84424],"type":"Point"}
}