{
  "type": "Feature",
  "properties": {
    "gn:admin1_code":"1.0",
    "gn:asciiname":"Mamuta",
    "gn:country_code":"SL",
    "gn:dem":361,
    "gn:feature_class":"P",
    "gn:feature_code":"PPL",
    "gn:name":"Mamuta",
    "gn:population":0,
    "gn:timezone":"Africa/Freetown",
    "iso:country":"SL",
    "name:eng_x_preferred":[
        "Mamuta"
    ],
    "wof:name":"Mamuta",
    "wof:placetype":"locality"
},
  "geometry": {"coordinates":[-10.45408,8.34542],"type":"Point"}
}