{
  "type": "Feature",
  "properties": {
    "gn:admin1_code":"1.0",
    "gn:asciiname":"Simbeck",
    "gn:country_code":"SL",
    "gn:dem":234,
    "gn:feature_class":"P",
    "gn:feature_code":"PPL",
    "gn:name":"Simbeck",
    "gn:population":0,
    "gn:timezone":"Africa/Freetown",
    "iso:country":"SL",
    "name:eng_x_preferred":[
        "Simbeck"
    ],
    "wof:name":"Simbeck",
    "wof:placetype":"locality"
},
  "geometry": {"coordinates":[-10.84603,8.32691],"type":"Point"}
}