{
  "type": "Feature",
  "properties": {
    "gn:admin1_code":"2.0",
    "gn:asciiname":"Fundu",
    "gn:country_code":"SL",
    "gn:dem":354,
    "gn:feature_class":"P",
    "gn:feature_code":"PPL",
    "gn:name":"Fundu",
    "gn:population":0,
    "gn:timezone":"Africa/Freetown",
    "iso:country":"SL",
    "name:eng_x_preferred":[
        "Fundu"
    ],
    "wof:name":"Fundu",
    "wof:placetype":"locality"
},
  "geometry": {"coordinates":[-11.53643,8.7763],"type":"Point"}
}