{
  "type": "Feature",
  "properties": {
    "gn:admin1_code":"2.0",
    "gn:asciiname":"Katimbo",
    "gn:country_code":"SL",
    "gn:dem":463,
    "gn:feature_class":"P",
    "gn:feature_code":"PPL",
    "gn:name":"Katimbo",
    "gn:population":0,
    "gn:timezone":"Africa/Freetown",
    "iso:country":"SL",
    "name:eng_x_preferred":[
        "Katimbo"
    ],
    "wof:name":"Katimbo",
    "wof:placetype":"locality"
},
  "geometry": {"coordinates":[-11.76634,9.35828],"type":"Point"}
}