{
  "type": "Feature",
  "properties": {
    "gn:admin1_code":"04",
    "gn:asciiname":"Sattia Town",
    "gn:country_code":"SL",
    "gn:dem":21,
    "gn:feature_class":"P",
    "gn:feature_code":"PPL",
    "gn:name":"Sattia Town",
    "gn:population":0,
    "gn:timezone":"Africa/Freetown",
    "iso:country":"SL",
    "name:eng_x_preferred":[
        "Sattia Town"
    ],
    "wof:name":"Sattia Town",
    "wof:placetype":"locality"
},
  "geometry": {"coordinates":[-13.0525,8.24625],"type":"Point"}
}