{
  "type": "Feature",
  "properties": {
    "gn:admin1_code":"2.0",
    "gn:asciiname":"Pahabohun",
    "gn:country_code":"SL",
    "gn:dem":181,
    "gn:feature_class":"P",
    "gn:feature_code":"PPL",
    "gn:name":"Pahabohun",
    "gn:population":0,
    "gn:timezone":"Africa/Freetown",
    "iso:country":"SL",
    "name:eng_x_preferred":[
        "Pahabohun"
    ],
    "wof:name":"Pahabohun",
    "wof:placetype":"locality"
},
  "geometry": {"coordinates":[-12.11893,9.24213],"type":"Point"}
}