{
  "type": "Feature",
  "properties": {
    "gn:admin1_code":"3.0",
    "gn:asciiname":"Yandebu",
    "gn:country_code":"SL",
    "gn:dem":111,
    "gn:feature_class":"P",
    "gn:feature_code":"PPL",
    "gn:name":"Yandebu",
    "gn:population":0,
    "gn:timezone":"Africa/Freetown",
    "iso:country":"SL",
    "name:eng_x_preferred":[
        "Yandebu"
    ],
    "wof:name":"Yandebu",
    "wof:placetype":"locality"
},
  "geometry": {"coordinates":[-11.80108,8.2554],"type":"Point"}
}