{
  "type": "Feature",
  "properties": {
    "gn:admin1_code":"3.0",
    "gn:asciiname":"Soso",
    "gn:country_code":"SL",
    "gn:dem":44,
    "gn:feature_class":"P",
    "gn:feature_code":"PPL",
    "gn:name":"Soso",
    "gn:population":0,
    "gn:timezone":"Africa/Freetown",
    "iso:country":"SL",
    "name:ceb_x_preferred":[
        "Soso"
    ],
    "name:eng_x_preferred":[
        "Soso"
    ],
    "name:fra_x_preferred":[
        "Soso"
    ],
    "name:ita_x_preferred":[
        "Soso"
    ],
    "name:rus_x_preferred":[
        "\u0421\u043e\u0441\u043e"
    ],
    "name:swe_x_preferred":[
        "Soso"
    ],
    "wof:name":"Soso",
    "wof:placetype":"locality"
},
  "geometry": {"coordinates":[-11.77253,7.39858],"type":"Point"}
}