{
  "type": "Feature",
  "properties": {
    "gn:admin1_code":"3.0",
    "gn:asciiname":"Mokota",
    "gn:country_code":"SL",
    "gn:dem":42,
    "gn:feature_class":"P",
    "gn:feature_code":"PPL",
    "gn:name":"Mokota",
    "gn:population":0,
    "gn:timezone":"Africa/Freetown",
    "iso:country":"SL",
    "name:eng_x_preferred":[
        "Mokota"
    ],
    "wof:name":"Mokota",
    "wof:placetype":"locality"
},
  "geometry": {"coordinates":[-12.1433,7.90006],"type":"Point"}
}