{
  "type": "Feature",
  "properties": {
    "gn:admin1_code":"3.0",
    "gn:asciiname":"Kunjondoma",
    "gn:country_code":"SL",
    "gn:dem":141,
    "gn:feature_class":"P",
    "gn:feature_code":"PPL",
    "gn:name":"Kunjondoma",
    "gn:population":0,
    "gn:timezone":"Africa/Freetown",
    "iso:country":"SL",
    "name:eng_x_preferred":[
        "Kunjondoma"
    ],
    "wof:name":"Kunjondoma",
    "wof:placetype":"locality"
},
  "geometry": {"coordinates":[-11.53729,8.10613],"type":"Point"}
}