{
  "type": "Feature",
  "properties": {
    "gn:admin1_code":"03",
    "gn:asciiname":"Sarma",
    "gn:country_code":"SL",
    "gn:dem":39,
    "gn:feature_class":"P",
    "gn:feature_code":"PPL",
    "gn:name":"Sarma",
    "gn:population":0,
    "gn:timezone":"Africa/Freetown",
    "iso:country":"SL",
    "name:ceb_x_preferred":[
        "Sarma"
    ],
    "name:deu_x_preferred":[
        "Sarma"
    ],
    "name:fra_x_preferred":[
        "Sarma"
    ],
    "name:ita_x_preferred":[
        "Sarma"
    ],
    "name:jpn_x_preferred":[
        "\u30b5\u30eb\u30de"
    ],
    "name:lav_x_preferred":[
        "Sarma"
    ],
    "name:nld_x_preferred":[
        "Sarma"
    ],
    "name:pol_x_preferred":[
        "Sarma"
    ],
    "name:scn_x_preferred":[
        "Sarma"
    ],
    "name:swe_x_preferred":[
        "Dolmar#Sarma"
    ],
    "name:und_x_variant":[
        "Saama"
    ],
    "wof:name":"Sarma",
    "wof:placetype":"locality"
},
  "geometry": {"coordinates":[-11.55528,7.21028],"type":"Point"}
}