{
  "type": "Feature",
  "properties": {
    "gn:admin1_code":"2.0",
    "gn:asciiname":"Bambugu",
    "gn:country_code":"SL",
    "gn:dem":456,
    "gn:feature_class":"P",
    "gn:feature_code":"PPL",
    "gn:name":"Bambugu",
    "gn:population":0,
    "gn:timezone":"Africa/Freetown",
    "iso:country":"SL",
    "name:eng_x_preferred":[
        "Bambugu"
    ],
    "wof:name":"Bambugu",
    "wof:placetype":"locality"
},
  "geometry": {"coordinates":[-11.02499,9.56751],"type":"Point"}
}