{
  "type": "Feature",
  "properties": {
    "gn:admin1_code":"3.0",
    "gn:asciiname":"Kpandemei",
    "gn:country_code":"SL",
    "gn:dem":30,
    "gn:feature_class":"P",
    "gn:feature_code":"PPL",
    "gn:name":"Kpandemei",
    "gn:population":0,
    "gn:timezone":"Africa/Freetown",
    "iso:country":"SL",
    "name:eng_x_preferred":[
        "Kpandemei"
    ],
    "wof:name":"Kpandemei",
    "wof:placetype":"locality"
},
  "geometry": {"coordinates":[-12.11551,7.67689],"type":"Point"}
}