{
  "type": "Feature",
  "properties": {
    "gn:admin1_code":"2.0",
    "gn:asciiname":"Baka",
    "gn:country_code":"SL",
    "gn:dem":73,
    "gn:feature_class":"P",
    "gn:feature_code":"PPL",
    "gn:name":"Baka",
    "gn:population":0,
    "gn:timezone":"Africa/Freetown",
    "iso:country":"SL",
    "name:eng_x_preferred":[
        "Baka"
    ],
    "wof:name":"Baka",
    "wof:placetype":"locality"
},
  "geometry": {"coordinates":[-12.27855,9.35815],"type":"Point"}
}