{
  "type": "Feature",
  "properties": {
    "gn:admin1_code":"3.0",
    "gn:asciiname":"Baoma",
    "gn:country_code":"SL",
    "gn:dem":15,
    "gn:feature_class":"P",
    "gn:feature_code":"PPL",
    "gn:name":"Baoma",
    "gn:population":0,
    "gn:timezone":"Africa/Freetown",
    "iso:country":"SL",
    "name:eng_x_preferred":[
        "Baoma"
    ],
    "name:und_x_variant":[
        "Boma"
    ],
    "wof:name":"Baoma",
    "wof:placetype":"locality"
},
  "geometry": {"coordinates":[-11.95585,7.28592],"type":"Point"}
}