{
  "type": "Feature",
  "properties": {
    "gn:admin1_code":"1.0",
    "gn:asciiname":"Pambawa",
    "gn:country_code":"SL",
    "gn:dem":417,
    "gn:feature_class":"P",
    "gn:feature_code":"PPL",
    "gn:name":"Pambawa",
    "gn:population":0,
    "gn:timezone":"Africa/Freetown",
    "iso:country":"SL",
    "name:eng_x_preferred":[
        "Pambawa"
    ],
    "wof:name":"Pambawa",
    "wof:placetype":"locality"
},
  "geometry": {"coordinates":[-10.94923,8.80723],"type":"Point"}
}