{
  "type": "Feature",
  "properties": {
    "gn:admin1_code":"2.0",
    "gn:asciiname":"Mawore",
    "gn:country_code":"SL",
    "gn:dem":99,
    "gn:feature_class":"P",
    "gn:feature_code":"PPL",
    "gn:name":"Mawore",
    "gn:population":0,
    "gn:timezone":"Africa/Freetown",
    "iso:country":"SL",
    "name:eng_x_preferred":[
        "Mawore"
    ],
    "wof:name":"Mawore",
    "wof:placetype":"locality"
},
  "geometry": {"coordinates":[-11.92773,9.2192],"type":"Point"}
}