{
  "type": "Feature",
  "properties": {
    "gn:admin1_code":"3.0",
    "gn:asciiname":"Jimi",
    "gn:country_code":"SL",
    "gn:dem":48,
    "gn:feature_class":"P",
    "gn:feature_code":"PPL",
    "gn:name":"Jimi",
    "gn:population":0,
    "gn:timezone":"Africa/Freetown",
    "iso:country":"SL",
    "name:ceb_x_preferred":[
        "Jimi"
    ],
    "name:deu_x_preferred":[
        "Jimi"
    ],
    "name:eng_x_preferred":[
        "Jimi"
    ],
    "name:fra_x_preferred":[
        "Jimi"
    ],
    "name:ita_x_preferred":[
        "Jimi"
    ],
    "name:swa_x_preferred":[
        "Kijimi"
    ],
    "name:swe_x_preferred":[
        "Jimi"
    ],
    "wof:name":"Jimi",
    "wof:placetype":"locality"
},
  "geometry": {"coordinates":[-11.81675,7.60422],"type":"Point"}
}