{
  "type": "Feature",
  "properties": {
    "gn:admin1_code":"3.0",
    "gn:asciiname":"Levume",
    "gn:country_code":"SL",
    "gn:dem":103,
    "gn:feature_class":"P",
    "gn:feature_code":"PPL",
    "gn:name":"Levume",
    "gn:population":0,
    "gn:timezone":"Africa/Freetown",
    "iso:country":"SL",
    "name:eng_x_preferred":[
        "Levume"
    ],
    "name:und_x_variant":[
        "Levuma"
    ],
    "wof:name":"Levume",
    "wof:placetype":"locality"
},
  "geometry": {"coordinates":[-11.7343,8.36423],"type":"Point"}
}