{
  "type": "Feature",
  "properties": {
    "gn:admin1_code":"2.0",
    "gn:asciiname":"Kamalan",
    "gn:country_code":"SL",
    "gn:dem":56,
    "gn:feature_class":"P",
    "gn:feature_code":"PPL",
    "gn:name":"Kamalan",
    "gn:population":0,
    "gn:timezone":"Africa/Freetown",
    "iso:country":"SL",
    "name:eng_x_preferred":[
        "Kamalan"
    ],
    "wof:name":"Kamalan",
    "wof:placetype":"locality"
},
  "geometry": {"coordinates":[-12.7589,8.96899],"type":"Point"}
}