{
  "type": "Feature",
  "properties": {
    "gn:admin1_code":"3.0",
    "gn:asciiname":"Mokombo",
    "gn:country_code":"SL",
    "gn:dem":77,
    "gn:feature_class":"P",
    "gn:feature_code":"PPL",
    "gn:name":"Mokombo",
    "gn:population":0,
    "gn:timezone":"Africa/Freetown",
    "iso:country":"SL",
    "name:eng_x_preferred":[
        "Mokombo"
    ],
    "wof:name":"Mokombo",
    "wof:placetype":"locality"
},
  "geometry": {"coordinates":[-11.81603,7.8226],"type":"Point"}
}