{
  "type": "Feature",
  "properties": {
    "gn:admin1_code":"02",
    "gn:asciiname":"Rogap",
    "gn:country_code":"SL",
    "gn:dem":18,
    "gn:feature_class":"P",
    "gn:feature_code":"PPL",
    "gn:name":"Rogap",
    "gn:population":0,
    "gn:timezone":"Africa/Freetown",
    "iso:country":"SL",
    "name:eng_x_preferred":[
        "Rogap"
    ],
    "wof:name":"Rogap",
    "wof:placetype":"locality"
},
  "geometry": {"coordinates":[-12.8645,8.89659],"type":"Point"}
}