{
  "type": "Feature",
  "properties": {
    "gn:admin1_code":"2.0",
    "gn:asciiname":"Makenko",
    "gn:country_code":"SL",
    "gn:dem":40,
    "gn:feature_class":"P",
    "gn:feature_code":"PPL",
    "gn:name":"Makenko",
    "gn:population":0,
    "gn:timezone":"Africa/Freetown",
    "iso:country":"SL",
    "name:eng_x_preferred":[
        "Makenko"
    ],
    "wof:name":"Makenko",
    "wof:placetype":"locality"
},
  "geometry": {"coordinates":[-12.91255,9.10996],"type":"Point"}
}