{
  "type": "Feature",
  "properties": {
    "gn:admin1_code":"03",
    "gn:asciiname":"Kowama",
    "gn:country_code":"SL",
    "gn:dem":89,
    "gn:feature_class":"P",
    "gn:feature_code":"PPL",
    "gn:name":"Kowama",
    "gn:population":0,
    "gn:timezone":"Africa/Freetown",
    "iso:country":"SL",
    "name:eng_x_preferred":[
        "Kowama"
    ],
    "name:und_x_variant":[
        "Nyadehun"
    ],
    "wof:name":"Kowama",
    "wof:placetype":"locality"
},
  "geometry": {"coordinates":[-11.71648,8.10095],"type":"Point"}
}