{
  "type": "Feature",
  "properties": {
    "gn:admin1_code":"3.0",
    "gn:asciiname":"Batbai",
    "gn:country_code":"SL",
    "gn:dem":14,
    "gn:feature_class":"P",
    "gn:feature_code":"PPL",
    "gn:name":"Batbai",
    "gn:population":0,
    "gn:timezone":"Africa/Freetown",
    "iso:country":"SL",
    "name:und_x_variant":[
        "Batbal",
        "Batbai"
    ],
    "wof:name":"Batbai",
    "wof:placetype":"locality"
},
  "geometry": {"coordinates":[-12.92479,8.17695],"type":"Point"}
}