{
  "type": "Feature",
  "properties": {
    "gn:admin1_code":"02",
    "gn:asciiname":"Rochin",
    "gn:country_code":"SL",
    "gn:dem":80,
    "gn:feature_class":"P",
    "gn:feature_code":"PPL",
    "gn:name":"Rochin",
    "gn:population":0,
    "gn:timezone":"Africa/Freetown",
    "iso:country":"SL",
    "name:eng_x_preferred":[
        "Rochin"
    ],
    "wof:name":"Rochin",
    "wof:placetype":"locality"
},
  "geometry": {"coordinates":[-12.29138,9.37599],"type":"Point"}
}