{
  "type": "Feature",
  "properties": {
    "gn:admin1_code":"2.0",
    "gn:asciiname":"Mabansa",
    "gn:country_code":"SL",
    "gn:dem":83,
    "gn:feature_class":"P",
    "gn:feature_code":"PPL",
    "gn:name":"Mabansa",
    "gn:population":0,
    "gn:timezone":"Africa/Freetown",
    "iso:country":"SL",
    "name:eng_x_preferred":[
        "Mabansa"
    ],
    "wof:name":"Mabansa",
    "wof:placetype":"locality"
},
  "geometry": {"coordinates":[-12.31479,8.39116],"type":"Point"}
}