{
  "type": "Feature",
  "properties": {
    "gn:admin1_code":"3.0",
    "gn:asciiname":"Momaya",
    "gn:country_code":"SL",
    "gn:dem":6,
    "gn:feature_class":"P",
    "gn:feature_code":"PPL",
    "gn:name":"Momaya",
    "gn:population":0,
    "gn:timezone":"Africa/Freetown",
    "iso:country":"SL",
    "name:eng_x_preferred":[
        "Momaya"
    ],
    "name:und_x_variant":[
        "Monaia"
    ],
    "wof:name":"Momaya",
    "wof:placetype":"locality"
},
  "geometry": {"coordinates":[-12.39972,7.53108],"type":"Point"}
}