{
  "type": "Feature",
  "properties": {
    "gn:admin1_code":"3.0",
    "gn:asciiname":"Naiaguehun",
    "gn:country_code":"SL",
    "gn:dem":145,
    "gn:feature_class":"P",
    "gn:feature_code":"PPL",
    "gn:name":"Naiaguehun",
    "gn:population":0,
    "gn:timezone":"Africa/Freetown",
    "iso:country":"SL",
    "wof:name":"Naiaguehun",
    "wof:placetype":"locality"
},
  "geometry": {"coordinates":[-11.53333,8.11667],"type":"Point"}
}