{
  "type": "Feature",
  "properties": {
    "gn:admin1_code":"01",
    "gn:asciiname":"Waiawayehun",
    "gn:country_code":"SL",
    "gn:dem":151,
    "gn:feature_class":"P",
    "gn:feature_code":"PPL",
    "gn:name":"Waiawayehun",
    "gn:population":0,
    "gn:timezone":"Africa/Freetown",
    "iso:country":"SL",
    "name:eng_x_preferred":[
        "Waiawayehun"
    ],
    "wof:name":"Waiawayehun",
    "wof:placetype":"locality"
},
  "geometry": {"coordinates":[-10.96081,7.59642],"type":"Point"}
}