{
  "type": "Feature",
  "properties": {
    "gn:admin1_code":"2.0",
    "gn:asciiname":"Masetia",
    "gn:country_code":"SL",
    "gn:dem":53,
    "gn:feature_class":"P",
    "gn:feature_code":"PPL",
    "gn:name":"Masetia",
    "gn:population":0,
    "gn:timezone":"Africa/Freetown",
    "iso:country":"SL",
    "name:eng_x_preferred":[
        "Masetia"
    ],
    "wof:name":"Masetia",
    "wof:placetype":"locality"
},
  "geometry": {"coordinates":[-12.71552,8.62778],"type":"Point"}
}