{
  "type": "Feature",
  "properties": {
    "gn:admin1_code":"01",
    "gn:asciiname":"Tungie",
    "gn:country_code":"SL",
    "gn:dem":337,
    "gn:feature_class":"P",
    "gn:feature_code":"PPL",
    "gn:name":"Tungie",
    "gn:population":0,
    "gn:timezone":"Africa/Freetown",
    "iso:country":"SL",
    "name:eng_x_preferred":[
        "Tungie"
    ],
    "wof:name":"Tungie",
    "wof:placetype":"locality"
},
  "geometry": {"coordinates":[-11.4432,8.27757],"type":"Point"}
}