{
  "type": "Feature",
  "properties": {
    "gn:admin1_code":"2.0",
    "gn:asciiname":"Makump",
    "gn:country_code":"SL",
    "gn:dem":58,
    "gn:feature_class":"P",
    "gn:feature_code":"PPL",
    "gn:name":"Makump",
    "gn:population":0,
    "gn:timezone":"Africa/Freetown",
    "iso:country":"SL",
    "name:eng_x_preferred":[
        "Makump"
    ],
    "wof:name":"Makump",
    "wof:placetype":"locality"
},
  "geometry": {"coordinates":[-12.66762,8.8915],"type":"Point"}
}