{
  "type": "Feature",
  "properties": {
    "gn:admin1_code":"2.0",
    "gn:asciiname":"Bunguema",
    "gn:country_code":"SL",
    "gn:dem":74,
    "gn:feature_class":"P",
    "gn:feature_code":"PPL",
    "gn:name":"Bunguema",
    "gn:population":0,
    "gn:timezone":"Africa/Freetown",
    "iso:country":"SL",
    "name:und_x_variant":[
        "Banguema",
        "Bunguema"
    ],
    "wof:name":"Bunguema",
    "wof:placetype":"locality"
},
  "geometry": {"coordinates":[-12.12678,8.99442],"type":"Point"}
}