{
  "type": "Feature",
  "properties": {
    "gn:admin1_code":"2.0",
    "gn:asciiname":"Kagbunko",
    "gn:country_code":"SL",
    "gn:dem":142,
    "gn:feature_class":"P",
    "gn:feature_code":"PPL",
    "gn:name":"Kagbunko",
    "gn:population":0,
    "gn:timezone":"Africa/Freetown",
    "iso:country":"SL",
    "name:eng_x_preferred":[
        "Kagbunko"
    ],
    "wof:name":"Kagbunko",
    "wof:placetype":"locality"
},
  "geometry": {"coordinates":[-11.9606,9.34396],"type":"Point"}
}