{
  "type": "Feature",
  "properties": {
    "gn:admin1_code":"2.0",
    "gn:asciiname":"Mamiri",
    "gn:country_code":"SL",
    "gn:dem":22,
    "gn:feature_class":"P",
    "gn:feature_code":"PPL",
    "gn:name":"Mamiri",
    "gn:population":0,
    "gn:timezone":"Africa/Freetown",
    "iso:country":"SL",
    "name:eng_x_preferred":[
        "Mamiri"
    ],
    "wof:name":"Mamiri",
    "wof:placetype":"locality"
},
  "geometry": {"coordinates":[-12.87139,8.51327],"type":"Point"}
}