{
  "type": "Feature",
  "properties": {
    "gn:admin1_code":"01",
    "gn:asciiname":"Sanga",
    "gn:country_code":"SL",
    "gn:dem":483,
    "gn:feature_class":"P",
    "gn:feature_code":"PPL",
    "gn:name":"Sanga",
    "gn:population":0,
    "gn:timezone":"Africa/Freetown",
    "iso:country":"SL",
    "name:ceb_x_preferred":[
        "Sanga"
    ],
    "name:deu_x_preferred":[
        "Sanga"
    ],
    "name:eng_x_preferred":[
        "Sanga"
    ],
    "name:fra_x_preferred":[
        "Sanga"
    ],
    "name:ita_x_preferred":[
        "Sanga"
    ],
    "name:por_x_preferred":[
        "Sanga"
    ],
    "name:swe_x_preferred":[
        "Sanga"
    ],
    "wof:name":"Sanga",
    "wof:placetype":"locality"
},
  "geometry": {"coordinates":[-10.31252,8.2002],"type":"Point"}
}