{
  "type": "Feature",
  "properties": {
    "gn:admin1_code":"2.0",
    "gn:asciiname":"Kiehuk",
    "gn:country_code":"SL",
    "gn:dem":13,
    "gn:feature_class":"P",
    "gn:feature_code":"PPL",
    "gn:name":"Kiehuk",
    "gn:population":0,
    "gn:timezone":"Africa/Freetown",
    "iso:country":"SL",
    "name:eng_x_preferred":[
        "Kiehuk"
    ],
    "wof:name":"Kiehuk",
    "wof:placetype":"locality"
},
  "geometry": {"coordinates":[-13.1845,8.84682],"type":"Point"}
}