{
  "type": "Feature",
  "properties": {
    "gn:admin1_code":"1.0",
    "gn:asciiname":"Kojehun",
    "gn:country_code":"SL",
    "gn:dem":377,
    "gn:feature_class":"P",
    "gn:feature_code":"PPL",
    "gn:name":"Kojehun",
    "gn:population":0,
    "gn:timezone":"Africa/Freetown",
    "iso:country":"SL",
    "name:eng_x_preferred":[
        "Kojehun"
    ],
    "name:und_x_variant":[
        "Kolujehun"
    ],
    "wof:name":"Kojehun",
    "wof:placetype":"locality"
},
  "geometry": {"coordinates":[-10.94042,8.33553],"type":"Point"}
}