{
  "type": "Feature",
  "properties": {
    "gn:admin1_code":"3.0",
    "gn:asciiname":"Kpetewoma",
    "gn:country_code":"SL",
    "gn:dem":59,
    "gn:feature_class":"P",
    "gn:feature_code":"PPL",
    "gn:name":"Kpetewoma",
    "gn:population":0,
    "gn:timezone":"Africa/Freetown",
    "iso:country":"SL",
    "name:eng_x_preferred":[
        "Kpetewoma"
    ],
    "wof:name":"Kpetewoma",
    "wof:placetype":"locality"
},
  "geometry": {"coordinates":[-12.0849,7.85422],"type":"Point"}
}