{
  "type": "Feature",
  "properties": {
    "gn:admin1_code":"2.0",
    "gn:asciiname":"Gbila",
    "gn:country_code":"SL",
    "gn:dem":76,
    "gn:feature_class":"P",
    "gn:feature_code":"PPL",
    "gn:name":"Gbila",
    "gn:population":0,
    "gn:timezone":"Africa/Freetown",
    "iso:country":"SL",
    "name:eng_x_preferred":[
        "Gbila"
    ],
    "wof:name":"Gbila",
    "wof:placetype":"locality"
},
  "geometry": {"coordinates":[-12.59759,8.91145],"type":"Point"}
}