{
  "type": "Feature",
  "properties": {
    "gn:admin1_code":"1.0",
    "gn:asciiname":"Gundama",
    "gn:country_code":"SL",
    "gn:dem":211,
    "gn:feature_class":"P",
    "gn:feature_code":"PPL",
    "gn:name":"Gundama",
    "gn:population":0,
    "gn:timezone":"Africa/Freetown",
    "iso:country":"SL",
    "name:eng_x_preferred":[
        "Gundama"
    ],
    "wof:name":"Gundama",
    "wof:placetype":"locality"
},
  "geometry": {"coordinates":[-11.08548,8.08716],"type":"Point"}
}