{
  "type": "Feature",
  "properties": {
    "gn:admin1_code":"3.0",
    "gn:asciiname":"Mokana",
    "gn:country_code":"SL",
    "gn:dem":21,
    "gn:feature_class":"P",
    "gn:feature_code":"PPL",
    "gn:name":"Mokana",
    "gn:population":0,
    "gn:timezone":"Africa/Freetown",
    "iso:country":"SL",
    "name:eng_x_preferred":[
        "Mokana"
    ],
    "wof:name":"Mokana",
    "wof:placetype":"locality"
},
  "geometry": {"coordinates":[-12.70012,7.93405],"type":"Point"}
}