{
  "type": "Feature",
  "properties": {
    "gn:admin1_code":"2.0",
    "gn:asciiname":"Magbulun",
    "gn:country_code":"SL",
    "gn:dem":49,
    "gn:feature_class":"P",
    "gn:feature_code":"PPL",
    "gn:name":"Magbulun",
    "gn:population":0,
    "gn:timezone":"Africa/Freetown",
    "iso:country":"SL",
    "name:eng_x_preferred":[
        "Magbulun"
    ],
    "wof:name":"Magbulun",
    "wof:placetype":"locality"
},
  "geometry": {"coordinates":[-12.77916,9.1311],"type":"Point"}
}