{
  "type": "Feature",
  "properties": {
    "gn:admin1_code":"2.0",
    "gn:asciiname":"Yanka",
    "gn:country_code":"SL",
    "gn:dem":90,
    "gn:feature_class":"P",
    "gn:feature_code":"PPL",
    "gn:name":"Yanka",
    "gn:population":0,
    "gn:timezone":"Africa/Freetown",
    "iso:country":"SL",
    "name:bel_x_preferred":[
        "\u042f\u043d\u043a\u0430"
    ],
    "name:ceb_x_preferred":[
        "Yanka"
    ],
    "name:eng_x_preferred":[
        "Yanka"
    ],
    "name:fra_x_preferred":[
        "Yanka"
    ],
    "name:rus_x_preferred":[
        "\u042f\u043d\u043a\u0430"
    ],
    "name:swe_x_preferred":[
        "Yanka"
    ],
    "name:ukr_x_preferred":[
        "\u042f\u043d\u043a\u0430"
    ],
    "wof:name":"Yanka",
    "wof:placetype":"locality"
},
  "geometry": {"coordinates":[-12.26323,9.4394],"type":"Point"}
}