{
  "type": "Feature",
  "properties": {
    "gn:admin1_code":"4.0",
    "gn:asciiname":"Samahun",
    "gn:country_code":"SL",
    "gn:dem":172,
    "gn:feature_class":"P",
    "gn:feature_code":"PPL",
    "gn:name":"Samahun",
    "gn:population":0,
    "gn:timezone":"Africa/Freetown",
    "iso:country":"SL",
    "name:eng_x_preferred":[
        "Samahun"
    ],
    "wof:name":"Samahun",
    "wof:placetype":"locality"
},
  "geometry": {"coordinates":[-13.10941,8.31358],"type":"Point"}
}