{
  "type": "Feature",
  "properties": {
    "gn:admin1_code":"1.0",
    "gn:asciiname":"Kpemalu",
    "gn:country_code":"SL",
    "gn:dem":341,
    "gn:feature_class":"P",
    "gn:feature_code":"PPL",
    "gn:name":"Kpemalu",
    "gn:population":0,
    "gn:timezone":"Africa/Freetown",
    "iso:country":"SL",
    "name:eng_x_preferred":[
        "Kpemalu"
    ],
    "wof:name":"Kpemalu",
    "wof:placetype":"locality"
},
  "geometry": {"coordinates":[-10.55408,8.29425],"type":"Point"}
}