{
  "type": "Feature",
  "properties": {
    "gn:admin1_code":"3.0",
    "gn:asciiname":"Gbewobu",
    "gn:country_code":"SL",
    "gn:dem":73,
    "gn:feature_class":"P",
    "gn:feature_code":"PPL",
    "gn:name":"Gbewobu",
    "gn:population":0,
    "gn:timezone":"Africa/Freetown",
    "iso:country":"SL",
    "name:eng_x_preferred":[
        "Gbewobu"
    ],
    "wof:name":"Gbewobu",
    "wof:placetype":"locality"
},
  "geometry": {"coordinates":[-12.13214,8.27776],"type":"Point"}
}