{
  "type": "Feature",
  "properties": {
    "gn:admin1_code":"2.0",
    "gn:asciiname":"Gbongba",
    "gn:country_code":"SL",
    "gn:dem":73,
    "gn:feature_class":"P",
    "gn:feature_code":"PPL",
    "gn:name":"Gbongba",
    "gn:population":0,
    "gn:timezone":"Africa/Freetown",
    "iso:country":"SL",
    "name:und_x_variant":[
        "Gbungba",
        "Gbongba"
    ],
    "wof:name":"Gbongba",
    "wof:placetype":"locality"
},
  "geometry": {"coordinates":[-12.30423,8.5531],"type":"Point"}
}