{
  "type": "Feature",
  "properties": {
    "gn:admin1_code":"3.0",
    "gn:asciiname":"Batli",
    "gn:country_code":"SL",
    "gn:dem":9,
    "gn:feature_class":"P",
    "gn:feature_code":"PPL",
    "gn:name":"Batli",
    "gn:population":0,
    "gn:timezone":"Africa/Freetown",
    "iso:country":"SL",
    "name:eng_x_preferred":[
        "Batli"
    ],
    "wof:name":"Batli",
    "wof:placetype":"locality"
},
  "geometry": {"coordinates":[-12.24878,7.58032],"type":"Point"}
}