{
  "type": "Feature",
  "properties": {
    "gn:admin1_code":"1.0",
    "gn:asciiname":"Bosodu",
    "gn:country_code":"SL",
    "gn:dem":537,
    "gn:feature_class":"P",
    "gn:feature_code":"PPL",
    "gn:name":"Bosodu",
    "gn:population":0,
    "gn:timezone":"Africa/Freetown",
    "iso:country":"SL",
    "name:eng_x_preferred":[
        "Bosodu"
    ],
    "wof:name":"Bosodu",
    "wof:placetype":"locality"
},
  "geometry": {"coordinates":[-10.35877,8.35444],"type":"Point"}
}