{
  "type": "Feature",
  "properties": {
    "gn:admin1_code":"1.0",
    "gn:asciiname":"Kudu",
    "gn:country_code":"SL",
    "gn:dem":397,
    "gn:feature_class":"P",
    "gn:feature_code":"PPL",
    "gn:name":"Kudu",
    "gn:population":0,
    "gn:timezone":"Africa/Freetown",
    "iso:country":"SL",
    "name:eng_x_preferred":[
        "Kudu"
    ],
    "wof:name":"Kudu",
    "wof:placetype":"locality"
},
  "geometry": {"coordinates":[-10.36674,8.44967],"type":"Point"}
}