{
  "type": "Feature",
  "properties": {
    "gn:admin1_code":"1.0",
    "gn:asciiname":"Kudu",
    "gn:country_code":"SL",
    "gn:dem":397,
    "gn:feature_class":"P",
    "gn:feature_code":"PPL",
    "gn:name":"Kudu",
    "gn:population":0,
    "gn:timezone":"Africa/Freetown",
    "iso:country":"SL",
    "name:ces_x_preferred":[
        "Kudu"
    ],
    "name:eng_x_preferred":[
        "Kudu"
    ],
    "name:fas_x_preferred":[
        "\u06a9\u0648\u062f\u0648"
    ],
    "name:fra_x_preferred":[
        "Koudou"
    ],
    "name:kaz_x_preferred":[
        "\u041a\u0443\u0434\u0443"
    ],
    "name:lez_x_preferred":[
        "\u041a\u0443\u0434\u0443"
    ],
    "name:msa_x_preferred":[
        "Kudu"
    ],
    "name:por_x_preferred":[
        "Cudo"
    ],
    "wof:name":"Kudu",
    "wof:placetype":"locality"
},
  "geometry": {"coordinates":[-10.36674,8.44967],"type":"Point"}
}