{
  "type": "Feature",
  "properties": {
    "gn:admin1_code":"1.0",
    "gn:asciiname":"Kijehun",
    "gn:country_code":"SL",
    "gn:dem":171,
    "gn:feature_class":"P",
    "gn:feature_code":"PPL",
    "gn:name":"Kijehun",
    "gn:population":0,
    "gn:timezone":"Africa/Freetown",
    "iso:country":"SL",
    "name:eng_x_preferred":[
        "Kijehun"
    ],
    "wof:name":"Kijehun",
    "wof:placetype":"locality"
},
  "geometry": {"coordinates":[-11.00838,7.99298],"type":"Point"}
}