{
  "type": "Feature",
  "properties": {
    "gn:admin1_code":"03",
    "gn:asciiname":"Tangabu",
    "gn:country_code":"SL",
    "gn:dem":12,
    "gn:feature_class":"P",
    "gn:feature_code":"PPL",
    "gn:name":"Tangabu",
    "gn:population":0,
    "gn:timezone":"Africa/Freetown",
    "iso:country":"SL",
    "name:eng_x_preferred":[
        "Tangabu"
    ],
    "wof:name":"Tangabu",
    "wof:placetype":"locality"
},
  "geometry": {"coordinates":[-12.85969,7.5829],"type":"Point"}
}