{
  "type": "Feature",
  "properties": {
    "gn:admin1_code":"1.0",
    "gn:asciiname":"Misila",
    "gn:country_code":"SL",
    "gn:dem":151,
    "gn:feature_class":"P",
    "gn:feature_code":"PPL",
    "gn:name":"Misila",
    "gn:population":0,
    "gn:timezone":"Africa/Freetown",
    "iso:country":"SL",
    "name:eng_x_preferred":[
        "Misila"
    ],
    "wof:name":"Misila",
    "wof:placetype":"locality"
},
  "geometry": {"coordinates":[-11.33282,8.10295],"type":"Point"}
}