{
  "type": "Feature",
  "properties": {
    "gn:admin1_code":"01",
    "gn:asciiname":"Bengema",
    "gn:country_code":"SL",
    "gn:dem":289,
    "gn:feature_class":"P",
    "gn:feature_code":"PPL",
    "gn:name":"Bengema",
    "gn:population":0,
    "gn:timezone":"Africa/Freetown",
    "iso:country":"SL",
    "name:eng_x_preferred":[
        "Bengema"
    ],
    "name:und_x_variant":[
        "Panguma"
    ],
    "wof:name":"Bengema",
    "wof:placetype":"locality"
},
  "geometry": {"coordinates":[-11.54062,8.43413],"type":"Point"}
}