{
  "type": "Feature",
  "properties": {
    "gn:admin1_code":"3.0",
    "gn:asciiname":"Kotumahun",
    "gn:country_code":"SL",
    "gn:dem":105,
    "gn:feature_class":"P",
    "gn:feature_code":"PPL",
    "gn:name":"Kotumahun",
    "gn:population":0,
    "gn:timezone":"Africa/Freetown",
    "iso:country":"SL",
    "name:eng_x_preferred":[
        "Kotumahun"
    ],
    "name:und_x_variant":[
        "Kotomahun"
    ],
    "wof:name":"Kotumahun",
    "wof:placetype":"locality"
},
  "geometry": {"coordinates":[-11.56347,7.85732],"type":"Point"}
}