{
  "type": "Feature",
  "properties": {
    "gn:admin1_code":"03",
    "gn:asciiname":"Panguma",
    "gn:country_code":"SL",
    "gn:dem":58,
    "gn:feature_class":"P",
    "gn:feature_code":"PPL",
    "gn:name":"Panguma",
    "gn:population":0,
    "gn:timezone":"Africa/Freetown",
    "iso:country":"SL",
    "name:eng_x_preferred":[
        "Panguma"
    ],
    "name:fin_x_preferred":[
        "Panguma"
    ],
    "name:haw_x_preferred":[
        "Panguma"
    ],
    "wof:name":"Panguma",
    "wof:placetype":"locality"
},
  "geometry": {"coordinates":[-11.79354,7.5248],"type":"Point"}
}