{
  "type": "Feature",
  "properties": {
    "gn:admin1_code":"3.0",
    "gn:asciiname":"Taiamawo",
    "gn:country_code":"SL",
    "gn:dem":17,
    "gn:feature_class":"P",
    "gn:feature_code":"PPL",
    "gn:name":"Taiamawo",
    "gn:population":0,
    "gn:timezone":"Africa/Freetown",
    "iso:country":"SL",
    "name:eng_x_preferred":[
        "Taiamawo"
    ],
    "wof:name":"Taiamawo",
    "wof:placetype":"locality"
},
  "geometry": {"coordinates":[-12.86855,7.85625],"type":"Point"}
}