{
  "type": "Feature",
  "properties": {
    "gn:admin1_code":"1.0",
    "gn:asciiname":"Fandu",
    "gn:country_code":"SL",
    "gn:dem":425,
    "gn:feature_class":"P",
    "gn:feature_code":"PPL",
    "gn:name":"Fandu",
    "gn:population":0,
    "gn:timezone":"Africa/Freetown",
    "iso:country":"SL",
    "name:eng_x_preferred":[
        "Fandu"
    ],
    "wof:name":"Fandu",
    "wof:placetype":"locality"
},
  "geometry": {"coordinates":[-10.30444,8.40679],"type":"Point"}
}