{
  "type": "Feature",
  "properties": {
    "gn:admin1_code":"1.0",
    "gn:asciiname":"Levuma",
    "gn:country_code":"SL",
    "gn:dem":181,
    "gn:feature_class":"P",
    "gn:feature_code":"PPL",
    "gn:name":"Levuma",
    "gn:population":0,
    "gn:timezone":"Africa/Freetown",
    "iso:country":"SL",
    "name:und_x_variant":[
        "Levume",
        "Levuma"
    ],
    "wof:name":"Levuma",
    "wof:placetype":"locality"
},
  "geometry": {"coordinates":[-10.66813,7.75258],"type":"Point"}
}