{
  "type": "Feature",
  "properties": {
    "gn:admin1_code":"02",
    "gn:asciiname":"Tambi",
    "gn:country_code":"SL",
    "gn:dem":63,
    "gn:feature_class":"P",
    "gn:feature_code":"PPL",
    "gn:name":"Tambi",
    "gn:population":0,
    "gn:timezone":"Africa/Freetown",
    "iso:country":"SL",
    "name:eng_x_preferred":[
        "Tambi"
    ],
    "name:fra_x_preferred":[
        "Tambi"
    ],
    "name:msa_x_preferred":[
        "Tambi"
    ],
    "wof:name":"Tambi",
    "wof:placetype":"locality"
},
  "geometry": {"coordinates":[-12.42407,9.47549],"type":"Point"}
}