{
  "type": "Feature",
  "properties": {
    "gn:admin1_code":"3.0",
    "gn:asciiname":"Mokarikon",
    "gn:country_code":"SL",
    "gn:dem":44,
    "gn:feature_class":"P",
    "gn:feature_code":"PPL",
    "gn:name":"Mokarikon",
    "gn:population":0,
    "gn:timezone":"Africa/Freetown",
    "iso:country":"SL",
    "name:eng_x_preferred":[
        "Mokarikon"
    ],
    "wof:name":"Mokarikon",
    "wof:placetype":"locality"
},
  "geometry": {"coordinates":[-12.72671,8.30201],"type":"Point"}
}