{
  "type": "Feature",
  "properties": {
    "gn:admin1_code":"1.0",
    "gn:asciiname":"Baoma",
    "gn:country_code":"SL",
    "gn:dem":387,
    "gn:feature_class":"P",
    "gn:feature_code":"PPL",
    "gn:name":"Baoma",
    "gn:population":0,
    "gn:timezone":"Africa/Freetown",
    "iso:country":"SL",
    "name:eng_x_preferred":[
        "Baoma"
    ],
    "wof:name":"Baoma",
    "wof:placetype":"locality"
},
  "geometry": {"coordinates":[-10.39375,8.29042],"type":"Point"}
}