{
  "type": "Feature",
  "properties": {
    "gn:admin1_code":"1.0",
    "gn:asciiname":"Sakiema",
    "gn:country_code":"SL",
    "gn:dem":190,
    "gn:feature_class":"P",
    "gn:feature_code":"PPL",
    "gn:name":"Sakiema",
    "gn:population":0,
    "gn:timezone":"Africa/Freetown",
    "iso:country":"SL",
    "name:eng_x_preferred":[
        "Sakiema"
    ],
    "wof:name":"Sakiema",
    "wof:placetype":"locality"
},
  "geometry": {"coordinates":[-10.92193,8.08476],"type":"Point"}
}