{
  "type": "Feature",
  "properties": {
    "gn:admin1_code":"2.0",
    "gn:asciiname":"Malambe",
    "gn:country_code":"SL",
    "gn:dem":30,
    "gn:feature_class":"P",
    "gn:feature_code":"PPL",
    "gn:name":"Malambe",
    "gn:population":0,
    "gn:timezone":"Africa/Freetown",
    "iso:country":"SL",
    "name:eng_x_preferred":[
        "Malambe"
    ],
    "wof:name":"Malambe",
    "wof:placetype":"locality"
},
  "geometry": {"coordinates":[-12.97392,8.89008],"type":"Point"}
}