{
  "type": "Feature",
  "properties": {
    "gn:admin1_code":"2.0",
    "gn:asciiname":"Yongro",
    "gn:country_code":"SL",
    "gn:dem":29,
    "gn:feature_class":"P",
    "gn:feature_code":"PPL",
    "gn:name":"Yongro",
    "gn:population":0,
    "gn:timezone":"Africa/Freetown",
    "iso:country":"SL",
    "name:eng_x_preferred":[
        "Yongro"
    ],
    "wof:name":"Yongro",
    "wof:placetype":"locality"
},
  "geometry": {"coordinates":[-12.99906,9.00514],"type":"Point"}
}