{
  "type": "Feature",
  "properties": {
    "gn:admin1_code":"2.0",
    "gn:asciiname":"Matarua",
    "gn:country_code":"SL",
    "gn:dem":113,
    "gn:feature_class":"P",
    "gn:feature_code":"PPL",
    "gn:name":"Matarua",
    "gn:population":0,
    "gn:timezone":"Africa/Freetown",
    "iso:country":"SL",
    "name:eng_x_preferred":[
        "Matarua"
    ],
    "wof:name":"Matarua",
    "wof:placetype":"locality"
},
  "geometry": {"coordinates":[-12.11696,9.13528],"type":"Point"}
}