{
  "type": "Feature",
  "properties": {
    "gn:admin1_code":"1.0",
    "gn:asciiname":"Vaama",
    "gn:country_code":"SL",
    "gn:dem":224,
    "gn:feature_class":"P",
    "gn:feature_code":"PPL",
    "gn:name":"Vaama",
    "gn:population":0,
    "gn:timezone":"Africa/Freetown",
    "iso:country":"SL",
    "name:eng_x_preferred":[
        "Vaama"
    ],
    "wof:name":"Vaama",
    "wof:placetype":"locality"
},
  "geometry": {"coordinates":[-10.91508,7.79024],"type":"Point"}
}