{
  "type": "Feature",
  "properties": {
    "gn:admin1_code":"01",
    "gn:asciiname":"Yokodu",
    "gn:country_code":"SL",
    "gn:dem":393,
    "gn:feature_class":"P",
    "gn:feature_code":"PPL",
    "gn:name":"Yokodu",
    "gn:population":0,
    "gn:timezone":"Africa/Freetown",
    "iso:country":"SL",
    "name:eng_x_preferred":[
        "Yokodu"
    ],
    "wof:name":"Yokodu",
    "wof:placetype":"locality"
},
  "geometry": {"coordinates":[-11.02946,8.78197],"type":"Point"}
}