{
  "type": "Feature",
  "properties": {
    "gn:admin1_code":"3.0",
    "gn:asciiname":"Towobu",
    "gn:country_code":"SL",
    "gn:dem":51,
    "gn:feature_class":"P",
    "gn:feature_code":"PPL",
    "gn:name":"Towobu",
    "gn:population":0,
    "gn:timezone":"Africa/Freetown",
    "iso:country":"SL",
    "name:eng_x_preferred":[
        "Towobu"
    ],
    "wof:name":"Towobu",
    "wof:placetype":"locality"
},
  "geometry": {"coordinates":[-12.37567,8.07625],"type":"Point"}
}