{
  "type": "Feature",
  "properties": {
    "gn:admin1_code":"01",
    "gn:asciiname":"Punduru",
    "gn:country_code":"SL",
    "gn:dem":287,
    "gn:feature_class":"P",
    "gn:feature_code":"PPL",
    "gn:name":"Punduru",
    "gn:population":0,
    "gn:timezone":"Africa/Freetown",
    "iso:country":"SL",
    "name:eng_x_preferred":[
        "Punduru"
    ],
    "wof:name":"Punduru",
    "wof:placetype":"locality"
},
  "geometry": {"coordinates":[-11.2874,8.48673],"type":"Point"}
}