{
  "type": "Feature",
  "properties": {
    "gn:admin1_code":"3.0",
    "gn:asciiname":"Jawonga",
    "gn:country_code":"SL",
    "gn:dem":216,
    "gn:feature_class":"P",
    "gn:feature_code":"PPL",
    "gn:name":"Jawonga",
    "gn:population":0,
    "gn:timezone":"Africa/Freetown",
    "iso:country":"SL",
    "name:eng_x_preferred":[
        "Jawonga"
    ],
    "wof:name":"Jawonga",
    "wof:placetype":"locality"
},
  "geometry": {"coordinates":[-11.74599,8.2465],"type":"Point"}
}