{
  "type": "Feature",
  "properties": {
    "gn:admin1_code":"4.0",
    "gn:asciiname":"Angola Town",
    "gn:country_code":"SL",
    "gn:dem":14,
    "gn:feature_class":"P",
    "gn:feature_code":"PPL",
    "gn:name":"Angola Town",
    "gn:population":0,
    "gn:timezone":"Africa/Freetown",
    "iso:country":"SL",
    "name:und_x_variant":[
        "Angola",
        "Angola Town"
    ],
    "wof:name":"Angola Town",
    "wof:placetype":"locality"
},
  "geometry": {"coordinates":[-13.26386,8.41208],"type":"Point"}
}