{
  "type": "Feature",
  "properties": {
    "gn:admin1_code":"2.0",
    "gn:asciiname":"Malua",
    "gn:country_code":"SL",
    "gn:dem":54,
    "gn:feature_class":"P",
    "gn:feature_code":"PPL",
    "gn:name":"Malua",
    "gn:population":0,
    "gn:timezone":"Africa/Freetown",
    "iso:country":"SL",
    "name:ceb_x_preferred":[
        "Malua"
    ],
    "name:eng_x_preferred":[
        "Malua"
    ],
    "wof:name":"Malua",
    "wof:placetype":"locality"
},
  "geometry": {"coordinates":[-12.6288,8.67152],"type":"Point"}
}