{
  "type": "Feature",
  "properties": {
    "gn:admin1_code":"2.0",
    "gn:asciiname":"Dalmusaia",
    "gn:country_code":"SL",
    "gn:dem":466,
    "gn:feature_class":"P",
    "gn:feature_code":"PPL",
    "gn:name":"Dalmusaia",
    "gn:population":0,
    "gn:timezone":"Africa/Freetown",
    "iso:country":"SL",
    "name:eng_x_preferred":[
        "Dalmusaia"
    ],
    "wof:name":"Dalmusaia",
    "wof:placetype":"locality"
},
  "geometry": {"coordinates":[-11.21861,9.78702],"type":"Point"}
}