{
  "type": "Feature",
  "properties": {
    "gn:admin1_code":"01",
    "gn:asciiname":"Sawula",
    "gn:country_code":"SL",
    "gn:dem":298,
    "gn:feature_class":"P",
    "gn:feature_code":"PPL",
    "gn:name":"Sawula",
    "gn:population":0,
    "gn:timezone":"Africa/Freetown",
    "iso:country":"SL",
    "name:eng_x_preferred":[
        "Sawula"
    ],
    "wof:name":"Sawula",
    "wof:placetype":"locality"
},
  "geometry": {"coordinates":[-10.87975,8.50895],"type":"Point"}
}