{
  "type": "Feature",
  "properties": {
    "gn:admin1_code":"2.0",
    "gn:asciiname":"Kulia",
    "gn:country_code":"SL",
    "gn:dem":358,
    "gn:feature_class":"P",
    "gn:feature_code":"PPL",
    "gn:name":"Kulia",
    "gn:population":0,
    "gn:timezone":"Africa/Freetown",
    "iso:country":"SL",
    "name:eng_x_preferred":[
        "Kulia"
    ],
    "wof:name":"Kulia",
    "wof:placetype":"locality"
},
  "geometry": {"coordinates":[-11.25015,9.05018],"type":"Point"}
}