{
  "type": "Feature",
  "properties": {
    "gn:admin1_code":"3.0",
    "gn:asciiname":"Kamasu",
    "gn:country_code":"SL",
    "gn:dem":15,
    "gn:feature_class":"P",
    "gn:feature_code":"PPL",
    "gn:name":"Kamasu",
    "gn:population":0,
    "gn:timezone":"Africa/Freetown",
    "iso:country":"SL",
    "name:eng_x_preferred":[
        "Kamasu"
    ],
    "wof:name":"Kamasu",
    "wof:placetype":"locality"
},
  "geometry": {"coordinates":[-11.97086,7.32375],"type":"Point"}
}