{
  "type": "Feature",
  "properties": {
    "gn:admin1_code":"1.0",
    "gn:asciiname":"Yawuema",
    "gn:country_code":"SL",
    "gn:dem":136,
    "gn:feature_class":"P",
    "gn:feature_code":"PPL",
    "gn:name":"Yawuema",
    "gn:population":0,
    "gn:timezone":"Africa/Freetown",
    "iso:country":"SL",
    "name:eng_x_preferred":[
        "Yawuema"
    ],
    "wof:name":"Yawuema",
    "wof:placetype":"locality"
},
  "geometry": {"coordinates":[-11.33618,7.85627],"type":"Point"}
}