{
  "type": "Feature",
  "properties": {
    "gn:admin1_code":"02",
    "gn:asciiname":"Rogbom",
    "gn:country_code":"SL",
    "gn:dem":8,
    "gn:feature_class":"P",
    "gn:feature_code":"PPL",
    "gn:name":"Rogbom",
    "gn:population":0,
    "gn:timezone":"Africa/Freetown",
    "iso:country":"SL",
    "name:und_x_variant":[
        "Rogbam",
        "Rogbom"
    ],
    "wof:name":"Rogbom",
    "wof:placetype":"locality"
},
  "geometry": {"coordinates":[-13.12776,8.87427],"type":"Point"}
}