{
  "type": "Feature",
  "properties": {
    "gn:admin1_code":"2.0",
    "gn:asciiname":"Ganya",
    "gn:country_code":"SL",
    "gn:dem":162,
    "gn:feature_class":"P",
    "gn:feature_code":"PPL",
    "gn:name":"Ganya",
    "gn:population":0,
    "gn:timezone":"Africa/Freetown",
    "iso:country":"SL",
    "name:eng_x_preferred":[
        "Ganya"
    ],
    "wof:name":"Ganya",
    "wof:placetype":"locality"
},
  "geometry": {"coordinates":[-12.23824,9.89259],"type":"Point"}
}