{
  "type": "Feature",
  "properties": {
    "gn:admin1_code":"3.0",
    "gn:asciiname":"Tokpombu",
    "gn:country_code":"SL",
    "gn:dem":70,
    "gn:feature_class":"P",
    "gn:feature_code":"PPL",
    "gn:name":"Tokpombu",
    "gn:population":0,
    "gn:timezone":"Africa/Freetown",
    "iso:country":"SL",
    "name:eng_x_preferred":[
        "Tokpombu"
    ],
    "wof:name":"Tokpombu",
    "wof:placetype":"locality"
},
  "geometry": {"coordinates":[-12.24931,8.32616],"type":"Point"}
}