{
  "type": "Feature",
  "properties": {
    "gn:admin1_code":"3.0",
    "gn:asciiname":"Moyogbo",
    "gn:country_code":"SL",
    "gn:dem":17,
    "gn:feature_class":"P",
    "gn:feature_code":"PPL",
    "gn:name":"Moyogbo",
    "gn:population":0,
    "gn:timezone":"Africa/Freetown",
    "iso:country":"SL",
    "name:eng_x_preferred":[
        "Moyogbo"
    ],
    "wof:name":"Moyogbo",
    "wof:placetype":"locality"
},
  "geometry": {"coordinates":[-12.09558,7.53653],"type":"Point"}
}