{
  "type": "Feature",
  "properties": {
    "gn:admin1_code":"4.0",
    "gn:asciiname":"Ma-mari",
    "gn:country_code":"SL",
    "gn:dem":11,
    "gn:feature_class":"P",
    "gn:feature_code":"PPL",
    "gn:name":"Ma-mari",
    "gn:population":0,
    "gn:timezone":"Africa/Freetown",
    "iso:country":"SL",
    "wof:name":"Ma-mari",
    "wof:placetype":"locality"
},
  "geometry": {"coordinates":[-12.95,8.33333],"type":"Point"}
}