{
  "type": "Feature",
  "properties": {
    "gn:admin1_code":"1.0",
    "gn:asciiname":"Gboyama",
    "gn:country_code":"SL",
    "gn:dem":324,
    "gn:feature_class":"P",
    "gn:feature_code":"PPL",
    "gn:name":"Gboyama",
    "gn:population":0,
    "gn:timezone":"Africa/Freetown",
    "iso:country":"SL",
    "name:eng_x_preferred":[
        "Gboyama"
    ],
    "wof:name":"Gboyama",
    "wof:placetype":"locality"
},
  "geometry": {"coordinates":[-10.72037,8.28393],"type":"Point"}
}