{
  "type": "Feature",
  "properties": {
    "gn:admin1_code":"3.0",
    "gn:asciiname":"Bowala",
    "gn:country_code":"SL",
    "gn:dem":46,
    "gn:feature_class":"P",
    "gn:feature_code":"PPL",
    "gn:name":"Bowala",
    "gn:population":0,
    "gn:timezone":"Africa/Freetown",
    "iso:country":"SL",
    "name:ceb_x_preferred":[
        "Bowala"
    ],
    "name:eng_x_preferred":[
        "Bowala"
    ],
    "name:swe_x_preferred":[
        "Bowala"
    ],
    "wof:name":"Bowala",
    "wof:placetype":"locality"
},
  "geometry": {"coordinates":[-12.184,7.92506],"type":"Point"}
}