{
  "type": "Feature",
  "properties": {
    "gn:admin1_code":"2.0",
    "gn:asciiname":"Yomboro Sansunkolia",
    "gn:country_code":"SL",
    "gn:dem":101,
    "gn:feature_class":"P",
    "gn:feature_code":"PPL",
    "gn:name":"Yomboro Sansunkolia",
    "gn:population":0,
    "gn:timezone":"Africa/Freetown",
    "iso:country":"SL",
    "name:eng_x_preferred":[
        "Yomboro Sansunkolia"
    ],
    "wof:name":"Yomboro Sansunkolia",
    "wof:placetype":"locality"
},
  "geometry": {"coordinates":[-12.63464,9.49475],"type":"Point"}
}