{
  "type": "Feature",
  "properties": {
    "gn:admin1_code":"3.0",
    "gn:asciiname":"Shenge",
    "gn:country_code":"SL",
    "gn:dem":23,
    "gn:feature_class":"P",
    "gn:feature_code":"PPL",
    "gn:name":"Shenge",
    "gn:population":0,
    "gn:timezone":"Africa/Freetown",
    "iso:country":"SL",
    "name:eng_x_preferred":[
        "Shenge"
    ],
    "wof:name":"Shenge",
    "wof:placetype":"locality"
},
  "geometry": {"coordinates":[-12.00425,7.66535],"type":"Point"}
}