{
  "type": "Feature",
  "properties": {
    "gn:admin1_code":"2.0",
    "gn:asciiname":"Durukoro",
    "gn:country_code":"SL",
    "gn:dem":736,
    "gn:feature_class":"P",
    "gn:feature_code":"PPL",
    "gn:name":"Durukoro",
    "gn:population":0,
    "gn:timezone":"Africa/Freetown",
    "iso:country":"SL",
    "name:eng_x_preferred":[
        "Durukoro"
    ],
    "wof:name":"Durukoro",
    "wof:placetype":"locality"
},
  "geometry": {"coordinates":[-10.7286,9.01281],"type":"Point"}
}