{
  "type": "Feature",
  "properties": {
    "gn:admin1_code":"3.0",
    "gn:asciiname":"Selehun",
    "gn:country_code":"SL",
    "gn:dem":100,
    "gn:feature_class":"P",
    "gn:feature_code":"PPL",
    "gn:name":"Selehun",
    "gn:population":0,
    "gn:timezone":"Africa/Freetown",
    "iso:country":"SL",
    "name:eng_x_preferred":[
        "Selehun"
    ],
    "wof:name":"Selehun",
    "wof:placetype":"locality"
},
  "geometry": {"coordinates":[-11.79846,7.8744],"type":"Point"}
}