{
  "type": "Feature",
  "properties": {
    "gn:admin1_code":"2.0",
    "gn:asciiname":"Gbap",
    "gn:country_code":"SL",
    "gn:dem":25,
    "gn:feature_class":"P",
    "gn:feature_code":"PPL",
    "gn:name":"Gbap",
    "gn:population":0,
    "gn:timezone":"Africa/Freetown",
    "iso:country":"SL",
    "name:eng_x_preferred":[
        "Gbap"
    ],
    "wof:name":"Gbap",
    "wof:placetype":"locality"
},
  "geometry": {"coordinates":[-13.04262,8.43759],"type":"Point"}
}