{
  "type": "Feature",
  "properties": {
    "gn:admin1_code":"2.0",
    "gn:asciiname":"Tawfayim",
    "gn:country_code":"SL",
    "gn:dem":26,
    "gn:feature_class":"P",
    "gn:feature_code":"PPL",
    "gn:name":"Tawfayim",
    "gn:population":0,
    "gn:timezone":"Africa/Freetown",
    "iso:country":"SL",
    "name:eng_x_preferred":[
        "Tawfayim"
    ],
    "wof:name":"Tawfayim",
    "wof:placetype":"locality"
},
  "geometry": {"coordinates":[-12.84894,8.72207],"type":"Point"}
}