{
  "type": "Feature",
  "properties": {
    "gn:admin1_code":"1.0",
    "gn:asciiname":"Jaluahun",
    "gn:country_code":"SL",
    "gn:dem":204,
    "gn:feature_class":"P",
    "gn:feature_code":"PPL",
    "gn:name":"Jaluahun",
    "gn:population":0,
    "gn:timezone":"Africa/Freetown",
    "iso:country":"SL",
    "name:eng_x_preferred":[
        "Jaluahun"
    ],
    "wof:name":"Jaluahun",
    "wof:placetype":"locality"
},
  "geometry": {"coordinates":[-10.91179,8.02697],"type":"Point"}
}