{
  "type": "Feature",
  "properties": {
    "gn:admin1_code":"3.0",
    "gn:asciiname":"Barbo",
    "gn:country_code":"SL",
    "gn:dem":13,
    "gn:feature_class":"P",
    "gn:feature_code":"PPL",
    "gn:name":"Barbo",
    "gn:population":0,
    "gn:timezone":"Africa/Freetown",
    "iso:country":"SL",
    "name:eng_x_preferred":[
        "Barbo"
    ],
    "name:und_x_variant":[
        "Babu"
    ],
    "wof:name":"Barbo",
    "wof:placetype":"locality"
},
  "geometry": {"coordinates":[-12.45812,7.44606],"type":"Point"}
}