{
  "type": "Feature",
  "properties": {
    "gn:admin1_code":"2.0",
    "gn:asciiname":"Mayesl",
    "gn:country_code":"SL",
    "gn:dem":78,
    "gn:feature_class":"P",
    "gn:feature_code":"PPL",
    "gn:name":"Mayesl",
    "gn:population":0,
    "gn:timezone":"Africa/Freetown",
    "iso:country":"SL",
    "name:eng_x_preferred":[
        "Mayesl"
    ],
    "wof:name":"Mayesl",
    "wof:placetype":"locality"
},
  "geometry": {"coordinates":[-11.9518,8.47024],"type":"Point"}
}