{
  "type": "Feature",
  "properties": {
    "gn:admin1_code":"1.0",
    "gn:asciiname":"Gigbema",
    "gn:country_code":"SL",
    "gn:dem":229,
    "gn:feature_class":"P",
    "gn:feature_code":"PPL",
    "gn:name":"Gigbema",
    "gn:population":0,
    "gn:timezone":"Africa/Freetown",
    "iso:country":"SL",
    "name:eng_x_preferred":[
        "Gigbema"
    ],
    "wof:name":"Gigbema",
    "wof:placetype":"locality"
},
  "geometry": {"coordinates":[-10.64218,8.10622],"type":"Point"}
}