{
  "type": "Feature",
  "properties": {
    "gn:admin1_code":"3.0",
    "gn:asciiname":"Kpakala",
    "gn:country_code":"SL",
    "gn:dem":56,
    "gn:feature_class":"P",
    "gn:feature_code":"PPL",
    "gn:name":"Kpakala",
    "gn:population":0,
    "gn:timezone":"Africa/Freetown",
    "iso:country":"SL",
    "name:eng_x_preferred":[
        "Kpakala"
    ],
    "wof:name":"Kpakala",
    "wof:placetype":"locality"
},
  "geometry": {"coordinates":[-11.38873,7.11908],"type":"Point"}
}