{
  "type": "Feature",
  "properties": {
    "gn:admin1_code":"1.0",
    "gn:asciiname":"Gumahun",
    "gn:country_code":"SL",
    "gn:dem":171,
    "gn:feature_class":"P",
    "gn:feature_code":"PPL",
    "gn:name":"Gumahun",
    "gn:population":0,
    "gn:timezone":"Africa/Freetown",
    "iso:country":"SL",
    "name:eng_x_preferred":[
        "Gumahun"
    ],
    "wof:name":"Gumahun",
    "wof:placetype":"locality"
},
  "geometry": {"coordinates":[-11.14764,7.88665],"type":"Point"}
}