{
  "type": "Feature",
  "properties": {
    "gn:admin1_code":"3.0",
    "gn:asciiname":"Pambela",
    "gn:country_code":"SL",
    "gn:dem":57,
    "gn:feature_class":"P",
    "gn:feature_code":"PPL",
    "gn:name":"Pambela",
    "gn:population":0,
    "gn:timezone":"Africa/Freetown",
    "iso:country":"SL",
    "name:eng_x_preferred":[
        "Pambela"
    ],
    "wof:name":"Pambela",
    "wof:placetype":"locality"
},
  "geometry": {"coordinates":[-12.07138,8.06226],"type":"Point"}
}