{
  "type": "Feature",
  "properties": {
    "gn:admin1_code":"3.0",
    "gn:asciiname":"Tuhe",
    "gn:country_code":"SL",
    "gn:dem":8,
    "gn:feature_class":"P",
    "gn:feature_code":"PPL",
    "gn:name":"Tuhe",
    "gn:population":0,
    "gn:timezone":"Africa/Freetown",
    "iso:country":"SL",
    "name:eng_x_preferred":[
        "Tuhe"
    ],
    "wof:name":"Tuhe",
    "wof:placetype":"locality"
},
  "geometry": {"coordinates":[-12.73442,7.54706],"type":"Point"}
}