{
  "type": "Feature",
  "properties": {
    "gn:admin1_code":"1.0",
    "gn:asciiname":"Manuwulo",
    "gn:country_code":"SL",
    "gn:dem":141,
    "gn:feature_class":"P",
    "gn:feature_code":"PPL",
    "gn:name":"Manuwulo",
    "gn:population":0,
    "gn:timezone":"Africa/Freetown",
    "iso:country":"SL",
    "name:eng_x_preferred":[
        "Manuwulo"
    ],
    "wof:name":"Manuwulo",
    "wof:placetype":"locality"
},
  "geometry": {"coordinates":[-11.36259,7.85439],"type":"Point"}
}