{
  "type": "Feature",
  "properties": {
    "gn:admin1_code":"1.0",
    "gn:asciiname":"Meama",
    "gn:country_code":"SL",
    "gn:dem":401,
    "gn:feature_class":"P",
    "gn:feature_code":"PPL",
    "gn:name":"Meama",
    "gn:population":0,
    "gn:timezone":"Africa/Freetown",
    "iso:country":"SL",
    "name:ceb_x_preferred":[
        "Meama"
    ],
    "name:eng_x_preferred":[
        "Meama"
    ],
    "name:ton_x_preferred":[
        "Meama"
    ],
    "wof:name":"Meama",
    "wof:placetype":"locality"
},
  "geometry": {"coordinates":[-10.94105,8.62216],"type":"Point"}
}