{
  "type": "Feature",
  "properties": {
    "gn:admin1_code":"3.0",
    "gn:asciiname":"Moshenge",
    "gn:country_code":"SL",
    "gn:dem":63,
    "gn:feature_class":"P",
    "gn:feature_code":"PPL",
    "gn:name":"Moshenge",
    "gn:population":0,
    "gn:timezone":"Africa/Freetown",
    "iso:country":"SL",
    "name:eng_x_preferred":[
        "Moshenge"
    ],
    "name:und_x_variant":[
        "Mosenge"
    ],
    "wof:name":"Moshenge",
    "wof:placetype":"locality"
},
  "geometry": {"coordinates":[-12.10054,8.21809],"type":"Point"}
}