{
  "type": "Feature",
  "properties": {
    "gn:admin1_code":"2.0",
    "gn:asciiname":"Maba-in",
    "gn:country_code":"SL",
    "gn:dem":44,
    "gn:feature_class":"P",
    "gn:feature_code":"PPL",
    "gn:name":"Maba-in",
    "gn:population":0,
    "gn:timezone":"Africa/Freetown",
    "iso:country":"SL",
    "name:eng_x_preferred":[
        "Maba-in"
    ],
    "wof:name":"Maba-in",
    "wof:placetype":"locality"
},
  "geometry": {"coordinates":[-12.94832,9.05755],"type":"Point"}
}