{
  "type": "Feature",
  "properties": {
    "gn:admin1_code":"2.0",
    "gn:asciiname":"Fentikhuri",
    "gn:country_code":"SL",
    "gn:dem":151,
    "gn:feature_class":"P",
    "gn:feature_code":"PPL",
    "gn:name":"Fentikhuri",
    "gn:population":0,
    "gn:timezone":"Africa/Freetown",
    "iso:country":"SL",
    "name:und_x_variant":[
        "Fentikhura",
        "Fentikhuri"
    ],
    "wof:name":"Fentikhuri",
    "wof:placetype":"locality"
},
  "geometry": {"coordinates":[-12.22536,9.87129],"type":"Point"}
}