{
  "type": "Feature",
  "properties": {
    "gn:admin1_code":"1.0",
    "gn:asciiname":"Kamdadu",
    "gn:country_code":"SL",
    "gn:dem":657,
    "gn:feature_class":"P",
    "gn:feature_code":"PPL",
    "gn:name":"Kamdadu",
    "gn:population":0,
    "gn:timezone":"Africa/Freetown",
    "iso:country":"SL",
    "name:eng_x_preferred":[
        "Kamdadu"
    ],
    "name:und_x_variant":[
        "Kembadu"
    ],
    "wof:name":"Kamdadu",
    "wof:placetype":"locality"
},
  "geometry": {"coordinates":[-11.10852,8.58768],"type":"Point"}
}