{
  "type": "Feature",
  "properties": {
    "gn:admin1_code":"1.0",
    "gn:asciiname":"Sefula",
    "gn:country_code":"SL",
    "gn:dem":137,
    "gn:feature_class":"P",
    "gn:feature_code":"PPL",
    "gn:name":"Sefula",
    "gn:population":0,
    "gn:timezone":"Africa/Freetown",
    "iso:country":"SL",
    "name:eng_x_preferred":[
        "Sefula"
    ],
    "wof:name":"Sefula",
    "wof:placetype":"locality"
},
  "geometry": {"coordinates":[-11.21277,7.47971],"type":"Point"}
}