{
  "type": "Feature",
  "properties": {
    "gn:admin1_code":"2.0",
    "gn:asciiname":"Fadugu",
    "gn:country_code":"SL",
    "gn:dem":305,
    "gn:feature_class":"P",
    "gn:feature_code":"PPL",
    "gn:name":"Fadugu",
    "gn:population":0,
    "gn:timezone":"Africa/Freetown",
    "iso:country":"SL",
    "name:eng_x_preferred":[
        "Fadugu"
    ],
    "wof:name":"Fadugu",
    "wof:placetype":"locality"
},
  "geometry": {"coordinates":[-11.76737,9.39092],"type":"Point"}
}