{
  "type": "Feature",
  "properties": {
    "gn:admin1_code":"2.0",
    "gn:asciiname":"Gbinti",
    "gn:country_code":"SL",
    "gn:dem":16,
    "gn:feature_class":"P",
    "gn:feature_code":"PPL",
    "gn:name":"Gbinti",
    "gn:population":0,
    "gn:timezone":"Africa/Freetown",
    "iso:country":"SL",
    "name:eng_x_preferred":[
        "Gbinti"
    ],
    "wof:name":"Gbinti",
    "wof:placetype":"locality"
},
  "geometry": {"coordinates":[-12.76263,8.59629],"type":"Point"}
}