{
  "type": "Feature",
  "properties": {
    "gn:admin1_code":"2.0",
    "gn:asciiname":"Kulakoya",
    "gn:country_code":"SL",
    "gn:dem":652,
    "gn:feature_class":"P",
    "gn:feature_code":"PPL",
    "gn:name":"Kulakoya",
    "gn:population":0,
    "gn:timezone":"Africa/Freetown",
    "iso:country":"SL",
    "name:eng_x_preferred":[
        "Kulakoya"
    ],
    "wof:name":"Kulakoya",
    "wof:placetype":"locality"
},
  "geometry": {"coordinates":[-10.69111,9.22295],"type":"Point"}
}