{
  "type": "Feature",
  "properties": {
    "gn:admin1_code":"3.0",
    "gn:asciiname":"Tolobu",
    "gn:country_code":"SL",
    "gn:dem":46,
    "gn:feature_class":"P",
    "gn:feature_code":"PPL",
    "gn:name":"Tolobu",
    "gn:population":0,
    "gn:timezone":"Africa/Freetown",
    "iso:country":"SL",
    "name:eng_x_preferred":[
        "Tolobu"
    ],
    "wof:name":"Tolobu",
    "wof:placetype":"locality"
},
  "geometry": {"coordinates":[-11.67908,7.38313],"type":"Point"}
}