{
  "type": "Feature",
  "properties": {
    "gn:admin1_code":"4.0",
    "gn:asciiname":"Mayenkineh",
    "gn:country_code":"SL",
    "gn:dem":184,
    "gn:feature_class":"P",
    "gn:feature_code":"PPL",
    "gn:name":"Mayenkineh",
    "gn:population":0,
    "gn:timezone":"Africa/Freetown",
    "iso:country":"SL",
    "name:eng_x_preferred":[
        "Mayenkineh"
    ],
    "wof:name":"Mayenkineh",
    "wof:placetype":"locality"
},
  "geometry": {"coordinates":[-13.1724,8.42652],"type":"Point"}
}