{
  "type": "Feature",
  "properties": {
    "gn:admin1_code":"3.0",
    "gn:asciiname":"Falaba",
    "gn:country_code":"SL",
    "gn:dem":61,
    "gn:feature_class":"P",
    "gn:feature_code":"PPL",
    "gn:name":"Falaba",
    "gn:population":0,
    "gn:timezone":"Africa/Freetown",
    "iso:country":"SL",
    "name:eng_x_preferred":[
        "Falaba"
    ],
    "wof:name":"Falaba",
    "wof:placetype":"locality"
},
  "geometry": {"coordinates":[-11.52828,7.41838],"type":"Point"}
}