{
  "type": "Feature",
  "properties": {
    "gn:admin1_code":"2.0",
    "gn:asciiname":"Makinkihe",
    "gn:country_code":"SL",
    "gn:dem":61,
    "gn:feature_class":"P",
    "gn:feature_code":"PPL",
    "gn:name":"Makinkihe",
    "gn:population":0,
    "gn:timezone":"Africa/Freetown",
    "iso:country":"SL",
    "name:eng_x_preferred":[
        "Makinkihe"
    ],
    "wof:name":"Makinkihe",
    "wof:placetype":"locality"
},
  "geometry": {"coordinates":[-12.40888,8.95913],"type":"Point"}
}