{
  "type": "Feature",
  "properties": {
    "gn:admin1_code":"2.0",
    "gn:asciiname":"Bakelimri",
    "gn:country_code":"SL",
    "gn:dem":8,
    "gn:feature_class":"P",
    "gn:feature_code":"PPL",
    "gn:name":"Bakelimri",
    "gn:population":0,
    "gn:timezone":"Africa/Freetown",
    "iso:country":"SL",
    "name:und_x_variant":[
        "Bekolimri",
        "Bakelimri"
    ],
    "wof:name":"Bakelimri",
    "wof:placetype":"locality"
},
  "geometry": {"coordinates":[-13.07288,8.85175],"type":"Point"}
}