{
  "type": "Feature",
  "properties": {
    "gn:admin1_code":"2.0",
    "gn:asciiname":"Basia",
    "gn:country_code":"SL",
    "gn:dem":377,
    "gn:feature_class":"P",
    "gn:feature_code":"PPL",
    "gn:name":"Basia",
    "gn:population":0,
    "gn:timezone":"Africa/Freetown",
    "iso:country":"SL",
    "name:eng_x_preferred":[
        "Basia"
    ],
    "wof:name":"Basia",
    "wof:placetype":"locality"
},
  "geometry": {"coordinates":[-11.50468,8.56964],"type":"Point"}
}