{
  "type": "Feature",
  "properties": {
    "gn:admin1_code":"2.0",
    "gn:asciiname":"Gbane",
    "gn:country_code":"SL",
    "gn:dem":103,
    "gn:feature_class":"P",
    "gn:feature_code":"PPL",
    "gn:name":"Gbane",
    "gn:population":0,
    "gn:timezone":"Africa/Freetown",
    "iso:country":"SL",
    "name:eng_x_preferred":[
        "Gbane"
    ],
    "wof:name":"Gbane",
    "wof:placetype":"locality"
},
  "geometry": {"coordinates":[-12.20116,9.35722],"type":"Point"}
}