{
  "type": "Feature",
  "properties": {
    "gn:admin1_code":"1.0",
    "gn:asciiname":"Giehun",
    "gn:country_code":"SL",
    "gn:dem":215,
    "gn:feature_class":"P",
    "gn:feature_code":"PPL",
    "gn:name":"Giehun",
    "gn:population":0,
    "gn:timezone":"Africa/Freetown",
    "iso:country":"SL",
    "name:eng_x_preferred":[
        "Giehun"
    ],
    "wof:name":"Giehun",
    "wof:placetype":"locality"
},
  "geometry": {"coordinates":[-10.82814,8.10136],"type":"Point"}
}