{
  "type": "Feature",
  "properties": {
    "gn:country":"SL",
    "gn:fcode":"PPL",
    "gn:population":4005,
    "iso:country":"SL",
    "name:eng_x_preferred":[
        "Tombu"
    ],
    "qs_pg:aaroncc":"SL",
    "qs_pg:gn_country":"SL",
    "qs_pg:gn_fcode":"PPL",
    "qs_pg:gn_pop":4005,
    "qs_pg:name":"Tombu",
    "qs_pg:photos_9r":0,
    "qs_pg:photos_sr":0,
    "qs_pg:pop_sr":4,
    "qs_pg:qs_pg_placetype":"locality",
    "wof:name":"Tombu",
    "wof:placetype":"locality",
    "wof:population":4005
},
  "geometry": {"coordinates":[-10.73333,8.53333],"type":"Point"}
}