{
  "type": "Feature",
  "properties": {
    "gn:admin1_code":"1.0",
    "gn:asciiname":"Kamadu",
    "gn:country_code":"SL",
    "gn:dem":397,
    "gn:feature_class":"P",
    "gn:feature_code":"PPL",
    "gn:name":"Kamadu",
    "gn:population":0,
    "gn:timezone":"Africa/Freetown",
    "iso:country":"SL",
    "wof:name":"Kamadu",
    "wof:placetype":"locality"
},
  "geometry": {"coordinates":[-10.99933,8.75136],"type":"Point"}
}