{
  "type": "Feature",
  "properties": {
    "gn:admin1_code":"1.0",
    "gn:asciiname":"Kundorbu",
    "gn:country_code":"SL",
    "gn:dem":143,
    "gn:feature_class":"P",
    "gn:feature_code":"PPL",
    "gn:name":"Kundorbu",
    "gn:population":0,
    "gn:timezone":"Africa/Freetown",
    "iso:country":"SL",
    "name:eng_x_preferred":[
        "Kundorbu"
    ],
    "wof:name":"Kundorbu",
    "wof:placetype":"locality"
},
  "geometry": {"coordinates":[-11.31767,7.92491],"type":"Point"}
}