{
  "type": "Feature",
  "properties": {
    "gn:admin1_code":"1.0",
    "gn:asciiname":"Soka",
    "gn:country_code":"SL",
    "gn:dem":195,
    "gn:feature_class":"P",
    "gn:feature_code":"PPL",
    "gn:name":"Soka",
    "gn:population":0,
    "gn:timezone":"Africa/Freetown",
    "iso:country":"SL",
    "name:eng_x_preferred":[
        "Soka"
    ],
    "wof:name":"Soka",
    "wof:placetype":"locality"
},
  "geometry": {"coordinates":[-10.95783,7.96437],"type":"Point"}
}