{
  "type": "Feature",
  "properties": {
    "gn:admin1_code":"3.0",
    "gn:asciiname":"Gbaama",
    "gn:country_code":"SL",
    "gn:dem":131,
    "gn:feature_class":"P",
    "gn:feature_code":"PPL",
    "gn:name":"Gbaama",
    "gn:population":0,
    "gn:timezone":"Africa/Freetown",
    "iso:country":"SL",
    "name:eng_x_preferred":[
        "Gbaama"
    ],
    "name:und_x_variant":[
        "Baoma"
    ],
    "wof:name":"Gbaama",
    "wof:placetype":"locality"
},
  "geometry": {"coordinates":[-11.4995,8.08372],"type":"Point"}
}