{
  "type": "Feature",
  "properties": {
    "gn:admin1_code":"01",
    "gn:asciiname":"Pandebu",
    "gn:country_code":"SL",
    "gn:dem":120,
    "gn:feature_class":"P",
    "gn:feature_code":"PPL",
    "gn:name":"Pandebu",
    "gn:population":0,
    "gn:timezone":"Africa/Freetown",
    "iso:country":"SL",
    "name:eng_x_preferred":[
        "Pandebu"
    ],
    "wof:name":"Pandebu",
    "wof:placetype":"locality"
},
  "geometry": {"coordinates":[-10.82873,7.5838],"type":"Point"}
}