{
  "type": "Feature",
  "properties": {
    "gn:admin1_code":"3.0",
    "gn:asciiname":"Toiyama",
    "gn:country_code":"SL",
    "gn:dem":199,
    "gn:feature_class":"P",
    "gn:feature_code":"PPL",
    "gn:name":"Toiyama",
    "gn:population":0,
    "gn:timezone":"Africa/Freetown",
    "iso:country":"SL",
    "name:eng_x_preferred":[
        "Toiyama"
    ],
    "wof:name":"Toiyama",
    "wof:placetype":"locality"
},
  "geometry": {"coordinates":[-11.64478,8.40427],"type":"Point"}
}