{
  "type": "Feature",
  "properties": {
    "gn:admin1_code":"3.0",
    "gn:asciiname":"Blama",
    "gn:country_code":"SL",
    "gn:dem":29,
    "gn:feature_class":"P",
    "gn:feature_code":"PPL",
    "gn:name":"Blama",
    "gn:population":0,
    "gn:timezone":"Africa/Freetown",
    "iso:country":"SL",
    "name:eng_x_preferred":[
        "Blama"
    ],
    "name:fra_x_preferred":[
        "Blama"
    ],
    "name:haw_x_preferred":[
        "Blama"
    ],
    "name:pol_x_preferred":[
        "Blama"
    ],
    "name:ron_x_preferred":[
        "Blama"
    ],
    "wof:name":"Blama",
    "wof:placetype":"locality"
},
  "geometry": {"coordinates":[-11.59121,7.12359],"type":"Point"}
}