{
  "type": "Feature",
  "properties": {
    "gn:admin1_code":"3.0",
    "gn:asciiname":"Laoma",
    "gn:country_code":"SL",
    "gn:dem":305,
    "gn:feature_class":"P",
    "gn:feature_code":"PPL",
    "gn:name":"Laoma",
    "gn:population":0,
    "gn:timezone":"Africa/Freetown",
    "iso:country":"SL",
    "name:eng_x_preferred":[
        "Laoma"
    ],
    "wof:name":"Laoma",
    "wof:placetype":"locality"
},
  "geometry": {"coordinates":[-11.55723,8.25803],"type":"Point"}
}