{
  "type": "Feature",
  "properties": {
    "gn:admin1_code":"2.0",
    "gn:asciiname":"Maforki",
    "gn:country_code":"SL",
    "gn:dem":79,
    "gn:feature_class":"P",
    "gn:feature_code":"PPL",
    "gn:name":"Maforki",
    "gn:population":0,
    "gn:timezone":"Africa/Freetown",
    "iso:country":"SL",
    "name:eng_x_preferred":[
        "Maforki"
    ],
    "wof:name":"Maforki",
    "wof:placetype":"locality"
},
  "geometry": {"coordinates":[-12.49441,8.69244],"type":"Point"}
}