{
  "type": "Feature",
  "properties": {
    "gn:admin1_code":"2.0",
    "gn:asciiname":"Korodu",
    "gn:country_code":"SL",
    "gn:dem":409,
    "gn:feature_class":"P",
    "gn:feature_code":"PPL",
    "gn:name":"Korodu",
    "gn:population":0,
    "gn:timezone":"Africa/Conakry",
    "iso:country":"SL",
    "name:eng_x_preferred":[
        "Korodu"
    ],
    "wof:name":"Korodu",
    "wof:placetype":"locality"
},
  "geometry": {"coordinates":[-10.58203,9.03278],"type":"Point"}
}