{
  "type": "Feature",
  "properties": {
    "gn:admin1_code":"02",
    "gn:asciiname":"Roten",
    "gn:country_code":"SL",
    "gn:dem":68,
    "gn:feature_class":"P",
    "gn:feature_code":"PPL",
    "gn:name":"Roten",
    "gn:population":0,
    "gn:timezone":"Africa/Freetown",
    "iso:country":"SL",
    "name:eng_x_preferred":[
        "Roten"
    ],
    "wof:name":"Roten",
    "wof:placetype":"locality"
},
  "geometry": {"coordinates":[-12.61218,8.97659],"type":"Point"}
}