{
  "type": "Feature",
  "properties": {
    "gn:admin1_code":"2.0",
    "gn:asciiname":"Makomba Lol",
    "gn:country_code":"SL",
    "gn:dem":77,
    "gn:feature_class":"P",
    "gn:feature_code":"PPL",
    "gn:name":"Makomba Lol",
    "gn:population":0,
    "gn:timezone":"Africa/Freetown",
    "iso:country":"SL",
    "name:eng_x_preferred":[
        "Makomba Lol"
    ],
    "wof:name":"Makomba Lol",
    "wof:placetype":"locality"
},
  "geometry": {"coordinates":[-12.41316,8.55266],"type":"Point"}
}