{
  "type": "Feature",
  "properties": {
    "gn:admin1_code":"3.0",
    "gn:asciiname":"Foindo",
    "gn:country_code":"SL",
    "gn:dem":38,
    "gn:feature_class":"P",
    "gn:feature_code":"PPL",
    "gn:name":"Foindo",
    "gn:population":0,
    "gn:timezone":"Africa/Freetown",
    "iso:country":"SL",
    "name:eng_x_preferred":[
        "Foindo"
    ],
    "wof:name":"Foindo",
    "wof:placetype":"locality"
},
  "geometry": {"coordinates":[-11.88114,7.81748],"type":"Point"}
}