{
  "type": "Feature",
  "properties": {
    "gn:admin1_code":"1.0",
    "gn:asciiname":"Gibina",
    "gn:country_code":"SL",
    "gn:dem":239,
    "gn:feature_class":"P",
    "gn:feature_code":"PPL",
    "gn:name":"Gibina",
    "gn:population":0,
    "gn:timezone":"Africa/Freetown",
    "iso:country":"SL",
    "name:eng_x_preferred":[
        "Gibina"
    ],
    "wof:name":"Gibina",
    "wof:placetype":"locality"
},
  "geometry": {"coordinates":[-11.07796,8.30624],"type":"Point"}
}