{
  "type": "Feature",
  "properties": {
    "gn:admin1_code":"2.0",
    "gn:asciiname":"Batkanu",
    "gn:country_code":"SL",
    "gn:dem":82,
    "gn:feature_class":"P",
    "gn:feature_code":"PPL",
    "gn:name":"Batkanu",
    "gn:population":0,
    "gn:timezone":"Africa/Freetown",
    "iso:country":"SL",
    "wof:name":"Batkanu",
    "wof:placetype":"locality"
},
  "geometry": {"coordinates":[-12.41541,9.07451],"type":"Point"}
}