{
  "type": "Feature",
  "properties": {
    "gn:admin1_code":"02",
    "gn:asciiname":"Yorondo",
    "gn:country_code":"SL",
    "gn:dem":685,
    "gn:feature_class":"P",
    "gn:feature_code":"PPL",
    "gn:name":"Yorondo",
    "gn:population":0,
    "gn:timezone":"Africa/Freetown",
    "iso:country":"SL",
    "wof:name":"Yorondo",
    "wof:placetype":"locality"
},
  "geometry": {"coordinates":[-11.05,9.16667],"type":"Point"}
}