{
  "type": "Feature",
  "properties": {
    "gn:admin1_code":"2.0",
    "gn:asciiname":"Sasi",
    "gn:country_code":"SL",
    "gn:dem":76,
    "gn:feature_class":"P",
    "gn:feature_code":"PPL",
    "gn:name":"Sasi",
    "gn:population":0,
    "gn:timezone":"Africa/Freetown",
    "iso:country":"SL",
    "name:bos_x_preferred":[
        "Sasi"
    ],
    "name:ceb_x_preferred":[
        "Sasi"
    ],
    "name:eng_x_preferred":[
        "Sasi"
    ],
    "name:mal_x_preferred":[
        "\u0d36\u0d36\u0d3f"
    ],
    "name:slk_x_preferred":[
        "Sasi"
    ],
    "name:swe_x_preferred":[
        "Sasi"
    ],
    "wof:name":"Sasi",
    "wof:placetype":"locality"
},
  "geometry": {"coordinates":[-12.03815,9.06662],"type":"Point"}
}