{
  "type": "Feature",
  "properties": {
    "gn:admin1_code":"02",
    "gn:asciiname":"Panlap",
    "gn:country_code":"SL",
    "gn:dem":111,
    "gn:feature_class":"P",
    "gn:feature_code":"PPL",
    "gn:name":"Panlap",
    "gn:population":0,
    "gn:timezone":"Africa/Freetown",
    "iso:country":"SL",
    "name:eng_x_preferred":[
        "Panlap"
    ],
    "wof:name":"Panlap",
    "wof:placetype":"locality"
},
  "geometry": {"coordinates":[-12.03019,8.9179],"type":"Point"}
}