{
  "type": "Feature",
  "properties": {
    "gn:admin1_code":"1.0",
    "gn:asciiname":"Bamandu",
    "gn:country_code":"SL",
    "gn:dem":310,
    "gn:feature_class":"P",
    "gn:feature_code":"PPL",
    "gn:name":"Bamandu",
    "gn:population":0,
    "gn:timezone":"Africa/Freetown",
    "iso:country":"SL",
    "name:eng_x_preferred":[
        "Bamandu"
    ],
    "wof:name":"Bamandu",
    "wof:placetype":"locality"
},
  "geometry": {"coordinates":[-10.57079,8.65338],"type":"Point"}
}