{
  "type": "Feature",
  "properties": {
    "gn:admin1_code":"3.0",
    "gn:asciiname":"Kambama",
    "gn:country_code":"SL",
    "gn:dem":83,
    "gn:feature_class":"P",
    "gn:feature_code":"PPL",
    "gn:name":"Kambama",
    "gn:population":0,
    "gn:timezone":"Africa/Freetown",
    "iso:country":"SL",
    "name:eng_x_preferred":[
        "Kambama"
    ],
    "wof:name":"Kambama",
    "wof:placetype":"locality"
},
  "geometry": {"coordinates":[-11.37672,7.44106],"type":"Point"}
}