{
  "type": "Feature",
  "properties": {
    "gn:admin1_code":"2.0",
    "gn:asciiname":"Kurakoro",
    "gn:country_code":"SL",
    "gn:dem":515,
    "gn:feature_class":"P",
    "gn:feature_code":"PPL",
    "gn:name":"Kurakoro",
    "gn:population":0,
    "gn:timezone":"Africa/Freetown",
    "iso:country":"SL",
    "name:eng_x_preferred":[
        "Kurakoro"
    ],
    "wof:name":"Kurakoro",
    "wof:placetype":"locality"
},
  "geometry": {"coordinates":[-11.51082,9.1356],"type":"Point"}
}