{
  "type": "Feature",
  "properties": {
    "gn:admin1_code":"2.0",
    "gn:asciiname":"Rogbane Bana",
    "gn:country_code":"SL",
    "gn:dem":33,
    "gn:feature_class":"P",
    "gn:feature_code":"PPL",
    "gn:name":"Rogbane Bana",
    "gn:population":0,
    "gn:timezone":"Africa/Freetown",
    "iso:country":"SL",
    "name:eng_x_preferred":[
        "Rogbane Bana"
    ],
    "wof:name":"Rogbane Bana",
    "wof:placetype":"locality"
},
  "geometry": {"coordinates":[-13.17851,8.67283],"type":"Point"}
}