{
  "type": "Feature",
  "properties": {
    "gn:admin1_code":"3.0",
    "gn:asciiname":"Negbema",
    "gn:country_code":"SL",
    "gn:dem":59,
    "gn:feature_class":"P",
    "gn:feature_code":"PPL",
    "gn:name":"Negbema",
    "gn:population":0,
    "gn:timezone":"Africa/Freetown",
    "iso:country":"SL",
    "name:eng_x_preferred":[
        "Negbema"
    ],
    "wof:name":"Negbema",
    "wof:placetype":"locality"
},
  "geometry": {"coordinates":[-12.00586,7.7327],"type":"Point"}
}