{
  "type": "Feature",
  "properties": {
    "gn:admin1_code":"1.0",
    "gn:asciiname":"Jerihun",
    "gn:country_code":"SL",
    "gn:dem":314,
    "gn:feature_class":"P",
    "gn:feature_code":"PPL",
    "gn:name":"Jerihun",
    "gn:population":0,
    "gn:timezone":"Africa/Freetown",
    "iso:country":"SL",
    "name:eng_x_preferred":[
        "Jerihun"
    ],
    "wof:name":"Jerihun",
    "wof:placetype":"locality"
},
  "geometry": {"coordinates":[-11.08759,8.32531],"type":"Point"}
}