{
  "type": "Feature",
  "properties": {
    "gn:admin1_code":"3.0",
    "gn:asciiname":"Baraka",
    "gn:country_code":"SL",
    "gn:dem":63,
    "gn:feature_class":"P",
    "gn:feature_code":"PPL",
    "gn:name":"Baraka",
    "gn:population":0,
    "gn:timezone":"Africa/Freetown",
    "iso:country":"SL",
    "name:ceb_x_preferred":[
        "Baraka"
    ],
    "name:ces_x_preferred":[
        "Baraka"
    ],
    "name:deu_x_preferred":[
        "Baraka"
    ],
    "name:eng_x_preferred":[
        "Baraka"
    ],
    "name:fin_x_preferred":[
        "Baraka"
    ],
    "name:fra_x_preferred":[
        "Baraka"
    ],
    "name:ita_x_preferred":[
        "Baraka"
    ],
    "name:jpn_x_preferred":[
        "\u30d0\u30e9\u30ab"
    ],
    "name:kor_x_preferred":[
        "\ubc14\ub77c\uce74"
    ],
    "name:nld_x_preferred":[
        "Baraka"
    ],
    "name:por_x_preferred":[
        "Baraca"
    ],
    "name:slk_x_preferred":[
        "Baraka"
    ],
    "name:spa_x_preferred":[
        "Baraka"
    ],
    "name:swe_x_preferred":[
        "Baraka"
    ],
    "name:vie_x_preferred":[
        "Baraka"
    ],
    "wof:name":"Baraka",
    "wof:placetype":"locality"
},
  "geometry": {"coordinates":[-12.37812,8.07817],"type":"Point"}
}