{
  "type": "Feature",
  "properties": {
    "gn:admin1_code":"2.0",
    "gn:asciiname":"Makunkabai",
    "gn:country_code":"SL",
    "gn:dem":86,
    "gn:feature_class":"P",
    "gn:feature_code":"PPL",
    "gn:name":"Makunkabai",
    "gn:population":0,
    "gn:timezone":"Africa/Freetown",
    "iso:country":"SL",
    "name:eng_x_preferred":[
        "Makunkabai"
    ],
    "wof:name":"Makunkabai",
    "wof:placetype":"locality"
},
  "geometry": {"coordinates":[-12.07594,8.75999],"type":"Point"}
}