{
  "type": "Feature",
  "properties": {
    "gn:admin1_code":"1.0",
    "gn:asciiname":"Kamindu",
    "gn:country_code":"SL",
    "gn:dem":600,
    "gn:feature_class":"P",
    "gn:feature_code":"PPL",
    "gn:name":"Kamindu",
    "gn:population":0,
    "gn:timezone":"Africa/Freetown",
    "iso:country":"SL",
    "name:eng_x_preferred":[
        "Kamindu"
    ],
    "name:und_x_variant":[
        "Kamiendo"
    ],
    "wof:name":"Kamindu",
    "wof:placetype":"locality"
},
  "geometry": {"coordinates":[-10.67309,8.68633],"type":"Point"}
}