{
  "type": "Feature",
  "properties": {
    "gn:admin1_code":"1.0",
    "gn:asciiname":"Nekabu",
    "gn:country_code":"SL",
    "gn:dem":185,
    "gn:feature_class":"P",
    "gn:feature_code":"PPL",
    "gn:name":"Nekabu",
    "gn:population":0,
    "gn:timezone":"Africa/Freetown",
    "iso:country":"SL",
    "name:und_x_variant":[
        "Nikiba",
        "Nekabu"
    ],
    "wof:name":"Nekabu",
    "wof:placetype":"locality"
},
  "geometry": {"coordinates":[-11.05476,7.92621],"type":"Point"}
}