{
  "type": "Feature",
  "properties": {
    "gn:admin1_code":"02",
    "gn:asciiname":"Tambakura",
    "gn:country_code":"SL",
    "gn:dem":59,
    "gn:feature_class":"P",
    "gn:feature_code":"PPL",
    "gn:name":"Tambakura",
    "gn:population":0,
    "gn:timezone":"Africa/Freetown",
    "iso:country":"SL",
    "name:eng_x_preferred":[
        "Tambakura"
    ],
    "wof:name":"Tambakura",
    "wof:placetype":"locality"
},
  "geometry": {"coordinates":[-12.59247,9.59277],"type":"Point"}
}