{
  "type": "Feature",
  "properties": {
    "gn:admin1_code":"02",
    "gn:asciiname":"Yakobi",
    "gn:country_code":"SL",
    "gn:dem":596,
    "gn:feature_class":"P",
    "gn:feature_code":"PPL",
    "gn:name":"Yakobi",
    "gn:population":0,
    "gn:timezone":"Africa/Freetown",
    "iso:country":"SL",
    "name:eng_x_preferred":[
        "Yakobi"
    ],
    "wof:name":"Yakobi",
    "wof:placetype":"locality"
},
  "geometry": {"coordinates":[-11.68333,9.61667],"type":"Point"}
}