{
  "type": "Feature",
  "properties": {
    "gn:admin1_code":"02",
    "gn:asciiname":"Tavyia",
    "gn:country_code":"SL",
    "gn:dem":16,
    "gn:feature_class":"P",
    "gn:feature_code":"PPL",
    "gn:name":"Tavyia",
    "gn:population":0,
    "gn:timezone":"Africa/Freetown",
    "iso:country":"SL",
    "name:und_x_variant":[
        "Tauyia"
    ],
    "wof:name":"Tavyia",
    "wof:placetype":"locality"
},
  "geometry": {"coordinates":[-12.94784,9.10178],"type":"Point"}
}