{
  "type": "Feature",
  "properties": {
    "gn:admin1_code":"3.0",
    "gn:asciiname":"Gerehun",
    "gn:country_code":"SL",
    "gn:dem":70,
    "gn:feature_class":"P",
    "gn:feature_code":"PPL",
    "gn:name":"Gerehun",
    "gn:population":0,
    "gn:timezone":"Africa/Freetown",
    "iso:country":"SL",
    "name:eng_x_preferred":[
        "Gerehun"
    ],
    "wof:name":"Gerehun",
    "wof:placetype":"locality"
},
  "geometry": {"coordinates":[-12.38931,8.25957],"type":"Point"}
}