{
  "type": "Feature",
  "properties": {
    "gn:admin1_code":"2.0",
    "gn:asciiname":"Yanfurandor",
    "gn:country_code":"SL",
    "gn:dem":387,
    "gn:feature_class":"P",
    "gn:feature_code":"PPL",
    "gn:name":"Yanfurandor",
    "gn:population":0,
    "gn:timezone":"Africa/Freetown",
    "iso:country":"SL",
    "name:eng_x_preferred":[
        "Yanfurandor"
    ],
    "wof:name":"Yanfurandor",
    "wof:placetype":"locality"
},
  "geometry": {"coordinates":[-11.51103,9.60253],"type":"Point"}
}