{
  "type": "Feature",
  "properties": {
    "gn:admin1_code":"02",
    "gn:asciiname":"Tunisi",
    "gn:country_code":"SL",
    "gn:dem":141,
    "gn:feature_class":"P",
    "gn:feature_code":"PPL",
    "gn:name":"Tunisi",
    "gn:population":0,
    "gn:timezone":"Africa/Freetown",
    "iso:country":"SL",
    "name:eng_x_preferred":[
        "Tunisi"
    ],
    "wof:name":"Tunisi",
    "wof:placetype":"locality"
},
  "geometry": {"coordinates":[-11.95423,9.36587],"type":"Point"}
}