{
  "type": "Feature",
  "properties": {
    "gn:admin1_code":"1.0",
    "gn:asciiname":"Kangama",
    "gn:country_code":"SL",
    "gn:dem":160,
    "gn:feature_class":"P",
    "gn:feature_code":"PPL",
    "gn:name":"Kangama",
    "gn:population":0,
    "gn:timezone":"Africa/Freetown",
    "iso:country":"SL",
    "name:eng_x_preferred":[
        "Kangama"
    ],
    "wof:name":"Kangama",
    "wof:placetype":"locality"
},
  "geometry": {"coordinates":[-11.07643,7.86424],"type":"Point"}
}