{
  "type": "Feature",
  "properties": {
    "gn:admin1_code":"02",
    "gn:asciiname":"Songo",
    "gn:country_code":"SL",
    "gn:dem":399,
    "gn:feature_class":"P",
    "gn:feature_code":"PPL",
    "gn:name":"Songo",
    "gn:population":0,
    "gn:timezone":"Africa/Freetown",
    "iso:country":"SL",
    "name:ceb_x_preferred":[
        "Songo"
    ],
    "name:deu_x_preferred":[
        "Songo"
    ],
    "name:eng_x_preferred":[
        "Songo"
    ],
    "name:fra_x_preferred":[
        "Songo"
    ],
    "name:por_x_preferred":[
        "Songo"
    ],
    "name:swe_x_preferred":[
        "Songo"
    ],
    "wof:name":"Songo",
    "wof:placetype":"locality"
},
  "geometry": {"coordinates":[-11.84484,9.96725],"type":"Point"}
}