{
  "type": "Feature",
  "properties": {
    "gn:admin1_code":"02",
    "gn:asciiname":"Tongbai",
    "gn:country_code":"SL",
    "gn:dem":84,
    "gn:feature_class":"P",
    "gn:feature_code":"PPL",
    "gn:name":"Tongbai",
    "gn:population":0,
    "gn:timezone":"Africa/Freetown",
    "iso:country":"SL",
    "name:eng_x_preferred":[
        "Tongbai"
    ],
    "wof:name":"Tongbai",
    "wof:placetype":"locality"
},
  "geometry": {"coordinates":[-12.41293,8.79029],"type":"Point"}
}