{
  "type": "Feature",
  "properties": {
    "gn:admin1_code":"1.0",
    "gn:asciiname":"Kwindo",
    "gn:country_code":"SL",
    "gn:dem":174,
    "gn:feature_class":"P",
    "gn:feature_code":"PPL",
    "gn:name":"Kwindo",
    "gn:population":0,
    "gn:timezone":"Africa/Freetown",
    "iso:country":"SL",
    "name:eng_x_preferred":[
        "Kwindo"
    ],
    "wof:name":"Kwindo",
    "wof:placetype":"locality"
},
  "geometry": {"coordinates":[-11.14246,7.96467],"type":"Point"}
}