{
  "type": "Feature",
  "properties": {
    "gn:admin1_code":"1.0",
    "gn:asciiname":"Deadu",
    "gn:country_code":"SL",
    "gn:dem":366,
    "gn:feature_class":"P",
    "gn:feature_code":"PPL",
    "gn:name":"Deadu",
    "gn:population":0,
    "gn:timezone":"Africa/Freetown",
    "iso:country":"SL",
    "name:eng_x_preferred":[
        "Deadu"
    ],
    "wof:name":"Deadu",
    "wof:placetype":"locality"
},
  "geometry": {"coordinates":[-11.21428,8.79146],"type":"Point"}
}