{
  "type": "Feature",
  "properties": {
    "gn:admin1_code":"1.0",
    "gn:asciiname":"Bourma",
    "gn:country_code":"SL",
    "gn:dem":429,
    "gn:feature_class":"P",
    "gn:feature_code":"PPL",
    "gn:name":"Bourma",
    "gn:population":0,
    "gn:timezone":"Africa/Freetown",
    "iso:country":"SL",
    "name:eng_x_preferred":[
        "Bourma"
    ],
    "name:und_x_variant":[
        "Boma"
    ],
    "wof:name":"Bourma",
    "wof:placetype":"locality"
},
  "geometry": {"coordinates":[-10.93235,8.7105],"type":"Point"}
}