{
  "type": "Feature",
  "properties": {
    "gn:admin1_code":"2.0",
    "gn:asciiname":"Saraia",
    "gn:country_code":"SL",
    "gn:dem":14,
    "gn:feature_class":"P",
    "gn:feature_code":"PPL",
    "gn:name":"Saraia",
    "gn:population":0,
    "gn:timezone":"Africa/Freetown",
    "iso:country":"SL",
    "name:eng_x_preferred":[
        "Saraia"
    ],
    "wof:name":"Saraia",
    "wof:placetype":"locality"
},
  "geometry": {"coordinates":[-12.9819,9.05471],"type":"Point"}
}