{
  "type": "Feature",
  "properties": {
    "gn:admin1_code":"1.0",
    "gn:asciiname":"Kayima",
    "gn:country_code":"SL",
    "gn:dem":281,
    "gn:feature_class":"P",
    "gn:feature_code":"PPL",
    "gn:name":"Kayima",
    "gn:population":0,
    "gn:timezone":"Africa/Freetown",
    "iso:country":"SL",
    "name:eng_x_preferred":[
        "Kayima"
    ],
    "wof:name":"Kayima",
    "wof:placetype":"locality"
},
  "geometry": {"coordinates":[-10.61875,8.3124],"type":"Point"}
}