{
  "type": "Feature",
  "properties": {
    "gn:admin1_code":"2.0",
    "gn:asciiname":"Gugbia",
    "gn:country_code":"SL",
    "gn:dem":126,
    "gn:feature_class":"P",
    "gn:feature_code":"PPL",
    "gn:name":"Gugbia",
    "gn:population":0,
    "gn:timezone":"Africa/Freetown",
    "iso:country":"SL",
    "name:eng_x_preferred":[
        "Gugbia"
    ],
    "wof:name":"Gugbia",
    "wof:placetype":"locality"
},
  "geometry": {"coordinates":[-12.06422,9.27743],"type":"Point"}
}