{
  "type": "Feature",
  "properties": {
    "gn:admin1_code":"3.0",
    "gn:asciiname":"Lombi",
    "gn:country_code":"SL",
    "gn:dem":20,
    "gn:feature_class":"P",
    "gn:feature_code":"PPL",
    "gn:name":"Lombi",
    "gn:population":0,
    "gn:timezone":"Africa/Freetown",
    "iso:country":"SL",
    "name:ceb_x_preferred":[
        "Lombi"
    ],
    "name:eng_x_preferred":[
        "Lombi"
    ],
    "name:nld_x_preferred":[
        "Lombi"
    ],
    "name:swe_x_preferred":[
        "Lombi"
    ],
    "wof:name":"Lombi",
    "wof:placetype":"locality"
},
  "geometry": {"coordinates":[-11.53921,7.12066],"type":"Point"}
}