{
  "type": "Feature",
  "properties": {
    "gn:admin1_code":"3.0",
    "gn:asciiname":"Nitti",
    "gn:country_code":"SL",
    "gn:dem":6,
    "gn:feature_class":"P",
    "gn:feature_code":"PPL",
    "gn:name":"Nitti",
    "gn:population":0,
    "gn:timezone":"Africa/Freetown",
    "iso:country":"SL",
    "name:deu_x_preferred":[
        "Nitti"
    ],
    "name:eng_x_preferred":[
        "Nitti"
    ],
    "name:ita_x_preferred":[
        "Nitti"
    ],
    "name:nds_x_preferred":[
        "Nitti"
    ],
    "name:ukr_x_preferred":[
        "\u041d\u0456\u0442\u0442\u0456"
    ],
    "wof:name":"Nitti",
    "wof:placetype":"locality"
},
  "geometry": {"coordinates":[-12.39704,7.76324],"type":"Point"}
}