{
  "type": "Feature",
  "properties": {
    "gn:admin1_code":"2.0",
    "gn:asciiname":"Mafuri",
    "gn:country_code":"SL",
    "gn:dem":75,
    "gn:feature_class":"P",
    "gn:feature_code":"PPL",
    "gn:name":"Mafuri",
    "gn:population":0,
    "gn:timezone":"Africa/Freetown",
    "iso:country":"SL",
    "name:eng_x_preferred":[
        "Mafuri"
    ],
    "wof:name":"Mafuri",
    "wof:placetype":"locality"
},
  "geometry": {"coordinates":[-12.41598,8.94316],"type":"Point"}
}