{
  "type": "Feature",
  "properties": {
    "gn:admin1_code":"02",
    "gn:asciiname":"Nyeldu",
    "gn:country_code":"SL",
    "gn:dem":480,
    "gn:feature_class":"P",
    "gn:feature_code":"PPL",
    "gn:name":"Nyeldu",
    "gn:population":0,
    "gn:timezone":"Africa/Freetown",
    "iso:country":"SL",
    "name:eng_x_preferred":[
        "Nyeldu"
    ],
    "wof:name":"Nyeldu",
    "wof:placetype":"locality"
},
  "geometry": {"coordinates":[-10.9266,9.38544],"type":"Point"}
}