{
  "type": "Feature",
  "properties": {
    "gn:admin1_code":"4.0",
    "gn:asciiname":"Batbai",
    "gn:country_code":"SL",
    "gn:dem":18,
    "gn:feature_class":"P",
    "gn:feature_code":"PPL",
    "gn:name":"Batbai",
    "gn:population":0,
    "gn:timezone":"Africa/Freetown",
    "iso:country":"SL",
    "name:eng_x_preferred":[
        "Batbai"
    ],
    "wof:name":"Batbai",
    "wof:placetype":"locality"
},
  "geometry": {"coordinates":[-13.04852,8.29454],"type":"Point"}
}