{
  "type": "Feature",
  "properties": {
    "gn:admin1_code":"1.0",
    "gn:asciiname":"Bambaworo",
    "gn:country_code":"SL",
    "gn:dem":190,
    "gn:feature_class":"P",
    "gn:feature_code":"PPL",
    "gn:name":"Bambaworo",
    "gn:population":0,
    "gn:timezone":"Africa/Freetown",
    "iso:country":"SL",
    "name:eng_x_preferred":[
        "Bambaworo"
    ],
    "wof:name":"Bambaworo",
    "wof:placetype":"locality"
},
  "geometry": {"coordinates":[-10.91846,8.04597],"type":"Point"}
}