{
  "type": "Feature",
  "properties": {
    "gn:admin1_code":"2.0",
    "gn:asciiname":"Kambana",
    "gn:country_code":"SL",
    "gn:dem":312,
    "gn:feature_class":"P",
    "gn:feature_code":"PPL",
    "gn:name":"Kambana",
    "gn:population":0,
    "gn:timezone":"Africa/Freetown",
    "iso:country":"SL",
    "wof:name":"Kambana",
    "wof:placetype":"locality"
},
  "geometry": {"coordinates":[-11.95,9.46667],"type":"Point"}
}