{
  "type": "Feature",
  "properties": {
    "gn:admin1_code":"02",
    "gn:asciiname":"Petifu",
    "gn:country_code":"SL",
    "gn:dem":26,
    "gn:feature_class":"P",
    "gn:feature_code":"PPL",
    "gn:name":"Petifu",
    "gn:population":0,
    "gn:timezone":"Africa/Freetown",
    "iso:country":"SL",
    "name:eng_x_preferred":[
        "Petifu"
    ],
    "wof:name":"Petifu",
    "wof:placetype":"locality"
},
  "geometry": {"coordinates":[-12.92142,8.68257],"type":"Point"}
}