{
  "type": "Feature",
  "properties": {
    "gn:admin1_code":"1.0",
    "gn:asciiname":"Tofawun",
    "gn:country_code":"SL",
    "gn:dem":209,
    "gn:feature_class":"P",
    "gn:feature_code":"PPL",
    "gn:name":"Tofawun",
    "gn:population":0,
    "gn:timezone":"Africa/Freetown",
    "iso:country":"SL",
    "name:eng_x_preferred":[
        "Tofawun"
    ],
    "wof:name":"Tofawun",
    "wof:placetype":"locality"
},
  "geometry": {"coordinates":[-10.70395,8.28453],"type":"Point"}
}