{
  "type": "Feature",
  "properties": {
    "gn:admin1_code":"2.0",
    "gn:asciiname":"Magbanasanka",
    "gn:country_code":"SL",
    "gn:dem":27,
    "gn:feature_class":"P",
    "gn:feature_code":"PPL",
    "gn:name":"Magbanasanka",
    "gn:population":0,
    "gn:timezone":"Africa/Freetown",
    "iso:country":"SL",
    "name:eng_x_preferred":[
        "Magbanasanka"
    ],
    "wof:name":"Magbanasanka",
    "wof:placetype":"locality"
},
  "geometry": {"coordinates":[-12.80729,8.42341],"type":"Point"}
}