{
  "type": "Feature",
  "properties": {
    "gn:admin1_code":"1.0",
    "gn:asciiname":"Jaomahun",
    "gn:country_code":"SL",
    "gn:dem":327,
    "gn:feature_class":"P",
    "gn:feature_code":"PPL",
    "gn:name":"Jaomahun",
    "gn:population":0,
    "gn:timezone":"Africa/Freetown",
    "iso:country":"SL",
    "name:eng_x_preferred":[
        "Jaomahun"
    ],
    "wof:name":"Jaomahun",
    "wof:placetype":"locality"
},
  "geometry": {"coordinates":[-11.52923,8.48034],"type":"Point"}
}