{
  "type": "Feature",
  "properties": {
    "gn:admin1_code":"3.0",
    "gn:asciiname":"Lau",
    "gn:country_code":"SL",
    "gn:dem":67,
    "gn:feature_class":"P",
    "gn:feature_code":"PPL",
    "gn:name":"Lau",
    "gn:population":0,
    "gn:timezone":"Africa/Freetown",
    "iso:country":"SL",
    "name:eng_x_preferred":[
        "Lau"
    ],
    "wof:name":"Lau",
    "wof:placetype":"locality"
},
  "geometry": {"coordinates":[-11.76714,7.80685],"type":"Point"}
}