{
  "type": "Feature",
  "properties": {
    "gn:admin1_code":"3.0",
    "gn:asciiname":"Mokayaka",
    "gn:country_code":"SL",
    "gn:dem":8,
    "gn:feature_class":"P",
    "gn:feature_code":"PPL",
    "gn:name":"Mokayaka",
    "gn:population":0,
    "gn:timezone":"Africa/Freetown",
    "iso:country":"SL",
    "name:eng_x_preferred":[
        "Mokayaka"
    ],
    "wof:name":"Mokayaka",
    "wof:placetype":"locality"
},
  "geometry": {"coordinates":[-12.01358,7.21976],"type":"Point"}
}