{
  "type": "Feature",
  "properties": {
    "gn:admin1_code":"1.0",
    "gn:asciiname":"Faaoh",
    "gn:country_code":"SL",
    "gn:dem":506,
    "gn:feature_class":"P",
    "gn:feature_code":"PPL",
    "gn:name":"Faaoh",
    "gn:population":0,
    "gn:timezone":"Africa/Freetown",
    "iso:country":"SL",
    "name:und_x_variant":[
        "Fafo"
    ],
    "wof:name":"Faaoh",
    "wof:placetype":"locality"
},
  "geometry": {"coordinates":[-10.64679,8.84783],"type":"Point"}
}