{
  "type": "Feature",
  "properties": {
    "gn:admin1_code":"1.0",
    "gn:asciiname":"Baladu",
    "gn:country_code":"SL",
    "gn:dem":435,
    "gn:feature_class":"P",
    "gn:feature_code":"PPL",
    "gn:name":"Baladu",
    "gn:population":0,
    "gn:timezone":"Africa/Freetown",
    "iso:country":"SL",
    "name:eng_x_preferred":[
        "Baladu"
    ],
    "name:und_x_variant":[
        "Baradu"
    ],
    "wof:name":"Baladu",
    "wof:placetype":"locality"
},
  "geometry": {"coordinates":[-10.30254,8.46017],"type":"Point"}
}