{
  "type": "Feature",
  "properties": {
    "iso:country":"SL",
    "name:eng_x_preferred":[
        "Koribundu"
    ],
    "qs:gn_country":"SL",
    "qs:gn_fcode":"PPL",
    "qs:gn_pop":4617,
    "qs:name":"Koribundu",
    "qs:name_adm0":"Sierra Leone",
    "qs:name_adm1":"Southern",
    "qs:photos":0,
    "qs:photos_1k":0,
    "qs:photos_9k":0,
    "qs:photos_9r":0,
    "qs:photos_all":0,
    "qs:photos_sr":0,
    "qs:placetype":"Town",
    "qs:pop_sr":"4",
    "qs:woe_adm0":23424946,
    "wof:name":"Koribundu",
    "wof:placetype":"locality",
    "wof:population":4617
},
  "geometry": {"coordinates":[-11.69222,7.71139],"type":"Point"}
}