{
  "type": "Feature",
  "properties": {
    "gn:admin1_code":"3.0",
    "gn:asciiname":"Bumpe",
    "gn:country_code":"SL",
    "gn:dem":11,
    "gn:feature_class":"P",
    "gn:feature_code":"PPL",
    "gn:name":"Bumpe",
    "gn:population":0,
    "gn:timezone":"Africa/Freetown",
    "iso:country":"SL",
    "name:eng_x_preferred":[
        "Bumpe"
    ],
    "wof:name":"Bumpe",
    "wof:placetype":"locality"
},
  "geometry": {"coordinates":[-12.71305,8.14007],"type":"Point"}
}