{
  "type": "Feature",
  "properties": {
    "gn:admin1_code":"3.0",
    "gn:asciiname":"Lungi",
    "gn:country_code":"SL",
    "gn:dem":49,
    "gn:feature_class":"P",
    "gn:feature_code":"PPL",
    "gn:name":"Lungi",
    "gn:population":0,
    "gn:timezone":"Africa/Freetown",
    "iso:country":"SL",
    "name:ben_x_preferred":[
        "\u09b2\u09c1\u0999\u09cd\u0997\u09bf"
    ],
    "name:deu_x_preferred":[
        "Lungi"
    ],
    "name:eng_x_preferred":[
        "Lungi"
    ],
    "name:epo_x_preferred":[
        "Lungi"
    ],
    "name:fra_x_preferred":[
        "Longhi"
    ],
    "name:hin_x_preferred":[
        "\u0932\u0941\u0902\u0917\u0940"
    ],
    "name:ind_x_preferred":[
        "Lungi"
    ],
    "name:jpn_x_preferred":[
        "\u30eb\u30f3\u30ae\u30fc"
    ],
    "name:kan_x_preferred":[
        "\u0cb2\u0cc1\u0c82\u0c97\u0cbf"
    ],
    "name:msa_x_preferred":[
        "Lungi"
    ],
    "name:nep_x_preferred":[
        "\u0932\u0941\u0919\u094d\u0917\u0940"
    ],
    "name:nld_x_preferred":[
        "Longhi"
    ],
    "name:nno_x_preferred":[
        "Lungi"
    ],
    "name:pol_x_preferred":[
        "Lungi"
    ],
    "name:spa_x_preferred":[
        "Lungui"
    ],
    "name:tam_x_preferred":[
        "\u0bb2\u0bc1\u0b99\u0bcd\u0b95\u0bbf"
    ],
    "name:tel_x_preferred":[
        "\u0c32\u0c41\u0c02\u0c17\u0c40"
    ],
    "wof:name":"Lungi",
    "wof:placetype":"locality"
},
  "geometry": {"coordinates":[-11.92139,8.03811],"type":"Point"}
}