{
  "type": "Feature",
  "properties": {
    "gn:admin1_code":"3.0",
    "gn:asciiname":"Madina",
    "gn:country_code":"SL",
    "gn:dem":19,
    "gn:feature_class":"P",
    "gn:feature_code":"PPL",
    "gn:name":"Madina",
    "gn:population":0,
    "gn:timezone":"Africa/Freetown",
    "iso:country":"SL",
    "name:und_x_variant":[
        "Madima",
        "Madina"
    ],
    "wof:name":"Madina",
    "wof:placetype":"locality"
},
  "geometry": {"coordinates":[-11.71992,7.14545],"type":"Point"}
}