{
  "type": "Feature",
  "properties": {
    "gn:admin1_code":"3.0",
    "gn:asciiname":"Boto",
    "gn:country_code":"SL",
    "gn:dem":10,
    "gn:feature_class":"P",
    "gn:feature_code":"PPL",
    "gn:name":"Boto",
    "gn:population":0,
    "gn:timezone":"Africa/Freetown",
    "iso:country":"SL",
    "name:eng_x_preferred":[
        "Boto"
    ],
    "name:por_x_preferred":[
        "Boto"
    ],
    "wof:name":"Boto",
    "wof:placetype":"locality"
},
  "geometry": {"coordinates":[-12.15733,7.39381],"type":"Point"}
}