{
  "type": "Feature",
  "properties": {
    "gn:admin1_code":"2.0",
    "gn:asciiname":"Tene",
    "gn:country_code":"SL",
    "gn:dem":86,
    "gn:feature_class":"P",
    "gn:feature_code":"PPL",
    "gn:name":"Tene",
    "gn:population":0,
    "gn:timezone":"Africa/Freetown",
    "iso:country":"SL",
    "name:ceb_x_preferred":[
        "Tene"
    ],
    "name:deu_x_preferred":[
        "Tene"
    ],
    "name:eng_x_preferred":[
        "Tene"
    ],
    "name:ita_x_preferred":[
        "Tene"
    ],
    "name:nld_x_preferred":[
        "Tene"
    ],
    "name:swe_x_preferred":[
        "Tene"
    ],
    "wof:name":"Tene",
    "wof:placetype":"locality"
},
  "geometry": {"coordinates":[-12.02265,8.79511],"type":"Point"}
}