{
  "type": "Feature",
  "properties": {
    "gn:admin1_code":"1.0",
    "gn:asciiname":"Kandior",
    "gn:country_code":"SL",
    "gn:dem":371,
    "gn:feature_class":"P",
    "gn:feature_code":"PPL",
    "gn:name":"Kandior",
    "gn:population":0,
    "gn:timezone":"Africa/Freetown",
    "iso:country":"SL",
    "name:eng_x_preferred":[
        "Kandior"
    ],
    "wof:name":"Kandior",
    "wof:placetype":"locality"
},
  "geometry": {"coordinates":[-10.95799,8.68141],"type":"Point"}
}