{
  "type": "Feature",
  "properties": {
    "gn:admin1_code":"2.0",
    "gn:asciiname":"Makane",
    "gn:country_code":"SL",
    "gn:dem":119,
    "gn:feature_class":"P",
    "gn:feature_code":"PPL",
    "gn:name":"Makane",
    "gn:population":0,
    "gn:timezone":"Africa/Freetown",
    "iso:country":"SL",
    "name:und_x_variant":[
        "Makare",
        "Makane"
    ],
    "wof:name":"Makane",
    "wof:placetype":"locality"
},
  "geometry": {"coordinates":[-12.0044,8.9988],"type":"Point"}
}