{
  "type": "Feature",
  "properties": {
    "gn:admin1_code":"2.0",
    "gn:asciiname":"Magbuna",
    "gn:country_code":"SL",
    "gn:dem":241,
    "gn:feature_class":"P",
    "gn:feature_code":"PPL",
    "gn:name":"Magbuna",
    "gn:population":0,
    "gn:timezone":"Africa/Freetown",
    "iso:country":"SL",
    "name:eng_x_preferred":[
        "Magbuna"
    ],
    "wof:name":"Magbuna",
    "wof:placetype":"locality"
},
  "geometry": {"coordinates":[-11.71942,8.68816],"type":"Point"}
}