{
  "type": "Feature",
  "properties": {
    "gn:admin1_code":"3.0",
    "gn:asciiname":"Garahun",
    "gn:country_code":"SL",
    "gn:dem":38,
    "gn:feature_class":"P",
    "gn:feature_code":"PPL",
    "gn:name":"Garahun",
    "gn:population":0,
    "gn:timezone":"Africa/Freetown",
    "iso:country":"SL",
    "name:eng_x_preferred":[
        "Garahun"
    ],
    "wof:name":"Garahun",
    "wof:placetype":"locality"
},
  "geometry": {"coordinates":[-12.01035,7.67678],"type":"Point"}
}