{
  "type": "Feature",
  "properties": {
    "gn:admin1_code":"3.0",
    "gn:asciiname":"Jayahun",
    "gn:country_code":"SL",
    "gn:dem":71,
    "gn:feature_class":"P",
    "gn:feature_code":"PPL",
    "gn:name":"Jayahun",
    "gn:population":0,
    "gn:timezone":"Africa/Freetown",
    "iso:country":"SL",
    "name:eng_x_preferred":[
        "Jayahun"
    ],
    "wof:name":"Jayahun",
    "wof:placetype":"locality"
},
  "geometry": {"coordinates":[-12.09595,7.98084],"type":"Point"}
}