{
  "type": "Feature",
  "properties": {
    "gn:admin1_code":"3.0",
    "gn:asciiname":"Kondebotihun",
    "gn:country_code":"SL",
    "gn:dem":57,
    "gn:feature_class":"P",
    "gn:feature_code":"PPL",
    "gn:name":"Kondebotihun",
    "gn:population":0,
    "gn:timezone":"Africa/Freetown",
    "iso:country":"SL",
    "name:eng_x_preferred":[
        "Kondebotihun"
    ],
    "wof:name":"Kondebotihun",
    "wof:placetype":"locality"
},
  "geometry": {"coordinates":[-12.41478,8.26464],"type":"Point"}
}