{
  "type": "Feature",
  "properties": {
    "gn:admin1_code":"2.0",
    "gn:asciiname":"Makoron",
    "gn:country_code":"SL",
    "gn:dem":64,
    "gn:feature_class":"P",
    "gn:feature_code":"PPL",
    "gn:name":"Makoron",
    "gn:population":0,
    "gn:timezone":"Africa/Freetown",
    "iso:country":"SL",
    "name:eng_x_preferred":[
        "Makoron"
    ],
    "wof:name":"Makoron",
    "wof:placetype":"locality"
},
  "geometry": {"coordinates":[-12.49731,8.48445],"type":"Point"}
}