{
  "type": "Feature",
  "properties": {
    "gn:admin1_code":"3.0",
    "gn:asciiname":"Salama",
    "gn:country_code":"SL",
    "gn:dem":7,
    "gn:feature_class":"P",
    "gn:feature_code":"PPL",
    "gn:name":"Salama",
    "gn:population":0,
    "gn:timezone":"Africa/Freetown",
    "iso:country":"SL",
    "name:eng_x_preferred":[
        "Salama"
    ],
    "wof:name":"Salama",
    "wof:placetype":"locality"
},
  "geometry": {"coordinates":[-12.6858,8.20988],"type":"Point"}
}