{
  "type": "Feature",
  "properties": {
    "gn:admin1_code":"3.0",
    "gn:asciiname":"Salama",
    "gn:country_code":"SL",
    "gn:dem":7,
    "gn:feature_class":"P",
    "gn:feature_code":"PPL",
    "gn:name":"Salama",
    "gn:population":0,
    "gn:timezone":"Africa/Freetown",
    "iso:country":"SL",
    "name:ceb_x_preferred":[
        "Salama"
    ],
    "name:deu_x_preferred":[
        "Salama"
    ],
    "name:eng_x_preferred":[
        "Salama"
    ],
    "name:fin_x_preferred":[
        "Salama"
    ],
    "name:fra_x_preferred":[
        "Salama"
    ],
    "name:heb_x_preferred":[
        "\u05e1\u05dc\u05d0\u05de\u05d4"
    ],
    "name:ita_x_preferred":[
        "Salama"
    ],
    "name:jpn_x_preferred":[
        "\u30b5\u30e9\u30fc\u30de"
    ],
    "name:rus_x_preferred":[
        "\u0421\u0430\u043b\u0430\u043c\u0430"
    ],
    "name:swe_x_preferred":[
        "Salama"
    ],
    "wof:name":"Salama",
    "wof:placetype":"locality"
},
  "geometry": {"coordinates":[-12.6858,8.20988],"type":"Point"}
}