{
  "type": "Feature",
  "properties": {
    "gn:admin1_code":"01",
    "gn:asciiname":"Sagbati",
    "gn:country_code":"SL",
    "gn:dem":283,
    "gn:feature_class":"P",
    "gn:feature_code":"PPL",
    "gn:name":"Sagbati",
    "gn:population":0,
    "gn:timezone":"Africa/Freetown",
    "iso:country":"SL",
    "name:eng_x_preferred":[
        "Sagbati"
    ],
    "name:und_x_variant":[
        "Sagpati"
    ],
    "wof:name":"Sagbati",
    "wof:placetype":"locality"
},
  "geometry": {"coordinates":[-11.19562,8.15464],"type":"Point"}
}