{
  "type": "Feature",
  "properties": {
    "gn:admin1_code":"3.0",
    "gn:asciiname":"Lablama",
    "gn:country_code":"SL",
    "gn:dem":350,
    "gn:feature_class":"P",
    "gn:feature_code":"PPL",
    "gn:name":"Lablama",
    "gn:population":0,
    "gn:timezone":"Africa/Freetown",
    "iso:country":"SL",
    "name:eng_x_preferred":[
        "Lablama"
    ],
    "wof:name":"Lablama",
    "wof:placetype":"locality"
},
  "geometry": {"coordinates":[-11.59235,8.46183],"type":"Point"}
}