{
  "type": "Feature",
  "properties": {
    "gn:admin1_code":"3.0",
    "gn:asciiname":"Masa",
    "gn:country_code":"SL",
    "gn:dem":27,
    "gn:feature_class":"P",
    "gn:feature_code":"PPL",
    "gn:name":"Masa",
    "gn:population":0,
    "gn:timezone":"Africa/Freetown",
    "iso:country":"SL",
    "name:eng_x_preferred":[
        "Masa"
    ],
    "name:fra_x_preferred":[
        "Masa"
    ],
    "name:kor_x_preferred":[
        "\ub9c8\uc0ac"
    ],
    "name:msa_x_preferred":[
        "Masa"
    ],
    "name:ukr_x_preferred":[
        "\u041c\u0430\u0441\u0430"
    ],
    "name:zho_x_preferred":[
        "\u9a6c\u8428"
    ],
    "wof:name":"Masa",
    "wof:placetype":"locality"
},
  "geometry": {"coordinates":[-12.64437,8.12356],"type":"Point"}
}