{
  "type": "Feature",
  "properties": {
    "gn:admin1_code":"2.0",
    "gn:asciiname":"Malal",
    "gn:country_code":"SL",
    "gn:dem":87,
    "gn:feature_class":"P",
    "gn:feature_code":"PPL",
    "gn:name":"Malal",
    "gn:population":0,
    "gn:timezone":"Africa/Freetown",
    "iso:country":"SL",
    "name:eng_x_preferred":[
        "Malal"
    ],
    "wof:name":"Malal",
    "wof:placetype":"locality"
},
  "geometry": {"coordinates":[-12.27383,9.29268],"type":"Point"}
}