{
  "type": "Feature",
  "properties": {
    "gn:admin1_code":"2.0",
    "gn:asciiname":"Kalanga",
    "gn:country_code":"SL",
    "gn:dem":325,
    "gn:feature_class":"P",
    "gn:feature_code":"PPL",
    "gn:name":"Kalanga",
    "gn:population":0,
    "gn:timezone":"Africa/Freetown",
    "iso:country":"SL",
    "name:ceb_x_preferred":[
        "Kalanga"
    ],
    "name:deu_x_preferred":[
        "Kalanga"
    ],
    "name:eng_x_preferred":[
        "Kalanga"
    ],
    "name:fra_x_preferred":[
        "Kalanga"
    ],
    "name:ita_x_preferred":[
        "Kalanga"
    ],
    "name:swe_x_preferred":[
        "Kalanga"
    ],
    "wof:name":"Kalanga",
    "wof:placetype":"locality"
},
  "geometry": {"coordinates":[-11.89966,9.544],"type":"Point"}
}