{
  "type": "Feature",
  "properties": {
    "gn:admin1_code":"1.0",
    "gn:asciiname":"Gbemaia",
    "gn:country_code":"SL",
    "gn:dem":432,
    "gn:feature_class":"P",
    "gn:feature_code":"PPL",
    "gn:name":"Gbemaia",
    "gn:population":0,
    "gn:timezone":"Africa/Freetown",
    "iso:country":"SL",
    "name:eng_x_preferred":[
        "Gbemaia"
    ],
    "wof:name":"Gbemaia",
    "wof:placetype":"locality"
},
  "geometry": {"coordinates":[-11.11597,8.90852],"type":"Point"}
}