{
  "type": "Feature",
  "properties": {
    "gn:admin1_code":"1.0",
    "gn:asciiname":"Kambda",
    "gn:country_code":"SL",
    "gn:dem":312,
    "gn:feature_class":"P",
    "gn:feature_code":"PPL",
    "gn:name":"Kambda",
    "gn:population":0,
    "gn:timezone":"Africa/Freetown",
    "iso:country":"SL",
    "name:eng_x_preferred":[
        "Kambda"
    ],
    "wof:name":"Kambda",
    "wof:placetype":"locality"
},
  "geometry": {"coordinates":[-10.54889,8.67754],"type":"Point"}
}