{
  "type": "Feature",
  "properties": {
    "gn:admin1_code":"01",
    "gn:asciiname":"Sedu",
    "gn:country_code":"SL",
    "gn:dem":499,
    "gn:feature_class":"P",
    "gn:feature_code":"PPL",
    "gn:name":"Sedu",
    "gn:population":0,
    "gn:timezone":"Africa/Freetown",
    "iso:country":"SL",
    "name:eng_x_preferred":[
        "Sedu"
    ],
    "wof:name":"Sedu",
    "wof:placetype":"locality"
},
  "geometry": {"coordinates":[-10.71667,8.88333],"type":"Point"}
}