{
  "type": "Feature",
  "properties": {
    "gn:admin1_code":"1.0",
    "gn:asciiname":"Sambo",
    "gn:country_code":"SL",
    "gn:dem":511,
    "gn:feature_class":"P",
    "gn:feature_code":"PPL",
    "gn:name":"Sambo",
    "gn:population":0,
    "gn:timezone":"Africa/Freetown",
    "iso:country":"SL",
    "name:ceb_x_preferred":[
        "Sambo"
    ],
    "name:dan_x_preferred":[
        "Sambo"
    ],
    "name:deu_x_preferred":[
        "Sambo"
    ],
    "name:eng_x_preferred":[
        "Sambo"
    ],
    "name:epo_x_preferred":[
        "Sambo"
    ],
    "name:heb_x_preferred":[
        "\u05e1\u05de\u05d1\u05d5"
    ],
    "name:ita_x_preferred":[
        "Sambo"
    ],
    "name:jpn_x_preferred":[
        "\u30b5\u30f3\u30dc"
    ],
    "name:nor_x_preferred":[
        "Sambo"
    ],
    "name:pol_x_preferred":[
        "Sambo"
    ],
    "name:por_x_preferred":[
        "Sambo"
    ],
    "name:rus_x_preferred":[
        "\u0421\u0430\u043c\u0431\u043e"
    ],
    "name:slk_x_preferred":[
        "Sambo"
    ],
    "name:swe_x_preferred":[
        "Sambo"
    ],
    "name:ukr_x_preferred":[
        "\u0421\u0430\u043c\u0431\u043e"
    ],
    "wof:name":"Sambo",
    "wof:placetype":"locality"
},
  "geometry": {"coordinates":[-10.96805,8.98523],"type":"Point"}
}