{
  "type": "Feature",
  "properties": {
    "gn:admin1_code":"02",
    "gn:asciiname":"Sekodeko",
    "gn:country_code":"SL",
    "gn:dem":102,
    "gn:feature_class":"P",
    "gn:feature_code":"PPL",
    "gn:name":"Sekodeko",
    "gn:population":0,
    "gn:timezone":"Africa/Freetown",
    "iso:country":"SL",
    "name:eng_x_preferred":[
        "Sekodeko"
    ],
    "wof:name":"Sekodeko",
    "wof:placetype":"locality"
},
  "geometry": {"coordinates":[-12.41907,9.8166],"type":"Point"}
}