{
  "type": "Feature",
  "properties": {
    "gn:admin1_code":"1.0",
    "gn:asciiname":"Bundema",
    "gn:country_code":"SL",
    "gn:dem":258,
    "gn:feature_class":"P",
    "gn:feature_code":"PPL",
    "gn:name":"Bundema",
    "gn:population":0,
    "gn:timezone":"Africa/Freetown",
    "iso:country":"SL",
    "wof:name":"Bundema",
    "wof:placetype":"locality"
},
  "geometry": {"coordinates":[-10.71667,8.31667],"type":"Point"}
}