{
  "type": "Feature",
  "properties": {
    "gn:admin1_code":"3.0",
    "gn:asciiname":"Lawana",
    "gn:country_code":"SL",
    "gn:dem":32,
    "gn:feature_class":"P",
    "gn:feature_code":"PPL",
    "gn:name":"Lawana",
    "gn:population":0,
    "gn:timezone":"Africa/Freetown",
    "iso:country":"SL",
    "name:und_x_variant":[
        "Laoma",
        "Lawana"
    ],
    "wof:name":"Lawana",
    "wof:placetype":"locality"
},
  "geometry": {"coordinates":[-12.0145,7.6429],"type":"Point"}
}