{
  "type": "Feature",
  "properties": {
    "gn:admin1_code":"1.0",
    "gn:asciiname":"Bandajuma",
    "gn:country_code":"SL",
    "gn:dem":219,
    "gn:feature_class":"P",
    "gn:feature_code":"PPL",
    "gn:name":"Bandajuma",
    "gn:population":0,
    "gn:timezone":"Africa/Freetown",
    "iso:country":"SL",
    "name:eng_x_preferred":[
        "Bandajuma"
    ],
    "wof:name":"Bandajuma",
    "wof:placetype":"locality"
},
  "geometry": {"coordinates":[-10.92316,8.23148],"type":"Point"}
}