{
  "type": "Feature",
  "properties": {
    "gn:admin1_code":"3.0",
    "gn:asciiname":"Gewenga",
    "gn:country_code":"SL",
    "gn:dem":53,
    "gn:feature_class":"P",
    "gn:feature_code":"PPL",
    "gn:name":"Gewenga",
    "gn:population":0,
    "gn:timezone":"Africa/Freetown",
    "iso:country":"SL",
    "name:eng_x_preferred":[
        "Gewenga"
    ],
    "wof:name":"Gewenga",
    "wof:placetype":"locality"
},
  "geometry": {"coordinates":[-12.40659,7.97135],"type":"Point"}
}