{
  "type": "Feature",
  "properties": {
    "gn:admin1_code":"2.0",
    "gn:asciiname":"Mansonia",
    "gn:country_code":"SL",
    "gn:dem":426,
    "gn:feature_class":"P",
    "gn:feature_code":"PPL",
    "gn:name":"Mansonia",
    "gn:population":0,
    "gn:timezone":"Africa/Freetown",
    "iso:country":"SL",
    "name:eng_x_preferred":[
        "Mansonia"
    ],
    "wof:name":"Mansonia",
    "wof:placetype":"locality"
},
  "geometry": {"coordinates":[-11.08488,9.13024],"type":"Point"}
}