{
  "type": "Feature",
  "properties": {
    "gn:admin1_code":"2.0",
    "gn:asciiname":"Manyaga",
    "gn:country_code":"SL",
    "gn:dem":110,
    "gn:feature_class":"P",
    "gn:feature_code":"PPL",
    "gn:name":"Manyaga",
    "gn:population":0,
    "gn:timezone":"Africa/Freetown",
    "iso:country":"SL",
    "name:eng_x_preferred":[
        "Manyaga"
    ],
    "wof:name":"Manyaga",
    "wof:placetype":"locality"
},
  "geometry": {"coordinates":[-12.13932,9.23226],"type":"Point"}
}