{
  "type": "Feature",
  "properties": {
    "gn:admin1_code":"2.0",
    "gn:asciiname":"Mayora",
    "gn:country_code":"SL",
    "gn:dem":93,
    "gn:feature_class":"P",
    "gn:feature_code":"PPL",
    "gn:name":"Mayora",
    "gn:population":0,
    "gn:timezone":"Africa/Freetown",
    "iso:country":"SL",
    "name:eng_x_preferred":[
        "Mayora"
    ],
    "wof:name":"Mayora",
    "wof:placetype":"locality"
},
  "geometry": {"coordinates":[-12.54558,9.04617],"type":"Point"}
}