{
  "type": "Feature",
  "properties": {
    "gn:admin1_code":"3.0",
    "gn:asciiname":"Kupung",
    "gn:country_code":"SL",
    "gn:dem":19,
    "gn:feature_class":"P",
    "gn:feature_code":"PPL",
    "gn:name":"Kupung",
    "gn:population":0,
    "gn:timezone":"Africa/Freetown",
    "iso:country":"SL",
    "name:eng_x_preferred":[
        "Kupung"
    ],
    "wof:name":"Kupung",
    "wof:placetype":"locality"
},
  "geometry": {"coordinates":[-11.70199,7.15305],"type":"Point"}
}