{
  "type": "Feature",
  "properties": {
    "gn:admin1_code":"03",
    "gn:asciiname":"Yakagi",
    "gn:country_code":"SL",
    "gn:dem":18,
    "gn:feature_class":"P",
    "gn:feature_code":"PPL",
    "gn:name":"Yakagi",
    "gn:population":0,
    "gn:timezone":"Africa/Freetown",
    "iso:country":"SL",
    "name:eng_x_preferred":[
        "Yakagi"
    ],
    "wof:name":"Yakagi",
    "wof:placetype":"locality"
},
  "geometry": {"coordinates":[-12.71846,7.82106],"type":"Point"}
}