{
  "type": "Feature",
  "properties": {
    "gn:admin1_code":"4.0",
    "gn:asciiname":"Ma-samana",
    "gn:country_code":"SL",
    "gn:dem":29,
    "gn:feature_class":"P",
    "gn:feature_code":"PPL",
    "gn:name":"Ma-samana",
    "gn:population":0,
    "gn:timezone":"Africa/Freetown",
    "iso:country":"SL",
    "name:eng_x_preferred":[
        "Ma-samana"
    ],
    "wof:name":"Ma-samana",
    "wof:placetype":"locality"
},
  "geometry": {"coordinates":[-13.01418,8.36437],"type":"Point"}
}