{
  "type": "Feature",
  "properties": {
    "gn:admin1_code":"02",
    "gn:asciiname":"Tinkifira",
    "gn:country_code":"SL",
    "gn:dem":433,
    "gn:feature_class":"P",
    "gn:feature_code":"PPL",
    "gn:name":"Tinkifira",
    "gn:population":0,
    "gn:timezone":"Africa/Freetown",
    "iso:country":"SL",
    "name:eng_x_preferred":[
        "Tinkifira"
    ],
    "name:und_x_variant":[
        "Tinglfira",
        "Tingipira"
    ],
    "wof:name":"Tinkifira",
    "wof:placetype":"locality"
},
  "geometry": {"coordinates":[-11.21076,9.63727],"type":"Point"}
}