{
  "type": "Feature",
  "properties": {
    "gn:admin1_code":"01",
    "gn:asciiname":"Yuabu",
    "gn:country_code":"SL",
    "gn:dem":346,
    "gn:feature_class":"P",
    "gn:feature_code":"PPL",
    "gn:name":"Yuabu",
    "gn:population":0,
    "gn:timezone":"Africa/Freetown",
    "iso:country":"SL",
    "name:eng_x_preferred":[
        "Yuabu"
    ],
    "wof:name":"Yuabu",
    "wof:placetype":"locality"
},
  "geometry": {"coordinates":[-11.4879,8.35147],"type":"Point"}
}