{
  "type": "Feature",
  "properties": {
    "gn:admin1_code":"2.0",
    "gn:asciiname":"Kuligbe",
    "gn:country_code":"SL",
    "gn:dem":366,
    "gn:feature_class":"P",
    "gn:feature_code":"PPL",
    "gn:name":"Kuligbe",
    "gn:population":0,
    "gn:timezone":"Africa/Freetown",
    "iso:country":"SL",
    "name:eng_x_preferred":[
        "Kuligbe"
    ],
    "wof:name":"Kuligbe",
    "wof:placetype":"locality"
},
  "geometry": {"coordinates":[-11.76163,9.75789],"type":"Point"}
}