{
  "type": "Feature",
  "properties": {
    "gn:admin1_code":"2.0",
    "gn:asciiname":"Kakanti",
    "gn:country_code":"SL",
    "gn:dem":120,
    "gn:feature_class":"P",
    "gn:feature_code":"PPL",
    "gn:name":"Kakanti",
    "gn:population":0,
    "gn:timezone":"Africa/Freetown",
    "iso:country":"SL",
    "name:eng_x_preferred":[
        "Kakanti"
    ],
    "wof:name":"Kakanti",
    "wof:placetype":"locality"
},
  "geometry": {"coordinates":[-12.27844,9.53905],"type":"Point"}
}