{
  "type": "Feature",
  "properties": {
    "gn:admin1_code":"3.0",
    "gn:asciiname":"Golala",
    "gn:country_code":"SL",
    "gn:dem":103,
    "gn:feature_class":"P",
    "gn:feature_code":"PPL",
    "gn:name":"Golala",
    "gn:population":0,
    "gn:timezone":"Africa/Freetown",
    "iso:country":"SL",
    "name:und_x_variant":[
        "Golalo"
    ],
    "wof:name":"Golala",
    "wof:placetype":"locality"
},
  "geometry": {"coordinates":[-11.56808,7.82436],"type":"Point"}
}