{
  "type": "Feature",
  "properties": {
    "gn:admin1_code":"2.0",
    "gn:asciiname":"Kamaro",
    "gn:country_code":"SL",
    "gn:dem":484,
    "gn:feature_class":"P",
    "gn:feature_code":"PPL",
    "gn:name":"Kamaro",
    "gn:population":0,
    "gn:timezone":"Africa/Freetown",
    "iso:country":"SL",
    "name:eng_x_preferred":[
        "Kamaro"
    ],
    "wof:name":"Kamaro",
    "wof:placetype":"locality"
},
  "geometry": {"coordinates":[-11.14848,8.97898],"type":"Point"}
}