{
  "type": "Feature",
  "properties": {
    "gn:admin1_code":"03",
    "gn:asciiname":"Kendi",
    "gn:country_code":"SL",
    "gn:dem":110,
    "gn:feature_class":"P",
    "gn:feature_code":"PPL",
    "gn:name":"Kendi",
    "gn:population":0,
    "gn:timezone":"Africa/Freetown",
    "iso:country":"SL",
    "name:eng_x_preferred":[
        "Kendi"
    ],
    "name:und_x_variant":[
        "Petema"
    ],
    "wof:name":"Kendi",
    "wof:placetype":"locality"
},
  "geometry": {"coordinates":[-11.63788,8.03832],"type":"Point"}
}