{
  "type": "Feature",
  "properties": {
    "gn:admin1_code":"2.0",
    "gn:asciiname":"Mamudia",
    "gn:country_code":"SL",
    "gn:dem":499,
    "gn:feature_class":"P",
    "gn:feature_code":"PPL",
    "gn:name":"Mamudia",
    "gn:population":0,
    "gn:timezone":"Africa/Freetown",
    "iso:country":"SL",
    "name:eng_x_preferred":[
        "Mamudia"
    ],
    "wof:name":"Mamudia",
    "wof:placetype":"locality"
},
  "geometry": {"coordinates":[-11.65839,9.79934],"type":"Point"}
}