{
  "type": "Feature",
  "properties": {
    "gn:admin1_code":"1.0",
    "gn:asciiname":"Sokebubu",
    "gn:country_code":"SL",
    "gn:dem":113,
    "gn:feature_class":"P",
    "gn:feature_code":"PPL",
    "gn:name":"Sokebubu",
    "gn:population":0,
    "gn:timezone":"Africa/Freetown",
    "iso:country":"SL",
    "name:eng_x_preferred":[
        "Sokebubu"
    ],
    "wof:name":"Sokebubu",
    "wof:placetype":"locality"
},
  "geometry": {"coordinates":[-11.39817,7.75872],"type":"Point"}
}