{
  "type": "Feature",
  "properties": {
    "gn:admin1_code":"3.0",
    "gn:asciiname":"Mokainwa",
    "gn:country_code":"SL",
    "gn:dem":14,
    "gn:feature_class":"P",
    "gn:feature_code":"PPL",
    "gn:name":"Mokainwa",
    "gn:population":0,
    "gn:timezone":"Africa/Freetown",
    "iso:country":"SL",
    "name:eng_x_preferred":[
        "Mokainwa"
    ],
    "name:und_x_variant":[
        "Mokenewa"
    ],
    "wof:name":"Mokainwa",
    "wof:placetype":"locality"
},
  "geometry": {"coordinates":[-12.3127,7.4905],"type":"Point"}
}