{
  "type": "Feature",
  "properties": {
    "gn:admin1_code":"3.0",
    "gn:asciiname":"Sumbuya",
    "gn:country_code":"SL",
    "gn:dem":26,
    "gn:feature_class":"P",
    "gn:feature_code":"PPL",
    "gn:name":"Sumbuya",
    "gn:population":0,
    "gn:timezone":"Africa/Freetown",
    "iso:country":"SL",
    "name:eng_x_preferred":[
        "Sumbuya"
    ],
    "wof:name":"Sumbuya",
    "wof:placetype":"locality"
},
  "geometry": {"coordinates":[-12.65242,8.11078],"type":"Point"}
}