{
  "type": "Feature",
  "properties": {
    "gn:admin1_code":"1.0",
    "gn:asciiname":"Periwahun",
    "gn:country_code":"SL",
    "gn:dem":155,
    "gn:feature_class":"P",
    "gn:feature_code":"PPL",
    "gn:name":"Periwahun",
    "gn:population":0,
    "gn:timezone":"Africa/Freetown",
    "iso:country":"SL",
    "name:eng_x_preferred":[
        "Periwahun"
    ],
    "wof:name":"Periwahun",
    "wof:placetype":"locality"
},
  "geometry": {"coordinates":[-11.28303,8.03977],"type":"Point"}
}