{
  "type": "Feature",
  "properties": {
    "gn:admin1_code":"1.0",
    "gn:asciiname":"Foindu",
    "gn:country_code":"SL",
    "gn:dem":322,
    "gn:feature_class":"P",
    "gn:feature_code":"PPL",
    "gn:name":"Foindu",
    "gn:population":0,
    "gn:timezone":"Africa/Freetown",
    "iso:country":"SL",
    "name:eng_x_preferred":[
        "Foindu"
    ],
    "wof:name":"Foindu",
    "wof:placetype":"locality"
},
  "geometry": {"coordinates":[-11.30384,8.57217],"type":"Point"}
}