{
  "type": "Feature",
  "properties": {
    "gn:admin1_code":"02",
    "gn:asciiname":"Yenkisa",
    "gn:country_code":"SL",
    "gn:dem":403,
    "gn:feature_class":"P",
    "gn:feature_code":"PPL",
    "gn:name":"Yenkisa",
    "gn:population":0,
    "gn:timezone":"Africa/Freetown",
    "iso:country":"SL",
    "wof:name":"Yenkisa",
    "wof:placetype":"locality"
},
  "geometry": {"coordinates":[-11.46667,9.81667],"type":"Point"}
}