{
  "type": "Feature",
  "properties": {
    "gn:admin1_code":"2.0",
    "gn:asciiname":"Pepel",
    "gn:country_code":"SL",
    "gn:dem":66,
    "gn:feature_class":"P",
    "gn:feature_code":"PPL",
    "gn:name":"Pepel",
    "gn:population":0,
    "gn:timezone":"Africa/Freetown",
    "iso:country":"SL",
    "name:ceb_x_preferred":[
        "Pepel"
    ],
    "name:deu_x_preferred":[
        "Pepel"
    ],
    "name:eng_x_preferred":[
        "Pepel"
    ],
    "name:fin_x_preferred":[
        "Pepel"
    ],
    "name:nld_x_preferred":[
        "Pepel"
    ],
    "name:pol_x_preferred":[
        "Pepel"
    ],
    "name:por_x_preferred":[
        "Pepel"
    ],
    "wof:name":"Pepel",
    "wof:placetype":"locality"
},
  "geometry": {"coordinates":[-12.43624,8.85114],"type":"Point"}
}