{
  "type": "Feature",
  "properties": {
    "gn:admin1_code":"2.0",
    "gn:asciiname":"Sanda",
    "gn:country_code":"SL",
    "gn:dem":29,
    "gn:feature_class":"P",
    "gn:feature_code":"PPL",
    "gn:name":"Sanda",
    "gn:population":0,
    "gn:timezone":"Africa/Freetown",
    "iso:country":"SL",
    "name:bul_x_preferred":[
        "\u0421\u0430\u043d\u0434\u0430"
    ],
    "name:ceb_x_preferred":[
        "Sanda"
    ],
    "name:deu_x_preferred":[
        "Sanda"
    ],
    "name:eng_x_preferred":[
        "Sanda"
    ],
    "name:fra_x_preferred":[
        "Sanda"
    ],
    "name:hin_x_preferred":[
        "\u0938\u093e\u0902\u0921\u093e"
    ],
    "name:jpn_x_preferred":[
        "\u30b5\u30f3\u30c0"
    ],
    "name:nld_x_preferred":[
        "Sanda"
    ],
    "name:pol_x_preferred":[
        "Sanda"
    ],
    "name:por_x_preferred":[
        "Sanda"
    ],
    "name:ron_x_preferred":[
        "Sanda"
    ],
    "name:rus_x_preferred":[
        "\u0421\u0430\u043d\u0434\u0430"
    ],
    "name:swe_x_preferred":[
        "Sanda"
    ],
    "wof:name":"Sanda",
    "wof:placetype":"locality"
},
  "geometry": {"coordinates":[-13.20664,8.65237],"type":"Point"}
}