{
  "type": "Feature",
  "properties": {
    "gn:admin1_code":"2.0",
    "gn:asciiname":"Sanda",
    "gn:country_code":"SL",
    "gn:dem":29,
    "gn:feature_class":"P",
    "gn:feature_code":"PPL",
    "gn:name":"Sanda",
    "gn:population":0,
    "gn:timezone":"Africa/Freetown",
    "iso:country":"SL",
    "name:eng_x_preferred":[
        "Sanda"
    ],
    "wof:name":"Sanda",
    "wof:placetype":"locality"
},
  "geometry": {"coordinates":[-13.20664,8.65237],"type":"Point"}
}