{
  "type": "Feature",
  "properties": {
    "gn:admin1_code":"01",
    "gn:asciiname":"Turadu",
    "gn:country_code":"SL",
    "gn:dem":414,
    "gn:feature_class":"P",
    "gn:feature_code":"PPL",
    "gn:name":"Turadu",
    "gn:population":0,
    "gn:timezone":"Africa/Freetown",
    "iso:country":"SL",
    "name:eng_x_preferred":[
        "Turadu"
    ],
    "wof:name":"Turadu",
    "wof:placetype":"locality"
},
  "geometry": {"coordinates":[-10.29753,8.4686],"type":"Point"}
}