{
  "type": "Feature",
  "properties": {
    "gn:admin1_code":"3.0",
    "gn:asciiname":"Blama",
    "gn:country_code":"SL",
    "gn:dem":42,
    "gn:feature_class":"P",
    "gn:feature_code":"PPL",
    "gn:name":"Blama",
    "gn:population":0,
    "gn:timezone":"Africa/Freetown",
    "iso:country":"SL",
    "name:eng_x_preferred":[
        "Blama"
    ],
    "wof:name":"Blama",
    "wof:placetype":"locality"
},
  "geometry": {"coordinates":[-11.81992,7.35762],"type":"Point"}
}