{
  "type": "Feature",
  "properties": {
    "gn:admin1_code":"3.0",
    "gn:asciiname":"Batiama",
    "gn:country_code":"SL",
    "gn:dem":60,
    "gn:feature_class":"P",
    "gn:feature_code":"PPL",
    "gn:name":"Batiama",
    "gn:population":0,
    "gn:timezone":"Africa/Freetown",
    "iso:country":"SL",
    "name:eng_x_preferred":[
        "Batiama"
    ],
    "wof:name":"Batiama",
    "wof:placetype":"locality"
},
  "geometry": {"coordinates":[-12.46492,8.2702],"type":"Point"}
}