{
  "type": "Feature",
  "properties": {
    "gn:admin1_code":"3.0",
    "gn:asciiname":"Gonorhun",
    "gn:country_code":"SL",
    "gn:dem":30,
    "gn:feature_class":"P",
    "gn:feature_code":"PPL",
    "gn:name":"Gonorhun",
    "gn:population":0,
    "gn:timezone":"Africa/Freetown",
    "iso:country":"SL",
    "name:eng_x_preferred":[
        "Gonorhun"
    ],
    "wof:name":"Gonorhun",
    "wof:placetype":"locality"
},
  "geometry": {"coordinates":[-11.57501,7.25566],"type":"Point"}
}