{
  "type": "Feature",
  "properties": {
    "gn:admin1_code":"2.0",
    "gn:asciiname":"Madigba",
    "gn:country_code":"SL",
    "gn:dem":25,
    "gn:feature_class":"P",
    "gn:feature_code":"PPL",
    "gn:name":"Madigba",
    "gn:population":0,
    "gn:timezone":"Africa/Freetown",
    "iso:country":"SL",
    "name:eng_x_preferred":[
        "Madigba"
    ],
    "wof:name":"Madigba",
    "wof:placetype":"locality"
},
  "geometry": {"coordinates":[-12.81451,8.58391],"type":"Point"}
}