{
  "type": "Feature",
  "properties": {
    "gn:admin1_code":"01",
    "gn:asciiname":"Swai Sawakor",
    "gn:country_code":"SL",
    "gn:dem":454,
    "gn:feature_class":"P",
    "gn:feature_code":"PPL",
    "gn:name":"Swai Sawakor",
    "gn:population":0,
    "gn:timezone":"Africa/Freetown",
    "iso:country":"SL",
    "name:eng_x_preferred":[
        "Swai Sawakor"
    ],
    "name:und_x_variant":[
        "Sawi",
        "Saokoro"
    ],
    "wof:name":"Swai Sawakor",
    "wof:placetype":"locality"
},
  "geometry": {"coordinates":[-10.8439,8.66349],"type":"Point"}
}