{
  "type": "Feature",
  "properties": {
    "gn:admin1_code":"1.0",
    "gn:asciiname":"Gbonima",
    "gn:country_code":"SL",
    "gn:dem":106,
    "gn:feature_class":"P",
    "gn:feature_code":"PPL",
    "gn:name":"Gbonima",
    "gn:population":0,
    "gn:timezone":"Africa/Freetown",
    "iso:country":"SL",
    "name:eng_x_preferred":[
        "Gbonima"
    ],
    "wof:name":"Gbonima",
    "wof:placetype":"locality"
},
  "geometry": {"coordinates":[-11.49227,7.5801],"type":"Point"}
}