{
  "type": "Feature",
  "properties": {
    "gn:admin1_code":"1.0",
    "gn:asciiname":"Bankanbaia",
    "gn:country_code":"SL",
    "gn:dem":382,
    "gn:feature_class":"P",
    "gn:feature_code":"PPL",
    "gn:name":"Bankanbaia",
    "gn:population":0,
    "gn:timezone":"Africa/Freetown",
    "iso:country":"SL",
    "name:eng_x_preferred":[
        "Bankanbaia"
    ],
    "wof:name":"Bankanbaia",
    "wof:placetype":"locality"
},
  "geometry": {"coordinates":[-11.17148,8.81907],"type":"Point"}
}