{
  "type": "Feature",
  "properties": {
    "gn:admin1_code":"3.0",
    "gn:asciiname":"Gandonhun",
    "gn:country_code":"SL",
    "gn:dem":64,
    "gn:feature_class":"P",
    "gn:feature_code":"PPL",
    "gn:name":"Gandonhun",
    "gn:population":0,
    "gn:timezone":"Africa/Freetown",
    "iso:country":"SL",
    "name:eng_x_preferred":[
        "Gandonhun"
    ],
    "wof:name":"Gandonhun",
    "wof:placetype":"locality"
},
  "geometry": {"coordinates":[-12.0994,7.74682],"type":"Point"}
}