{
  "type": "Feature",
  "properties": {
    "gn:admin1_code":"03",
    "gn:asciiname":"Yikandor",
    "gn:country_code":"SL",
    "gn:dem":37,
    "gn:feature_class":"P",
    "gn:feature_code":"PPL",
    "gn:name":"Yikandor",
    "gn:population":0,
    "gn:timezone":"Africa/Freetown",
    "iso:country":"SL",
    "name:eng_x_preferred":[
        "Yikandor"
    ],
    "name:und_x_variant":[
        "Yikabdaw",
        "Yikandaw"
    ],
    "wof:name":"Yikandor",
    "wof:placetype":"locality"
},
  "geometry": {"coordinates":[-11.76763,7.36489],"type":"Point"}
}