{
  "type": "Feature",
  "properties": {
    "gn:admin1_code":"3.0",
    "gn:asciiname":"Komendi",
    "gn:country_code":"SL",
    "gn:dem":92,
    "gn:feature_class":"P",
    "gn:feature_code":"PPL",
    "gn:name":"Komendi",
    "gn:population":0,
    "gn:timezone":"Africa/Freetown",
    "iso:country":"SL",
    "name:und_x_variant":[
        "Komende",
        "Komendi"
    ],
    "wof:name":"Komendi",
    "wof:placetype":"locality"
},
  "geometry": {"coordinates":[-11.40414,7.42964],"type":"Point"}
}