{
  "type": "Feature",
  "properties": {
    "gn:admin1_code":"2.0",
    "gn:asciiname":"Bariwa",
    "gn:country_code":"SL",
    "gn:dem":75,
    "gn:feature_class":"P",
    "gn:feature_code":"PPL",
    "gn:name":"Bariwa",
    "gn:population":0,
    "gn:timezone":"Africa/Freetown",
    "iso:country":"SL",
    "name:eng_x_preferred":[
        "Bariwa"
    ],
    "wof:name":"Bariwa",
    "wof:placetype":"locality"
},
  "geometry": {"coordinates":[-12.12658,8.45095],"type":"Point"}
}