{
  "type": "Feature",
  "properties": {
    "gn:admin1_code":"1.0",
    "gn:asciiname":"Mofindo",
    "gn:country_code":"SL",
    "gn:dem":366,
    "gn:feature_class":"P",
    "gn:feature_code":"PPL",
    "gn:name":"Mofindo",
    "gn:population":0,
    "gn:timezone":"Africa/Freetown",
    "iso:country":"SL",
    "name:eng_x_preferred":[
        "Mofindo"
    ],
    "wof:name":"Mofindo",
    "wof:placetype":"locality"
},
  "geometry": {"coordinates":[-10.70799,8.53474],"type":"Point"}
}