{
  "type": "Feature",
  "properties": {
    "gn:admin1_code":"2.0",
    "gn:asciiname":"Funikia",
    "gn:country_code":"SL",
    "gn:dem":63,
    "gn:feature_class":"P",
    "gn:feature_code":"PPL",
    "gn:name":"Funikia",
    "gn:population":0,
    "gn:timezone":"Africa/Freetown",
    "iso:country":"SL",
    "name:eng_x_preferred":[
        "Funikia"
    ],
    "wof:name":"Funikia",
    "wof:placetype":"locality"
},
  "geometry": {"coordinates":[-12.42754,8.69669],"type":"Point"}
}