{
  "type": "Feature",
  "properties": {
    "gn:admin1_code":"3.0",
    "gn:asciiname":"Kpademi",
    "gn:country_code":"SL",
    "gn:dem":63,
    "gn:feature_class":"P",
    "gn:feature_code":"PPL",
    "gn:name":"Kpademi",
    "gn:population":0,
    "gn:timezone":"Africa/Freetown",
    "iso:country":"SL",
    "name:eng_x_preferred":[
        "Kpademi"
    ],
    "wof:name":"Kpademi",
    "wof:placetype":"locality"
},
  "geometry": {"coordinates":[-12.00351,7.8815],"type":"Point"}
}