{
  "type": "Feature",
  "properties": {
    "gn:admin1_code":"2.0",
    "gn:asciiname":"Mansonya",
    "gn:country_code":"SL",
    "gn:dem":45,
    "gn:feature_class":"P",
    "gn:feature_code":"PPL",
    "gn:name":"Mansonya",
    "gn:population":0,
    "gn:timezone":"Africa/Freetown",
    "iso:country":"SL",
    "name:eng_x_preferred":[
        "Mansonya"
    ],
    "wof:name":"Mansonya",
    "wof:placetype":"locality"
},
  "geometry": {"coordinates":[-12.87982,9.26055],"type":"Point"}
}