{
  "type": "Feature",
  "properties": {
    "gn:admin1_code":"3.0",
    "gn:asciiname":"Kotumahun",
    "gn:country_code":"SL",
    "gn:dem":102,
    "gn:feature_class":"P",
    "gn:feature_code":"PPL",
    "gn:name":"Kotumahun",
    "gn:population":0,
    "gn:timezone":"Africa/Freetown",
    "iso:country":"SL",
    "name:eng_x_preferred":[
        "Kotumahun"
    ],
    "wof:name":"Kotumahun",
    "wof:placetype":"locality"
},
  "geometry": {"coordinates":[-11.7972,8.05284],"type":"Point"}
}