{
  "type": "Feature",
  "properties": {
    "gn:admin1_code":"3.0",
    "gn:asciiname":"Wobul",
    "gn:country_code":"SL",
    "gn:dem":17,
    "gn:feature_class":"P",
    "gn:feature_code":"PPL",
    "gn:name":"Wobul",
    "gn:population":0,
    "gn:timezone":"Africa/Freetown",
    "iso:country":"SL",
    "name:eng_x_preferred":[
        "Wobul"
    ],
    "wof:name":"Wobul",
    "wof:placetype":"locality"
},
  "geometry": {"coordinates":[-11.89592,7.39496],"type":"Point"}
}