{
  "type": "Feature",
  "properties": {
    "gn:admin1_code":"3.0",
    "gn:asciiname":"Matemei",
    "gn:country_code":"SL",
    "gn:dem":157,
    "gn:feature_class":"P",
    "gn:feature_code":"PPL",
    "gn:name":"Matemei",
    "gn:population":0,
    "gn:timezone":"Africa/Freetown",
    "iso:country":"SL",
    "name:eng_x_preferred":[
        "Matemei"
    ],
    "name:und_x_variant":[
        "Matama"
    ],
    "wof:name":"Matemei",
    "wof:placetype":"locality"
},
  "geometry": {"coordinates":[-11.3987,8.03949],"type":"Point"}
}