{
  "type": "Feature",
  "properties": {
    "gn:admin1_code":"2.0",
    "gn:asciiname":"Sinaia",
    "gn:country_code":"SL",
    "gn:dem":48,
    "gn:feature_class":"P",
    "gn:feature_code":"PPL",
    "gn:name":"Sinaia",
    "gn:population":0,
    "gn:timezone":"Africa/Freetown",
    "iso:country":"SL",
    "name:ara_x_preferred":[
        "\u0633\u064a\u0646\u0627\u064a\u0627"
    ],
    "name:arz_x_preferred":[
        "\u0633\u064a\u0646\u0627\u064a\u0627"
    ],
    "name:bel_x_preferred":[
        "\u0421\u0456\u043d\u0430\u044f"
    ],
    "name:ben_x_preferred":[
        "\u09b8\u09bf\u09a8\u09be\u09af\u09bc\u09be"
    ],
    "name:bul_x_preferred":[
        "\u0421\u0438\u043d\u0430\u044f"
    ],
    "name:cat_x_preferred":[
        "Sinaia"
    ],
    "name:ceb_x_preferred":[
        "Ora\u0219 Sinaia"
    ],
    "name:dan_x_preferred":[
        "Sinaia"
    ],
    "name:deu_x_preferred":[
        "Sinaia"
    ],
    "name:eng_x_preferred":[
        "Sinaia"
    ],
    "name:epo_x_preferred":[
        "Sinaia"
    ],
    "name:fas_x_preferred":[
        "\u0633\u06cc\u0646\u0627\u06cc\u0627"
    ],
    "name:fin_x_preferred":[
        "Sinaia"
    ],
    "name:fra_x_preferred":[
        "Sinaia"
    ],
    "name:heb_x_preferred":[
        "\u05e1\u05d9\u05e0\u05d0\u05d9\u05d4"
    ],
    "name:hun_x_preferred":[
        "Sinaia"
    ],
    "name:ind_x_preferred":[
        "Sinaia"
    ],
    "name:ita_x_preferred":[
        "Sinaia"
    ],
    "name:jpn_x_preferred":[
        "\u30b7\u30ca\u30e4"
    ],
    "name:kat_x_preferred":[
        "\u10e1\u10d8\u10dc\u10d0\u10d8\u10d0"
    ],
    "name:kor_x_preferred":[
        "\uc2dc\ub098\uc774\uc544"
    ],
    "name:lat_x_preferred":[
        "Sinaia"
    ],
    "name:lit_x_preferred":[
        "Sinaja"
    ],
    "name:min_x_preferred":[
        "Sinaia"
    ],
    "name:msa_x_preferred":[
        "Sinaia"
    ],
    "name:nld_x_preferred":[
        "Sinaia"
    ],
    "name:nov_x_preferred":[
        "Sinaia"
    ],
    "name:pol_x_preferred":[
        "Sinaia"
    ],
    "name:por_x_preferred":[
        "Sinaia"
    ],
    "name:ron_x_preferred":[
        "Sinaia"
    ],
    "name:rus_x_preferred":[
        "\u0421\u0438\u043d\u0430\u044f"
    ],
    "name:sco_x_preferred":[
        "Sinaia"
    ],
    "name:slv_x_preferred":[
        "Sinaia"
    ],
    "name:spa_x_preferred":[
        "Sinaia"
    ],
    "name:srp_x_preferred":[
        "\u0421\u0438\u043d\u0430\u0458\u0430"
    ],
    "name:swe_x_preferred":[
        "Sinaia"
    ],
    "name:szl_x_preferred":[
        "Sinaia"
    ],
    "name:tgk_x_preferred":[
        "\u0421\u0438\u043d\u0430\u044f"
    ],
    "name:tur_x_preferred":[
        "Sinaia"
    ],
    "name:ukr_x_preferred":[
        "\u0421\u0456\u043d\u0430\u044f"
    ],
    "name:vie_x_preferred":[
        "Sinaia"
    ],
    "name:zho_x_preferred":[
        "\u932b\u7d0d\u4e9e"
    ],
    "wof:name":"Sinaia",
    "wof:placetype":"locality"
},
  "geometry": {"coordinates":[-12.66779,9.40517],"type":"Point"}
}