{
  "type": "Feature",
  "properties": {
    "gn:admin1_code":"2.0",
    "gn:asciiname":"Sinaia",
    "gn:country_code":"SL",
    "gn:dem":48,
    "gn:feature_class":"P",
    "gn:feature_code":"PPL",
    "gn:name":"Sinaia",
    "gn:population":0,
    "gn:timezone":"Africa/Freetown",
    "iso:country":"SL",
    "name:eng_x_preferred":[
        "Sinaia"
    ],
    "wof:name":"Sinaia",
    "wof:placetype":"locality"
},
  "geometry": {"coordinates":[-12.66779,9.40517],"type":"Point"}
}