{
  "type": "Feature",
  "properties": {
    "gn:admin1_code":"2.0",
    "gn:asciiname":"Tuba",
    "gn:country_code":"SL",
    "gn:dem":438,
    "gn:feature_class":"P",
    "gn:feature_code":"PPL",
    "gn:name":"Tuba",
    "gn:population":0,
    "gn:timezone":"Africa/Freetown",
    "iso:country":"SL",
    "name:eng_x_preferred":[
        "Tuba"
    ],
    "wof:name":"Tuba",
    "wof:placetype":"locality"
},
  "geometry": {"coordinates":[-11.05884,9.38704],"type":"Point"}
}