{
  "type": "Feature",
  "properties": {
    "gn:admin1_code":"2.0",
    "gn:asciiname":"Manga Tambaia",
    "gn:country_code":"SL",
    "gn:dem":386,
    "gn:feature_class":"P",
    "gn:feature_code":"PPL",
    "gn:name":"Manga Tambaia",
    "gn:population":0,
    "gn:timezone":"Africa/Freetown",
    "iso:country":"SL",
    "name:eng_x_preferred":[
        "Manga Tambaia"
    ],
    "wof:name":"Manga Tambaia",
    "wof:placetype":"locality"
},
  "geometry": {"coordinates":[-11.35303,9.87195],"type":"Point"}
}