{
  "type": "Feature",
  "properties": {
    "gn:admin1_code":"3.0",
    "gn:asciiname":"Lenbo",
    "gn:country_code":"SL",
    "gn:dem":19,
    "gn:feature_class":"P",
    "gn:feature_code":"PPL",
    "gn:name":"Lenbo",
    "gn:population":0,
    "gn:timezone":"Africa/Freetown",
    "iso:country":"SL",
    "name:eng_x_preferred":[
        "Lenbo"
    ],
    "wof:name":"Lenbo",
    "wof:placetype":"locality"
},
  "geometry": {"coordinates":[-11.96189,7.31768],"type":"Point"}
}