{
  "type": "Feature",
  "properties": {
    "gn:admin1_code":"1.0",
    "gn:asciiname":"Jopowahun",
    "gn:country_code":"SL",
    "gn:dem":173,
    "gn:feature_class":"P",
    "gn:feature_code":"PPL",
    "gn:name":"Jopowahun",
    "gn:population":0,
    "gn:timezone":"Africa/Freetown",
    "iso:country":"SL",
    "name:und_x_variant":[
        "Topowahun",
        "Jopowahun"
    ],
    "wof:name":"Jopowahun",
    "wof:placetype":"locality"
},
  "geometry": {"coordinates":[-11.04864,7.7446],"type":"Point"}
}