{
  "type": "Feature",
  "properties": {
    "gn:admin1_code":"3.0",
    "gn:asciiname":"Hima",
    "gn:country_code":"SL",
    "gn:dem":37,
    "gn:feature_class":"P",
    "gn:feature_code":"PPL",
    "gn:name":"Hima",
    "gn:population":0,
    "gn:timezone":"Africa/Freetown",
    "iso:country":"SL",
    "name:eng_x_preferred":[
        "Hima"
    ],
    "wof:name":"Hima",
    "wof:placetype":"locality"
},
  "geometry": {"coordinates":[-11.90102,7.73979],"type":"Point"}
}