{
  "type": "Feature",
  "properties": {
    "gn:admin1_code":"2.0",
    "gn:asciiname":"Mangugbe",
    "gn:country_code":"SL",
    "gn:dem":64,
    "gn:feature_class":"P",
    "gn:feature_code":"PPL",
    "gn:name":"Mangugbe",
    "gn:population":0,
    "gn:timezone":"Africa/Freetown",
    "iso:country":"SL",
    "name:eng_x_preferred":[
        "Mangugbe"
    ],
    "wof:name":"Mangugbe",
    "wof:placetype":"locality"
},
  "geometry": {"coordinates":[-12.46132,8.95505],"type":"Point"}
}