{
  "type": "Feature",
  "properties": {
    "gn:admin1_code":"02",
    "gn:asciiname":"Tanehun",
    "gn:country_code":"SL",
    "gn:dem":138,
    "gn:feature_class":"P",
    "gn:feature_code":"PPL",
    "gn:name":"Tanehun",
    "gn:population":0,
    "gn:timezone":"Africa/Freetown",
    "iso:country":"SL",
    "name:eng_x_preferred":[
        "Tanehun"
    ],
    "wof:name":"Tanehun",
    "wof:placetype":"locality"
},
  "geometry": {"coordinates":[-12.18314,8.99411],"type":"Point"}
}