{
  "type": "Feature",
  "properties": {
    "gn:admin1_code":"01",
    "gn:asciiname":"Twilo",
    "gn:country_code":"SL",
    "gn:dem":330,
    "gn:feature_class":"P",
    "gn:feature_code":"PPL",
    "gn:name":"Twilo",
    "gn:population":0,
    "gn:timezone":"Africa/Freetown",
    "iso:country":"SL",
    "name:eng_x_preferred":[
        "Twilo"
    ],
    "wof:name":"Twilo",
    "wof:placetype":"locality"
},
  "geometry": {"coordinates":[-10.66667,8.58333],"type":"Point"}
}