{
  "type": "Feature",
  "properties": {
    "gn:admin1_code":"3.0",
    "gn:asciiname":"Grima",
    "gn:country_code":"SL",
    "gn:dem":23,
    "gn:feature_class":"P",
    "gn:feature_code":"PPL",
    "gn:name":"Grima",
    "gn:population":0,
    "gn:timezone":"Africa/Freetown",
    "iso:country":"SL",
    "name:eng_x_preferred":[
        "Grima"
    ],
    "wof:name":"Grima",
    "wof:placetype":"locality"
},
  "geometry": {"coordinates":[-11.68145,7.28686],"type":"Point"}
}