{
  "type": "Feature",
  "properties": {
    "gn:admin1_code":"2.0",
    "gn:asciiname":"Mabura",
    "gn:country_code":"SL",
    "gn:dem":73,
    "gn:feature_class":"P",
    "gn:feature_code":"PPL",
    "gn:name":"Mabura",
    "gn:population":0,
    "gn:timezone":"Africa/Freetown",
    "iso:country":"SL",
    "name:eng_x_preferred":[
        "Mabura"
    ],
    "wof:name":"Mabura",
    "wof:placetype":"locality"
},
  "geometry": {"coordinates":[-12.32751,8.63427],"type":"Point"}
}