{
  "type": "Feature",
  "properties": {
    "gn:admin1_code":"2.0",
    "gn:asciiname":"Mateikaw",
    "gn:country_code":"SL",
    "gn:dem":15,
    "gn:feature_class":"P",
    "gn:feature_code":"PPL",
    "gn:name":"Mateikaw",
    "gn:population":0,
    "gn:timezone":"Africa/Freetown",
    "iso:country":"SL",
    "name:eng_x_preferred":[
        "Mateikaw"
    ],
    "wof:name":"Mateikaw",
    "wof:placetype":"locality"
},
  "geometry": {"coordinates":[-12.84118,8.64514],"type":"Point"}
}