{
  "type": "Feature",
  "properties": {
    "gn:admin1_code":"2.0",
    "gn:asciiname":"Kandambaya",
    "gn:country_code":"SL",
    "gn:dem":386,
    "gn:feature_class":"P",
    "gn:feature_code":"PPL",
    "gn:name":"Kandambaya",
    "gn:population":0,
    "gn:timezone":"Africa/Freetown",
    "iso:country":"SL",
    "name:eng_x_preferred":[
        "Kandambaya"
    ],
    "wof:name":"Kandambaya",
    "wof:placetype":"locality"
},
  "geometry": {"coordinates":[-11.55175,9.04711],"type":"Point"}
}