{
  "type": "Feature",
  "properties": {
    "gn:admin1_code":"3.0",
    "gn:asciiname":"Suako",
    "gn:country_code":"SL",
    "gn:dem":17,
    "gn:feature_class":"P",
    "gn:feature_code":"PPL",
    "gn:name":"Suako",
    "gn:population":0,
    "gn:timezone":"Africa/Freetown",
    "iso:country":"SL",
    "name:eng_x_preferred":[
        "Suako"
    ],
    "wof:name":"Suako",
    "wof:placetype":"locality"
},
  "geometry": {"coordinates":[-11.64923,7.18256],"type":"Point"}
}