{
  "type": "Feature",
  "properties": {
    "gn:admin1_code":"02",
    "gn:asciiname":"Wundefili",
    "gn:country_code":"SL",
    "gn:dem":152,
    "gn:feature_class":"P",
    "gn:feature_code":"PPL",
    "gn:name":"Wundefili",
    "gn:population":0,
    "gn:timezone":"Africa/Freetown",
    "iso:country":"SL",
    "name:eng_x_preferred":[
        "Wundefili"
    ],
    "wof:name":"Wundefili",
    "wof:placetype":"locality"
},
  "geometry": {"coordinates":[-12.47556,9.68418],"type":"Point"}
}