{
  "type": "Feature",
  "properties": {
    "gn:admin1_code":"2.0",
    "gn:asciiname":"Funkuya",
    "gn:country_code":"SL",
    "gn:dem":246,
    "gn:feature_class":"P",
    "gn:feature_code":"PPL",
    "gn:name":"Funkuya",
    "gn:population":0,
    "gn:timezone":"Africa/Freetown",
    "iso:country":"SL",
    "wof:name":"Funkuya",
    "wof:placetype":"locality"
},
  "geometry": {"coordinates":[-11.78333,9.08333],"type":"Point"}
}