{
  "type": "Feature",
  "properties": {
    "gn:admin1_code":"3.0",
    "gn:asciiname":"Kormasi",
    "gn:country_code":"SL",
    "gn:dem":210,
    "gn:feature_class":"P",
    "gn:feature_code":"PPL",
    "gn:name":"Kormasi",
    "gn:population":0,
    "gn:timezone":"Africa/Freetown",
    "iso:country":"SL",
    "name:eng_x_preferred":[
        "Kormasi"
    ],
    "wof:name":"Kormasi",
    "wof:placetype":"locality"
},
  "geometry": {"coordinates":[-11.70561,8.22983],"type":"Point"}
}