{
  "type": "Feature",
  "properties": {
    "gn:admin1_code":"3.0",
    "gn:asciiname":"Jawi",
    "gn:country_code":"SL",
    "gn:dem":24,
    "gn:feature_class":"P",
    "gn:feature_code":"PPL",
    "gn:name":"Jawi",
    "gn:population":0,
    "gn:timezone":"Africa/Freetown",
    "iso:country":"SL",
    "name:ara_x_preferred":[
        "\u062c\u0627\u0648\u064a"
    ],
    "name:ceb_x_preferred":[
        "Jawi"
    ],
    "name:eng_x_preferred":[
        "Jawi"
    ],
    "name:msa_x_preferred":[
        "Jawi"
    ],
    "name:nld_x_preferred":[
        "Jawi"
    ],
    "name:tha_x_preferred":[
        "\u0e2d\u0e31\u0e01\u0e29\u0e23\u0e22\u0e32\u0e27\u0e35"
    ],
    "wof:name":"Jawi",
    "wof:placetype":"locality"
},
  "geometry": {"coordinates":[-11.51959,7.20344],"type":"Point"}
}