{
  "type": "Feature",
  "properties": {
    "gn:admin1_code":"3.0",
    "gn:asciiname":"Jawi",
    "gn:country_code":"SL",
    "gn:dem":24,
    "gn:feature_class":"P",
    "gn:feature_code":"PPL",
    "gn:name":"Jawi",
    "gn:population":0,
    "gn:timezone":"Africa/Freetown",
    "iso:country":"SL",
    "name:eng_x_preferred":[
        "Jawi"
    ],
    "wof:name":"Jawi",
    "wof:placetype":"locality"
},
  "geometry": {"coordinates":[-11.51959,7.20344],"type":"Point"}
}