{
  "type": "Feature",
  "properties": {
    "gn:admin1_code":"1.0",
    "gn:asciiname":"Dandabu",
    "gn:country_code":"SL",
    "gn:dem":265,
    "gn:feature_class":"P",
    "gn:feature_code":"PPL",
    "gn:name":"Dandabu",
    "gn:population":0,
    "gn:timezone":"Africa/Freetown",
    "iso:country":"SL",
    "name:eng_x_preferred":[
        "Dandabu"
    ],
    "name:und_x_variant":[
        "Koyehun"
    ],
    "wof:name":"Dandabu",
    "wof:placetype":"locality"
},
  "geometry": {"coordinates":[-11.08244,8.13098],"type":"Point"}
}