{
  "type": "Feature",
  "properties": {
    "gn:admin1_code":"2.0",
    "gn:asciiname":"Gahan",
    "gn:country_code":"SL",
    "gn:dem":166,
    "gn:feature_class":"P",
    "gn:feature_code":"PPL",
    "gn:name":"Gahan",
    "gn:population":0,
    "gn:timezone":"Africa/Freetown",
    "iso:country":"SL",
    "name:deu_x_preferred":[
        "Gahan"
    ],
    "name:eng_x_preferred":[
        "Gahan"
    ],
    "name:fra_x_preferred":[
        "Gahan"
    ],
    "wof:name":"Gahan",
    "wof:placetype":"locality"
},
  "geometry": {"coordinates":[-12.07851,9.23056],"type":"Point"}
}