{
  "type": "Feature",
  "properties": {
    "gn:admin1_code":"1.0",
    "gn:asciiname":"Mavehun",
    "gn:country_code":"SL",
    "gn:dem":227,
    "gn:feature_class":"P",
    "gn:feature_code":"PPL",
    "gn:name":"Mavehun",
    "gn:population":0,
    "gn:timezone":"Africa/Freetown",
    "iso:country":"SL",
    "name:eng_x_preferred":[
        "Mavehun"
    ],
    "wof:name":"Mavehun",
    "wof:placetype":"locality"
},
  "geometry": {"coordinates":[-11.06628,8.22195],"type":"Point"}
}