{
  "type": "Feature",
  "properties": {
    "gn:admin1_code":"1.0",
    "gn:asciiname":"Kundaw bengu",
    "gn:country_code":"SL",
    "gn:dem":446,
    "gn:feature_class":"P",
    "gn:feature_code":"PPL",
    "gn:name":"Kundaw bengu",
    "gn:population":0,
    "gn:timezone":"Africa/Freetown",
    "iso:country":"SL",
    "name:eng_x_preferred":[
        "Kundaw bengu"
    ],
    "wof:name":"Kundaw bengu",
    "wof:placetype":"locality"
},
  "geometry": {"coordinates":[-10.31866,8.29419],"type":"Point"}
}