{
  "type": "Feature",
  "properties": {
    "gn:admin1_code":"2.0",
    "gn:asciiname":"Maghere",
    "gn:country_code":"SL",
    "gn:dem":264,
    "gn:feature_class":"P",
    "gn:feature_code":"PPL",
    "gn:name":"Maghere",
    "gn:population":0,
    "gn:timezone":"Africa/Freetown",
    "iso:country":"SL",
    "wof:name":"Maghere",
    "wof:placetype":"locality"
},
  "geometry": {"coordinates":[-11.76667,9.11667],"type":"Point"}
}