{
  "type": "Feature",
  "properties": {
    "gn:admin1_code":"3.0",
    "gn:asciiname":"Dikpaya",
    "gn:country_code":"SL",
    "gn:dem":71,
    "gn:feature_class":"P",
    "gn:feature_code":"PPL",
    "gn:name":"Dikpaya",
    "gn:population":0,
    "gn:timezone":"Africa/Freetown",
    "iso:country":"SL",
    "name:eng_x_preferred":[
        "Dikpaya"
    ],
    "wof:name":"Dikpaya",
    "wof:placetype":"locality"
},
  "geometry": {"coordinates":[-11.78109,7.83176],"type":"Point"}
}