{
  "type": "Feature",
  "properties": {
    "gn:admin1_code":"2.0",
    "gn:asciiname":"Gbenti",
    "gn:country_code":"SL",
    "gn:dem":16,
    "gn:feature_class":"P",
    "gn:feature_code":"PPL",
    "gn:name":"Gbenti",
    "gn:population":0,
    "gn:timezone":"Africa/Freetown",
    "iso:country":"SL",
    "name:und_x_variant":[
        "Gberti",
        "Gbenti"
    ],
    "wof:name":"Gbenti",
    "wof:placetype":"locality"
},
  "geometry": {"coordinates":[-13.10966,8.80425],"type":"Point"}
}