{
  "type": "Feature",
  "properties": {
    "gn:admin1_code":"1.0",
    "gn:asciiname":"Gondima",
    "gn:country_code":"SL",
    "gn:dem":246,
    "gn:feature_class":"P",
    "gn:feature_code":"PPL",
    "gn:name":"Gondima",
    "gn:population":0,
    "gn:timezone":"Africa/Freetown",
    "iso:country":"SL",
    "name:eng_x_preferred":[
        "Gondima"
    ],
    "wof:name":"Gondima",
    "wof:placetype":"locality"
},
  "geometry": {"coordinates":[-10.69429,8.33559],"type":"Point"}
}