{
  "type": "Feature",
  "properties": {
    "gn:admin1_code":"3.0",
    "gn:asciiname":"Gbangbama",
    "gn:country_code":"SL",
    "gn:dem":60,
    "gn:feature_class":"P",
    "gn:feature_code":"PPL",
    "gn:name":"Gbangbama",
    "gn:population":0,
    "gn:timezone":"Africa/Freetown",
    "iso:country":"SL",
    "name:und_x_variant":[
        "Bangbama",
        "Gbangbama"
    ],
    "wof:name":"Gbangbama",
    "wof:placetype":"locality"
},
  "geometry": {"coordinates":[-12.32998,8.24742],"type":"Point"}
}