{
  "type": "Feature",
  "properties": {
    "gn:admin1_code":"1.0",
    "gn:asciiname":"Maima",
    "gn:country_code":"SL",
    "gn:dem":373,
    "gn:feature_class":"P",
    "gn:feature_code":"PPL",
    "gn:name":"Maima",
    "gn:population":0,
    "gn:timezone":"Africa/Freetown",
    "iso:country":"SL",
    "name:eng_x_preferred":[
        "Maima"
    ],
    "name:est_x_preferred":[
        "Maima"
    ],
    "name:hye_x_preferred":[
        "\u0544\u0561\u056b\u0574\u0561"
    ],
    "name:pol_x_preferred":[
        "Maima"
    ],
    "name:spa_x_preferred":[
        "Maima"
    ],
    "name:vol_x_preferred":[
        "Maima"
    ],
    "wof:name":"Maima",
    "wof:placetype":"locality"
},
  "geometry": {"coordinates":[-11.1722,8.80542],"type":"Point"}
}