{
  "type": "Feature",
  "properties": {
    "gn:admin1_code":"2.0",
    "gn:asciiname":"Fotani",
    "gn:country_code":"SL",
    "gn:dem":70,
    "gn:feature_class":"P",
    "gn:feature_code":"PPL",
    "gn:name":"Fotani",
    "gn:population":0,
    "gn:timezone":"Africa/Freetown",
    "iso:country":"SL",
    "name:eng_x_preferred":[
        "Fotani"
    ],
    "wof:name":"Fotani",
    "wof:placetype":"locality"
},
  "geometry": {"coordinates":[-12.43642,8.7371],"type":"Point"}
}