{
  "type": "Feature",
  "properties": {
    "gn:admin1_code":"3.0",
    "gn:asciiname":"Momesin",
    "gn:country_code":"SL",
    "gn:dem":16,
    "gn:feature_class":"P",
    "gn:feature_code":"PPL",
    "gn:name":"Momesin",
    "gn:population":0,
    "gn:timezone":"Africa/Freetown",
    "iso:country":"SL",
    "name:eng_x_preferred":[
        "Momesin"
    ],
    "wof:name":"Momesin",
    "wof:placetype":"locality"
},
  "geometry": {"coordinates":[-12.68264,7.91037],"type":"Point"}
}