{
  "type": "Feature",
  "properties": {
    "gn:admin1_code":"1.0",
    "gn:asciiname":"Dandando",
    "gn:country_code":"SL",
    "gn:dem":418,
    "gn:feature_class":"P",
    "gn:feature_code":"PPL",
    "gn:name":"Dandando",
    "gn:population":0,
    "gn:timezone":"Africa/Freetown",
    "iso:country":"SL",
    "name:eng_x_preferred":[
        "Dandando"
    ],
    "wof:name":"Dandando",
    "wof:placetype":"locality"
},
  "geometry": {"coordinates":[-10.91315,8.70886],"type":"Point"}
}