{
  "type": "Feature",
  "properties": {
    "gn:admin1_code":"3.0",
    "gn:asciiname":"Banale",
    "gn:country_code":"SL",
    "gn:dem":20,
    "gn:feature_class":"P",
    "gn:feature_code":"PPL",
    "gn:name":"Banale",
    "gn:population":0,
    "gn:timezone":"Africa/Freetown",
    "iso:country":"SL",
    "name:eng_x_preferred":[
        "Banale"
    ],
    "wof:name":"Banale",
    "wof:placetype":"locality"
},
  "geometry": {"coordinates":[-11.97674,7.47344],"type":"Point"}
}