{
  "type": "Feature",
  "properties": {
    "gn:admin1_code":"2.0",
    "gn:asciiname":"Kawono",
    "gn:country_code":"SL",
    "gn:dem":113,
    "gn:feature_class":"P",
    "gn:feature_code":"PPL",
    "gn:name":"Kawono",
    "gn:population":0,
    "gn:timezone":"Africa/Freetown",
    "iso:country":"SL",
    "wof:name":"Kawono",
    "wof:placetype":"locality"
},
  "geometry": {"coordinates":[-11.88333,9.66667],"type":"Point"}
}