{
  "type": "Feature",
  "properties": {
    "gn:admin1_code":"3.0",
    "gn:asciiname":"Moseneh",
    "gn:country_code":"SL",
    "gn:dem":13,
    "gn:feature_class":"P",
    "gn:feature_code":"PPL",
    "gn:name":"Moseneh",
    "gn:population":0,
    "gn:timezone":"Africa/Freetown",
    "iso:country":"SL",
    "name:eng_x_preferred":[
        "Moseneh"
    ],
    "wof:name":"Moseneh",
    "wof:placetype":"locality"
},
  "geometry": {"coordinates":[-12.5944,7.52063],"type":"Point"}
}