{
  "type": "Feature",
  "properties": {
    "gn:admin1_code":"3.0",
    "gn:asciiname":"Moimbawuro",
    "gn:country_code":"SL",
    "gn:dem":87,
    "gn:feature_class":"P",
    "gn:feature_code":"PPL",
    "gn:name":"Moimbawuro",
    "gn:population":0,
    "gn:timezone":"Africa/Freetown",
    "iso:country":"SL",
    "name:eng_x_preferred":[
        "Moimbawuro"
    ],
    "wof:name":"Moimbawuro",
    "wof:placetype":"locality"
},
  "geometry": {"coordinates":[-11.77164,8.33852],"type":"Point"}
}