{
  "type": "Feature",
  "properties": {
    "gn:admin1_code":"1.0",
    "gn:asciiname":"Levuma",
    "gn:country_code":"SL",
    "gn:dem":191,
    "gn:feature_class":"P",
    "gn:feature_code":"PPL",
    "gn:name":"Levuma",
    "gn:population":0,
    "gn:timezone":"Africa/Freetown",
    "iso:country":"SL",
    "name:eng_x_preferred":[
        "Levuma"
    ],
    "wof:name":"Levuma",
    "wof:placetype":"locality"
},
  "geometry": {"coordinates":[-10.91071,7.89469],"type":"Point"}
}