{
  "type": "Feature",
  "properties": {
    "gn:admin1_code":"02",
    "gn:asciiname":"Sansankama",
    "gn:country_code":"SL",
    "gn:dem":469,
    "gn:feature_class":"P",
    "gn:feature_code":"PPL",
    "gn:name":"Sansankama",
    "gn:population":0,
    "gn:timezone":"Africa/Freetown",
    "iso:country":"SL",
    "name:eng_x_preferred":[
        "Sansankama"
    ],
    "wof:name":"Sansankama",
    "wof:placetype":"locality"
},
  "geometry": {"coordinates":[-11.10881,9.81329],"type":"Point"}
}