{
  "type": "Feature",
  "properties": {
    "gn:admin1_code":"4.0",
    "gn:asciiname":"Ma-bampo",
    "gn:country_code":"SL",
    "gn:dem":16,
    "gn:feature_class":"P",
    "gn:feature_code":"PPL",
    "gn:name":"Ma-bampo",
    "gn:population":0,
    "gn:timezone":"Africa/Freetown",
    "iso:country":"SL",
    "name:eng_x_preferred":[
        "Ma-bampo"
    ],
    "wof:name":"Ma-bampo",
    "wof:placetype":"locality"
},
  "geometry": {"coordinates":[-13.02733,8.27646],"type":"Point"}
}