{
  "type": "Feature",
  "properties": {
    "gn:admin1_code":"3.0",
    "gn:asciiname":"Bendu",
    "gn:country_code":"SL",
    "gn:dem":22,
    "gn:feature_class":"P",
    "gn:feature_code":"PPL",
    "gn:name":"Bendu",
    "gn:population":0,
    "gn:timezone":"Africa/Freetown",
    "iso:country":"SL",
    "name:eng_x_preferred":[
        "Bendu"
    ],
    "wof:name":"Bendu",
    "wof:placetype":"locality"
},
  "geometry": {"coordinates":[-11.66695,7.29934],"type":"Point"}
}