{
  "type": "Feature",
  "properties": {
    "gn:admin1_code":"3.0",
    "gn:asciiname":"Fuliwama",
    "gn:country_code":"SL",
    "gn:dem":75,
    "gn:feature_class":"P",
    "gn:feature_code":"PPL",
    "gn:name":"Fuliwama",
    "gn:population":0,
    "gn:timezone":"Africa/Freetown",
    "iso:country":"SL",
    "name:eng_x_preferred":[
        "Fuliwama"
    ],
    "wof:name":"Fuliwama",
    "wof:placetype":"locality"
},
  "geometry": {"coordinates":[-12.08365,7.95246],"type":"Point"}
}