{
  "type": "Feature",
  "properties": {
    "gn:admin1_code":"3.0",
    "gn:asciiname":"Golala",
    "gn:country_code":"SL",
    "gn:dem":67,
    "gn:feature_class":"P",
    "gn:feature_code":"PPL",
    "gn:name":"Golala",
    "gn:population":0,
    "gn:timezone":"Africa/Freetown",
    "iso:country":"SL",
    "name:eng_x_preferred":[
        "Golala"
    ],
    "wof:name":"Golala",
    "wof:placetype":"locality"
},
  "geometry": {"coordinates":[-12.14718,7.79408],"type":"Point"}
}