{
  "type": "Feature",
  "properties": {
    "gn:admin1_code":"1.0",
    "gn:asciiname":"Njaiama-Sewafe",
    "gn:country_code":"SL",
    "gn:dem":286,
    "gn:feature_class":"P",
    "gn:feature_code":"PPL",
    "gn:name":"Njaiama-Sewafe",
    "gn:population":0,
    "gn:timezone":"Africa/Freetown",
    "iso:country":"SL",
    "name:eng_x_preferred":[
        "Njaiama-Sewafe"
    ],
    "name:und_x_variant":[
        "Njaiama",
        "Jaiama Nimiyama",
        "Jaiama"
    ],
    "wof:name":"Njaiama-Sewafe",
    "wof:placetype":"locality"
},
  "geometry": {"coordinates":[-11.2445,8.54021],"type":"Point"}
}