{
  "type": "Feature",
  "properties": {
    "gn:admin1_code":"2.0",
    "gn:asciiname":"Rosint",
    "gn:country_code":"SL",
    "gn:dem":25,
    "gn:feature_class":"P",
    "gn:feature_code":"PPL",
    "gn:name":"Rosint",
    "gn:population":0,
    "gn:timezone":"Africa/Freetown",
    "iso:country":"SL",
    "wof:name":"Rosint",
    "wof:placetype":"locality"
},
  "geometry": {"coordinates":[-13.16306,8.55472],"type":"Point"}
}