{
  "type": "Feature",
  "properties": {
    "gn:admin1_code":"1.0",
    "gn:asciiname":"Manjoru",
    "gn:country_code":"SL",
    "gn:dem":212,
    "gn:feature_class":"P",
    "gn:feature_code":"PPL",
    "gn:name":"Manjoru",
    "gn:population":0,
    "gn:timezone":"Africa/Freetown",
    "iso:country":"SL",
    "name:eng_x_preferred":[
        "Manjoru"
    ],
    "name:und_x_variant":[
        "Manjulu"
    ],
    "wof:name":"Manjoru",
    "wof:placetype":"locality"
},
  "geometry": {"coordinates":[-10.87216,8.11971],"type":"Point"}
}