{
  "type": "Feature",
  "properties": {
    "gn:admin1_code":"2.0",
    "gn:asciiname":"Mamina",
    "gn:country_code":"SL",
    "gn:dem":36,
    "gn:feature_class":"P",
    "gn:feature_code":"PPL",
    "gn:name":"Mamina",
    "gn:population":0,
    "gn:timezone":"Africa/Freetown",
    "iso:country":"SL",
    "name:eng_x_preferred":[
        "Mamina"
    ],
    "wof:name":"Mamina",
    "wof:placetype":"locality"
},
  "geometry": {"coordinates":[-12.85316,8.62966],"type":"Point"}
}