{
  "type": "Feature",
  "properties": {
    "gn:admin1_code":"1.0",
    "gn:asciiname":"Mara",
    "gn:country_code":"SL",
    "gn:dem":396,
    "gn:feature_class":"P",
    "gn:feature_code":"PPL",
    "gn:name":"Mara",
    "gn:population":0,
    "gn:timezone":"Africa/Freetown",
    "iso:country":"SL",
    "name:eng_x_preferred":[
        "Mara"
    ],
    "wof:name":"Mara",
    "wof:placetype":"locality"
},
  "geometry": {"coordinates":[-10.50415,8.7022],"type":"Point"}
}