{
  "type": "Feature",
  "properties": {
    "gn:admin1_code":"02",
    "gn:asciiname":"Rokawlon",
    "gn:country_code":"SL",
    "gn:dem":77,
    "gn:feature_class":"P",
    "gn:feature_code":"PPL",
    "gn:name":"Rokawlon",
    "gn:population":0,
    "gn:timezone":"Africa/Freetown",
    "iso:country":"SL",
    "name:eng_x_preferred":[
        "Rokawlon"
    ],
    "wof:name":"Rokawlon",
    "wof:placetype":"locality"
},
  "geometry": {"coordinates":[-12.43052,8.51893],"type":"Point"}
}