{
  "type": "Feature",
  "properties": {
    "gn:admin1_code":"2.0",
    "gn:asciiname":"Malap",
    "gn:country_code":"SL",
    "gn:dem":23,
    "gn:feature_class":"P",
    "gn:feature_code":"PPL",
    "gn:name":"Malap",
    "gn:population":0,
    "gn:timezone":"Africa/Freetown",
    "iso:country":"SL",
    "name:eng_x_preferred":[
        "Malap"
    ],
    "wof:name":"Malap",
    "wof:placetype":"locality"
},
  "geometry": {"coordinates":[-12.9615,8.60661],"type":"Point"}
}