{
  "type": "Feature",
  "properties": {
    "gn:admin1_code":"01",
    "gn:asciiname":"Yeikado",
    "gn:country_code":"SL",
    "gn:dem":206,
    "gn:feature_class":"P",
    "gn:feature_code":"PPL",
    "gn:name":"Yeikado",
    "gn:population":0,
    "gn:timezone":"Africa/Freetown",
    "iso:country":"SL",
    "name:eng_x_preferred":[
        "Yeikado"
    ],
    "name:und_x_variant":[
        "Yikando"
    ],
    "wof:name":"Yeikado",
    "wof:placetype":"locality"
},
  "geometry": {"coordinates":[-10.91037,7.98882],"type":"Point"}
}