{
  "type": "Feature",
  "properties": {
    "gn:admin1_code":"3.0",
    "gn:asciiname":"Fulaninahun",
    "gn:country_code":"SL",
    "gn:dem":55,
    "gn:feature_class":"P",
    "gn:feature_code":"PPL",
    "gn:name":"Fulaninahun",
    "gn:population":0,
    "gn:timezone":"Africa/Freetown",
    "iso:country":"SL",
    "name:eng_x_preferred":[
        "Fulaninahun"
    ],
    "wof:name":"Fulaninahun",
    "wof:placetype":"locality"
},
  "geometry": {"coordinates":[-12.04484,7.90616],"type":"Point"}
}