{
  "type": "Feature",
  "properties": {
    "gn:admin1_code":"2.0",
    "gn:asciiname":"Manangbe",
    "gn:country_code":"SL",
    "gn:dem":401,
    "gn:feature_class":"P",
    "gn:feature_code":"PPL",
    "gn:name":"Manangbe",
    "gn:population":0,
    "gn:timezone":"Africa/Freetown",
    "iso:country":"SL",
    "name:eng_x_preferred":[
        "Manangbe"
    ],
    "wof:name":"Manangbe",
    "wof:placetype":"locality"
},
  "geometry": {"coordinates":[-11.32624,9.77523],"type":"Point"}
}