{
  "type": "Feature",
  "properties": {
    "gn:admin1_code":"3.0",
    "gn:asciiname":"Kuehvama",
    "gn:country_code":"SL",
    "gn:dem":121,
    "gn:feature_class":"P",
    "gn:feature_code":"PPL",
    "gn:name":"Kuehvama",
    "gn:population":0,
    "gn:timezone":"Africa/Freetown",
    "iso:country":"SL",
    "name:eng_x_preferred":[
        "Kuehvama"
    ],
    "wof:name":"Kuehvama",
    "wof:placetype":"locality"
},
  "geometry": {"coordinates":[-11.73932,8.25831],"type":"Point"}
}