{
  "type": "Feature",
  "properties": {
    "gn:admin1_code":"3.0",
    "gn:asciiname":"Petewoma",
    "gn:country_code":"SL",
    "gn:dem":91,
    "gn:feature_class":"P",
    "gn:feature_code":"PPL",
    "gn:name":"Petewoma",
    "gn:population":0,
    "gn:timezone":"Africa/Freetown",
    "iso:country":"SL",
    "name:eng_x_preferred":[
        "Petewoma"
    ],
    "wof:name":"Petewoma",
    "wof:placetype":"locality"
},
  "geometry": {"coordinates":[-11.80618,7.87412],"type":"Point"}
}