{
  "type": "Feature",
  "properties": {
    "gn:admin1_code":"2.0",
    "gn:asciiname":"Robun",
    "gn:country_code":"SL",
    "gn:dem":66,
    "gn:feature_class":"P",
    "gn:feature_code":"PPL",
    "gn:name":"Robun",
    "gn:population":0,
    "gn:timezone":"Africa/Freetown",
    "iso:country":"SL",
    "name:eng_x_preferred":[
        "Robun"
    ],
    "wof:name":"Robun",
    "wof:placetype":"locality"
},
  "geometry": {"coordinates":[-12.6152,8.83963],"type":"Point"}
}