{
  "type": "Feature",
  "properties": {
    "gn:admin1_code":"01",
    "gn:asciiname":"Patobu",
    "gn:country_code":"SL",
    "gn:dem":161,
    "gn:feature_class":"P",
    "gn:feature_code":"PPL",
    "gn:name":"Patobu",
    "gn:population":0,
    "gn:timezone":"Africa/Freetown",
    "iso:country":"SL",
    "name:eng_x_preferred":[
        "Patobu"
    ],
    "wof:name":"Patobu",
    "wof:placetype":"locality"
},
  "geometry": {"coordinates":[-11.07712,7.61606],"type":"Point"}
}