{
  "type": "Feature",
  "properties": {
    "gn:admin1_code":"03",
    "gn:asciiname":"Poima",
    "gn:country_code":"SL",
    "gn:dem":42,
    "gn:feature_class":"P",
    "gn:feature_code":"PPL",
    "gn:name":"Poima",
    "gn:population":0,
    "gn:timezone":"Africa/Freetown",
    "iso:country":"SL",
    "name:eng_x_preferred":[
        "Poima"
    ],
    "wof:name":"Poima",
    "wof:placetype":"locality"
},
  "geometry": {"coordinates":[-11.45687,6.96005],"type":"Point"}
}