{
  "type": "Feature",
  "properties": {
    "gn:admin1_code":"2.0",
    "gn:asciiname":"Pawnka",
    "gn:country_code":"SL",
    "gn:dem":10,
    "gn:feature_class":"P",
    "gn:feature_code":"PPL",
    "gn:name":"Pawnka",
    "gn:population":0,
    "gn:timezone":"Africa/Freetown",
    "iso:country":"SL",
    "name:eng_x_preferred":[
        "Pawnka"
    ],
    "wof:name":"Pawnka",
    "wof:placetype":"locality"
},
  "geometry": {"coordinates":[-12.89213,8.54012],"type":"Point"}
}