{
  "type": "Feature",
  "properties": {
    "gn:admin1_code":"01",
    "gn:asciiname":"Pujehun",
    "gn:country_code":"SL",
    "gn:dem":272,
    "gn:feature_class":"P",
    "gn:feature_code":"PPL",
    "gn:name":"Pujehun",
    "gn:population":0,
    "gn:timezone":"Africa/Freetown",
    "iso:country":"SL",
    "name:ceb_x_preferred":[
        "Pujehun"
    ],
    "name:deu_x_preferred":[
        "Pujehun"
    ],
    "name:eng_x_preferred":[
        "Pujehun"
    ],
    "name:fin_x_preferred":[
        "Pujehun"
    ],
    "name:fra_x_preferred":[
        "Pujehun"
    ],
    "name:ita_x_preferred":[
        "Pujehun"
    ],
    "name:lit_x_preferred":[
        "Pud\u017eehunas"
    ],
    "name:pol_x_preferred":[
        "Pujehun"
    ],
    "name:ron_x_preferred":[
        "Pujehun"
    ],
    "name:zho_x_preferred":[
        "\u666e\u5091\u6d2a"
    ],
    "wof:name":"Pujehun",
    "wof:placetype":"locality"
},
  "geometry": {"coordinates":[-10.87118,8.34236],"type":"Point"}
}