{
  "type": "Feature",
  "properties": {
    "gn:admin1_code":"3.0",
    "gn:asciiname":"Mendekelema",
    "gn:country_code":"SL",
    "gn:dem":319,
    "gn:feature_class":"P",
    "gn:feature_code":"PPL",
    "gn:name":"Mendekelema",
    "gn:population":0,
    "gn:timezone":"Africa/Freetown",
    "iso:country":"SL",
    "name:und_x_variant":[
        "Mendegerem"
    ],
    "wof:name":"Mendekelema",
    "wof:placetype":"locality"
},
  "geometry": {"coordinates":[-11.57124,8.44725],"type":"Point"}
}