{
  "type": "Feature",
  "properties": {
    "gn:admin1_code":"1.0",
    "gn:asciiname":"Kpuwabu",
    "gn:country_code":"SL",
    "gn:dem":194,
    "gn:feature_class":"P",
    "gn:feature_code":"PPL",
    "gn:name":"Kpuwabu",
    "gn:population":0,
    "gn:timezone":"Africa/Freetown",
    "iso:country":"SL",
    "name:eng_x_preferred":[
        "Kpuwabu"
    ],
    "wof:name":"Kpuwabu",
    "wof:placetype":"locality"
},
  "geometry": {"coordinates":[-10.86392,8.29266],"type":"Point"}
}