{
  "type": "Feature",
  "properties": {
    "gn:admin1_code":"1.0",
    "gn:asciiname":"Senehun",
    "gn:country_code":"SL",
    "gn:dem":397,
    "gn:feature_class":"P",
    "gn:feature_code":"PPL",
    "gn:name":"Senehun",
    "gn:population":0,
    "gn:timezone":"Africa/Freetown",
    "iso:country":"SL",
    "name:eng_x_preferred":[
        "Senehun"
    ],
    "wof:name":"Senehun",
    "wof:placetype":"locality"
},
  "geometry": {"coordinates":[-10.39003,8.3196],"type":"Point"}
}