{
  "type": "Feature",
  "properties": {
    "gn:admin1_code":"1.0",
    "gn:asciiname":"Guabu",
    "gn:country_code":"SL",
    "gn:dem":244,
    "gn:feature_class":"P",
    "gn:feature_code":"PPL",
    "gn:name":"Guabu",
    "gn:population":0,
    "gn:timezone":"Africa/Freetown",
    "iso:country":"SL",
    "name:eng_x_preferred":[
        "Guabu"
    ],
    "wof:name":"Guabu",
    "wof:placetype":"locality"
},
  "geometry": {"coordinates":[-10.98345,8.33763],"type":"Point"}
}