{
  "type": "Feature",
  "properties": {
    "gn:admin1_code":"2.0",
    "gn:asciiname":"Tendata",
    "gn:country_code":"SL",
    "gn:dem":64,
    "gn:feature_class":"P",
    "gn:feature_code":"PPL",
    "gn:name":"Tendata",
    "gn:population":0,
    "gn:timezone":"Africa/Freetown",
    "iso:country":"SL",
    "name:eng_x_preferred":[
        "Tendata"
    ],
    "wof:name":"Tendata",
    "wof:placetype":"locality"
},
  "geometry": {"coordinates":[-12.5212,8.68948],"type":"Point"}
}