{
  "type": "Feature",
  "properties": {
    "gn:admin1_code":"3.0",
    "gn:asciiname":"Gbograma",
    "gn:country_code":"SL",
    "gn:dem":65,
    "gn:feature_class":"P",
    "gn:feature_code":"PPL",
    "gn:name":"Gbograma",
    "gn:population":0,
    "gn:timezone":"Africa/Freetown",
    "iso:country":"SL",
    "name:eng_x_preferred":[
        "Gbograma"
    ],
    "wof:name":"Gbograma",
    "wof:placetype":"locality"
},
  "geometry": {"coordinates":[-12.4392,8.23303],"type":"Point"}
}