{
  "type": "Feature",
  "properties": {
    "gn:admin1_code":"01",
    "gn:asciiname":"Togboie",
    "gn:country_code":"SL",
    "gn:dem":217,
    "gn:feature_class":"P",
    "gn:feature_code":"PPL",
    "gn:name":"Togboie",
    "gn:population":0,
    "gn:timezone":"Africa/Freetown",
    "iso:country":"SL",
    "name:eng_x_preferred":[
        "Togboie"
    ],
    "wof:name":"Togboie",
    "wof:placetype":"locality"
},
  "geometry": {"coordinates":[-10.82017,8.1155],"type":"Point"}
}