{
  "type": "Feature",
  "properties": {
    "gn:admin1_code":"1.0",
    "gn:asciiname":"Koakor",
    "gn:country_code":"SL",
    "gn:dem":439,
    "gn:feature_class":"P",
    "gn:feature_code":"PPL",
    "gn:name":"Koakor",
    "gn:population":0,
    "gn:timezone":"Africa/Freetown",
    "iso:country":"SL",
    "name:eng_x_preferred":[
        "Koakor"
    ],
    "wof:name":"Koakor",
    "wof:placetype":"locality"
},
  "geometry": {"coordinates":[-10.80938,8.6739],"type":"Point"}
}