{
  "type": "Feature",
  "properties": {
    "gn:admin1_code":"3.0",
    "gn:asciiname":"Bohun",
    "gn:country_code":"SL",
    "gn:dem":147,
    "gn:feature_class":"P",
    "gn:feature_code":"PPL",
    "gn:name":"Bohun",
    "gn:population":0,
    "gn:timezone":"Africa/Freetown",
    "iso:country":"SL",
    "name:deu_x_preferred":[
        "Bohun"
    ],
    "name:eng_x_preferred":[
        "Bohun"
    ],
    "name:fra_x_preferred":[
        "Bohun"
    ],
    "name:pol_x_preferred":[
        "Bohun"
    ],
    "name:rus_x_preferred":[
        "\u0411\u043e\u0433\u0443\u043d"
    ],
    "name:ukr_x_preferred":[
        "\u0411\u043e\u0433\u0443\u043d"
    ],
    "wof:name":"Bohun",
    "wof:placetype":"locality"
},
  "geometry": {"coordinates":[-11.35528,8.15165],"type":"Point"}
}