{
  "type": "Feature",
  "properties": {
    "gn:admin1_code":"04",
    "gn:asciiname":"Ro-kundu",
    "gn:country_code":"SL",
    "gn:dem":23,
    "gn:feature_class":"P",
    "gn:feature_code":"PPL",
    "gn:name":"Ro-kundu",
    "gn:population":0,
    "gn:timezone":"Africa/Freetown",
    "iso:country":"SL",
    "name:eng_x_preferred":[
        "Ro-kundu"
    ],
    "wof:name":"Ro-kundu",
    "wof:placetype":"locality"
},
  "geometry": {"coordinates":[-12.9262,8.31234],"type":"Point"}
}