{
  "type": "Feature",
  "properties": {
    "gn:admin1_code":"2.0",
    "gn:asciiname":"Kamansu",
    "gn:country_code":"SL",
    "gn:dem":435,
    "gn:feature_class":"P",
    "gn:feature_code":"PPL",
    "gn:name":"Kamansu",
    "gn:population":0,
    "gn:timezone":"Africa/Freetown",
    "iso:country":"SL",
    "name:eng_x_preferred":[
        "Kamansu"
    ],
    "wof:name":"Kamansu",
    "wof:placetype":"locality"
},
  "geometry": {"coordinates":[-11.59898,9.49905],"type":"Point"}
}