{
  "type": "Feature",
  "properties": {
    "gn:admin1_code":"2.0",
    "gn:asciiname":"Kalenke",
    "gn:country_code":"SL",
    "gn:dem":14,
    "gn:feature_class":"P",
    "gn:feature_code":"PPL",
    "gn:name":"Kalenke",
    "gn:population":0,
    "gn:timezone":"Africa/Freetown",
    "iso:country":"SL",
    "name:eng_x_preferred":[
        "Kalenke"
    ],
    "wof:name":"Kalenke",
    "wof:placetype":"locality"
},
  "geometry": {"coordinates":[-13.09408,8.88422],"type":"Point"}
}