{
  "type": "Feature",
  "properties": {
    "gn:admin1_code":"3.0",
    "gn:asciiname":"Bimaso",
    "gn:country_code":"SL",
    "gn:dem":22,
    "gn:feature_class":"P",
    "gn:feature_code":"PPL",
    "gn:name":"Bimaso",
    "gn:population":0,
    "gn:timezone":"Africa/Freetown",
    "iso:country":"SL",
    "name:eng_x_preferred":[
        "Bimaso"
    ],
    "wof:name":"Bimaso",
    "wof:placetype":"locality"
},
  "geometry": {"coordinates":[-11.56781,7.05788],"type":"Point"}
}