{
  "type": "Feature",
  "properties": {
    "gn:admin1_code":"1.0",
    "gn:asciiname":"Danfiaya",
    "gn:country_code":"SL",
    "gn:dem":433,
    "gn:feature_class":"P",
    "gn:feature_code":"PPL",
    "gn:name":"Danfiaya",
    "gn:population":0,
    "gn:timezone":"Africa/Freetown",
    "iso:country":"SL",
    "name:eng_x_preferred":[
        "Danfiaya"
    ],
    "wof:name":"Danfiaya",
    "wof:placetype":"locality"
},
  "geometry": {"coordinates":[-10.91925,8.88137],"type":"Point"}
}