{
  "type": "Feature",
  "properties": {
    "gn:admin1_code":"2.0",
    "gn:asciiname":"Kasompona",
    "gn:country_code":"SL",
    "gn:dem":208,
    "gn:feature_class":"P",
    "gn:feature_code":"PPL",
    "gn:name":"Kasompona",
    "gn:population":0,
    "gn:timezone":"Africa/Freetown",
    "iso:country":"SL",
    "name:eng_x_preferred":[
        "Kasompona"
    ],
    "wof:name":"Kasompona",
    "wof:placetype":"locality"
},
  "geometry": {"coordinates":[-11.88235,9.18018],"type":"Point"}
}