{
  "type": "Feature",
  "properties": {
    "gn:admin1_code":"01",
    "gn:asciiname":"Yuya",
    "gn:country_code":"SL",
    "gn:dem":435,
    "gn:feature_class":"P",
    "gn:feature_code":"PPL",
    "gn:name":"Yuya",
    "gn:population":0,
    "gn:timezone":"Africa/Freetown",
    "iso:country":"SL",
    "name:eng_x_preferred":[
        "Yuya"
    ],
    "wof:name":"Yuya",
    "wof:placetype":"locality"
},
  "geometry": {"coordinates":[-10.99768,8.9287],"type":"Point"}
}