{
  "type": "Feature",
  "properties": {
    "gn:admin1_code":"01",
    "gn:asciiname":"Yuya",
    "gn:country_code":"SL",
    "gn:dem":435,
    "gn:feature_class":"P",
    "gn:feature_code":"PPL",
    "gn:name":"Yuya",
    "gn:population":0,
    "gn:timezone":"Africa/Freetown",
    "iso:country":"SL",
    "name:ara_x_preferred":[
        "\u064a\u0648\u064a\u0627"
    ],
    "name:aze_x_preferred":[
        "Yuya"
    ],
    "name:cat_x_preferred":[
        "Yuya"
    ],
    "name:deu_x_preferred":[
        "Juja"
    ],
    "name:eng_x_preferred":[
        "Yuya"
    ],
    "name:fas_x_preferred":[
        "\u06cc\u0648\u06cc\u0627"
    ],
    "name:fin_x_preferred":[
        "Juja"
    ],
    "name:fra_x_preferred":[
        "Youya"
    ],
    "name:heb_x_preferred":[
        "\u05d9\u05d5\u05d9\u05d4"
    ],
    "name:hrv_x_preferred":[
        "Juja"
    ],
    "name:hun_x_preferred":[
        "Juja"
    ],
    "name:ind_x_preferred":[
        "Yuya"
    ],
    "name:ita_x_preferred":[
        "Yuya"
    ],
    "name:nld_x_preferred":[
        "Joeja"
    ],
    "name:por_x_preferred":[
        "Yuia"
    ],
    "name:rus_x_preferred":[
        "\u0419\u0443\u0439\u044f"
    ],
    "name:swe_x_preferred":[
        "Juja"
    ],
    "name:ukr_x_preferred":[
        "\u042e\u0439\u044f"
    ],
    "name:vie_x_preferred":[
        "Yuya"
    ],
    "name:yor_x_preferred":[
        "Yuya"
    ],
    "wof:name":"Yuya",
    "wof:placetype":"locality"
},
  "geometry": {"coordinates":[-10.99768,8.9287],"type":"Point"}
}