{
  "type": "Feature",
  "properties": {
    "gn:admin1_code":"3.0",
    "gn:asciiname":"Mombawa",
    "gn:country_code":"SL",
    "gn:dem":36,
    "gn:feature_class":"P",
    "gn:feature_code":"PPL",
    "gn:name":"Mombawa",
    "gn:population":0,
    "gn:timezone":"Africa/Freetown",
    "iso:country":"SL",
    "name:eng_x_preferred":[
        "Mombawa"
    ],
    "wof:name":"Mombawa",
    "wof:placetype":"locality"
},
  "geometry": {"coordinates":[-12.21497,7.72799],"type":"Point"}
}