{
  "type": "Feature",
  "properties": {
    "gn:admin1_code":"1.0",
    "gn:asciiname":"Kekeya",
    "gn:country_code":"SL",
    "gn:dem":573,
    "gn:feature_class":"P",
    "gn:feature_code":"PPL",
    "gn:name":"Kekeya",
    "gn:population":0,
    "gn:timezone":"Africa/Freetown",
    "iso:country":"SL",
    "name:eng_x_preferred":[
        "Kekeya"
    ],
    "wof:name":"Kekeya",
    "wof:placetype":"locality"
},
  "geometry": {"coordinates":[-10.64817,8.96946],"type":"Point"}
}