{
  "type": "Feature",
  "properties": {
    "gn:admin1_code":"2.0",
    "gn:asciiname":"Makaranke",
    "gn:country_code":"SL",
    "gn:dem":81,
    "gn:feature_class":"P",
    "gn:feature_code":"PPL",
    "gn:name":"Makaranke",
    "gn:population":0,
    "gn:timezone":"Africa/Freetown",
    "iso:country":"SL",
    "name:eng_x_preferred":[
        "Makaranke"
    ],
    "wof:name":"Makaranke",
    "wof:placetype":"locality"
},
  "geometry": {"coordinates":[-12.23779,8.45203],"type":"Point"}
}