{
  "type": "Feature",
  "properties": {
    "gn:admin1_code":"2.0",
    "gn:asciiname":"Yindia",
    "gn:country_code":"SL",
    "gn:dem":30,
    "gn:feature_class":"P",
    "gn:feature_code":"PPL",
    "gn:name":"Yindia",
    "gn:population":0,
    "gn:timezone":"Africa/Freetown",
    "iso:country":"SL",
    "wof:name":"Yindia",
    "wof:placetype":"locality"
},
  "geometry": {"coordinates":[-13.04917,8.70806],"type":"Point"}
}