{
  "type": "Feature",
  "properties": {
    "gn:admin1_code":"1.0",
    "gn:asciiname":"Saama",
    "gn:country_code":"SL",
    "gn:dem":195,
    "gn:feature_class":"P",
    "gn:feature_code":"PPL",
    "gn:name":"Saama",
    "gn:population":0,
    "gn:timezone":"Africa/Freetown",
    "iso:country":"SL",
    "name:eng_x_preferred":[
        "Saama"
    ],
    "wof:name":"Saama",
    "wof:placetype":"locality"
},
  "geometry": {"coordinates":[-10.92754,7.9169],"type":"Point"}
}