{
  "type": "Feature",
  "properties": {
    "gn:admin1_code":"2.0",
    "gn:asciiname":"Matoli",
    "gn:country_code":"SL",
    "gn:dem":34,
    "gn:feature_class":"P",
    "gn:feature_code":"PPL",
    "gn:name":"Matoli",
    "gn:population":0,
    "gn:timezone":"Africa/Freetown",
    "iso:country":"SL",
    "name:eng_x_preferred":[
        "Matoli"
    ],
    "wof:name":"Matoli",
    "wof:placetype":"locality"
},
  "geometry": {"coordinates":[-13.01426,8.39975],"type":"Point"}
}