{
  "type": "Feature",
  "properties": {
    "gn:admin1_code":"01",
    "gn:asciiname":"Kambadu",
    "gn:country_code":"SL",
    "gn:dem":310,
    "gn:feature_class":"P",
    "gn:feature_code":"PPL",
    "gn:name":"Kambadu",
    "gn:population":0,
    "gn:timezone":"Africa/Freetown",
    "iso:country":"SL",
    "name:eng_x_preferred":[
        "Kambadu"
    ],
    "name:fra_x_preferred":[
        "Yamandu"
    ],
    "name:und_x_variant":[
        "Yamandu"
    ],
    "name:urd_x_preferred":[
        "\u06cc\u0645\u0627\u0646\u062f\u0648"
    ],
    "wof:name":"Kambadu",
    "wof:placetype":"locality"
},
  "geometry": {"coordinates":[-10.86731,8.49031],"type":"Point"}
}