{
  "type": "Feature",
  "properties": {
    "gn:admin1_code":"01",
    "gn:asciiname":"Yomanja",
    "gn:country_code":"SL",
    "gn:dem":343,
    "gn:feature_class":"P",
    "gn:feature_code":"PPL",
    "gn:name":"Yomanja",
    "gn:population":0,
    "gn:timezone":"Africa/Freetown",
    "iso:country":"SL",
    "name:eng_x_preferred":[
        "Yomanja"
    ],
    "wof:name":"Yomanja",
    "wof:placetype":"locality"
},
  "geometry": {"coordinates":[-11.30756,8.60557],"type":"Point"}
}