{
  "type": "Feature",
  "properties": {
    "gn:admin1_code":"2.0",
    "gn:asciiname":"Kabari",
    "gn:country_code":"SL",
    "gn:dem":149,
    "gn:feature_class":"P",
    "gn:feature_code":"PPL",
    "gn:name":"Kabari",
    "gn:population":0,
    "gn:timezone":"Africa/Freetown",
    "iso:country":"SL",
    "name:und_x_variant":[
        "Kaban",
        "Kabari"
    ],
    "wof:name":"Kabari",
    "wof:placetype":"locality"
},
  "geometry": {"coordinates":[-11.76465,9.01906],"type":"Point"}
}