{
  "type": "Feature",
  "properties": {
    "gn:admin1_code":"1.0",
    "gn:asciiname":"Yituma",
    "gn:country_code":"SL",
    "gn:dem":333,
    "gn:feature_class":"P",
    "gn:feature_code":"PPL",
    "gn:name":"Yituma",
    "gn:population":0,
    "gn:timezone":"Africa/Freetown",
    "iso:country":"SL",
    "name:eng_x_preferred":[
        "Yituma"
    ],
    "wof:name":"Yituma",
    "wof:placetype":"locality"
},
  "geometry": {"coordinates":[-10.66266,8.54627],"type":"Point"}
}