{
  "type": "Feature",
  "properties": {
    "gn:admin1_code":"2.0",
    "gn:asciiname":"Kaberere",
    "gn:country_code":"SL",
    "gn:dem":504,
    "gn:feature_class":"P",
    "gn:feature_code":"PPL",
    "gn:name":"Kaberere",
    "gn:population":0,
    "gn:timezone":"Africa/Freetown",
    "iso:country":"SL",
    "name:eng_x_preferred":[
        "Kaberere"
    ],
    "name:und_x_variant":[
        "Kabere"
    ],
    "wof:name":"Kaberere",
    "wof:placetype":"locality"
},
  "geometry": {"coordinates":[-11.74028,9.52126],"type":"Point"}
}