{
  "type": "Feature",
  "properties": {
    "gn:admin1_code":"2.0",
    "gn:asciiname":"Mendi",
    "gn:country_code":"SL",
    "gn:dem":81,
    "gn:feature_class":"P",
    "gn:feature_code":"PPL",
    "gn:name":"Mendi",
    "gn:population":0,
    "gn:timezone":"Africa/Freetown",
    "iso:country":"SL",
    "name:ceb_x_preferred":[
        "Mendi"
    ],
    "name:deu_x_preferred":[
        "Mendi"
    ],
    "name:eng_x_preferred":[
        "Mendi"
    ],
    "name:fas_x_preferred":[
        "\u0645\u0646\u062f\u06cc"
    ],
    "name:fra_x_preferred":[
        "Mendi"
    ],
    "name:glg_x_preferred":[
        "Mendi"
    ],
    "name:ita_x_preferred":[
        "Mendi"
    ],
    "name:jpn_x_preferred":[
        "\u30e1\u30f3\u30c7\u30a3"
    ],
    "name:kor_x_preferred":[
        "\uba58\ub514"
    ],
    "name:nld_x_preferred":[
        "Mendi"
    ],
    "name:pol_x_preferred":[
        "Mendi"
    ],
    "name:rus_x_preferred":[
        "\u041c\u0435\u043d\u0434\u0438"
    ],
    "name:tpi_x_preferred":[
        "Mendi"
    ],
    "name:urd_x_preferred":[
        "\u0645\u06cc\u0646\u062f\u06cc"
    ],
    "name:zho_x_preferred":[
        "\u9580\u8fea"
    ],
    "wof:name":"Mendi",
    "wof:placetype":"locality"
},
  "geometry": {"coordinates":[-12.4854,8.75764],"type":"Point"}
}