{
  "type": "Feature",
  "properties": {
    "iso:country":"SL",
    "name:bul_x_preferred":[
        "\u0417\u0438\u043c\u0438"
    ],
    "name:eng_x_preferred":[
        "Zimmi"
    ],
    "name:nld_x_preferred":[
        "Zimmi"
    ],
    "name:unk_x_variant":[
        "Zimi"
    ],
    "qs:gn_country":"SL",
    "qs:gn_fcode":"PPL",
    "qs:gn_pop":4796,
    "qs:name":"Zimmi",
    "qs:name_adm0":"Sierra Leone",
    "qs:name_adm1":"Southern",
    "qs:photos":0,
    "qs:photos_1k":0,
    "qs:photos_9k":1,
    "qs:photos_9r":1,
    "qs:photos_all":1,
    "qs:photos_sr":0,
    "qs:placetype":"Town",
    "qs:pop_sr":"4",
    "qs:woe_adm0":23424946,
    "wd:wordcount":118,
    "wof:name":"Zimmi",
    "wof:placetype":"locality",
    "wof:population":4796
},
  "geometry": {"coordinates":[-11.30611,7.31528],"type":"Point"}
}