{
  "type": "Feature",
  "properties": {
    "gn:admin1_code":"3.0",
    "gn:asciiname":"Maina",
    "gn:country_code":"SL",
    "gn:dem":96,
    "gn:feature_class":"P",
    "gn:feature_code":"PPL",
    "gn:name":"Maina",
    "gn:population":0,
    "gn:timezone":"Africa/Freetown",
    "iso:country":"SL",
    "name:eng_x_preferred":[
        "Maina"
    ],
    "name:und_x_variant":[
        "Mina"
    ],
    "wof:name":"Maina",
    "wof:placetype":"locality"
},
  "geometry": {"coordinates":[-11.63222,7.8907],"type":"Point"}
}