{
  "type": "Feature",
  "properties": {
    "gn:admin1_code":"3.0",
    "gn:asciiname":"Potama",
    "gn:country_code":"SL",
    "gn:dem":75,
    "gn:feature_class":"P",
    "gn:feature_code":"PPL",
    "gn:name":"Potama",
    "gn:population":0,
    "gn:timezone":"Africa/Freetown",
    "iso:country":"SL",
    "name:eng_x_preferred":[
        "Potama"
    ],
    "wof:name":"Potama",
    "wof:placetype":"locality"
},
  "geometry": {"coordinates":[-11.75529,7.85415],"type":"Point"}
}