{
  "type": "Feature",
  "properties": {
    "gn:admin1_code":"02",
    "gn:asciiname":"Sakuta",
    "gn:country_code":"SL",
    "gn:dem":445,
    "gn:feature_class":"P",
    "gn:feature_code":"PPL",
    "gn:name":"Sakuta",
    "gn:population":0,
    "gn:timezone":"Africa/Freetown",
    "iso:country":"SL",
    "name:eng_x_preferred":[
        "Sakuta"
    ],
    "wof:name":"Sakuta",
    "wof:placetype":"locality"
},
  "geometry": {"coordinates":[-11.69199,9.65987],"type":"Point"}
}