{
  "type": "Feature",
  "properties": {
    "gn:admin1_code":"3.0",
    "gn:asciiname":"Molaga",
    "gn:country_code":"SL",
    "gn:dem":29,
    "gn:feature_class":"P",
    "gn:feature_code":"PPL",
    "gn:name":"Molaga",
    "gn:population":0,
    "gn:timezone":"Africa/Freetown",
    "iso:country":"SL",
    "name:eng_x_preferred":[
        "Molaga"
    ],
    "wof:name":"Molaga",
    "wof:placetype":"locality"
},
  "geometry": {"coordinates":[-12.68508,7.87709],"type":"Point"}
}