{
  "type": "Feature",
  "properties": {
    "gn:admin1_code":"1.0",
    "gn:asciiname":"Kaine",
    "gn:country_code":"SL",
    "gn:dem":247,
    "gn:feature_class":"P",
    "gn:feature_code":"PPL",
    "gn:name":"Kaine",
    "gn:population":0,
    "gn:timezone":"Africa/Freetown",
    "iso:country":"SL",
    "name:deu_x_preferred":[
        "Kaine"
    ],
    "name:fra_x_preferred":[
        "Kaine"
    ],
    "name:spa_x_preferred":[
        "Kaine"
    ],
    "wof:name":"Kaine",
    "wof:placetype":"locality"
},
  "geometry": {"coordinates":[-10.85,8.38333],"type":"Point"}
}