{
  "type": "Feature",
  "properties": {
    "gn:admin1_code":"2.0",
    "gn:asciiname":"Keimadugu",
    "gn:country_code":"SL",
    "gn:dem":407,
    "gn:feature_class":"P",
    "gn:feature_code":"PPL",
    "gn:name":"Keimadugu",
    "gn:population":0,
    "gn:timezone":"Africa/Freetown",
    "iso:country":"SL",
    "name:eng_x_preferred":[
        "Keimadugu"
    ],
    "wof:name":"Keimadugu",
    "wof:placetype":"locality"
},
  "geometry": {"coordinates":[-11.66397,9.00664],"type":"Point"}
}