{
  "type": "Feature",
  "properties": {
    "gn:admin1_code":"3.0",
    "gn:asciiname":"Waiwaihun",
    "gn:country_code":"SL",
    "gn:dem":49,
    "gn:feature_class":"P",
    "gn:feature_code":"PPL",
    "gn:name":"Waiwaihun",
    "gn:population":0,
    "gn:timezone":"Africa/Freetown",
    "iso:country":"SL",
    "name:eng_x_preferred":[
        "Waiwaihun"
    ],
    "wof:name":"Waiwaihun",
    "wof:placetype":"locality"
},
  "geometry": {"coordinates":[-12.00288,7.7205],"type":"Point"}
}