{
  "type": "Feature",
  "properties": {
    "gn:admin1_code":"1.0",
    "gn:asciiname":"Kpangbani",
    "gn:country_code":"SL",
    "gn:dem":401,
    "gn:feature_class":"P",
    "gn:feature_code":"PPL",
    "gn:name":"Kpangbani",
    "gn:population":0,
    "gn:timezone":"Africa/Freetown",
    "iso:country":"SL",
    "name:eng_x_preferred":[
        "Kpangbani"
    ],
    "wof:name":"Kpangbani",
    "wof:placetype":"locality"
},
  "geometry": {"coordinates":[-10.33224,8.43723],"type":"Point"}
}