{
  "type": "Feature",
  "properties": {
    "gn:admin1_code":"2.0",
    "gn:asciiname":"Mane",
    "gn:country_code":"SL",
    "gn:dem":70,
    "gn:feature_class":"P",
    "gn:feature_code":"PPL",
    "gn:name":"Mane",
    "gn:population":0,
    "gn:timezone":"Africa/Freetown",
    "iso:country":"SL",
    "name:eng_x_preferred":[
        "Mane"
    ],
    "wof:name":"Mane",
    "wof:placetype":"locality"
},
  "geometry": {"coordinates":[-12.3371,8.7421],"type":"Point"}
}