{
  "type": "Feature",
  "properties": {
    "gn:admin1_code":"3.0",
    "gn:asciiname":"Baiama",
    "gn:country_code":"SL",
    "gn:dem":110,
    "gn:feature_class":"P",
    "gn:feature_code":"PPL",
    "gn:name":"Baiama",
    "gn:population":0,
    "gn:timezone":"Africa/Freetown",
    "iso:country":"SL",
    "name:eng_x_preferred":[
        "Baiama"
    ],
    "wof:name":"Baiama",
    "wof:placetype":"locality"
},
  "geometry": {"coordinates":[-11.74811,7.99953],"type":"Point"}
}