{
  "type": "Feature",
  "properties": {
    "gn:admin1_code":"1.0",
    "gn:asciiname":"Gengelu",
    "gn:country_code":"SL",
    "gn:dem":212,
    "gn:feature_class":"P",
    "gn:feature_code":"PPL",
    "gn:name":"Gengelu",
    "gn:population":0,
    "gn:timezone":"Africa/Freetown",
    "iso:country":"SL",
    "name:eng_x_preferred":[
        "Gengelu"
    ],
    "wof:name":"Gengelu",
    "wof:placetype":"locality"
},
  "geometry": {"coordinates":[-11.22073,7.89179],"type":"Point"}
}