{
  "type": "Feature",
  "properties": {
    "gn:admin1_code":"3.0",
    "gn:asciiname":"Bonjema",
    "gn:country_code":"SL",
    "gn:dem":48,
    "gn:feature_class":"P",
    "gn:feature_code":"PPL",
    "gn:name":"Bonjema",
    "gn:population":0,
    "gn:timezone":"Africa/Freetown",
    "iso:country":"SL",
    "name:eng_x_preferred":[
        "Bonjema"
    ],
    "wof:name":"Bonjema",
    "wof:placetype":"locality"
},
  "geometry": {"coordinates":[-11.97414,7.97657],"type":"Point"}
}