{
  "type": "Feature",
  "properties": {
    "gn:admin1_code":"2.0",
    "gn:asciiname":"Manankan",
    "gn:country_code":"SL",
    "gn:dem":354,
    "gn:feature_class":"P",
    "gn:feature_code":"PPL",
    "gn:name":"Manankan",
    "gn:population":0,
    "gn:timezone":"Africa/Freetown",
    "iso:country":"SL",
    "name:eng_x_preferred":[
        "Manankan"
    ],
    "wof:name":"Manankan",
    "wof:placetype":"locality"
},
  "geometry": {"coordinates":[-11.48809,9.75791],"type":"Point"}
}