{
  "type": "Feature",
  "properties": {
    "gn:admin1_code":"1.0",
    "gn:asciiname":"Kwakor",
    "gn:country_code":"SL",
    "gn:dem":516,
    "gn:feature_class":"P",
    "gn:feature_code":"PPL",
    "gn:name":"Kwakor",
    "gn:population":0,
    "gn:timezone":"Africa/Freetown",
    "iso:country":"SL",
    "name:eng_x_preferred":[
        "Kwakor"
    ],
    "wof:name":"Kwakor",
    "wof:placetype":"locality"
},
  "geometry": {"coordinates":[-10.76163,8.62112],"type":"Point"}
}