{
  "type": "Feature",
  "properties": {
    "gn:admin1_code":"2.0",
    "gn:asciiname":"Buia",
    "gn:country_code":"SL",
    "gn:dem":90,
    "gn:feature_class":"P",
    "gn:feature_code":"PPL",
    "gn:name":"Buia",
    "gn:population":0,
    "gn:timezone":"Africa/Freetown",
    "iso:country":"SL",
    "name:eng_x_preferred":[
        "Buia"
    ],
    "wof:name":"Buia",
    "wof:placetype":"locality"
},
  "geometry": {"coordinates":[-12.00845,8.87469],"type":"Point"}
}