{
  "type": "Feature",
  "properties": {
    "gn:admin1_code":"1.0",
    "gn:asciiname":"Ngandonde",
    "gn:country_code":"SL",
    "gn:dem":395,
    "gn:feature_class":"P",
    "gn:feature_code":"PPL",
    "gn:name":"Ngandonde",
    "gn:population":0,
    "gn:timezone":"Africa/Freetown",
    "iso:country":"SL",
    "name:eng_x_preferred":[
        "Ngandonde"
    ],
    "wof:name":"Ngandonde",
    "wof:placetype":"locality"
},
  "geometry": {"coordinates":[-11.06872,8.65659],"type":"Point"}
}