{
  "type": "Feature",
  "properties": {
    "gn:admin1_code":"2.0",
    "gn:asciiname":"Magbara",
    "gn:country_code":"SL",
    "gn:dem":20,
    "gn:feature_class":"P",
    "gn:feature_code":"PPL",
    "gn:name":"Magbara",
    "gn:population":0,
    "gn:timezone":"Africa/Freetown",
    "iso:country":"SL",
    "name:eng_x_preferred":[
        "Magbara"
    ],
    "wof:name":"Magbara",
    "wof:placetype":"locality"
},
  "geometry": {"coordinates":[-12.79823,8.54502],"type":"Point"}
}