{
  "type": "Feature",
  "properties": {
    "gn:admin1_code":"1.0",
    "gn:asciiname":"Dema Nina",
    "gn:country_code":"SL",
    "gn:dem":210,
    "gn:feature_class":"P",
    "gn:feature_code":"PPL",
    "gn:name":"Dema Nina",
    "gn:population":0,
    "gn:timezone":"Africa/Freetown",
    "iso:country":"SL",
    "name:eng_x_preferred":[
        "Dema Nina"
    ],
    "wof:name":"Dema Nina",
    "wof:placetype":"locality"
},
  "geometry": {"coordinates":[-10.80134,8.10839],"type":"Point"}
}