{
  "type": "Feature",
  "properties": {
    "gn:admin1_code":"02",
    "gn:asciiname":"Sangbania",
    "gn:country_code":"SL",
    "gn:dem":644,
    "gn:feature_class":"P",
    "gn:feature_code":"PPL",
    "gn:name":"Sangbania",
    "gn:population":0,
    "gn:timezone":"Africa/Freetown",
    "iso:country":"SL",
    "name:eng_x_preferred":[
        "Sangbania"
    ],
    "wof:name":"Sangbania",
    "wof:placetype":"locality"
},
  "geometry": {"coordinates":[-11.0137,9.19217],"type":"Point"}
}