{
  "type": "Feature",
  "properties": {
    "gn:admin1_code":"2.0",
    "gn:asciiname":"Benia",
    "gn:country_code":"SL",
    "gn:dem":477,
    "gn:feature_class":"P",
    "gn:feature_code":"PPL",
    "gn:name":"Benia",
    "gn:population":0,
    "gn:timezone":"Africa/Freetown",
    "iso:country":"SL",
    "name:eng_x_preferred":[
        "Benia"
    ],
    "wof:name":"Benia",
    "wof:placetype":"locality"
},
  "geometry": {"coordinates":[-11.58713,9.60281],"type":"Point"}
}