{
  "type": "Feature",
  "properties": {
    "gn:admin1_code":"2.0",
    "gn:asciiname":"Mokebi",
    "gn:country_code":"SL",
    "gn:dem":69,
    "gn:feature_class":"P",
    "gn:feature_code":"PPL",
    "gn:name":"Mokebi",
    "gn:population":0,
    "gn:timezone":"Africa/Freetown",
    "iso:country":"SL",
    "name:eng_x_preferred":[
        "Mokebi"
    ],
    "wof:name":"Mokebi",
    "wof:placetype":"locality"
},
  "geometry": {"coordinates":[-12.21327,8.38067],"type":"Point"}
}