{
  "type": "Feature",
  "properties": {
    "gn:admin1_code":"1.0",
    "gn:asciiname":"Wordu",
    "gn:country_code":"SL",
    "gn:dem":411,
    "gn:feature_class":"P",
    "gn:feature_code":"PPL",
    "gn:name":"Wordu",
    "gn:population":0,
    "gn:timezone":"Africa/Freetown",
    "iso:country":"SL",
    "name:eng_x_preferred":[
        "Wordu"
    ],
    "wof:name":"Wordu",
    "wof:placetype":"locality"
},
  "geometry": {"coordinates":[-11.0044,8.72538],"type":"Point"}
}