{
  "type": "Feature",
  "properties": {
    "gn:admin1_code":"3.0",
    "gn:asciiname":"Bawalihun",
    "gn:country_code":"SL",
    "gn:dem":3,
    "gn:feature_class":"P",
    "gn:feature_code":"PPL",
    "gn:name":"Bawalihun",
    "gn:population":0,
    "gn:timezone":"Africa/Freetown",
    "iso:country":"SL",
    "name:eng_x_preferred":[
        "Bawalihun"
    ],
    "wof:name":"Bawalihun",
    "wof:placetype":"locality"
},
  "geometry": {"coordinates":[-12.42456,7.55744],"type":"Point"}
}