{
  "type": "Feature",
  "properties": {
    "gn:admin1_code":"1.0",
    "gn:asciiname":"Kasadu",
    "gn:country_code":"SL",
    "gn:dem":471,
    "gn:feature_class":"P",
    "gn:feature_code":"PPL",
    "gn:name":"Kasadu",
    "gn:population":0,
    "gn:timezone":"Africa/Freetown",
    "iso:country":"SL",
    "name:eng_x_preferred":[
        "Kasadu"
    ],
    "wof:name":"Kasadu",
    "wof:placetype":"locality"
},
  "geometry": {"coordinates":[-10.87899,8.59892],"type":"Point"}
}