{
  "type": "Feature",
  "properties": {
    "gn:admin1_code":"2.0",
    "gn:asciiname":"Masuri",
    "gn:country_code":"SL",
    "gn:dem":343,
    "gn:feature_class":"P",
    "gn:feature_code":"PPL",
    "gn:name":"Masuri",
    "gn:population":0,
    "gn:timezone":"Africa/Freetown",
    "iso:country":"SL",
    "name:ceb_x_preferred":[
        "Masuri"
    ],
    "name:eng_x_preferred":[
        "Masuri"
    ],
    "name:swe_x_preferred":[
        "Masuri"
    ],
    "wof:name":"Masuri",
    "wof:placetype":"locality"
},
  "geometry": {"coordinates":[-11.62416,8.68011],"type":"Point"}
}