{
  "type": "Feature",
  "properties": {
    "gn:admin1_code":"1.0",
    "gn:asciiname":"Goala",
    "gn:country_code":"SL",
    "gn:dem":206,
    "gn:feature_class":"P",
    "gn:feature_code":"PPL",
    "gn:name":"Goala",
    "gn:population":0,
    "gn:timezone":"Africa/Freetown",
    "iso:country":"SL",
    "name:ceb_x_preferred":[
        "Goala"
    ],
    "name:eng_x_preferred":[
        "Goala"
    ],
    "name:swe_x_preferred":[
        "Goala"
    ],
    "wof:name":"Goala",
    "wof:placetype":"locality"
},
  "geometry": {"coordinates":[-10.9671,8.1639],"type":"Point"}
}