{
  "type": "Feature",
  "properties": {
    "gn:admin1_code":"3.0",
    "gn:asciiname":"Kpekedu",
    "gn:country_code":"SL",
    "gn:dem":28,
    "gn:feature_class":"P",
    "gn:feature_code":"PPL",
    "gn:name":"Kpekedu",
    "gn:population":0,
    "gn:timezone":"Africa/Freetown",
    "iso:country":"SL",
    "name:eng_x_preferred":[
        "Kpekedu"
    ],
    "wof:name":"Kpekedu",
    "wof:placetype":"locality"
},
  "geometry": {"coordinates":[-11.76334,7.38588],"type":"Point"}
}