{
  "type": "Feature",
  "properties": {
    "gn:country":"SL",
    "gn:fcode":"PPL",
    "gn:pop":4462,
    "iso:country":"SL",
    "name:bul_x_preferred":[
        "\u041f\u0435\u043f\u0435\u043b"
    ],
    "name:dut_x_preferred":[
        "Pepel"
    ],
    "name:eng_x_preferred":[
        "Pepel"
    ],
    "name:fin_x_preferred":[
        "Pepel"
    ],
    "name:ger_x_preferred":[
        "Pepel"
    ],
    "name:jpn_x_preferred":[
        "\u30da\u30da\u30eb"
    ],
    "name:pol_x_preferred":[
        "Pepel"
    ],
    "name:por_x_preferred":[
        "Pepel"
    ],
    "qs:name":"Pepel",
    "qs:photos_9r":0,
    "qs:photos_sr":0,
    "qs:pop_sr":"4",
    "wd:wordcount":139,
    "wof:name":"Pepel",
    "wof:placetype":"locality",
    "wof:population":4462
},
  "geometry": {"coordinates":[-13.06278,8.58167],"type":"Point"}
}