{
  "type": "Feature",
  "properties": {
    "gn:admin1_code":"4.0",
    "gn:asciiname":"Baponto",
    "gn:country_code":"SL",
    "gn:dem":12,
    "gn:feature_class":"P",
    "gn:feature_code":"PPL",
    "gn:name":"Baponto",
    "gn:population":0,
    "gn:timezone":"Africa/Freetown",
    "iso:country":"SL",
    "name:eng_x_preferred":[
        "Baponto"
    ],
    "wof:name":"Baponto",
    "wof:placetype":"locality"
},
  "geometry": {"coordinates":[-13.06743,8.28148],"type":"Point"}
}