{
  "type": "Feature",
  "properties": {
    "gn:admin1_code":"2.0",
    "gn:asciiname":"Magbenkaworo",
    "gn:country_code":"SL",
    "gn:dem":70,
    "gn:feature_class":"P",
    "gn:feature_code":"PPL",
    "gn:name":"Magbenkaworo",
    "gn:population":0,
    "gn:timezone":"Africa/Freetown",
    "iso:country":"SL",
    "name:eng_x_preferred":[
        "Magbenkaworo"
    ],
    "wof:name":"Magbenkaworo",
    "wof:placetype":"locality"
},
  "geometry": {"coordinates":[-12.52516,8.28587],"type":"Point"}
}