{
  "type": "Feature",
  "properties": {
    "gn:admin1_code":"2.0",
    "gn:asciiname":"Mabente",
    "gn:country_code":"SL",
    "gn:dem":127,
    "gn:feature_class":"P",
    "gn:feature_code":"PPL",
    "gn:name":"Mabente",
    "gn:population":0,
    "gn:timezone":"Africa/Freetown",
    "iso:country":"SL",
    "name:eng_x_preferred":[
        "Mabente"
    ],
    "wof:name":"Mabente",
    "wof:placetype":"locality"
},
  "geometry": {"coordinates":[-11.76792,8.76033],"type":"Point"}
}