{
  "type": "Feature",
  "properties": {
    "gn:admin1_code":"2.0",
    "gn:asciiname":"Limbaya",
    "gn:country_code":"SL",
    "gn:dem":447,
    "gn:feature_class":"P",
    "gn:feature_code":"PPL",
    "gn:name":"Limbaya",
    "gn:population":0,
    "gn:timezone":"Africa/Freetown",
    "iso:country":"SL",
    "name:eng_x_preferred":[
        "Limbaya"
    ],
    "wof:name":"Limbaya",
    "wof:placetype":"locality"
},
  "geometry": {"coordinates":[-11.26249,9.81463],"type":"Point"}
}