{
  "type": "Feature",
  "properties": {
    "gn:admin1_code":"03",
    "gn:asciiname":"Senehun Bulema",
    "gn:country_code":"SL",
    "gn:dem":57,
    "gn:feature_class":"P",
    "gn:feature_code":"PPL",
    "gn:name":"Senehun Bulema",
    "gn:population":0,
    "gn:timezone":"Africa/Freetown",
    "iso:country":"SL",
    "name:eng_x_preferred":[
        "Senehun Bulema"
    ],
    "wof:name":"Senehun Bulema",
    "wof:placetype":"locality"
},
  "geometry": {"coordinates":[-11.32263,7.21874],"type":"Point"}
}