{
  "type": "Feature",
  "properties": {
    "gn:admin1_code":"03",
    "gn:asciiname":"Victoria",
    "gn:country_code":"SL",
    "gn:dem":278,
    "gn:feature_class":"P",
    "gn:feature_code":"PPL",
    "gn:name":"Victoria",
    "gn:population":0,
    "gn:timezone":"Africa/Freetown",
    "iso:country":"SL",
    "name:eng_x_preferred":[
        "Victoria"
    ],
    "wof:name":"Victoria",
    "wof:placetype":"locality"
},
  "geometry": {"coordinates":[-11.72971,8.47969],"type":"Point"}
}