{
  "type": "Feature",
  "properties": {
    "gn:admin1_code":"3.0",
    "gn:asciiname":"Kamato",
    "gn:country_code":"SL",
    "gn:dem":69,
    "gn:feature_class":"P",
    "gn:feature_code":"PPL",
    "gn:name":"Kamato",
    "gn:population":0,
    "gn:timezone":"Africa/Freetown",
    "iso:country":"SL",
    "name:eng_x_preferred":[
        "Kamato"
    ],
    "wof:name":"Kamato",
    "wof:placetype":"locality"
},
  "geometry": {"coordinates":[-12.10632,8.14109],"type":"Point"}
}