{
  "type": "Feature",
  "properties": {
    "gn:admin1_code":"1.0",
    "gn:asciiname":"Koyandu",
    "gn:country_code":"SL",
    "gn:dem":562,
    "gn:feature_class":"P",
    "gn:feature_code":"PPL",
    "gn:name":"Koyandu",
    "gn:population":0,
    "gn:timezone":"Africa/Freetown",
    "iso:country":"SL",
    "name:eng_x_preferred":[
        "Koyandu"
    ],
    "wof:name":"Koyandu",
    "wof:placetype":"locality"
},
  "geometry": {"coordinates":[-10.73723,8.69237],"type":"Point"}
}