{
  "type": "Feature",
  "properties": {
    "gn:admin1_code":"1.0",
    "gn:asciiname":"Kpefe",
    "gn:country_code":"SL",
    "gn:dem":152,
    "gn:feature_class":"P",
    "gn:feature_code":"PPL",
    "gn:name":"Kpefe",
    "gn:population":0,
    "gn:timezone":"Africa/Freetown",
    "iso:country":"SL",
    "wof:name":"Kpefe",
    "wof:placetype":"locality"
},
  "geometry": {"coordinates":[-11.31667,8.31667],"type":"Point"}
}