{
  "type": "Feature",
  "properties": {
    "gn:admin1_code":"2.0",
    "gn:asciiname":"Rotifunk",
    "gn:country_code":"SL",
    "gn:dem":22,
    "gn:feature_class":"P",
    "gn:feature_code":"PPL",
    "gn:name":"Rotifunk",
    "gn:population":0,
    "gn:timezone":"Africa/Freetown",
    "iso:country":"SL",
    "name:ceb_x_preferred":[
        "Rotifunk"
    ],
    "name:deu_x_preferred":[
        "Rotifunk"
    ],
    "name:eng_x_preferred":[
        "Rotifunk"
    ],
    "name:fin_x_preferred":[
        "Rotifunk"
    ],
    "name:nld_x_preferred":[
        "Rotifunk"
    ],
    "wof:name":"Rotifunk",
    "wof:placetype":"locality"
},
  "geometry": {"coordinates":[-13.11523,8.98389],"type":"Point"}
}