{
  "type": "Feature",
  "properties": {
    "gn:admin1_code":"3.0",
    "gn:asciiname":"Gbeyahun",
    "gn:country_code":"SL",
    "gn:dem":100,
    "gn:feature_class":"P",
    "gn:feature_code":"PPL",
    "gn:name":"Gbeyahun",
    "gn:population":0,
    "gn:timezone":"Africa/Freetown",
    "iso:country":"SL",
    "name:eng_x_preferred":[
        "Gbeyahun"
    ],
    "name:und_x_variant":[
        "Buyehun"
    ],
    "wof:name":"Gbeyahun",
    "wof:placetype":"locality"
},
  "geometry": {"coordinates":[-11.71105,8.14411],"type":"Point"}
}