{
  "type": "Feature",
  "properties": {
    "gn:admin1_code":"02",
    "gn:asciiname":"Sakuma",
    "gn:country_code":"SL",
    "gn:dem":173,
    "gn:feature_class":"P",
    "gn:feature_code":"PPL",
    "gn:name":"Sakuma",
    "gn:population":0,
    "gn:timezone":"Africa/Freetown",
    "iso:country":"SL",
    "name:eng_x_preferred":[
        "Sakuma"
    ],
    "wof:name":"Sakuma",
    "wof:placetype":"locality"
},
  "geometry": {"coordinates":[-12.21939,9.28544],"type":"Point"}
}