{
  "type": "Feature",
  "properties": {
    "gn:admin1_code":"2.0",
    "gn:asciiname":"Tugure",
    "gn:country_code":"SL",
    "gn:dem":131,
    "gn:feature_class":"P",
    "gn:feature_code":"PPL",
    "gn:name":"Tugure",
    "gn:population":0,
    "gn:timezone":"Africa/Freetown",
    "iso:country":"SL",
    "name:eng_x_preferred":[
        "Tugure"
    ],
    "wof:name":"Tugure",
    "wof:placetype":"locality"
},
  "geometry": {"coordinates":[-12.24077,9.82033],"type":"Point"}
}