{
  "type": "Feature",
  "properties": {
    "gn:admin1_code":"3.0",
    "gn:asciiname":"Motami",
    "gn:country_code":"SL",
    "gn:dem":35,
    "gn:feature_class":"P",
    "gn:feature_code":"PPL",
    "gn:name":"Motami",
    "gn:population":0,
    "gn:timezone":"Africa/Freetown",
    "iso:country":"SL",
    "name:eng_x_preferred":[
        "Motami"
    ],
    "wof:name":"Motami",
    "wof:placetype":"locality"
},
  "geometry": {"coordinates":[-12.09863,7.67456],"type":"Point"}
}