{
  "type": "Feature",
  "properties": {
    "gn:admin1_code":"1.0",
    "gn:asciiname":"Sengbeyema",
    "gn:country_code":"SL",
    "gn:dem":213,
    "gn:feature_class":"P",
    "gn:feature_code":"PPL",
    "gn:name":"Sengbeyema",
    "gn:population":0,
    "gn:timezone":"Africa/Freetown",
    "iso:country":"SL",
    "name:eng_x_preferred":[
        "Sengbeyema"
    ],
    "wof:name":"Sengbeyema",
    "wof:placetype":"locality"
},
  "geometry": {"coordinates":[-10.73887,8.08972],"type":"Point"}
}