{
  "type": "Feature",
  "properties": {
    "gn:admin1_code":"2.0",
    "gn:asciiname":"Mayagba",
    "gn:country_code":"SL",
    "gn:dem":96,
    "gn:feature_class":"P",
    "gn:feature_code":"PPL",
    "gn:name":"Mayagba",
    "gn:population":0,
    "gn:timezone":"Africa/Freetown",
    "iso:country":"SL",
    "name:eng_x_preferred":[
        "Mayagba"
    ],
    "wof:name":"Mayagba",
    "wof:placetype":"locality"
},
  "geometry": {"coordinates":[-11.96886,8.75578],"type":"Point"}
}