{
  "type": "Feature",
  "properties": {
    "gn:admin1_code":"03",
    "gn:asciiname":"Petema",
    "gn:country_code":"SL",
    "gn:dem":67,
    "gn:feature_class":"P",
    "gn:feature_code":"PPL",
    "gn:name":"Petema",
    "gn:population":0,
    "gn:timezone":"Africa/Freetown",
    "iso:country":"SL",
    "name:eng_x_preferred":[
        "Petema"
    ],
    "wof:name":"Petema",
    "wof:placetype":"locality"
},
  "geometry": {"coordinates":[-12.16541,8.03104],"type":"Point"}
}