{
  "type": "Feature",
  "properties": {
    "gn:admin1_code":"2.0",
    "gn:asciiname":"Mahun",
    "gn:country_code":"SL",
    "gn:dem":43,
    "gn:feature_class":"P",
    "gn:feature_code":"PPL",
    "gn:name":"Mahun",
    "gn:population":0,
    "gn:timezone":"Africa/Freetown",
    "iso:country":"SL",
    "name:eng_x_preferred":[
        "Mahun"
    ],
    "wof:name":"Mahun",
    "wof:placetype":"locality"
},
  "geometry": {"coordinates":[-13.15063,8.68821],"type":"Point"}
}