{
  "type": "Feature",
  "properties": {
    "gn:admin1_code":"3.0",
    "gn:asciiname":"Momango",
    "gn:country_code":"SL",
    "gn:dem":62,
    "gn:feature_class":"P",
    "gn:feature_code":"PPL",
    "gn:name":"Momango",
    "gn:population":0,
    "gn:timezone":"Africa/Freetown",
    "iso:country":"SL",
    "name:eng_x_preferred":[
        "Momango"
    ],
    "wof:name":"Momango",
    "wof:placetype":"locality"
},
  "geometry": {"coordinates":[-12.4412,7.92885],"type":"Point"}
}