{
  "type": "Feature",
  "properties": {
    "gn:admin1_code":"1.0",
    "gn:asciiname":"Kwango",
    "gn:country_code":"SL",
    "gn:dem":185,
    "gn:feature_class":"P",
    "gn:feature_code":"PPL",
    "gn:name":"Kwango",
    "gn:population":0,
    "gn:timezone":"Africa/Freetown",
    "iso:country":"SL",
    "name:eng_x_preferred":[
        "Kwango"
    ],
    "wof:name":"Kwango",
    "wof:placetype":"locality"
},
  "geometry": {"coordinates":[-10.97895,7.86729],"type":"Point"}
}