{
  "type": "Feature",
  "properties": {
    "gn:admin1_code":"2.0",
    "gn:asciiname":"Maso",
    "gn:country_code":"SL",
    "gn:dem":79,
    "gn:feature_class":"P",
    "gn:feature_code":"PPL",
    "gn:name":"Maso",
    "gn:population":0,
    "gn:timezone":"Africa/Freetown",
    "iso:country":"SL",
    "name:bul_x_preferred":[
        "\u041c\u0430\u0437\u043e\u043d"
    ],
    "name:ceb_x_preferred":[
        "Maso"
    ],
    "name:deu_x_preferred":[
        "Maso"
    ],
    "name:eng_x_preferred":[
        "Maso"
    ],
    "name:fra_x_preferred":[
        "Maso"
    ],
    "name:ita_x_preferred":[
        "Maso"
    ],
    "name:rus_x_preferred":[
        "\u041c\u0430\u0441\u043e"
    ],
    "name:spa_x_preferred":[
        "Maso"
    ],
    "name:srp_x_preferred":[
        "Maso"
    ],
    "name:swe_x_preferred":[
        "Maso"
    ],
    "wof:name":"Maso",
    "wof:placetype":"locality"
},
  "geometry": {"coordinates":[-12.44341,8.80947],"type":"Point"}
}