{
  "type": "Feature",
  "properties": {
    "gn:admin1_code":"3.0",
    "gn:asciiname":"Gangama",
    "gn:country_code":"SL",
    "gn:dem":91,
    "gn:feature_class":"P",
    "gn:feature_code":"PPL",
    "gn:name":"Gangama",
    "gn:population":0,
    "gn:timezone":"Africa/Freetown",
    "iso:country":"SL",
    "name:eng_x_preferred":[
        "Gangama"
    ],
    "wof:name":"Gangama",
    "wof:placetype":"locality"
},
  "geometry": {"coordinates":[-11.81698,8.11684],"type":"Point"}
}