{
  "type": "Feature",
  "properties": {
    "gn:admin1_code":"3.0",
    "gn:asciiname":"Gbahama",
    "gn:country_code":"SL",
    "gn:dem":62,
    "gn:feature_class":"P",
    "gn:feature_code":"PPL",
    "gn:name":"Gbahama",
    "gn:population":0,
    "gn:timezone":"Africa/Freetown",
    "iso:country":"SL",
    "name:und_x_variant":[
        "Bahama",
        "Gbahama"
    ],
    "wof:name":"Gbahama",
    "wof:placetype":"locality"
},
  "geometry": {"coordinates":[-11.34967,7.29631],"type":"Point"}
}