{
  "type": "Feature",
  "properties": {
    "gn:admin1_code":"2.0",
    "gn:asciiname":"Makul",
    "gn:country_code":"SL",
    "gn:dem":43,
    "gn:feature_class":"P",
    "gn:feature_code":"PPL",
    "gn:name":"Makul",
    "gn:population":0,
    "gn:timezone":"Africa/Freetown",
    "iso:country":"SL",
    "name:eng_x_preferred":[
        "Makul"
    ],
    "wof:name":"Makul",
    "wof:placetype":"locality"
},
  "geometry": {"coordinates":[-12.76344,9.07953],"type":"Point"}
}