{
  "type": "Feature",
  "properties": {
    "gn:admin1_code":"2.0",
    "gn:asciiname":"Rogbom",
    "gn:country_code":"SL",
    "gn:dem":50,
    "gn:feature_class":"P",
    "gn:feature_code":"PPL",
    "gn:name":"Rogbom",
    "gn:population":0,
    "gn:timezone":"Africa/Freetown",
    "iso:country":"SL",
    "name:eng_x_preferred":[
        "Rogbom"
    ],
    "wof:name":"Rogbom",
    "wof:placetype":"locality"
},
  "geometry": {"coordinates":[-12.72724,8.72519],"type":"Point"}
}