{
  "type": "Feature",
  "properties": {
    "gn:admin1_code":"1.0",
    "gn:asciiname":"Bungema",
    "gn:country_code":"SL",
    "gn:dem":288,
    "gn:feature_class":"P",
    "gn:feature_code":"PPL",
    "gn:name":"Bungema",
    "gn:population":0,
    "gn:timezone":"Africa/Freetown",
    "iso:country":"SL",
    "name:eng_x_preferred":[
        "Bungema"
    ],
    "wof:name":"Bungema",
    "wof:placetype":"locality"
},
  "geometry": {"coordinates":[-11.10568,8.23718],"type":"Point"}
}