{
  "type": "Feature",
  "properties": {
    "gn:admin1_code":"2.0",
    "gn:asciiname":"Makono",
    "gn:country_code":"SL",
    "gn:dem":52,
    "gn:feature_class":"P",
    "gn:feature_code":"PPL",
    "gn:name":"Makono",
    "gn:population":0,
    "gn:timezone":"Africa/Freetown",
    "iso:country":"SL",
    "name:eng_x_preferred":[
        "Makono"
    ],
    "wof:name":"Makono",
    "wof:placetype":"locality"
},
  "geometry": {"coordinates":[-12.56717,8.49033],"type":"Point"}
}