{
  "type": "Feature",
  "properties": {
    "gn:admin1_code":"1.0",
    "gn:asciiname":"Kissi Town",
    "gn:country_code":"SL",
    "gn:dem":442,
    "gn:feature_class":"P",
    "gn:feature_code":"PPL",
    "gn:name":"Kissi Town",
    "gn:population":0,
    "gn:timezone":"Africa/Freetown",
    "iso:country":"SL",
    "name:eng_x_preferred":[
        "Kissi Town"
    ],
    "wof:name":"Kissi Town",
    "wof:placetype":"locality"
},
  "geometry": {"coordinates":[-10.79926,8.69982],"type":"Point"}
}