{
  "type": "Feature",
  "properties": {
    "gn:admin1_code":"1.0",
    "gn:asciiname":"Jombohun",
    "gn:country_code":"SL",
    "gn:dem":230,
    "gn:feature_class":"P",
    "gn:feature_code":"PPL",
    "gn:name":"Jombohun",
    "gn:population":0,
    "gn:timezone":"Africa/Freetown",
    "iso:country":"SL",
    "name:eng_x_preferred":[
        "Jombohun"
    ],
    "wof:name":"Jombohun",
    "wof:placetype":"locality"
},
  "geometry": {"coordinates":[-10.72778,7.91693],"type":"Point"}
}