{
  "type": "Feature",
  "properties": {
    "gn:admin1_code":"02",
    "gn:asciiname":"Yama",
    "gn:country_code":"SL",
    "gn:dem":84,
    "gn:feature_class":"P",
    "gn:feature_code":"PPL",
    "gn:name":"Yama",
    "gn:population":0,
    "gn:timezone":"Africa/Freetown",
    "iso:country":"SL",
    "name:und_x_variant":[
        "Yema",
        "Yama"
    ],
    "wof:name":"Yama",
    "wof:placetype":"locality"
},
  "geometry": {"coordinates":[-12.46625,8.88781],"type":"Point"}
}