{
  "type": "Feature",
  "properties": {
    "gn:admin1_code":"02",
    "gn:asciiname":"Yama",
    "gn:country_code":"SL",
    "gn:dem":84,
    "gn:feature_class":"P",
    "gn:feature_code":"PPL",
    "gn:name":"Yama",
    "gn:population":0,
    "gn:timezone":"Africa/Freetown",
    "iso:country":"SL",
    "name:als_x_preferred":[
        "Yama"
    ],
    "name:bod_x_preferred":[
        "\u0f42\u0f64\u0f72\u0f53\u0f0b\u0f62\u0f97\u0f7a\u0f0d"
    ],
    "name:cat_x_preferred":[
        "Yama"
    ],
    "name:ces_x_preferred":[
        "Jama"
    ],
    "name:dan_x_preferred":[
        "Yama"
    ],
    "name:deu_x_preferred":[
        "Yama"
    ],
    "name:fas_x_preferred":[
        "\u06cc\u0645\u0627"
    ],
    "name:fin_x_preferred":[
        "Yama"
    ],
    "name:fra_x_preferred":[
        "Yama"
    ],
    "name:hun_x_preferred":[
        "Jama"
    ],
    "name:ind_x_preferred":[
        "Yama"
    ],
    "name:ita_x_preferred":[
        "Yama"
    ],
    "name:jav_x_preferred":[
        "Yama"
    ],
    "name:lav_x_preferred":[
        "Jama"
    ],
    "name:lit_x_preferred":[
        "Jama"
    ],
    "name:mal_x_preferred":[
        "\u0d2f\u0d2e\u0d7b"
    ],
    "name:msa_x_preferred":[
        "Yama"
    ],
    "name:nep_x_preferred":[
        "\u092f\u092e\u0930\u093e\u091c"
    ],
    "name:nld_x_preferred":[
        "Yama"
    ],
    "name:nno_x_preferred":[
        "Jama"
    ],
    "name:nor_x_preferred":[
        "Yama"
    ],
    "name:pol_x_preferred":[
        "Jama"
    ],
    "name:ron_x_preferred":[
        "Yama"
    ],
    "name:rus_x_preferred":[
        "\u042f\u043c\u0430"
    ],
    "name:slk_x_preferred":[
        "Jama"
    ],
    "name:slv_x_preferred":[
        "Jama"
    ],
    "name:spa_x_preferred":[
        "Iama"
    ],
    "name:swe_x_preferred":[
        "Yama"
    ],
    "name:tat_x_preferred":[
        "\u042f\u043c\u0430 \u0420\u0430\u0434\u0436"
    ],
    "name:tel_x_preferred":[
        "\u0c2f\u0c2e\u0c41\u0c21\u0c41"
    ],
    "name:tha_x_preferred":[
        "\u0e1e\u0e23\u0e30\u0e22\u0e21"
    ],
    "name:ukr_x_preferred":[
        "\u042f\u043c\u0430"
    ],
    "name:und_x_variant":[
        "Yema"
    ],
    "name:vie_x_preferred":[
        "Di\u00eam v\u01b0\u01a1ng"
    ],
    "wof:name":"Yama",
    "wof:placetype":"locality"
},
  "geometry": {"coordinates":[-12.46625,8.88781],"type":"Point"}
}