{
  "type": "Feature",
  "properties": {
    "gn:admin1_code":"2.0",
    "gn:asciiname":"Momanki",
    "gn:country_code":"SL",
    "gn:dem":69,
    "gn:feature_class":"P",
    "gn:feature_code":"PPL",
    "gn:name":"Momanki",
    "gn:population":0,
    "gn:timezone":"Africa/Freetown",
    "iso:country":"SL",
    "name:eng_x_preferred":[
        "Momanki"
    ],
    "wof:name":"Momanki",
    "wof:placetype":"locality"
},
  "geometry": {"coordinates":[-12.50836,8.33939],"type":"Point"}
}