{
  "type": "Feature",
  "properties": {
    "gn:admin1_code":"3.0",
    "gn:asciiname":"Dandabu",
    "gn:country_code":"SL",
    "gn:dem":107,
    "gn:feature_class":"P",
    "gn:feature_code":"PPL",
    "gn:name":"Dandabu",
    "gn:population":0,
    "gn:timezone":"Africa/Freetown",
    "iso:country":"SL",
    "name:eng_x_preferred":[
        "Dandabu"
    ],
    "wof:name":"Dandabu",
    "wof:placetype":"locality"
},
  "geometry": {"coordinates":[-11.64429,8.14883],"type":"Point"}
}