{
  "type": "Feature",
  "properties": {
    "gn:admin1_code":"2.0",
    "gn:asciiname":"Manane",
    "gn:country_code":"SL",
    "gn:dem":69,
    "gn:feature_class":"P",
    "gn:feature_code":"PPL",
    "gn:name":"Manane",
    "gn:population":0,
    "gn:timezone":"Africa/Freetown",
    "iso:country":"SL",
    "name:eng_x_preferred":[
        "Manane"
    ],
    "wof:name":"Manane",
    "wof:placetype":"locality"
},
  "geometry": {"coordinates":[-12.08114,8.48839],"type":"Point"}
}