{
  "type": "Feature",
  "properties": {
    "gn:admin1_code":"02",
    "gn:asciiname":"Sindugu",
    "gn:country_code":"SL",
    "gn:dem":130,
    "gn:feature_class":"P",
    "gn:feature_code":"PPL",
    "gn:name":"Sindugu",
    "gn:population":0,
    "gn:timezone":"Africa/Freetown",
    "iso:country":"SL",
    "name:eng_x_preferred":[
        "Sindugu"
    ],
    "wof:name":"Sindugu",
    "wof:placetype":"locality"
},
  "geometry": {"coordinates":[-12.24628,9.18521],"type":"Point"}
}