{
  "type": "Feature",
  "properties": {
    "gn:admin1_code":"1.0",
    "gn:asciiname":"Bindika",
    "gn:country_code":"SL",
    "gn:dem":288,
    "gn:feature_class":"P",
    "gn:feature_code":"PPL",
    "gn:name":"Bindika",
    "gn:population":0,
    "gn:timezone":"Africa/Freetown",
    "iso:country":"SL",
    "name:eng_x_preferred":[
        "Bindika"
    ],
    "wof:name":"Bindika",
    "wof:placetype":"locality"
},
  "geometry": {"coordinates":[-11.19126,8.20949],"type":"Point"}
}