{
  "type": "Feature",
  "properties": {
    "gn:admin1_code":"03",
    "gn:asciiname":"Yerima",
    "gn:country_code":"SL",
    "gn:dem":101,
    "gn:feature_class":"P",
    "gn:feature_code":"PPL",
    "gn:name":"Yerima",
    "gn:population":0,
    "gn:timezone":"Africa/Freetown",
    "iso:country":"SL",
    "name:eng_x_preferred":[
        "Yerima"
    ],
    "wof:name":"Yerima",
    "wof:placetype":"locality"
},
  "geometry": {"coordinates":[-11.83718,8.30642],"type":"Point"}
}