{
  "type": "Feature",
  "properties": {
    "gn:admin1_code":"2.0",
    "gn:asciiname":"Fana",
    "gn:country_code":"SL",
    "gn:dem":94,
    "gn:feature_class":"P",
    "gn:feature_code":"PPL",
    "gn:name":"Fana",
    "gn:population":0,
    "gn:timezone":"Africa/Freetown",
    "iso:country":"SL",
    "name:ell_x_preferred":[
        "\u03a6\u03ac\u03bd\u03b1"
    ],
    "name:eng_x_preferred":[
        "Fana"
    ],
    "name:fra_x_preferred":[
        "Fana"
    ],
    "name:jav_x_preferred":[
        "Fana"
    ],
    "name:msa_x_preferred":[
        "Fana"
    ],
    "name:nld_x_preferred":[
        "Fana"
    ],
    "name:nno_x_preferred":[
        "Fana"
    ],
    "name:nor_x_preferred":[
        "Fana"
    ],
    "name:swe_x_preferred":[
        "Fana"
    ],
    "name:tur_x_preferred":[
        "Fana"
    ],
    "wof:name":"Fana",
    "wof:placetype":"locality"
},
  "geometry": {"coordinates":[-12.42004,9.7055],"type":"Point"}
}