{
  "type": "Feature",
  "properties": {
    "gn:admin1_code":"2.0",
    "gn:asciiname":"Mankaia",
    "gn:country_code":"SL",
    "gn:dem":12,
    "gn:feature_class":"P",
    "gn:feature_code":"PPL",
    "gn:name":"Mankaia",
    "gn:population":0,
    "gn:timezone":"Africa/Freetown",
    "iso:country":"SL",
    "name:eng_x_preferred":[
        "Mankaia"
    ],
    "wof:name":"Mankaia",
    "wof:placetype":"locality"
},
  "geometry": {"coordinates":[-13.10668,8.9042],"type":"Point"}
}