{
  "type": "Feature",
  "properties": {
    "gn:admin1_code":"2.0",
    "gn:asciiname":"Makama",
    "gn:country_code":"SL",
    "gn:dem":375,
    "gn:feature_class":"P",
    "gn:feature_code":"PPL",
    "gn:name":"Makama",
    "gn:population":0,
    "gn:timezone":"Africa/Freetown",
    "iso:country":"SL",
    "name:eng_x_preferred":[
        "Makama"
    ],
    "wof:name":"Makama",
    "wof:placetype":"locality"
},
  "geometry": {"coordinates":[-11.59095,8.59663],"type":"Point"}
}