{
  "type": "Feature",
  "properties": {
    "gn:admin1_code":"1.0",
    "gn:asciiname":"Jopowahun",
    "gn:country_code":"SL",
    "gn:dem":114,
    "gn:feature_class":"P",
    "gn:feature_code":"PPL",
    "gn:name":"Jopowahun",
    "gn:population":0,
    "gn:timezone":"Africa/Freetown",
    "iso:country":"SL",
    "name:eng_x_preferred":[
        "Jopowahun"
    ],
    "wof:name":"Jopowahun",
    "wof:placetype":"locality"
},
  "geometry": {"coordinates":[-11.23207,7.41921],"type":"Point"}
}