{
  "type": "Feature",
  "properties": {
    "gn:admin1_code":"1.0",
    "gn:asciiname":"Ndeigoima",
    "gn:country_code":"SL",
    "gn:dem":322,
    "gn:feature_class":"P",
    "gn:feature_code":"PPL",
    "gn:name":"Ndeigoima",
    "gn:population":0,
    "gn:timezone":"Africa/Freetown",
    "iso:country":"SL",
    "name:eng_x_preferred":[
        "Ndeigoima"
    ],
    "wof:name":"Ndeigoima",
    "wof:placetype":"locality"
},
  "geometry": {"coordinates":[-10.71126,7.91299],"type":"Point"}
}