{
  "type": "Feature",
  "properties": {
    "gn:admin1_code":"2.0",
    "gn:asciiname":"Mateboi",
    "gn:country_code":"SL",
    "gn:dem":61,
    "gn:feature_class":"P",
    "gn:feature_code":"PPL",
    "gn:name":"Mateboi",
    "gn:population":0,
    "gn:timezone":"Africa/Freetown",
    "iso:country":"SL",
    "wof:name":"Mateboi",
    "wof:placetype":"locality"
},
  "geometry": {"coordinates":[-12.35985,9.10489],"type":"Point"}
}