{
  "type": "Feature",
  "properties": {
    "gn:admin1_code":"2.0",
    "gn:asciiname":"Maton",
    "gn:country_code":"SL",
    "gn:dem":59,
    "gn:feature_class":"P",
    "gn:feature_code":"PPL",
    "gn:name":"Maton",
    "gn:population":0,
    "gn:timezone":"Africa/Freetown",
    "iso:country":"SL",
    "name:eng_x_preferred":[
        "Maton"
    ],
    "name:fra_x_preferred":[
        "Maton"
    ],
    "wof:name":"Maton",
    "wof:placetype":"locality"
},
  "geometry": {"coordinates":[-12.94186,9.25614],"type":"Point"}
}