{
  "type": "Feature",
  "properties": {
    "gn:admin1_code":"2.0",
    "gn:asciiname":"Bombalibana",
    "gn:country_code":"SL",
    "gn:dem":89,
    "gn:feature_class":"P",
    "gn:feature_code":"PPL",
    "gn:name":"Bombalibana",
    "gn:population":0,
    "gn:timezone":"Africa/Freetown",
    "iso:country":"SL",
    "name:eng_x_preferred":[
        "Bombalibana"
    ],
    "wof:name":"Bombalibana",
    "wof:placetype":"locality"
},
  "geometry": {"coordinates":[-12.03343,8.96521],"type":"Point"}
}