{
  "type": "Feature",
  "properties": {
    "gn:admin1_code":"3.0",
    "gn:asciiname":"Mobessi",
    "gn:country_code":"SL",
    "gn:dem":58,
    "gn:feature_class":"P",
    "gn:feature_code":"PPL",
    "gn:name":"Mobessi",
    "gn:population":0,
    "gn:timezone":"Africa/Freetown",
    "iso:country":"SL",
    "name:eng_x_preferred":[
        "Mobessi"
    ],
    "wof:name":"Mobessi",
    "wof:placetype":"locality"
},
  "geometry": {"coordinates":[-12.11845,8.04994],"type":"Point"}
}