{
  "type": "Feature",
  "properties": {
    "gn:admin1_code":"2.0",
    "gn:asciiname":"Masesay",
    "gn:country_code":"SL",
    "gn:dem":53,
    "gn:feature_class":"P",
    "gn:feature_code":"PPL",
    "gn:name":"Masesay",
    "gn:population":0,
    "gn:timezone":"Africa/Freetown",
    "iso:country":"SL",
    "name:und_x_variant":[
        "Masifsif",
        "Masesay"
    ],
    "wof:name":"Masesay",
    "wof:placetype":"locality"
},
  "geometry": {"coordinates":[-12.57863,8.47623],"type":"Point"}
}