{
  "type": "Feature",
  "properties": {
    "gn:admin1_code":"2.0",
    "gn:asciiname":"Moyamba",
    "gn:country_code":"SL",
    "gn:dem":48,
    "gn:feature_class":"P",
    "gn:feature_code":"PPL",
    "gn:name":"Moyamba",
    "gn:population":0,
    "gn:timezone":"Africa/Freetown",
    "iso:country":"SL",
    "name:ceb_x_preferred":[
        "Moyamba"
    ],
    "name:deu_x_preferred":[
        "Moyamba"
    ],
    "name:eng_x_preferred":[
        "Moyamba"
    ],
    "name:fin_x_preferred":[
        "Moyamba"
    ],
    "name:fra_x_preferred":[
        "Moyamba"
    ],
    "name:ita_x_preferred":[
        "Moyamba"
    ],
    "name:lit_x_preferred":[
        "Mojamba"
    ],
    "name:pol_x_preferred":[
        "Moyamba"
    ],
    "name:por_x_preferred":[
        "Moyamba"
    ],
    "name:zho_x_preferred":[
        "\u83ab\u63da\u5df4"
    ],
    "wof:name":"Moyamba",
    "wof:placetype":"locality"
},
  "geometry": {"coordinates":[-12.67883,8.48424],"type":"Point"}
}