{
  "type": "Feature",
  "properties": {
    "gn:admin1_code":"2.0",
    "gn:asciiname":"Moyamba",
    "gn:country_code":"SL",
    "gn:dem":48,
    "gn:feature_class":"P",
    "gn:feature_code":"PPL",
    "gn:name":"Moyamba",
    "gn:population":0,
    "gn:timezone":"Africa/Freetown",
    "iso:country":"SL",
    "name:eng_x_preferred":[
        "Moyamba"
    ],
    "wof:name":"Moyamba",
    "wof:placetype":"locality"
},
  "geometry": {"coordinates":[-12.67883,8.48424],"type":"Point"}
}