{
  "type": "Feature",
  "properties": {
    "gn:admin1_code":"01",
    "gn:asciiname":"Nyandawao",
    "gn:country_code":"SL",
    "gn:dem":587,
    "gn:feature_class":"P",
    "gn:feature_code":"PPL",
    "gn:name":"Nyandawao",
    "gn:population":0,
    "gn:timezone":"Africa/Freetown",
    "iso:country":"SL",
    "name:eng_x_preferred":[
        "Nyandawao"
    ],
    "name:und_x_variant":[
        "Nyandoworo",
        "Nyandeworo"
    ],
    "wof:name":"Nyandawao",
    "wof:placetype":"locality"
},
  "geometry": {"coordinates":[-10.61824,8.95287],"type":"Point"}
}