{
  "type": "Feature",
  "properties": {
    "gn:admin1_code":"1.0",
    "gn:asciiname":"Fiyawoh",
    "gn:country_code":"SL",
    "gn:dem":435,
    "gn:feature_class":"P",
    "gn:feature_code":"PPL",
    "gn:name":"Fiyawoh",
    "gn:population":0,
    "gn:timezone":"Africa/Freetown",
    "iso:country":"SL",
    "name:eng_x_preferred":[
        "Fiyawoh"
    ],
    "name:und_x_variant":[
        "Fiawo"
    ],
    "wof:name":"Fiyawoh",
    "wof:placetype":"locality"
},
  "geometry": {"coordinates":[-10.91618,8.54558],"type":"Point"}
}