{
  "type": "Feature",
  "properties": {
    "gn:admin1_code":"3.0",
    "gn:asciiname":"Fala",
    "gn:country_code":"SL",
    "gn:dem":125,
    "gn:feature_class":"P",
    "gn:feature_code":"PPL",
    "gn:name":"Fala",
    "gn:population":0,
    "gn:timezone":"Africa/Freetown",
    "iso:country":"SL",
    "name:bos_x_preferred":[
        "Fala"
    ],
    "name:ceb_x_preferred":[
        "Fala"
    ],
    "name:deu_x_preferred":[
        "Fala"
    ],
    "name:eng_x_preferred":[
        "Fala"
    ],
    "name:eus_x_preferred":[
        "Fala"
    ],
    "name:fra_x_preferred":[
        "Fala"
    ],
    "name:hrv_x_preferred":[
        "Fala"
    ],
    "name:ita_x_preferred":[
        "Fala"
    ],
    "name:nld_x_preferred":[
        "Fala"
    ],
    "name:pol_x_preferred":[
        "Fala"
    ],
    "name:por_x_preferred":[
        "Fala"
    ],
    "name:slv_x_preferred":[
        "Fala"
    ],
    "name:spa_x_preferred":[
        "Fala"
    ],
    "name:swe_x_preferred":[
        "Fala"
    ],
    "wof:name":"Fala",
    "wof:placetype":"locality"
},
  "geometry": {"coordinates":[-11.4786,8.04342],"type":"Point"}
}