{
  "type": "Feature",
  "properties": {
    "gn:admin1_code":"1.0",
    "gn:asciiname":"Njaiama",
    "gn:country_code":"SL",
    "gn:dem":405,
    "gn:feature_class":"P",
    "gn:feature_code":"PPL",
    "gn:name":"Njaiama",
    "gn:population":0,
    "gn:timezone":"Africa/Freetown",
    "iso:country":"SL",
    "name:und_x_variant":[
        "Jaiama Nimiko",
        "Jaiama"
    ],
    "wof:name":"Njaiama",
    "wof:placetype":"locality"
},
  "geometry": {"coordinates":[-11.09067,8.54546],"type":"Point"}
}