{
  "type": "Feature",
  "properties": {
    "gn:admin1_code":"2.0",
    "gn:asciiname":"Magbanakonte",
    "gn:country_code":"SL",
    "gn:dem":90,
    "gn:feature_class":"P",
    "gn:feature_code":"PPL",
    "gn:name":"Magbanakonte",
    "gn:population":0,
    "gn:timezone":"Africa/Freetown",
    "iso:country":"SL",
    "name:eng_x_preferred":[
        "Magbanakonte"
    ],
    "wof:name":"Magbanakonte",
    "wof:placetype":"locality"
},
  "geometry": {"coordinates":[-12.35891,8.61212],"type":"Point"}
}