{
  "type": "Feature",
  "properties": {
    "gn:admin1_code":"3.0",
    "gn:asciiname":"Gbowuhahun",
    "gn:country_code":"SL",
    "gn:dem":70,
    "gn:feature_class":"P",
    "gn:feature_code":"PPL",
    "gn:name":"Gbowuhahun",
    "gn:population":0,
    "gn:timezone":"Africa/Freetown",
    "iso:country":"SL",
    "name:eng_x_preferred":[
        "Gbowuhahun"
    ],
    "wof:name":"Gbowuhahun",
    "wof:placetype":"locality"
},
  "geometry": {"coordinates":[-11.79358,7.83828],"type":"Point"}
}