{
  "type": "Feature",
  "properties": {
    "gn:admin1_code":"3.0",
    "gn:asciiname":"Mokombi",
    "gn:country_code":"SL",
    "gn:dem":1,
    "gn:feature_class":"P",
    "gn:feature_code":"PPL",
    "gn:name":"Mokombi",
    "gn:population":0,
    "gn:timezone":"Africa/Freetown",
    "iso:country":"SL",
    "name:eng_x_preferred":[
        "Mokombi"
    ],
    "wof:name":"Mokombi",
    "wof:placetype":"locality"
},
  "geometry": {"coordinates":[-12.56963,7.52569],"type":"Point"}
}