{
  "type": "Feature",
  "properties": {
    "gn:admin1_code":"2.0",
    "gn:asciiname":"Kambaia",
    "gn:country_code":"SL",
    "gn:dem":488,
    "gn:feature_class":"P",
    "gn:feature_code":"PPL",
    "gn:name":"Kambaia",
    "gn:population":0,
    "gn:timezone":"Africa/Freetown",
    "iso:country":"SL",
    "name:eng_x_preferred":[
        "Kambaia"
    ],
    "wof:name":"Kambaia",
    "wof:placetype":"locality"
},
  "geometry": {"coordinates":[-11.06717,9.80297],"type":"Point"}
}