{
  "type": "Feature",
  "properties": {
    "gn:admin1_code":"1.0",
    "gn:asciiname":"Kunduma",
    "gn:country_code":"SL",
    "gn:dem":413,
    "gn:feature_class":"P",
    "gn:feature_code":"PPL",
    "gn:name":"Kunduma",
    "gn:population":0,
    "gn:timezone":"Africa/Freetown",
    "iso:country":"SL",
    "name:und_x_variant":[
        "Kondoma",
        "Kondama"
    ],
    "wof:name":"Kunduma",
    "wof:placetype":"locality"
},
  "geometry": {"coordinates":[-10.39056,8.40395],"type":"Point"}
}