{
  "type": "Feature",
  "properties": {
    "gn:admin1_code":"03",
    "gn:asciiname":"Yegele",
    "gn:country_code":"SL",
    "gn:dem":29,
    "gn:feature_class":"P",
    "gn:feature_code":"PPL",
    "gn:name":"Yegele",
    "gn:population":0,
    "gn:timezone":"Africa/Freetown",
    "iso:country":"SL",
    "name:eng_x_preferred":[
        "Yegele"
    ],
    "name:und_x_variant":[
        "Yegile"
    ],
    "wof:name":"Yegele",
    "wof:placetype":"locality"
},
  "geometry": {"coordinates":[-11.9591,7.5688],"type":"Point"}
}