{
  "type": "Feature",
  "properties": {
    "gn:admin1_code":"3.0",
    "gn:asciiname":"Benduma",
    "gn:country_code":"SL",
    "gn:dem":13,
    "gn:feature_class":"P",
    "gn:feature_code":"PPL",
    "gn:name":"Benduma",
    "gn:population":0,
    "gn:timezone":"Africa/Freetown",
    "iso:country":"SL",
    "name:eng_x_preferred":[
        "Benduma"
    ],
    "wof:name":"Benduma",
    "wof:placetype":"locality"
},
  "geometry": {"coordinates":[-11.96235,7.26585],"type":"Point"}
}