{
  "type": "Feature",
  "properties": {
    "gn:admin1_code":"2.0",
    "gn:asciiname":"Matenki",
    "gn:country_code":"SL",
    "gn:dem":100,
    "gn:feature_class":"P",
    "gn:feature_code":"PPL",
    "gn:name":"Matenki",
    "gn:population":0,
    "gn:timezone":"Africa/Freetown",
    "iso:country":"SL",
    "name:eng_x_preferred":[
        "Matenki"
    ],
    "wof:name":"Matenki",
    "wof:placetype":"locality"
},
  "geometry": {"coordinates":[-11.90209,8.71496],"type":"Point"}
}