{
  "type": "Feature",
  "properties": {
    "gn:admin1_code":"3.0",
    "gn:asciiname":"Mosampo",
    "gn:cc2":"SL",
    "gn:country_code":"SL",
    "gn:dem":33,
    "gn:feature_class":"P",
    "gn:feature_code":"PPL",
    "gn:name":"Mosampo",
    "gn:population":0,
    "gn:timezone":"Africa/Freetown",
    "iso:country":"SL",
    "name:und_x_variant":[
        "Mosapbo",
        "Mosampo"
    ],
    "wof:name":"Mosampo",
    "wof:placetype":"locality"
},
  "geometry": {"coordinates":[-12.18333,7.76667],"type":"Point"}
}