{
  "type": "Feature",
  "properties": {
    "gn:admin1_code":"1.0",
    "gn:asciiname":"Gbendema",
    "gn:country_code":"SL",
    "gn:dem":207,
    "gn:feature_class":"P",
    "gn:feature_code":"PPL",
    "gn:name":"Gbendema",
    "gn:population":0,
    "gn:timezone":"Africa/Freetown",
    "iso:country":"SL",
    "name:eng_x_preferred":[
        "Gbendema"
    ],
    "wof:name":"Gbendema",
    "wof:placetype":"locality"
},
  "geometry": {"coordinates":[-10.89922,7.83572],"type":"Point"}
}