{
  "type": "Feature",
  "properties": {
    "gn:admin1_code":"3.0",
    "gn:asciiname":"Futa",
    "gn:country_code":"SL",
    "gn:dem":56,
    "gn:feature_class":"P",
    "gn:feature_code":"PPL",
    "gn:name":"Futa",
    "gn:population":0,
    "gn:timezone":"Africa/Freetown",
    "iso:country":"SL",
    "name:ceb_x_preferred":[
        "Futa"
    ],
    "name:eng_x_preferred":[
        "Futa"
    ],
    "name:swe_x_preferred":[
        "Futa"
    ],
    "wof:name":"Futa",
    "wof:placetype":"locality"
},
  "geometry": {"coordinates":[-12.30268,7.85395],"type":"Point"}
}