{
  "type": "Feature",
  "properties": {
    "gn:admin1_code":"1.0",
    "gn:asciiname":"Bandafada",
    "gn:country_code":"SL",
    "gn:dem":398,
    "gn:feature_class":"P",
    "gn:feature_code":"PPL",
    "gn:name":"Bandafada",
    "gn:population":0,
    "gn:timezone":"Africa/Freetown",
    "iso:country":"SL",
    "name:eng_x_preferred":[
        "Bandafada"
    ],
    "wof:name":"Bandafada",
    "wof:placetype":"locality"
},
  "geometry": {"coordinates":[-11.03261,8.59273],"type":"Point"}
}