{
  "type": "Feature",
  "properties": {
    "gn:admin1_code":"2.0",
    "gn:asciiname":"Pulunmant",
    "gn:country_code":"SL",
    "gn:dem":0,
    "gn:feature_class":"P",
    "gn:feature_code":"PPL",
    "gn:name":"Pulunmant",
    "gn:population":0,
    "gn:timezone":"Africa/Freetown",
    "iso:country":"SL",
    "name:eng_x_preferred":[
        "Pulunmant"
    ],
    "wof:name":"Pulunmant",
    "wof:placetype":"locality"
},
  "geometry": {"coordinates":[-13.0875,8.53944],"type":"Point"}
}