{
  "type": "Feature",
  "properties": {
    "gn:admin1_code":"2.0",
    "gn:asciiname":"Karawani",
    "gn:country_code":"SL",
    "gn:dem":486,
    "gn:feature_class":"P",
    "gn:feature_code":"PPL",
    "gn:name":"Karawani",
    "gn:population":0,
    "gn:timezone":"Africa/Freetown",
    "iso:country":"SL",
    "name:eng_x_preferred":[
        "Karawani"
    ],
    "wof:name":"Karawani",
    "wof:placetype":"locality"
},
  "geometry": {"coordinates":[-10.92403,9.46999],"type":"Point"}
}