{
  "type": "Feature",
  "properties": {
    "gn:admin1_code":"2.0",
    "gn:asciiname":"Mafile",
    "gn:country_code":"SL",
    "gn:dem":33,
    "gn:feature_class":"P",
    "gn:feature_code":"PPL",
    "gn:name":"Mafile",
    "gn:population":0,
    "gn:timezone":"Africa/Freetown",
    "iso:country":"SL",
    "name:eng_x_preferred":[
        "Mafile"
    ],
    "wof:name":"Mafile",
    "wof:placetype":"locality"
},
  "geometry": {"coordinates":[-12.99668,8.40236],"type":"Point"}
}