{
  "type": "Feature",
  "properties": {
    "gn:admin1_code":"3.0",
    "gn:asciiname":"Takpanga",
    "gn:country_code":"SL",
    "gn:dem":59,
    "gn:feature_class":"P",
    "gn:feature_code":"PPL",
    "gn:name":"Takpanga",
    "gn:population":0,
    "gn:timezone":"Africa/Freetown",
    "iso:country":"SL",
    "name:eng_x_preferred":[
        "Takpanga"
    ],
    "wof:name":"Takpanga",
    "wof:placetype":"locality"
},
  "geometry": {"coordinates":[-12.03617,8.0395],"type":"Point"}
}