{
  "type": "Feature",
  "properties": {
    "gn:admin1_code":"3.0",
    "gn:asciiname":"Kpowuibu",
    "gn:country_code":"SL",
    "gn:dem":20,
    "gn:feature_class":"P",
    "gn:feature_code":"PPL",
    "gn:name":"Kpowuibu",
    "gn:population":0,
    "gn:timezone":"Africa/Freetown",
    "iso:country":"SL",
    "name:eng_x_preferred":[
        "Kpowuibu"
    ],
    "wof:name":"Kpowuibu",
    "wof:placetype":"locality"
},
  "geometry": {"coordinates":[-12.23394,7.48606],"type":"Point"}
}