{
  "type": "Feature",
  "properties": {
    "gn:admin1_code":"2.0",
    "gn:asciiname":"Kamayimbo",
    "gn:country_code":"SL",
    "gn:dem":271,
    "gn:feature_class":"P",
    "gn:feature_code":"PPL",
    "gn:name":"Kamayimbo",
    "gn:population":0,
    "gn:timezone":"Africa/Freetown",
    "iso:country":"SL",
    "name:eng_x_preferred":[
        "Kamayimbo"
    ],
    "wof:name":"Kamayimbo",
    "wof:placetype":"locality"
},
  "geometry": {"coordinates":[-11.70214,9.4542],"type":"Point"}
}