{
  "type": "Feature",
  "properties": {
    "gn:admin1_code":"3.0",
    "gn:asciiname":"Kanga",
    "gn:country_code":"SL",
    "gn:dem":21,
    "gn:feature_class":"P",
    "gn:feature_code":"PPL",
    "gn:name":"Kanga",
    "gn:population":0,
    "gn:timezone":"Africa/Freetown",
    "iso:country":"SL",
    "name:ceb_x_preferred":[
        "Kanga"
    ],
    "name:deu_x_preferred":[
        "Kanga"
    ],
    "name:eng_x_preferred":[
        "Kanga"
    ],
    "name:fra_x_preferred":[
        "Kanga"
    ],
    "name:ita_x_preferred":[
        "Kanga"
    ],
    "name:nld_x_preferred":[
        "Kanga"
    ],
    "name:rus_x_preferred":[
        "\u041a\u0430\u043d\u0433\u0430"
    ],
    "name:swa_x_preferred":[
        "Kanga"
    ],
    "name:swe_x_preferred":[
        "Kanga"
    ],
    "wof:name":"Kanga",
    "wof:placetype":"locality"
},
  "geometry": {"coordinates":[-11.4375,7.10458],"type":"Point"}
}