{
  "type": "Feature",
  "properties": {
    "gn:admin1_code":"4.0",
    "gn:asciiname":"Ma-tindi",
    "gn:country_code":"SL",
    "gn:dem":26,
    "gn:feature_class":"P",
    "gn:feature_code":"PPL",
    "gn:name":"Ma-tindi",
    "gn:population":0,
    "gn:timezone":"Africa/Freetown",
    "iso:country":"SL",
    "name:und_x_variant":[
        "Ma-Tinde",
        "Ma-tindi"
    ],
    "wof:name":"Ma-tindi",
    "wof:placetype":"locality"
},
  "geometry": {"coordinates":[-13.06037,8.29321],"type":"Point"}
}