{
  "type": "Feature",
  "properties": {
    "gn:admin1_code":"02",
    "gn:asciiname":"Sankori",
    "gn:country_code":"SL",
    "gn:dem":421,
    "gn:feature_class":"P",
    "gn:feature_code":"PPL",
    "gn:name":"Sankori",
    "gn:population":0,
    "gn:timezone":"Africa/Freetown",
    "iso:country":"SL",
    "name:eng_x_preferred":[
        "Sankori"
    ],
    "wof:name":"Sankori",
    "wof:placetype":"locality"
},
  "geometry": {"coordinates":[-11.73747,9.26268],"type":"Point"}
}