{
  "type": "Feature",
  "properties": {
    "gn:admin1_code":"2.0",
    "gn:asciiname":"Kasanka",
    "gn:country_code":"SL",
    "gn:dem":18,
    "gn:feature_class":"P",
    "gn:feature_code":"PPL",
    "gn:name":"Kasanka",
    "gn:population":0,
    "gn:timezone":"Africa/Freetown",
    "iso:country":"SL",
    "name:eng_x_preferred":[
        "Kasanka"
    ],
    "wof:name":"Kasanka",
    "wof:placetype":"locality"
},
  "geometry": {"coordinates":[-12.88552,8.75363],"type":"Point"}
}