{
  "type": "Feature",
  "properties": {
    "gn:admin1_code":"1.0",
    "gn:asciiname":"Kamboiyabu",
    "gn:country_code":"SL",
    "gn:dem":169,
    "gn:feature_class":"P",
    "gn:feature_code":"PPL",
    "gn:name":"Kamboiyabu",
    "gn:population":0,
    "gn:timezone":"Africa/Freetown",
    "iso:country":"SL",
    "name:eng_x_preferred":[
        "Kamboiyabu"
    ],
    "wof:name":"Kamboiyabu",
    "wof:placetype":"locality"
},
  "geometry": {"coordinates":[-11.21737,7.837],"type":"Point"}
}