{
  "type": "Feature",
  "properties": {
    "gn:admin1_code":"3.0",
    "gn:asciiname":"Fakabai",
    "gn:country_code":"SL",
    "gn:dem":16,
    "gn:feature_class":"P",
    "gn:feature_code":"PPL",
    "gn:name":"Fakabai",
    "gn:population":0,
    "gn:timezone":"Africa/Freetown",
    "iso:country":"SL",
    "name:eng_x_preferred":[
        "Fakabai"
    ],
    "wof:name":"Fakabai",
    "wof:placetype":"locality"
},
  "geometry": {"coordinates":[-12.78539,7.98412],"type":"Point"}
}