{
  "type": "Feature",
  "properties": {
    "gn:admin1_code":"1.0",
    "gn:asciiname":"Kanjama",
    "gn:country_code":"SL",
    "gn:dem":204,
    "gn:feature_class":"P",
    "gn:feature_code":"PPL",
    "gn:name":"Kanjama",
    "gn:population":0,
    "gn:timezone":"Africa/Freetown",
    "iso:country":"SL",
    "name:eng_x_preferred":[
        "Kanjama"
    ],
    "wof:name":"Kanjama",
    "wof:placetype":"locality"
},
  "geometry": {"coordinates":[-10.93719,7.77774],"type":"Point"}
}