{
  "type": "Feature",
  "properties": {
    "gn:admin1_code":"1.0",
    "gn:asciiname":"Komendinja",
    "gn:country_code":"SL",
    "gn:dem":380,
    "gn:feature_class":"P",
    "gn:feature_code":"PPL",
    "gn:name":"Komendinja",
    "gn:population":0,
    "gn:timezone":"Africa/Freetown",
    "iso:country":"SL",
    "name:eng_x_preferred":[
        "Komendinja"
    ],
    "wof:name":"Komendinja",
    "wof:placetype":"locality"
},
  "geometry": {"coordinates":[-10.97551,8.74872],"type":"Point"}
}