{
  "type": "Feature",
  "properties": {
    "gn:admin1_code":"2.0",
    "gn:asciiname":"Makondo",
    "gn:country_code":"SL",
    "gn:dem":87,
    "gn:feature_class":"P",
    "gn:feature_code":"PPL",
    "gn:name":"Makondo",
    "gn:population":0,
    "gn:timezone":"Africa/Freetown",
    "iso:country":"SL",
    "name:eng_x_preferred":[
        "Makondo"
    ],
    "wof:name":"Makondo",
    "wof:placetype":"locality"
},
  "geometry": {"coordinates":[-12.07202,9.09541],"type":"Point"}
}