{
  "type": "Feature",
  "properties": {
    "gn:admin1_code":"04",
    "gn:asciiname":"Number Two Village",
    "gn:country_code":"SL",
    "gn:dem":13,
    "gn:feature_class":"P",
    "gn:feature_code":"PPL",
    "gn:name":"Number Two Village",
    "gn:population":0,
    "gn:timezone":"Africa/Freetown",
    "iso:country":"SL",
    "name:und_x_variant":[
        "Number Two",
        "Number Two Village"
    ],
    "wof:name":"Number Two Village",
    "wof:placetype":"locality"
},
  "geometry": {"coordinates":[-13.20601,8.33668],"type":"Point"}
}