{
  "type": "Feature",
  "properties": {
    "gn:admin1_code":"2.0",
    "gn:asciiname":"Makamba",
    "gn:country_code":"SL",
    "gn:dem":95,
    "gn:feature_class":"P",
    "gn:feature_code":"PPL",
    "gn:name":"Makamba",
    "gn:population":0,
    "gn:timezone":"Africa/Freetown",
    "iso:country":"SL",
    "name:ceb_x_preferred":[
        "Makamba"
    ],
    "name:eng_x_preferred":[
        "Makamba"
    ],
    "name:heb_x_preferred":[
        "\u05de\u05e7\u05d0\u05d8\u05d9"
    ],
    "name:hun_x_preferred":[
        "Makamba"
    ],
    "name:nld_x_preferred":[
        "Makamba"
    ],
    "name:swe_x_preferred":[
        "Makamba"
    ],
    "wof:name":"Makamba",
    "wof:placetype":"locality"
},
  "geometry": {"coordinates":[-12.49655,9.00247],"type":"Point"}
}