{
  "type": "Feature",
  "properties": {
    "gn:admin1_code":"3.0",
    "gn:asciiname":"Chondalen",
    "gn:country_code":"SL",
    "gn:dem":13,
    "gn:feature_class":"P",
    "gn:feature_code":"PPL",
    "gn:name":"Chondalen",
    "gn:population":0,
    "gn:timezone":"Africa/Freetown",
    "iso:country":"SL",
    "name:eng_x_preferred":[
        "Chondalen"
    ],
    "wof:name":"Chondalen",
    "wof:placetype":"locality"
},
  "geometry": {"coordinates":[-12.65692,7.54007],"type":"Point"}
}