{
  "type": "Feature",
  "properties": {
    "gn:admin1_code":"1.0",
    "gn:asciiname":"Basikor",
    "gn:country_code":"SL",
    "gn:dem":545,
    "gn:feature_class":"P",
    "gn:feature_code":"PPL",
    "gn:name":"Basikor",
    "gn:population":0,
    "gn:timezone":"Africa/Freetown",
    "iso:country":"SL",
    "name:eng_x_preferred":[
        "Basikor"
    ],
    "wof:name":"Basikor",
    "wof:placetype":"locality"
},
  "geometry": {"coordinates":[-10.67066,8.80533],"type":"Point"}
}