{
  "type": "Feature",
  "properties": {
    "gn:admin1_code":"2.0",
    "gn:asciiname":"Bomboya",
    "gn:country_code":"SL",
    "gn:dem":82,
    "gn:feature_class":"P",
    "gn:feature_code":"PPL",
    "gn:name":"Bomboya",
    "gn:population":0,
    "gn:timezone":"Africa/Freetown",
    "iso:country":"SL",
    "name:eng_x_preferred":[
        "Bomboya"
    ],
    "wof:name":"Bomboya",
    "wof:placetype":"locality"
},
  "geometry": {"coordinates":[-12.22745,9.41968],"type":"Point"}
}