{
  "type": "Feature",
  "properties": {
    "gn:admin1_code":"2.0",
    "gn:asciiname":"Komoia",
    "gn:country_code":"SL",
    "gn:dem":96,
    "gn:feature_class":"P",
    "gn:feature_code":"PPL",
    "gn:name":"Komoia",
    "gn:population":0,
    "gn:timezone":"Africa/Freetown",
    "iso:country":"SL",
    "name:eng_x_preferred":[
        "Komoia"
    ],
    "wof:name":"Komoia",
    "wof:placetype":"locality"
},
  "geometry": {"coordinates":[-12.29103,9.71876],"type":"Point"}
}