{
  "type": "Feature",
  "properties": {
    "gn:admin1_code":"1.0",
    "gn:asciiname":"Mende",
    "gn:country_code":"SL",
    "gn:dem":192,
    "gn:feature_class":"P",
    "gn:feature_code":"PPL",
    "gn:name":"Mende",
    "gn:population":0,
    "gn:timezone":"Africa/Freetown",
    "iso:country":"SL",
    "name:eng_x_preferred":[
        "Mende"
    ],
    "wof:name":"Mende",
    "wof:placetype":"locality"
},
  "geometry": {"coordinates":[-10.89023,8.12257],"type":"Point"}
}