{
  "type": "Feature",
  "properties": {
    "gn:admin1_code":"1.0",
    "gn:asciiname":"Mende",
    "gn:country_code":"SL",
    "gn:dem":192,
    "gn:feature_class":"P",
    "gn:feature_code":"PPL",
    "gn:name":"Mende",
    "gn:population":0,
    "gn:timezone":"Africa/Freetown",
    "iso:country":"SL",
    "name:bre_x_preferred":[
        "Mende"
    ],
    "name:cat_x_preferred":[
        "Mende"
    ],
    "name:ceb_x_preferred":[
        "Mende"
    ],
    "name:ces_x_preferred":[
        "Mende"
    ],
    "name:deu_x_preferred":[
        "Mende"
    ],
    "name:eng_x_preferred":[
        "Mende"
    ],
    "name:epo_x_preferred":[
        "Mende"
    ],
    "name:fin_x_preferred":[
        "Mende"
    ],
    "name:fra_x_preferred":[
        "Mende"
    ],
    "name:glg_x_preferred":[
        "Mende"
    ],
    "name:hrv_x_preferred":[
        "Mende"
    ],
    "name:ita_x_preferred":[
        "Mende"
    ],
    "name:nds_x_preferred":[
        "Mende"
    ],
    "name:nld_x_preferred":[
        "Mende"
    ],
    "name:nno_x_preferred":[
        "Mende"
    ],
    "name:oci_x_preferred":[
        "Mende"
    ],
    "name:pol_x_preferred":[
        "Mende"
    ],
    "name:ron_x_preferred":[
        "Mende"
    ],
    "name:rus_x_preferred":[
        "\u041c\u0435\u043d\u0434\u0435"
    ],
    "name:slk_x_preferred":[
        "Mende"
    ],
    "name:spa_x_preferred":[
        "Mende"
    ],
    "name:swe_x_preferred":[
        "Mende"
    ],
    "name:yor_x_preferred":[
        "Mende"
    ],
    "wof:name":"Mende",
    "wof:placetype":"locality"
},
  "geometry": {"coordinates":[-10.89023,8.12257],"type":"Point"}
}