{
  "type": "Feature",
  "properties": {
    "gn:admin1_code":"2.0",
    "gn:asciiname":"Lontonkhuri",
    "gn:country_code":"SL",
    "gn:dem":101,
    "gn:feature_class":"P",
    "gn:feature_code":"PPL",
    "gn:name":"Lontonkhuri",
    "gn:population":0,
    "gn:timezone":"Africa/Freetown",
    "iso:country":"SL",
    "name:eng_x_preferred":[
        "Lontonkhuri"
    ],
    "wof:name":"Lontonkhuri",
    "wof:placetype":"locality"
},
  "geometry": {"coordinates":[-12.35588,9.71557],"type":"Point"}
}