{
  "type": "Feature",
  "properties": {
    "gn:admin1_code":"3.0",
    "gn:asciiname":"Mokpedeh",
    "gn:country_code":"SL",
    "gn:dem":144,
    "gn:feature_class":"P",
    "gn:feature_code":"PPL",
    "gn:name":"Mokpedeh",
    "gn:population":0,
    "gn:timezone":"Africa/Freetown",
    "iso:country":"SL",
    "name:eng_x_preferred":[
        "Mokpedeh"
    ],
    "name:und_x_variant":[
        "Mogbende"
    ],
    "wof:name":"Mokpedeh",
    "wof:placetype":"locality"
},
  "geometry": {"coordinates":[-11.49387,8.10559],"type":"Point"}
}