{
  "type": "Feature",
  "properties": {
    "gn:admin1_code":"1.0",
    "gn:asciiname":"Jayema",
    "gn:country_code":"SL",
    "gn:dem":150,
    "gn:feature_class":"P",
    "gn:feature_code":"PPL",
    "gn:name":"Jayema",
    "gn:population":0,
    "gn:timezone":"Africa/Freetown",
    "iso:country":"SL",
    "name:eng_x_preferred":[
        "Jayema"
    ],
    "wof:name":"Jayema",
    "wof:placetype":"locality"
},
  "geometry": {"coordinates":[-11.27173,7.42444],"type":"Point"}
}