{
  "type": "Feature",
  "properties": {
    "gn:admin1_code":"2.0",
    "gn:asciiname":"Maseri",
    "gn:country_code":"SL",
    "gn:dem":51,
    "gn:feature_class":"P",
    "gn:feature_code":"PPL",
    "gn:name":"Maseri",
    "gn:population":0,
    "gn:timezone":"Africa/Freetown",
    "iso:country":"SL",
    "name:eng_x_preferred":[
        "Maseri"
    ],
    "wof:name":"Maseri",
    "wof:placetype":"locality"
},
  "geometry": {"coordinates":[-12.89194,9.10768],"type":"Point"}
}