{
  "type": "Feature",
  "properties": {
    "gn:admin1_code":"2.0",
    "gn:asciiname":"Masuriton",
    "gn:country_code":"SL",
    "gn:dem":29,
    "gn:feature_class":"P",
    "gn:feature_code":"PPL",
    "gn:name":"Masuriton",
    "gn:population":0,
    "gn:timezone":"Africa/Freetown",
    "iso:country":"SL",
    "name:eng_x_preferred":[
        "Masuriton"
    ],
    "wof:name":"Masuriton",
    "wof:placetype":"locality"
},
  "geometry": {"coordinates":[-12.67621,8.5974],"type":"Point"}
}