{
  "type": "Feature",
  "properties": {
    "gn:admin1_code":"3.0",
    "gn:asciiname":"Bondoyelahun",
    "gn:country_code":"SL",
    "gn:dem":74,
    "gn:feature_class":"P",
    "gn:feature_code":"PPL",
    "gn:name":"Bondoyelahun",
    "gn:population":0,
    "gn:timezone":"Africa/Freetown",
    "iso:country":"SL",
    "name:eng_x_preferred":[
        "Bondoyelahun"
    ],
    "wof:name":"Bondoyelahun",
    "wof:placetype":"locality"
},
  "geometry": {"coordinates":[-11.82681,7.68666],"type":"Point"}
}