{
  "type": "Feature",
  "properties": {
    "gn:admin1_code":"3.0",
    "gn:asciiname":"Maselu",
    "gn:country_code":"SL",
    "gn:dem":16,
    "gn:feature_class":"P",
    "gn:feature_code":"PPL",
    "gn:name":"Maselu",
    "gn:population":0,
    "gn:timezone":"Africa/Freetown",
    "iso:country":"SL",
    "name:eng_x_preferred":[
        "Maselu"
    ],
    "wof:name":"Maselu",
    "wof:placetype":"locality"
},
  "geometry": {"coordinates":[-12.81585,8.34394],"type":"Point"}
}