{
  "type": "Feature",
  "properties": {
    "gn:admin1_code":"2.0",
    "gn:asciiname":"Kemosaia",
    "gn:country_code":"SL",
    "gn:dem":456,
    "gn:feature_class":"P",
    "gn:feature_code":"PPL",
    "gn:name":"Kemosaia",
    "gn:population":0,
    "gn:timezone":"Africa/Freetown",
    "iso:country":"SL",
    "name:eng_x_preferred":[
        "Kemosaia"
    ],
    "wof:name":"Kemosaia",
    "wof:placetype":"locality"
},
  "geometry": {"coordinates":[-10.88554,9.30185],"type":"Point"}
}