{
  "type": "Feature",
  "properties": {
    "gn:admin1_code":"2.0",
    "gn:asciiname":"Masegea",
    "gn:country_code":"SL",
    "gn:dem":98,
    "gn:feature_class":"P",
    "gn:feature_code":"PPL",
    "gn:name":"Masegea",
    "gn:population":0,
    "gn:timezone":"Africa/Freetown",
    "iso:country":"SL",
    "name:eng_x_preferred":[
        "Masegea"
    ],
    "wof:name":"Masegea",
    "wof:placetype":"locality"
},
  "geometry": {"coordinates":[-12.3094,9.46776],"type":"Point"}
}