{
  "type": "Feature",
  "properties": {
    "gn:admin1_code":"3.0",
    "gn:asciiname":"Gbangema",
    "gn:country_code":"SL",
    "gn:dem":105,
    "gn:feature_class":"P",
    "gn:feature_code":"PPL",
    "gn:name":"Gbangema",
    "gn:population":0,
    "gn:timezone":"Africa/Freetown",
    "iso:country":"SL",
    "name:eng_x_preferred":[
        "Gbangema"
    ],
    "wof:name":"Gbangema",
    "wof:placetype":"locality"
},
  "geometry": {"coordinates":[-11.752,8.06966],"type":"Point"}
}