{
  "type": "Feature",
  "properties": {
    "gn:admin1_code":"2.0",
    "gn:asciiname":"Mahia",
    "gn:country_code":"SL",
    "gn:dem":120,
    "gn:feature_class":"P",
    "gn:feature_code":"PPL",
    "gn:name":"Mahia",
    "gn:population":0,
    "gn:timezone":"Africa/Freetown",
    "iso:country":"SL",
    "name:eng_x_preferred":[
        "Mahia"
    ],
    "wof:name":"Mahia",
    "wof:placetype":"locality"
},
  "geometry": {"coordinates":[-11.97034,9.30459],"type":"Point"}
}