{
  "type": "Feature",
  "properties": {
    "gn:admin1_code":"2.0",
    "gn:asciiname":"Masoto",
    "gn:country_code":"SL",
    "gn:dem":363,
    "gn:feature_class":"P",
    "gn:feature_code":"PPL",
    "gn:name":"Masoto",
    "gn:population":0,
    "gn:timezone":"Africa/Freetown",
    "iso:country":"SL",
    "name:eng_x_preferred":[
        "Masoto"
    ],
    "wof:name":"Masoto",
    "wof:placetype":"locality"
},
  "geometry": {"coordinates":[-11.70708,9.71711],"type":"Point"}
}