{
  "type": "Feature",
  "properties": {
    "gn:admin1_code":"1.0",
    "gn:asciiname":"Gbayala",
    "gn:country_code":"SL",
    "gn:dem":208,
    "gn:feature_class":"P",
    "gn:feature_code":"PPL",
    "gn:name":"Gbayala",
    "gn:population":0,
    "gn:timezone":"Africa/Freetown",
    "iso:country":"SL",
    "name:eng_x_preferred":[
        "Gbayala"
    ],
    "wof:name":"Gbayala",
    "wof:placetype":"locality"
},
  "geometry": {"coordinates":[-10.89116,8.02235],"type":"Point"}
}