{
  "type": "Feature",
  "properties": {
    "gn:admin1_code":"2.0",
    "gn:asciiname":"Kumidagi",
    "gn:country_code":"SL",
    "gn:dem":382,
    "gn:feature_class":"P",
    "gn:feature_code":"PPL",
    "gn:name":"Kumidagi",
    "gn:population":0,
    "gn:timezone":"Africa/Freetown",
    "iso:country":"SL",
    "name:eng_x_preferred":[
        "Kumidagi"
    ],
    "wof:name":"Kumidagi",
    "wof:placetype":"locality"
},
  "geometry": {"coordinates":[-11.46667,9.91667],"type":"Point"}
}