{
  "type": "Feature",
  "properties": {
    "gn:admin1_code":"02",
    "gn:asciiname":"Sengbe",
    "gn:country_code":"SL",
    "gn:dem":53,
    "gn:feature_class":"P",
    "gn:feature_code":"PPL",
    "gn:name":"Sengbe",
    "gn:population":0,
    "gn:timezone":"Africa/Freetown",
    "iso:country":"SL",
    "name:eng_x_preferred":[
        "Sengbe"
    ],
    "wof:name":"Sengbe",
    "wof:placetype":"locality"
},
  "geometry": {"coordinates":[-12.88543,8.9327],"type":"Point"}
}