{
  "type": "Feature",
  "properties": {
    "gn:admin1_code":"3.0",
    "gn:asciiname":"Gbuwaleil",
    "gn:country_code":"SL",
    "gn:dem":15,
    "gn:feature_class":"P",
    "gn:feature_code":"PPL",
    "gn:name":"Gbuwaleil",
    "gn:population":0,
    "gn:timezone":"Africa/Freetown",
    "iso:country":"SL",
    "name:eng_x_preferred":[
        "Gbuwaleil"
    ],
    "wof:name":"Gbuwaleil",
    "wof:placetype":"locality"
},
  "geometry": {"coordinates":[-12.67589,7.76295],"type":"Point"}
}