{
  "type": "Feature",
  "properties": {
    "gn:admin1_code":"3.0",
    "gn:asciiname":"Konima",
    "gn:country_code":"SL",
    "gn:dem":103,
    "gn:feature_class":"P",
    "gn:feature_code":"PPL",
    "gn:name":"Konima",
    "gn:population":0,
    "gn:timezone":"Africa/Freetown",
    "iso:country":"SL",
    "name:eng_x_preferred":[
        "Konima"
    ],
    "wof:name":"Konima",
    "wof:placetype":"locality"
},
  "geometry": {"coordinates":[-11.76101,8.37865],"type":"Point"}
}