{
  "type": "Feature",
  "properties": {
    "gn:admin1_code":"01",
    "gn:asciiname":"Nyamoima",
    "gn:country_code":"SL",
    "gn:dem":428,
    "gn:feature_class":"P",
    "gn:feature_code":"PPL",
    "gn:name":"Nyamoima",
    "gn:population":0,
    "gn:timezone":"Africa/Freetown",
    "iso:country":"SL",
    "name:eng_x_preferred":[
        "Nyamoima"
    ],
    "wof:name":"Nyamoima",
    "wof:placetype":"locality"
},
  "geometry": {"coordinates":[-10.84015,8.75752],"type":"Point"}
}