{
  "type": "Feature",
  "properties": {
    "gn:admin1_code":"2.0",
    "gn:asciiname":"Kalangbani",
    "gn:country_code":"SL",
    "gn:dem":56,
    "gn:feature_class":"P",
    "gn:feature_code":"PPL",
    "gn:name":"Kalangbani",
    "gn:population":0,
    "gn:timezone":"Africa/Freetown",
    "iso:country":"SL",
    "name:eng_x_preferred":[
        "Kalangbani"
    ],
    "wof:name":"Kalangbani",
    "wof:placetype":"locality"
},
  "geometry": {"coordinates":[-12.70101,8.90699],"type":"Point"}
}