{
  "type": "Feature",
  "properties": {
    "gn:admin1_code":"3.0",
    "gn:asciiname":"Mano",
    "gn:country_code":"SL",
    "gn:dem":79,
    "gn:feature_class":"P",
    "gn:feature_code":"PPL",
    "gn:name":"Mano",
    "gn:population":0,
    "gn:timezone":"Africa/Freetown",
    "iso:country":"SL",
    "name:ceb_x_preferred":[
        "Mano"
    ],
    "name:deu_x_preferred":[
        "Mano"
    ],
    "name:fra_x_preferred":[
        "Mano"
    ],
    "name:ita_x_preferred":[
        "Mano"
    ],
    "name:nld_x_preferred":[
        "Mano"
    ],
    "name:pol_x_preferred":[
        "Mano"
    ],
    "name:rus_x_preferred":[
        "\u041c\u0430\u043d\u043e"
    ],
    "name:spa_x_preferred":[
        "Mano"
    ],
    "name:swe_x_preferred":[
        "Mano"
    ],
    "name:tur_x_preferred":[
        "Mano"
    ],
    "name:und_x_variant":[
        "Tuba"
    ],
    "wof:name":"Mano",
    "wof:placetype":"locality"
},
  "geometry": {"coordinates":[-11.71153,7.77048],"type":"Point"}
}