{
  "type": "Feature",
  "properties": {
    "gn:admin1_code":"2.0",
    "gn:asciiname":"Mafenda",
    "gn:country_code":"SL",
    "gn:dem":392,
    "gn:feature_class":"P",
    "gn:feature_code":"PPL",
    "gn:name":"Mafenda",
    "gn:population":0,
    "gn:timezone":"Africa/Freetown",
    "iso:country":"SL",
    "name:eng_x_preferred":[
        "Mafenda"
    ],
    "wof:name":"Mafenda",
    "wof:placetype":"locality"
},
  "geometry": {"coordinates":[-11.5714,9.68443],"type":"Point"}
}