{
  "type": "Feature",
  "properties": {
    "gn:admin1_code":"3.0",
    "gn:asciiname":"Mokandagbe",
    "gn:country_code":"SL",
    "gn:dem":8,
    "gn:feature_class":"P",
    "gn:feature_code":"PPL",
    "gn:name":"Mokandagbe",
    "gn:population":0,
    "gn:timezone":"Africa/Freetown",
    "iso:country":"SL",
    "name:eng_x_preferred":[
        "Mokandagbe"
    ],
    "name:und_x_variant":[
        "Kandagbe"
    ],
    "wof:name":"Mokandagbe",
    "wof:placetype":"locality"
},
  "geometry": {"coordinates":[-12.60412,7.77814],"type":"Point"}
}