{
  "type": "Feature",
  "properties": {
    "gn:admin1_code":"01",
    "gn:asciiname":"Patama",
    "gn:country_code":"SL",
    "gn:dem":281,
    "gn:feature_class":"P",
    "gn:feature_code":"PPL",
    "gn:name":"Patama",
    "gn:population":0,
    "gn:timezone":"Africa/Freetown",
    "iso:country":"SL",
    "name:eng_x_preferred":[
        "Patama"
    ],
    "wof:name":"Patama",
    "wof:placetype":"locality"
},
  "geometry": {"coordinates":[-11.20573,8.10621],"type":"Point"}
}