{
  "type": "Feature",
  "properties": {
    "gn:admin1_code":"01",
    "gn:asciiname":"Tagbwema",
    "gn:country_code":"SL",
    "gn:dem":295,
    "gn:feature_class":"P",
    "gn:feature_code":"PPL",
    "gn:name":"Tagbwema",
    "gn:population":0,
    "gn:timezone":"Africa/Freetown",
    "iso:country":"SL",
    "wof:name":"Tagbwema",
    "wof:placetype":"locality"
},
  "geometry": {"coordinates":[-10.63333,8.23333],"type":"Point"}
}