{
  "type": "Feature",
  "properties": {
    "gn:admin1_code":"1.0",
    "gn:asciiname":"Gbarima",
    "gn:country_code":"SL",
    "gn:dem":405,
    "gn:feature_class":"P",
    "gn:feature_code":"PPL",
    "gn:name":"Gbarima",
    "gn:population":0,
    "gn:timezone":"Africa/Freetown",
    "iso:country":"SL",
    "name:eng_x_preferred":[
        "Gbarima"
    ],
    "wof:name":"Gbarima",
    "wof:placetype":"locality"
},
  "geometry": {"coordinates":[-10.36857,8.32799],"type":"Point"}
}