{
  "type": "Feature",
  "properties": {
    "gn:admin1_code":"2.0",
    "gn:asciiname":"Konkowakoro",
    "gn:country_code":"SL",
    "gn:dem":513,
    "gn:feature_class":"P",
    "gn:feature_code":"PPL",
    "gn:name":"Konkowakoro",
    "gn:population":0,
    "gn:timezone":"Africa/Freetown",
    "iso:country":"SL",
    "name:eng_x_preferred":[
        "Konkowakoro"
    ],
    "wof:name":"Konkowakoro",
    "wof:placetype":"locality"
},
  "geometry": {"coordinates":[-10.76217,9.34876],"type":"Point"}
}