{
  "type": "Feature",
  "properties": {
    "gn:admin1_code":"2.0",
    "gn:asciiname":"Lohindi",
    "gn:country_code":"SL",
    "gn:dem":88,
    "gn:feature_class":"P",
    "gn:feature_code":"PPL",
    "gn:name":"Lohindi",
    "gn:population":0,
    "gn:timezone":"Africa/Freetown",
    "iso:country":"SL",
    "name:eng_x_preferred":[
        "Lohindi"
    ],
    "wof:name":"Lohindi",
    "wof:placetype":"locality"
},
  "geometry": {"coordinates":[-12.13771,9.12325],"type":"Point"}
}