{
  "type": "Feature",
  "properties": {
    "gn:admin1_code":"3.0",
    "gn:asciiname":"Mendewa",
    "gn:country_code":"SL",
    "gn:dem":100,
    "gn:feature_class":"P",
    "gn:feature_code":"PPL",
    "gn:name":"Mendewa",
    "gn:population":0,
    "gn:timezone":"Africa/Freetown",
    "iso:country":"SL",
    "name:eng_x_preferred":[
        "Mendewa"
    ],
    "wof:name":"Mendewa",
    "wof:placetype":"locality"
},
  "geometry": {"coordinates":[-11.74358,7.93554],"type":"Point"}
}