{
  "type": "Feature",
  "properties": {
    "gn:admin1_code":"2.0",
    "gn:asciiname":"Kania",
    "gn:country_code":"SL",
    "gn:dem":50,
    "gn:feature_class":"P",
    "gn:feature_code":"PPL",
    "gn:name":"Kania",
    "gn:population":0,
    "gn:timezone":"Africa/Freetown",
    "iso:country":"SL",
    "name:ceb_x_preferred":[
        "Kania"
    ],
    "name:ces_x_preferred":[
        "Kania"
    ],
    "name:deu_x_preferred":[
        "Kania"
    ],
    "name:eng_x_preferred":[
        "Kania"
    ],
    "name:fra_x_preferred":[
        "Kania"
    ],
    "name:ita_x_preferred":[
        "Kania"
    ],
    "name:nld_x_preferred":[
        "Kania"
    ],
    "name:pol_x_preferred":[
        "Kania"
    ],
    "name:rus_x_preferred":[
        "\u041a\u0430\u043d\u044f"
    ],
    "name:swe_x_preferred":[
        "Kania"
    ],
    "name:ukr_x_preferred":[
        "\u041a\u0430\u043d\u044f"
    ],
    "wof:name":"Kania",
    "wof:placetype":"locality"
},
  "geometry": {"coordinates":[-12.78606,9.18967],"type":"Point"}
}