{
  "type": "Feature",
  "properties": {
    "gn:admin1_code":"3.0",
    "gn:asciiname":"Sahun",
    "gn:country_code":"SL",
    "gn:dem":145,
    "gn:feature_class":"P",
    "gn:feature_code":"PPL",
    "gn:name":"Sahun",
    "gn:population":0,
    "gn:timezone":"Africa/Freetown",
    "iso:country":"SL",
    "name:eng_x_preferred":[
        "Sahun"
    ],
    "wof:name":"Sahun",
    "wof:placetype":"locality"
},
  "geometry": {"coordinates":[-11.33604,8.07998],"type":"Point"}
}