{
  "type": "Feature",
  "properties": {
    "gn:admin1_code":"02",
    "gn:asciiname":"Tambianu",
    "gn:country_code":"SL",
    "gn:dem":76,
    "gn:feature_class":"P",
    "gn:feature_code":"PPL",
    "gn:name":"Tambianu",
    "gn:population":0,
    "gn:timezone":"Africa/Freetown",
    "iso:country":"SL",
    "name:und_x_variant":[
        "Tambiama",
        "Tambianu"
    ],
    "wof:name":"Tambianu",
    "wof:placetype":"locality"
},
  "geometry": {"coordinates":[-12.11126,8.99599],"type":"Point"}
}