{
  "type": "Feature",
  "properties": {
    "gn:admin1_code":"1.0",
    "gn:asciiname":"Mandowora",
    "gn:country_code":"SL",
    "gn:dem":226,
    "gn:feature_class":"P",
    "gn:feature_code":"PPL",
    "gn:name":"Mandowora",
    "gn:population":0,
    "gn:timezone":"Africa/Freetown",
    "iso:country":"SL",
    "name:eng_x_preferred":[
        "Mandowora"
    ],
    "wof:name":"Mandowora",
    "wof:placetype":"locality"
},
  "geometry": {"coordinates":[-10.68938,7.91536],"type":"Point"}
}