{
  "type": "Feature",
  "properties": {
    "gn:admin1_code":"3.0",
    "gn:asciiname":"Mayepema",
    "gn:country_code":"SL",
    "gn:dem":45,
    "gn:feature_class":"P",
    "gn:feature_code":"PPL",
    "gn:name":"Mayepema",
    "gn:population":0,
    "gn:timezone":"Africa/Freetown",
    "iso:country":"SL",
    "name:und_x_variant":[
        "Masipema"
    ],
    "wof:name":"Mayepema",
    "wof:placetype":"locality"
},
  "geometry": {"coordinates":[-11.61585,7.41893],"type":"Point"}
}