{
  "type": "Feature",
  "properties": {
    "gn:admin1_code":"4.0",
    "gn:asciiname":"Ma-suri",
    "gn:country_code":"SL",
    "gn:dem":18,
    "gn:feature_class":"P",
    "gn:feature_code":"PPL",
    "gn:name":"Ma-suri",
    "gn:population":0,
    "gn:timezone":"Africa/Freetown",
    "iso:country":"SL",
    "name:eng_x_preferred":[
        "Ma-suri"
    ],
    "wof:name":"Ma-suri",
    "wof:placetype":"locality"
},
  "geometry": {"coordinates":[-12.9419,8.31258],"type":"Point"}
}