{
  "type": "Feature",
  "properties": {
    "gn:admin1_code":"3.0",
    "gn:asciiname":"Mondema",
    "gn:country_code":"SL",
    "gn:dem":74,
    "gn:feature_class":"P",
    "gn:feature_code":"PPL",
    "gn:name":"Mondema",
    "gn:population":0,
    "gn:timezone":"Africa/Freetown",
    "iso:country":"SL",
    "name:eng_x_preferred":[
        "Mondema"
    ],
    "wof:name":"Mondema",
    "wof:placetype":"locality"
},
  "geometry": {"coordinates":[-12.3699,8.26906],"type":"Point"}
}