{
  "type": "Feature",
  "properties": {
    "gn:admin1_code":"3.0",
    "gn:asciiname":"Gbamusu",
    "gn:country_code":"SL",
    "gn:dem":39,
    "gn:feature_class":"P",
    "gn:feature_code":"PPL",
    "gn:name":"Gbamusu",
    "gn:population":0,
    "gn:timezone":"Africa/Freetown",
    "iso:country":"SL",
    "name:eng_x_preferred":[
        "Gbamusu"
    ],
    "name:und_x_variant":[
        "Gbamusa"
    ],
    "wof:name":"Gbamusu",
    "wof:placetype":"locality"
},
  "geometry": {"coordinates":[-12.56756,7.98398],"type":"Point"}
}