{
  "type": "Feature",
  "properties": {
    "gn:admin1_code":"2.0",
    "gn:asciiname":"Makeli",
    "gn:country_code":"SL",
    "gn:dem":71,
    "gn:feature_class":"P",
    "gn:feature_code":"PPL",
    "gn:name":"Makeli",
    "gn:population":0,
    "gn:timezone":"Africa/Freetown",
    "iso:country":"SL",
    "name:eng_x_preferred":[
        "Makeli"
    ],
    "wof:name":"Makeli",
    "wof:placetype":"locality"
},
  "geometry": {"coordinates":[-11.97605,8.41338],"type":"Point"}
}