{
  "type": "Feature",
  "properties": {
    "gn:admin1_code":"3.0",
    "gn:asciiname":"Mopofai",
    "gn:country_code":"SL",
    "gn:dem":9,
    "gn:feature_class":"P",
    "gn:feature_code":"PPL",
    "gn:name":"Mopofai",
    "gn:population":0,
    "gn:timezone":"Africa/Freetown",
    "iso:country":"SL",
    "name:eng_x_preferred":[
        "Mopofai"
    ],
    "wof:name":"Mopofai",
    "wof:placetype":"locality"
},
  "geometry": {"coordinates":[-12.6656,8.1307],"type":"Point"}
}