{
  "type": "Feature",
  "properties": {
    "gn:admin1_code":"2.0",
    "gn:asciiname":"Kania",
    "gn:country_code":"SL",
    "gn:dem":412,
    "gn:feature_class":"P",
    "gn:feature_code":"PPL",
    "gn:name":"Kania",
    "gn:population":0,
    "gn:timezone":"Africa/Freetown",
    "iso:country":"SL",
    "name:eng_x_preferred":[
        "Kania"
    ],
    "wof:name":"Kania",
    "wof:placetype":"locality"
},
  "geometry": {"coordinates":[-11.60898,9.21246],"type":"Point"}
}