{
  "type": "Feature",
  "properties": {
    "gn:admin1_code":"2.0",
    "gn:asciiname":"Makobonko",
    "gn:country_code":"SL",
    "gn:dem":58,
    "gn:feature_class":"P",
    "gn:feature_code":"PPL",
    "gn:name":"Makobonko",
    "gn:population":0,
    "gn:timezone":"Africa/Freetown",
    "iso:country":"SL",
    "name:eng_x_preferred":[
        "Makobonko"
    ],
    "wof:name":"Makobonko",
    "wof:placetype":"locality"
},
  "geometry": {"coordinates":[-12.37259,9.17105],"type":"Point"}
}