{
  "type": "Feature",
  "properties": {
    "gn:admin1_code":"3.0",
    "gn:asciiname":"Naiaguehun",
    "gn:country_code":"SL",
    "gn:dem":79,
    "gn:feature_class":"P",
    "gn:feature_code":"PPL",
    "gn:name":"Naiaguehun",
    "gn:population":0,
    "gn:timezone":"Africa/Freetown",
    "iso:country":"SL",
    "name:eng_x_preferred":[
        "Naiaguehun"
    ],
    "wof:name":"Naiaguehun",
    "wof:placetype":"locality"
},
  "geometry": {"coordinates":[-12.17483,8.09447],"type":"Point"}
}