{
  "type": "Feature",
  "properties": {
    "gn:admin1_code":"3.0",
    "gn:asciiname":"Bondan",
    "gn:country_code":"SL",
    "gn:dem":26,
    "gn:feature_class":"P",
    "gn:feature_code":"PPL",
    "gn:name":"Bondan",
    "gn:population":0,
    "gn:timezone":"Africa/Freetown",
    "iso:country":"SL",
    "name:eng_x_preferred":[
        "Bondan"
    ],
    "name:und_x_variant":[
        "Bondal"
    ],
    "wof:name":"Bondan",
    "wof:placetype":"locality"
},
  "geometry": {"coordinates":[-12.78111,7.995],"type":"Point"}
}