{
  "type": "Feature",
  "properties": {
    "gn:admin1_code":"1.0",
    "gn:asciiname":"Palawa",
    "gn:country_code":"SL",
    "gn:dem":511,
    "gn:feature_class":"P",
    "gn:feature_code":"PPL",
    "gn:name":"Palawa",
    "gn:population":0,
    "gn:timezone":"Africa/Freetown",
    "iso:country":"SL",
    "name:eng_x_preferred":[
        "Palawa"
    ],
    "wof:name":"Palawa",
    "wof:placetype":"locality"
},
  "geometry": {"coordinates":[-10.6034,9.00388],"type":"Point"}
}