{
  "type": "Feature",
  "properties": {
    "gn:admin1_code":"1.0",
    "gn:asciiname":"Sembehun",
    "gn:country_code":"SL",
    "gn:dem":171,
    "gn:feature_class":"P",
    "gn:feature_code":"PPL",
    "gn:name":"Sembehun",
    "gn:population":0,
    "gn:timezone":"Africa/Freetown",
    "iso:country":"SL",
    "name:eng_x_preferred":[
        "Sembehun"
    ],
    "wof:name":"Sembehun",
    "wof:placetype":"locality"
},
  "geometry": {"coordinates":[-11.09943,7.74327],"type":"Point"}
}