{
  "type": "Feature",
  "properties": {
    "gn:admin1_code":"1.0",
    "gn:asciiname":"Maboka",
    "gn:country_code":"SL",
    "gn:dem":152,
    "gn:feature_class":"P",
    "gn:feature_code":"PPL",
    "gn:name":"Maboka",
    "gn:population":0,
    "gn:timezone":"Africa/Freetown",
    "iso:country":"SL",
    "name:eng_x_preferred":[
        "Maboka"
    ],
    "wof:name":"Maboka",
    "wof:placetype":"locality"
},
  "geometry": {"coordinates":[-11.26387,7.93673],"type":"Point"}
}