{
  "type": "Feature",
  "properties": {
    "gn:admin1_code":"1.0",
    "gn:asciiname":"Sau",
    "gn:country_code":"SL",
    "gn:dem":197,
    "gn:feature_class":"P",
    "gn:feature_code":"PPL",
    "gn:name":"Sau",
    "gn:population":0,
    "gn:timezone":"Africa/Freetown",
    "iso:country":"SL",
    "name:ceb_x_preferred":[
        "Sau"
    ],
    "name:deu_x_preferred":[
        "Sau"
    ],
    "name:eng_x_preferred":[
        "Sau"
    ],
    "name:rus_x_preferred":[
        "\u0421\u0430\u0443"
    ],
    "name:swe_x_preferred":[
        "Sau"
    ],
    "wof:name":"Sau",
    "wof:placetype":"locality"
},
  "geometry": {"coordinates":[-11.07798,8.01322],"type":"Point"}
}