{
  "type": "Feature",
  "properties": {
    "gn:admin1_code":"3.0",
    "gn:asciiname":"Baoma",
    "gn:country_code":"SL",
    "gn:dem":100,
    "gn:feature_class":"P",
    "gn:feature_code":"PPL",
    "gn:name":"Baoma",
    "gn:population":7044,
    "gn:timezone":"Africa/Freetown",
    "iso:country":"SL",
    "name:ceb_x_preferred":[
        "Baoma"
    ],
    "name:ron_x_preferred":[
        "Baoma"
    ],
    "wof:name":"Baoma",
    "wof:placetype":"locality",
    "wof:population":7044
},
  "geometry": {"coordinates":[-11.71468,7.99344],"type":"Point"}
}