{
  "type": "Feature",
  "properties": {
    "gn:admin1_code":"3.0",
    "gn:asciiname":"Mamboma",
    "gn:country_code":"SL",
    "gn:dem":72,
    "gn:feature_class":"P",
    "gn:feature_code":"PPL",
    "gn:name":"Mamboma",
    "gn:population":0,
    "gn:timezone":"Africa/Freetown",
    "iso:country":"SL",
    "name:eng_x_preferred":[
        "Mamboma"
    ],
    "wof:name":"Mamboma",
    "wof:placetype":"locality"
},
  "geometry": {"coordinates":[-11.63407,7.54433],"type":"Point"}
}