{
  "type": "Feature",
  "properties": {
    "gn:admin1_code":"2.0",
    "gn:asciiname":"Manteremu",
    "gn:country_code":"SL",
    "gn:dem":61,
    "gn:feature_class":"P",
    "gn:feature_code":"PPL",
    "gn:name":"Manteremu",
    "gn:population":0,
    "gn:timezone":"Africa/Freetown",
    "iso:country":"SL",
    "name:und_x_variant":[
        "Manterema",
        "Manteremu"
    ],
    "wof:name":"Manteremu",
    "wof:placetype":"locality"
},
  "geometry": {"coordinates":[-12.36934,9.32385],"type":"Point"}
}