{
  "type": "Feature",
  "properties": {
    "gn:admin1_code":"2.0",
    "gn:asciiname":"Kunto",
    "gn:country_code":"SL",
    "gn:dem":19,
    "gn:feature_class":"P",
    "gn:feature_code":"PPL",
    "gn:name":"Kunto",
    "gn:population":0,
    "gn:timezone":"Africa/Freetown",
    "iso:country":"SL",
    "name:eng_x_preferred":[
        "Kunto"
    ],
    "wof:name":"Kunto",
    "wof:placetype":"locality"
},
  "geometry": {"coordinates":[-12.95952,8.97162],"type":"Point"}
}