{
  "type": "Feature",
  "properties": {
    "gn:admin1_code":"01",
    "gn:asciiname":"Tijoema",
    "gn:country_code":"SL",
    "gn:dem":164,
    "gn:feature_class":"P",
    "gn:feature_code":"PPL",
    "gn:name":"Tijoema",
    "gn:population":0,
    "gn:timezone":"Africa/Freetown",
    "iso:country":"SL",
    "name:eng_x_preferred":[
        "Tijoema"
    ],
    "wof:name":"Tijoema",
    "wof:placetype":"locality"
},
  "geometry": {"coordinates":[-11.16283,7.63035],"type":"Point"}
}