{
  "type": "Feature",
  "properties": {
    "gn:admin1_code":"2.0",
    "gn:asciiname":"Masindugu",
    "gn:country_code":"SL",
    "gn:dem":481,
    "gn:feature_class":"P",
    "gn:feature_code":"PPL",
    "gn:name":"Masindugu",
    "gn:population":0,
    "gn:timezone":"Africa/Freetown",
    "iso:country":"SL",
    "name:eng_x_preferred":[
        "Masindugu"
    ],
    "wof:name":"Masindugu",
    "wof:placetype":"locality"
},
  "geometry": {"coordinates":[-11.62896,9.04049],"type":"Point"}
}