{
  "type": "Feature",
  "properties": {
    "gn:admin1_code":"1.0",
    "gn:asciiname":"Fuero",
    "gn:country_code":"SL",
    "gn:dem":329,
    "gn:feature_class":"P",
    "gn:feature_code":"PPL",
    "gn:name":"Fuero",
    "gn:population":0,
    "gn:timezone":"Africa/Freetown",
    "iso:country":"SL",
    "name:als_x_preferred":[
        "Fueros"
    ],
    "name:cat_x_preferred":[
        "Furs"
    ],
    "name:deu_x_preferred":[
        "Fuero"
    ],
    "name:eng_x_preferred":[
        "Fuero"
    ],
    "name:epo_x_preferred":[
        "Foruo"
    ],
    "name:eus_x_preferred":[
        "Foru"
    ],
    "name:fra_x_preferred":[
        "For"
    ],
    "name:hun_x_preferred":[
        "Fuero"
    ],
    "name:ind_x_preferred":[
        "Fuero"
    ],
    "name:ita_x_preferred":[
        "Fuero"
    ],
    "name:jpn_x_preferred":[
        "\u30d5\u30a8\u30ed"
    ],
    "name:lat_x_preferred":[
        "Forum"
    ],
    "name:oci_x_preferred":[
        "F\u00f2r"
    ],
    "name:pol_x_preferred":[
        "Fuero"
    ],
    "name:rus_x_preferred":[
        "\u0424\u0443\u044d\u0440\u043e\u0441"
    ],
    "name:spa_x_preferred":[
        "Fuero"
    ],
    "name:swe_x_preferred":[
        "Foralr\u00e4tt"
    ],
    "name:ukr_x_preferred":[
        "\u0424\u0443\u0435\u0440\u043e"
    ],
    "wof:name":"Fuero",
    "wof:placetype":"locality"
},
  "geometry": {"coordinates":[-10.64097,8.59285],"type":"Point"}
}