{
  "type": "Feature",
  "properties": {
    "gn:admin1_code":"02",
    "gn:asciiname":"Worowaia",
    "gn:country_code":"SL",
    "gn:dem":372,
    "gn:feature_class":"P",
    "gn:feature_code":"PPL",
    "gn:name":"Worowaia",
    "gn:population":0,
    "gn:timezone":"Africa/Freetown",
    "iso:country":"SL",
    "name:eng_x_preferred":[
        "Worowaia"
    ],
    "wof:name":"Worowaia",
    "wof:placetype":"locality"
},
  "geometry": {"coordinates":[-11.66138,9.16552],"type":"Point"}
}