{
  "type": "Feature",
  "properties": {
    "gn:admin1_code":"2.0",
    "gn:asciiname":"Gbankona",
    "gn:country_code":"SL",
    "gn:dem":127,
    "gn:feature_class":"P",
    "gn:feature_code":"PPL",
    "gn:name":"Gbankona",
    "gn:population":0,
    "gn:timezone":"Africa/Freetown",
    "iso:country":"SL",
    "name:eng_x_preferred":[
        "Gbankona"
    ],
    "wof:name":"Gbankona",
    "wof:placetype":"locality"
},
  "geometry": {"coordinates":[-11.80227,9.04478],"type":"Point"}
}