{
  "type": "Feature",
  "properties": {
    "gn:admin1_code":"2.0",
    "gn:asciiname":"Kasasi",
    "gn:country_code":"SL",
    "gn:dem":142,
    "gn:feature_class":"P",
    "gn:feature_code":"PPL",
    "gn:name":"Kasasi",
    "gn:population":0,
    "gn:timezone":"Africa/Freetown",
    "iso:country":"SL",
    "name:eng_x_preferred":[
        "Kasasi"
    ],
    "wof:name":"Kasasi",
    "wof:placetype":"locality"
},
  "geometry": {"coordinates":[-12.22231,9.53344],"type":"Point"}
}