{
  "type": "Feature",
  "properties": {
    "gn:admin1_code":"03",
    "gn:asciiname":"Yandiama",
    "gn:country_code":"SL",
    "gn:dem":78,
    "gn:feature_class":"P",
    "gn:feature_code":"PPL",
    "gn:name":"Yandiama",
    "gn:population":0,
    "gn:timezone":"Africa/Freetown",
    "iso:country":"SL",
    "name:eng_x_preferred":[
        "Yandiama"
    ],
    "name:und_x_variant":[
        "Yandama"
    ],
    "wof:name":"Yandiama",
    "wof:placetype":"locality"
},
  "geometry": {"coordinates":[-11.74268,7.76184],"type":"Point"}
}