{
  "type": "Feature",
  "properties": {
    "gn:admin1_code":"2.0",
    "gn:asciiname":"Kakarima",
    "gn:country_code":"SL",
    "gn:dem":451,
    "gn:feature_class":"P",
    "gn:feature_code":"PPL",
    "gn:name":"Kakarima",
    "gn:population":0,
    "gn:timezone":"Africa/Freetown",
    "iso:country":"SL",
    "name:eng_x_preferred":[
        "Kakarima"
    ],
    "wof:name":"Kakarima",
    "wof:placetype":"locality"
},
  "geometry": {"coordinates":[-11.76941,9.46687],"type":"Point"}
}