{
  "type": "Feature",
  "properties": {
    "gn:admin1_code":"3.0",
    "gn:asciiname":"Mokapinta",
    "gn:country_code":"SL",
    "gn:dem":20,
    "gn:feature_class":"P",
    "gn:feature_code":"PPL",
    "gn:name":"Mokapinta",
    "gn:population":0,
    "gn:timezone":"Africa/Freetown",
    "iso:country":"SL",
    "name:eng_x_preferred":[
        "Mokapinta"
    ],
    "wof:name":"Mokapinta",
    "wof:placetype":"locality"
},
  "geometry": {"coordinates":[-12.62428,7.96662],"type":"Point"}
}