{
  "type": "Feature",
  "properties": {
    "gn:admin1_code":"2.0",
    "gn:asciiname":"Mafala",
    "gn:country_code":"SL",
    "gn:dem":41,
    "gn:feature_class":"P",
    "gn:feature_code":"PPL",
    "gn:name":"Mafala",
    "gn:population":0,
    "gn:timezone":"Africa/Freetown",
    "iso:country":"SL",
    "name:eng_x_preferred":[
        "Mafala"
    ],
    "wof:name":"Mafala",
    "wof:placetype":"locality"
},
  "geometry": {"coordinates":[-12.92725,9.2542],"type":"Point"}
}