{
  "type": "Feature",
  "properties": {
    "gn:admin1_code":"3.0",
    "gn:asciiname":"Mokano",
    "gn:country_code":"SL",
    "gn:dem":5,
    "gn:feature_class":"P",
    "gn:feature_code":"PPL",
    "gn:name":"Mokano",
    "gn:population":0,
    "gn:timezone":"Africa/Freetown",
    "iso:country":"SL",
    "name:eng_x_preferred":[
        "Mokano"
    ],
    "wof:name":"Mokano",
    "wof:placetype":"locality"
},
  "geometry": {"coordinates":[-12.37546,7.60047],"type":"Point"}
}