{
  "type": "Feature",
  "properties": {
    "gn:admin1_code":"2.0",
    "gn:asciiname":"Firawa",
    "gn:country_code":"SL",
    "gn:dem":514,
    "gn:feature_class":"P",
    "gn:feature_code":"PPL",
    "gn:name":"Firawa",
    "gn:population":0,
    "gn:timezone":"Africa/Freetown",
    "iso:country":"SL",
    "name:eng_x_preferred":[
        "Firawa"
    ],
    "wof:name":"Firawa",
    "wof:placetype":"locality"
},
  "geometry": {"coordinates":[-10.85616,9.5116],"type":"Point"}
}