{
  "type": "Feature",
  "properties": {
    "gn:admin1_code":"2.0",
    "gn:asciiname":"Magbasa",
    "gn:country_code":"SL",
    "gn:dem":65,
    "gn:feature_class":"P",
    "gn:feature_code":"PPL",
    "gn:name":"Magbasa",
    "gn:population":0,
    "gn:timezone":"Africa/Freetown",
    "iso:country":"SL",
    "name:eng_x_preferred":[
        "Magbasa"
    ],
    "wof:name":"Magbasa",
    "wof:placetype":"locality"
},
  "geometry": {"coordinates":[-12.28161,9.1602],"type":"Point"}
}