{
  "type": "Feature",
  "properties": {
    "gn:admin1_code":"3.0",
    "gn:asciiname":"Mogbangi",
    "gn:country_code":"SL",
    "gn:dem":74,
    "gn:feature_class":"P",
    "gn:feature_code":"PPL",
    "gn:name":"Mogbangi",
    "gn:population":0,
    "gn:timezone":"Africa/Freetown",
    "iso:country":"SL",
    "name:eng_x_preferred":[
        "Mogbangi"
    ],
    "wof:name":"Mogbangi",
    "wof:placetype":"locality"
},
  "geometry": {"coordinates":[-12.43393,7.95998],"type":"Point"}
}