{
  "type": "Feature",
  "properties": {
    "gn:admin1_code":"1.0",
    "gn:asciiname":"Bekedu",
    "gn:country_code":"SL",
    "gn:dem":435,
    "gn:feature_class":"P",
    "gn:feature_code":"PPL",
    "gn:name":"Bekedu",
    "gn:population":0,
    "gn:timezone":"Africa/Freetown",
    "iso:country":"SL",
    "name:eng_x_preferred":[
        "Bekedu"
    ],
    "wof:name":"Bekedu",
    "wof:placetype":"locality"
},
  "geometry": {"coordinates":[-10.33285,8.18649],"type":"Point"}
}