{
  "type": "Feature",
  "properties": {
    "gn:admin1_code":"2.0",
    "gn:asciiname":"Dian Sokurela",
    "gn:country_code":"SL",
    "gn:dem":335,
    "gn:feature_class":"P",
    "gn:feature_code":"PPL",
    "gn:name":"Dian Sokurela",
    "gn:population":0,
    "gn:timezone":"Africa/Freetown",
    "iso:country":"SL",
    "name:eng_x_preferred":[
        "Dian Sokurela"
    ],
    "wof:name":"Dian Sokurela",
    "wof:placetype":"locality"
},
  "geometry": {"coordinates":[-11.50834,9.35687],"type":"Point"}
}