{
  "type": "Feature",
  "properties": {
    "gn:admin1_code":"1.0",
    "gn:asciiname":"Gbangbau",
    "gn:country_code":"SL",
    "gn:dem":200,
    "gn:feature_class":"P",
    "gn:feature_code":"PPL",
    "gn:name":"Gbangbau",
    "gn:population":0,
    "gn:timezone":"Africa/Freetown",
    "iso:country":"SL",
    "name:eng_x_preferred":[
        "Gbangbau"
    ],
    "wof:name":"Gbangbau",
    "wof:placetype":"locality"
},
  "geometry": {"coordinates":[-11.08365,8.03635],"type":"Point"}
}