{
  "type": "Feature",
  "properties": {
    "gn:admin1_code":"2.0",
    "gn:asciiname":"Maleni",
    "gn:country_code":"SL",
    "gn:dem":142,
    "gn:feature_class":"P",
    "gn:feature_code":"PPL",
    "gn:name":"Maleni",
    "gn:population":0,
    "gn:timezone":"Africa/Freetown",
    "iso:country":"SL",
    "name:eng_x_preferred":[
        "Maleni"
    ],
    "wof:name":"Maleni",
    "wof:placetype":"locality"
},
  "geometry": {"coordinates":[-11.90558,9.35374],"type":"Point"}
}