{
  "type": "Feature",
  "properties": {
    "gn:admin1_code":"1.0",
    "gn:asciiname":"Mandutawahun",
    "gn:country_code":"SL",
    "gn:dem":213,
    "gn:feature_class":"P",
    "gn:feature_code":"PPL",
    "gn:name":"Mandutawahun",
    "gn:population":0,
    "gn:timezone":"Africa/Freetown",
    "iso:country":"SL",
    "name:eng_x_preferred":[
        "Mandutawahun"
    ],
    "wof:name":"Mandutawahun",
    "wof:placetype":"locality"
},
  "geometry": {"coordinates":[-10.75773,8.03611],"type":"Point"}
}