{
  "type": "Feature",
  "properties": {
    "gn:admin1_code":"3.0",
    "gn:asciiname":"Gbomuko",
    "gn:country_code":"SL",
    "gn:dem":15,
    "gn:feature_class":"P",
    "gn:feature_code":"PPL",
    "gn:name":"Gbomuko",
    "gn:population":0,
    "gn:timezone":"Africa/Freetown",
    "iso:country":"SL",
    "name:eng_x_preferred":[
        "Gbomuko"
    ],
    "wof:name":"Gbomuko",
    "wof:placetype":"locality"
},
  "geometry": {"coordinates":[-11.71737,7.19682],"type":"Point"}
}