{
  "type": "Feature",
  "properties": {
    "gn:admin1_code":"3.0",
    "gn:asciiname":"Gbangbama",
    "gn:country_code":"SL",
    "gn:dem":20,
    "gn:feature_class":"P",
    "gn:feature_code":"PPL",
    "gn:name":"Gbangbama",
    "gn:population":0,
    "gn:timezone":"Africa/Freetown",
    "iso:country":"SL",
    "name:eng_x_preferred":[
        "Gbangbama"
    ],
    "wof:name":"Gbangbama",
    "wof:placetype":"locality"
},
  "geometry": {"coordinates":[-12.52605,7.96424],"type":"Point"}
}