{
  "type": "Feature",
  "properties": {
    "gn:admin1_code":"02",
    "gn:asciiname":"Senguinya",
    "gn:country_code":"SL",
    "gn:dem":132,
    "gn:feature_class":"P",
    "gn:feature_code":"PPL",
    "gn:name":"Senguinya",
    "gn:population":0,
    "gn:timezone":"Africa/Freetown",
    "iso:country":"SL",
    "wof:name":"Senguinya",
    "wof:placetype":"locality"
},
  "geometry": {"coordinates":[-11.93333,9.35],"type":"Point"}
}