{
  "type": "Feature",
  "properties": {
    "gn:admin1_code":"3.0",
    "gn:asciiname":"Baka",
    "gn:country_code":"SL",
    "gn:dem":13,
    "gn:feature_class":"P",
    "gn:feature_code":"PPL",
    "gn:name":"Baka",
    "gn:population":0,
    "gn:timezone":"Africa/Freetown",
    "iso:country":"SL",
    "name:bel_x_preferred":[
        "\u0411\u0430\u043a\u0430"
    ],
    "name:cat_x_preferred":[
        "Baka"
    ],
    "name:ceb_x_preferred":[
        "Baka"
    ],
    "name:deu_x_preferred":[
        "Baka"
    ],
    "name:eng_x_preferred":[
        "Baka"
    ],
    "name:fra_x_preferred":[
        "Baka"
    ],
    "name:hun_x_preferred":[
        "Baka"
    ],
    "name:ita_x_preferred":[
        "Baka"
    ],
    "name:lav_x_preferred":[
        "Baka"
    ],
    "name:nld_x_preferred":[
        "Baka"
    ],
    "name:pol_x_preferred":[
        "Baka"
    ],
    "name:rus_x_preferred":[
        "\u0411\u0430\u043a\u0430"
    ],
    "name:spa_x_preferred":[
        "Baka"
    ],
    "name:srp_x_preferred":[
        "\u0411\u0430\u043a\u0430"
    ],
    "name:swe_x_preferred":[
        "Baka"
    ],
    "name:tgl_x_preferred":[
        "Baka"
    ],
    "name:ukr_x_preferred":[
        "\u0411\u0430\u043a\u0430"
    ],
    "wof:name":"Baka",
    "wof:placetype":"locality"
},
  "geometry": {"coordinates":[-12.8413,7.87525],"type":"Point"}
}