{
  "type": "Feature",
  "properties": {
    "gn:admin1_code":"3.0",
    "gn:asciiname":"Kpowabu",
    "gn:country_code":"SL",
    "gn:dem":297,
    "gn:feature_class":"P",
    "gn:feature_code":"PPL",
    "gn:name":"Kpowabu",
    "gn:population":0,
    "gn:timezone":"Africa/Freetown",
    "iso:country":"SL",
    "name:eng_x_preferred":[
        "Kpowabu"
    ],
    "name:und_x_variant":[
        "Buabu"
    ],
    "wof:name":"Kpowabu",
    "wof:placetype":"locality"
},
  "geometry": {"coordinates":[-11.42627,8.14277],"type":"Point"}
}