{
  "type": "Feature",
  "properties": {
    "gn:admin1_code":"02",
    "gn:asciiname":"Yof",
    "gn:country_code":"SL",
    "gn:dem":20,
    "gn:feature_class":"P",
    "gn:feature_code":"PPL",
    "gn:name":"Yof",
    "gn:population":0,
    "gn:timezone":"Africa/Freetown",
    "iso:country":"SL",
    "name:eng_x_preferred":[
        "Yof"
    ],
    "wof:name":"Yof",
    "wof:placetype":"locality"
},
  "geometry": {"coordinates":[-13.06254,8.42396],"type":"Point"}
}