{
  "type": "Feature",
  "properties": {
    "gn:admin1_code":"2.0",
    "gn:asciiname":"Gbonkomayira",
    "gn:country_code":"SL",
    "gn:dem":20,
    "gn:feature_class":"P",
    "gn:feature_code":"PPL",
    "gn:name":"Gbonkomayira",
    "gn:population":0,
    "gn:timezone":"Africa/Freetown",
    "iso:country":"SL",
    "name:und_x_variant":[
        "Gbonkomayina",
        "Gbonkomayira"
    ],
    "wof:name":"Gbonkomayira",
    "wof:placetype":"locality"
},
  "geometry": {"coordinates":[-12.87452,8.67682],"type":"Point"}
}