{
  "type": "Feature",
  "properties": {
    "gn:admin1_code":"2.0",
    "gn:asciiname":"Mansiraia",
    "gn:country_code":"SL",
    "gn:dem":421,
    "gn:feature_class":"P",
    "gn:feature_code":"PPL",
    "gn:name":"Mansiraia",
    "gn:population":0,
    "gn:timezone":"Africa/Freetown",
    "iso:country":"SL",
    "name:eng_x_preferred":[
        "Mansiraia"
    ],
    "wof:name":"Mansiraia",
    "wof:placetype":"locality"
},
  "geometry": {"coordinates":[-11.40775,9.01504],"type":"Point"}
}