{
  "type": "Feature",
  "properties": {
    "gn:admin1_code":"2.0",
    "gn:asciiname":"Sana",
    "gn:country_code":"SL",
    "gn:dem":130,
    "gn:feature_class":"P",
    "gn:feature_code":"PPL",
    "gn:name":"Sana",
    "gn:population":0,
    "gn:timezone":"Africa/Freetown",
    "iso:country":"SL",
    "name:eng_x_preferred":[
        "Sana"
    ],
    "wof:name":"Sana",
    "wof:placetype":"locality"
},
  "geometry": {"coordinates":[-12.23242,9.19645],"type":"Point"}
}