{
  "type": "Feature",
  "properties": {
    "gn:admin1_code":"2.0",
    "gn:asciiname":"Sana",
    "gn:country_code":"SL",
    "gn:dem":130,
    "gn:feature_class":"P",
    "gn:feature_code":"PPL",
    "gn:name":"Sana",
    "gn:population":0,
    "gn:timezone":"Africa/Freetown",
    "iso:country":"SL",
    "name:bul_x_preferred":[
        "\u0421\u0430\u043d\u0430"
    ],
    "name:ceb_x_preferred":[
        "Sana"
    ],
    "name:ces_x_preferred":[
        "Sana"
    ],
    "name:deu_x_preferred":[
        "Sana"
    ],
    "name:eng_x_preferred":[
        "Sana"
    ],
    "name:fin_x_preferred":[
        "Sana"
    ],
    "name:fra_x_preferred":[
        "Sana"
    ],
    "name:hrv_x_preferred":[
        "Sana"
    ],
    "name:ita_x_preferred":[
        "Sana"
    ],
    "name:jpn_x_preferred":[
        "\u3055\u306a"
    ],
    "name:kor_x_preferred":[
        "\uc0ac\ub098"
    ],
    "name:lav_x_preferred":[
        "Sana"
    ],
    "name:nld_x_preferred":[
        "Sana"
    ],
    "name:nor_x_preferred":[
        "Sana"
    ],
    "name:pol_x_preferred":[
        "Sana"
    ],
    "name:por_x_preferred":[
        "Sana"
    ],
    "name:rus_x_preferred":[
        "\u0421\u0430\u043d\u0430"
    ],
    "name:slk_x_preferred":[
        "Sana"
    ],
    "name:slv_x_preferred":[
        "Sana"
    ],
    "name:spa_x_preferred":[
        "Sana"
    ],
    "name:srp_x_preferred":[
        "\u0421\u0430\u043d\u0430"
    ],
    "name:swe_x_preferred":[
        "Sana"
    ],
    "name:tgl_x_preferred":[
        "Sana"
    ],
    "name:tur_x_preferred":[
        "Sana"
    ],
    "name:zho_x_preferred":[
        "Sana"
    ],
    "wof:name":"Sana",
    "wof:placetype":"locality"
},
  "geometry": {"coordinates":[-12.23242,9.19645],"type":"Point"}
}