{
  "type": "Feature",
  "properties": {
    "gn:admin1_code":"02",
    "gn:asciiname":"Probo",
    "gn:country_code":"SL",
    "gn:dem":10,
    "gn:feature_class":"P",
    "gn:feature_code":"PPL",
    "gn:name":"Probo",
    "gn:population":0,
    "gn:timezone":"Africa/Freetown",
    "iso:country":"SL",
    "name:eng_x_preferred":[
        "Probo"
    ],
    "wof:name":"Probo",
    "wof:placetype":"locality"
},
  "geometry": {"coordinates":[-13.1958,8.85449],"type":"Point"}
}