{
  "type": "Feature",
  "properties": {
    "gn:admin1_code":"03",
    "gn:asciiname":"Pejebu",
    "gn:country_code":"SL",
    "gn:dem":32,
    "gn:feature_class":"P",
    "gn:feature_code":"PPL",
    "gn:name":"Pejebu",
    "gn:population":0,
    "gn:timezone":"Africa/Freetown",
    "iso:country":"SL",
    "wof:name":"Pejebu",
    "wof:placetype":"locality"
},
  "geometry": {"coordinates":[-12.24194,7.73833],"type":"Point"}
}