{
  "type": "Feature",
  "properties": {
    "gn:admin1_code":"02",
    "gn:asciiname":"Warakasona",
    "gn:country_code":"SL",
    "gn:dem":120,
    "gn:feature_class":"P",
    "gn:feature_code":"PPL",
    "gn:name":"Warakasona",
    "gn:population":0,
    "gn:timezone":"Africa/Freetown",
    "iso:country":"SL",
    "name:und_x_variant":[
        "Warakasonia",
        "Warakasona"
    ],
    "wof:name":"Warakasona",
    "wof:placetype":"locality"
},
  "geometry": {"coordinates":[-11.95801,9.38159],"type":"Point"}
}