{
  "type": "Feature",
  "properties": {
    "gn:admin1_code":"2.0",
    "gn:asciiname":"Mamaso",
    "gn:country_code":"SL",
    "gn:dem":94,
    "gn:feature_class":"P",
    "gn:feature_code":"PPL",
    "gn:name":"Mamaso",
    "gn:population":0,
    "gn:timezone":"Africa/Freetown",
    "iso:country":"SL",
    "name:eng_x_preferred":[
        "Mamaso"
    ],
    "wof:name":"Mamaso",
    "wof:placetype":"locality"
},
  "geometry": {"coordinates":[-11.95002,8.71053],"type":"Point"}
}