{
  "type": "Feature",
  "properties": {
    "gn:admin1_code":"2.0",
    "gn:asciiname":"Maronka",
    "gn:country_code":"SL",
    "gn:dem":326,
    "gn:feature_class":"P",
    "gn:feature_code":"PPL",
    "gn:name":"Maronka",
    "gn:population":0,
    "gn:timezone":"Africa/Freetown",
    "iso:country":"SL",
    "name:eng_x_preferred":[
        "Maronka"
    ],
    "wof:name":"Maronka",
    "wof:placetype":"locality"
},
  "geometry": {"coordinates":[-11.66444,8.8012],"type":"Point"}
}