{
  "type": "Feature",
  "properties": {
    "gn:admin1_code":"3.0",
    "gn:asciiname":"Bamyamahun",
    "gn:country_code":"SL",
    "gn:dem":343,
    "gn:feature_class":"P",
    "gn:feature_code":"PPL",
    "gn:name":"Bamyamahun",
    "gn:population":0,
    "gn:timezone":"Africa/Freetown",
    "iso:country":"SL",
    "name:eng_x_preferred":[
        "Bamyamahun"
    ],
    "name:und_x_variant":[
        "Banyamahun"
    ],
    "wof:name":"Bamyamahun",
    "wof:placetype":"locality"
},
  "geometry": {"coordinates":[-11.43069,8.22629],"type":"Point"}
}