{
  "type": "Feature",
  "properties": {
    "gn:admin1_code":"1.0",
    "gn:asciiname":"Helegohun",
    "gn:country_code":"SL",
    "gn:dem":354,
    "gn:feature_class":"P",
    "gn:feature_code":"PPL",
    "gn:name":"Helegohun",
    "gn:population":0,
    "gn:timezone":"Africa/Freetown",
    "iso:country":"SL",
    "name:eng_x_preferred":[
        "Helegohun"
    ],
    "name:und_x_variant":[
        "Heligahun",
        "Heligohun"
    ],
    "wof:name":"Helegohun",
    "wof:placetype":"locality"
},
  "geometry": {"coordinates":[-11.40826,8.54224],"type":"Point"}
}