{
  "type": "Feature",
  "properties": {
    "gn:admin1_code":"2.0",
    "gn:asciiname":"Matai",
    "gn:country_code":"SL",
    "gn:dem":21,
    "gn:feature_class":"P",
    "gn:feature_code":"PPL",
    "gn:name":"Matai",
    "gn:population":0,
    "gn:timezone":"Africa/Freetown",
    "iso:country":"SL",
    "name:ceb_x_preferred":[
        "Matai"
    ],
    "name:deu_x_preferred":[
        "Matai"
    ],
    "name:eng_x_preferred":[
        "Matai"
    ],
    "name:swe_x_preferred":[
        "Matai"
    ],
    "wof:name":"Matai",
    "wof:placetype":"locality"
},
  "geometry": {"coordinates":[-13.11047,8.79362],"type":"Point"}
}