{
  "type": "Feature",
  "properties": {
    "gn:admin1_code":"2.0",
    "gn:asciiname":"Masepina",
    "gn:country_code":"SL",
    "gn:dem":321,
    "gn:feature_class":"P",
    "gn:feature_code":"PPL",
    "gn:name":"Masepina",
    "gn:population":0,
    "gn:timezone":"Africa/Freetown",
    "iso:country":"SL",
    "name:eng_x_preferred":[
        "Masepina"
    ],
    "wof:name":"Masepina",
    "wof:placetype":"locality"
},
  "geometry": {"coordinates":[-11.71919,9.26023],"type":"Point"}
}