{
  "type": "Feature",
  "properties": {
    "gn:admin1_code":"2.0",
    "gn:asciiname":"Kasanko",
    "gn:country_code":"SL",
    "gn:dem":16,
    "gn:feature_class":"P",
    "gn:feature_code":"PPL",
    "gn:name":"Kasanko",
    "gn:population":0,
    "gn:timezone":"Africa/Freetown",
    "iso:country":"SL",
    "name:eng_x_preferred":[
        "Kasanko"
    ],
    "wof:name":"Kasanko",
    "wof:placetype":"locality"
},
  "geometry": {"coordinates":[-12.95253,8.58227],"type":"Point"}
}