{
  "type": "Feature",
  "properties": {
    "gn:admin1_code":"01",
    "gn:asciiname":"Sawula",
    "gn:country_code":"SL",
    "gn:dem":142,
    "gn:feature_class":"P",
    "gn:feature_code":"PPL",
    "gn:name":"Sawula",
    "gn:population":0,
    "gn:timezone":"Africa/Freetown",
    "iso:country":"SL",
    "name:und_x_variant":[
        "Sawala",
        "Sawula"
    ],
    "wof:name":"Sawula",
    "wof:placetype":"locality"
},
  "geometry": {"coordinates":[-11.31068,7.95369],"type":"Point"}
}