{
  "type": "Feature",
  "properties": {
    "gn:admin1_code":"3.0",
    "gn:asciiname":"Saiama",
    "gn:country_code":"SL",
    "gn:dem":78,
    "gn:feature_class":"P",
    "gn:feature_code":"PPL",
    "gn:name":"Saiama",
    "gn:population":0,
    "gn:timezone":"Africa/Freetown",
    "iso:country":"SL",
    "name:eng_x_preferred":[
        "Saiama"
    ],
    "wof:name":"Saiama",
    "wof:placetype":"locality"
},
  "geometry": {"coordinates":[-11.3604,7.24827],"type":"Point"}
}