{
  "type": "Feature",
  "properties": {
    "gn:admin1_code":"3.0",
    "gn:asciiname":"Koilewa",
    "gn:country_code":"SL",
    "gn:dem":43,
    "gn:feature_class":"P",
    "gn:feature_code":"PPL",
    "gn:name":"Koilewa",
    "gn:population":0,
    "gn:timezone":"Africa/Freetown",
    "iso:country":"SL",
    "name:eng_x_preferred":[
        "Koilewa"
    ],
    "wof:name":"Koilewa",
    "wof:placetype":"locality"
},
  "geometry": {"coordinates":[-11.67429,7.20774],"type":"Point"}
}