{
  "type": "Feature",
  "properties": {
    "gn:admin1_code":"1.0",
    "gn:asciiname":"Dandu",
    "gn:country_code":"SL",
    "gn:dem":412,
    "gn:feature_class":"P",
    "gn:feature_code":"PPL",
    "gn:name":"Dandu",
    "gn:population":0,
    "gn:timezone":"Africa/Freetown",
    "iso:country":"SL",
    "name:eng_x_preferred":[
        "Dandu"
    ],
    "wof:name":"Dandu",
    "wof:placetype":"locality"
},
  "geometry": {"coordinates":[-11.06662,8.93388],"type":"Point"}
}