{
  "type": "Feature",
  "properties": {
    "gn:admin1_code":"3.0",
    "gn:asciiname":"Niahalahun",
    "gn:country_code":"SL",
    "gn:dem":85,
    "gn:feature_class":"P",
    "gn:feature_code":"PPL",
    "gn:name":"Niahalahun",
    "gn:population":0,
    "gn:timezone":"Africa/Freetown",
    "iso:country":"SL",
    "name:eng_x_preferred":[
        "Niahalahun"
    ],
    "wof:name":"Niahalahun",
    "wof:placetype":"locality"
},
  "geometry": {"coordinates":[-12.19918,8.16031],"type":"Point"}
}