{
  "type": "Feature",
  "properties": {
    "gn:admin1_code":"3.0",
    "gn:asciiname":"Jombohun",
    "gn:country_code":"SL",
    "gn:dem":91,
    "gn:feature_class":"P",
    "gn:feature_code":"PPL",
    "gn:name":"Jombohun",
    "gn:population":0,
    "gn:timezone":"Africa/Freetown",
    "iso:country":"SL",
    "name:und_x_variant":[
        "Jambohun"
    ],
    "wof:name":"Jombohun",
    "wof:placetype":"locality"
},
  "geometry": {"coordinates":[-11.64407,7.73199],"type":"Point"}
}