{
  "type": "Feature",
  "properties": {
    "gn:admin1_code":"3.0",
    "gn:asciiname":"Tikonko",
    "gn:country_code":"SL",
    "gn:dem":58,
    "gn:feature_class":"P",
    "gn:feature_code":"PPL",
    "gn:name":"Tikonko",
    "gn:population":0,
    "gn:timezone":"Africa/Freetown",
    "iso:country":"SL",
    "name:eng_x_preferred":[
        "Tikonko"
    ],
    "name:ukr_x_preferred":[
        "\u0422\u0456\u043a\u043e\u043d\u043a\u043e"
    ],
    "wof:name":"Tikonko",
    "wof:placetype":"locality"
},
  "geometry": {"coordinates":[-11.72783,7.49949],"type":"Point"}
}