{
  "type": "Feature",
  "properties": {
    "gn:admin1_code":"3.0",
    "gn:asciiname":"Gbanduma",
    "gn:country_code":"SL",
    "gn:dem":14,
    "gn:feature_class":"P",
    "gn:feature_code":"PPL",
    "gn:name":"Gbanduma",
    "gn:population":0,
    "gn:timezone":"Africa/Freetown",
    "iso:country":"SL",
    "name:eng_x_preferred":[
        "Gbanduma"
    ],
    "wof:name":"Gbanduma",
    "wof:placetype":"locality"
},
  "geometry": {"coordinates":[-12.13259,7.54093],"type":"Point"}
}