{
  "type": "Feature",
  "properties": {
    "gn:admin1_code":"3.0",
    "gn:asciiname":"Makemuma",
    "gn:country_code":"SL",
    "gn:dem":40,
    "gn:feature_class":"P",
    "gn:feature_code":"PPL",
    "gn:name":"Makemuma",
    "gn:population":0,
    "gn:timezone":"Africa/Freetown",
    "iso:country":"SL",
    "name:eng_x_preferred":[
        "Makemuma"
    ],
    "wof:name":"Makemuma",
    "wof:placetype":"locality"
},
  "geometry": {"coordinates":[-11.66033,7.41421],"type":"Point"}
}