{
  "type": "Feature",
  "properties": {
    "gn:admin1_code":"2.0",
    "gn:asciiname":"Bonga",
    "gn:country_code":"SL",
    "gn:dem":11,
    "gn:feature_class":"P",
    "gn:feature_code":"PPL",
    "gn:name":"Bonga",
    "gn:population":0,
    "gn:timezone":"Africa/Freetown",
    "iso:country":"SL",
    "name:eng_x_preferred":[
        "Bonga"
    ],
    "wof:name":"Bonga",
    "wof:placetype":"locality"
},
  "geometry": {"coordinates":[-13.20633,8.93263],"type":"Point"}
}