{
  "type": "Feature",
  "properties": {
    "gn:admin1_code":"2.0",
    "gn:asciiname":"Bonga",
    "gn:country_code":"SL",
    "gn:dem":11,
    "gn:feature_class":"P",
    "gn:feature_code":"PPL",
    "gn:name":"Bonga",
    "gn:population":0,
    "gn:timezone":"Africa/Freetown",
    "iso:country":"SL",
    "name:amh_x_preferred":[
        "\u1266\u1295\u130b"
    ],
    "name:deu_x_preferred":[
        "Bonga"
    ],
    "name:eng_x_preferred":[
        "Bonga"
    ],
    "name:fra_x_preferred":[
        "Bonga"
    ],
    "name:ita_x_preferred":[
        "Bonga"
    ],
    "name:pol_x_preferred":[
        "Bonga"
    ],
    "name:ron_x_preferred":[
        "Bonga"
    ],
    "name:rus_x_preferred":[
        "\u0411\u043e\u043d\u0433\u0430"
    ],
    "wof:name":"Bonga",
    "wof:placetype":"locality"
},
  "geometry": {"coordinates":[-13.20633,8.93263],"type":"Point"}
}