{
  "type": "Feature",
  "properties": {
    "gn:admin1_code":"3.0",
    "gn:asciiname":"Gorahun",
    "gn:country_code":"SL",
    "gn:dem":27,
    "gn:feature_class":"P",
    "gn:feature_code":"PPL",
    "gn:name":"Gorahun",
    "gn:population":0,
    "gn:timezone":"Africa/Freetown",
    "iso:country":"SL",
    "name:eng_x_preferred":[
        "Gorahun"
    ],
    "wof:name":"Gorahun",
    "wof:placetype":"locality"
},
  "geometry": {"coordinates":[-11.78468,7.39877],"type":"Point"}
}