{
  "type": "Feature",
  "properties": {
    "gn:admin1_code":"2.0",
    "gn:asciiname":"Mayanku",
    "gn:country_code":"SL",
    "gn:dem":71,
    "gn:feature_class":"P",
    "gn:feature_code":"PPL",
    "gn:name":"Mayanku",
    "gn:population":0,
    "gn:timezone":"Africa/Freetown",
    "iso:country":"SL",
    "name:eng_x_preferred":[
        "Mayanku"
    ],
    "wof:name":"Mayanku",
    "wof:placetype":"locality"
},
  "geometry": {"coordinates":[-12.43056,8.84623],"type":"Point"}
}