{
  "type": "Feature",
  "properties": {
    "gn:admin1_code":"2.0",
    "gn:asciiname":"Magbass",
    "gn:country_code":"SL",
    "gn:dem":111,
    "gn:feature_class":"P",
    "gn:feature_code":"PPL",
    "gn:name":"Magbass",
    "gn:population":0,
    "gn:timezone":"Africa/Freetown",
    "iso:country":"SL",
    "wof:name":"Magbass",
    "wof:placetype":"locality"
},
  "geometry": {"coordinates":[-11.94333,8.71694],"type":"Point"}
}