{
  "type": "Feature",
  "properties": {
    "gn:admin1_code":"2.0",
    "gn:asciiname":"Bucha",
    "gn:country_code":"SL",
    "gn:dem":65,
    "gn:feature_class":"P",
    "gn:feature_code":"PPL",
    "gn:name":"Bucha",
    "gn:population":0,
    "gn:timezone":"Africa/Freetown",
    "iso:country":"SL",
    "name:ceb_x_preferred":[
        "Bucha"
    ],
    "name:deu_x_preferred":[
        "Bucha"
    ],
    "name:eng_x_preferred":[
        "Bucha"
    ],
    "name:epo_x_preferred":[
        "Bucha"
    ],
    "name:eus_x_preferred":[
        "Bucha"
    ],
    "name:ita_x_preferred":[
        "Bucha"
    ],
    "name:nld_x_preferred":[
        "Bucha"
    ],
    "name:pol_x_preferred":[
        "Bucha"
    ],
    "name:por_x_preferred":[
        "Bucha"
    ],
    "name:rus_x_preferred":[
        "\u0411\u0443\u0447\u0430"
    ],
    "name:swe_x_preferred":[
        "Bucha"
    ],
    "name:ukr_x_preferred":[
        "\u0411\u0443\u0447\u0430"
    ],
    "name:vol_x_preferred":[
        "Bucha"
    ],
    "wof:name":"Bucha",
    "wof:placetype":"locality"
},
  "geometry": {"coordinates":[-12.8383,9.03138],"type":"Point"}
}