{
  "type": "Feature",
  "properties": {
    "gn:admin1_code":"3.0",
    "gn:asciiname":"Kongoworo",
    "gn:country_code":"SL",
    "gn:dem":73,
    "gn:feature_class":"P",
    "gn:feature_code":"PPL",
    "gn:name":"Kongoworo",
    "gn:population":0,
    "gn:timezone":"Africa/Freetown",
    "iso:country":"SL",
    "name:eng_x_preferred":[
        "Kongoworo"
    ],
    "wof:name":"Kongoworo",
    "wof:placetype":"locality"
},
  "geometry": {"coordinates":[-12.44595,8.14335],"type":"Point"}
}