{
  "type": "Feature",
  "properties": {
    "gn:admin1_code":"3.0",
    "gn:asciiname":"Jayewulo",
    "gn:country_code":"SL",
    "gn:dem":71,
    "gn:feature_class":"P",
    "gn:feature_code":"PPL",
    "gn:name":"Jayewulo",
    "gn:population":0,
    "gn:timezone":"Africa/Freetown",
    "iso:country":"SL",
    "name:eng_x_preferred":[
        "Jayewulo"
    ],
    "wof:name":"Jayewulo",
    "wof:placetype":"locality"
},
  "geometry": {"coordinates":[-11.65034,7.60659],"type":"Point"}
}