{
  "type": "Feature",
  "properties": {
    "gn:admin1_code":"2.0",
    "gn:asciiname":"Kuikonki",
    "gn:country_code":"SL",
    "gn:dem":11,
    "gn:feature_class":"P",
    "gn:feature_code":"PPL",
    "gn:name":"Kuikonki",
    "gn:population":0,
    "gn:timezone":"Africa/Freetown",
    "iso:country":"SL",
    "name:eng_x_preferred":[
        "Kuikonki"
    ],
    "wof:name":"Kuikonki",
    "wof:placetype":"locality"
},
  "geometry": {"coordinates":[-13.16001,8.90427],"type":"Point"}
}