{
  "type": "Feature",
  "properties": {
    "gn:admin1_code":"2.0",
    "gn:asciiname":"Katik",
    "gn:country_code":"SL",
    "gn:dem":15,
    "gn:feature_class":"P",
    "gn:feature_code":"PPL",
    "gn:name":"Katik",
    "gn:population":0,
    "gn:timezone":"Africa/Freetown",
    "iso:country":"SL",
    "name:eng_x_preferred":[
        "Katik"
    ],
    "wof:name":"Katik",
    "wof:placetype":"locality"
},
  "geometry": {"coordinates":[-13.12828,8.93636],"type":"Point"}
}