{
  "type": "Feature",
  "properties": {
    "gn:admin1_code":"2.0",
    "gn:asciiname":"Magbundo",
    "gn:country_code":"SL",
    "gn:dem":70,
    "gn:feature_class":"P",
    "gn:feature_code":"PPL",
    "gn:name":"Magbundo",
    "gn:population":0,
    "gn:timezone":"Africa/Freetown",
    "iso:country":"SL",
    "name:eng_x_preferred":[
        "Magbundo"
    ],
    "wof:name":"Magbundo",
    "wof:placetype":"locality"
},
  "geometry": {"coordinates":[-11.96341,8.40935],"type":"Point"}
}