{
  "type": "Feature",
  "properties": {
    "gn:admin1_code":"3.0",
    "gn:asciiname":"Kenema",
    "gn:country_code":"SL",
    "gn:dem":32,
    "gn:feature_class":"P",
    "gn:feature_code":"PPL",
    "gn:name":"Kenema",
    "gn:population":0,
    "gn:timezone":"Africa/Freetown",
    "iso:country":"SL",
    "name:eng_x_preferred":[
        "Kenema"
    ],
    "wof:name":"Kenema",
    "wof:placetype":"locality"
},
  "geometry": {"coordinates":[-11.4244,7.22616],"type":"Point"}
}