{
  "type": "Feature",
  "properties": {
    "gn:admin1_code":"2.0",
    "gn:asciiname":"Mayemi",
    "gn:country_code":"SL",
    "gn:dem":23,
    "gn:feature_class":"P",
    "gn:feature_code":"PPL",
    "gn:name":"Mayemi",
    "gn:population":0,
    "gn:timezone":"Africa/Freetown",
    "iso:country":"SL",
    "name:eng_x_preferred":[
        "Mayemi"
    ],
    "wof:name":"Mayemi",
    "wof:placetype":"locality"
},
  "geometry": {"coordinates":[-12.80518,8.69027],"type":"Point"}
}