{
  "type": "Feature",
  "properties": {
    "gn:admin1_code":"01",
    "gn:asciiname":"Yibema",
    "gn:country_code":"SL",
    "gn:dem":356,
    "gn:feature_class":"P",
    "gn:feature_code":"PPL",
    "gn:name":"Yibema",
    "gn:population":0,
    "gn:timezone":"Africa/Freetown",
    "iso:country":"SL",
    "name:eng_x_preferred":[
        "Yibema"
    ],
    "wof:name":"Yibema",
    "wof:placetype":"locality"
},
  "geometry": {"coordinates":[-10.47657,8.35677],"type":"Point"}
}