{
  "type": "Feature",
  "properties": {
    "gn:admin1_code":"2.0",
    "gn:asciiname":"Makapr",
    "gn:country_code":"SL",
    "gn:dem":84,
    "gn:feature_class":"P",
    "gn:feature_code":"PPL",
    "gn:name":"Makapr",
    "gn:population":0,
    "gn:timezone":"Africa/Freetown",
    "iso:country":"SL",
    "name:eng_x_preferred":[
        "Makapr"
    ],
    "wof:name":"Makapr",
    "wof:placetype":"locality"
},
  "geometry": {"coordinates":[-12.5187,8.91396],"type":"Point"}
}