{
  "type": "Feature",
  "properties": {
    "gn:admin1_code":"1.0",
    "gn:asciiname":"Gama",
    "gn:country_code":"SL",
    "gn:dem":150,
    "gn:feature_class":"P",
    "gn:feature_code":"PPL",
    "gn:name":"Gama",
    "gn:population":0,
    "gn:timezone":"Africa/Freetown",
    "iso:country":"SL",
    "name:ceb_x_preferred":[
        "Gama"
    ],
    "name:deu_x_preferred":[
        "Gama"
    ],
    "name:eus_x_preferred":[
        "Gama"
    ],
    "name:fra_x_preferred":[
        "Gama"
    ],
    "name:ita_x_preferred":[
        "Gama"
    ],
    "name:jpn_x_preferred":[
        "\u30ac\u30de"
    ],
    "name:kor_x_preferred":[
        "\uac00\ub9c8"
    ],
    "name:nld_x_preferred":[
        "Gama"
    ],
    "name:pol_x_preferred":[
        "Gama"
    ],
    "name:por_x_preferred":[
        "Gama"
    ],
    "name:sco_x_preferred":[
        "Gama"
    ],
    "name:slk_x_preferred":[
        "Gama"
    ],
    "name:spa_x_preferred":[
        "Gama"
    ],
    "name:swe_x_preferred":[
        "Gama"
    ],
    "name:tur_x_preferred":[
        "Gama"
    ],
    "name:und_x_variant":[
        "Gaama",
        "Gama"
    ],
    "wof:name":"Gama",
    "wof:placetype":"locality"
},
  "geometry": {"coordinates":[-11.21945,7.73318],"type":"Point"}
}