{
  "type": "Feature",
  "properties": {
    "gn:admin1_code":"1.0",
    "gn:asciiname":"Faabu",
    "gn:country_code":"SL",
    "gn:dem":202,
    "gn:feature_class":"P",
    "gn:feature_code":"PPL",
    "gn:name":"Faabu",
    "gn:population":0,
    "gn:timezone":"Africa/Freetown",
    "iso:country":"SL",
    "name:eng_x_preferred":[
        "Faabu"
    ],
    "wof:name":"Faabu",
    "wof:placetype":"locality"
},
  "geometry": {"coordinates":[-11.30434,8.21864],"type":"Point"}
}