{
  "type": "Feature",
  "properties": {
    "gn:admin1_code":"4.0",
    "gn:asciiname":"Hamilton",
    "gn:country_code":"SL",
    "gn:dem":18,
    "gn:feature_class":"P",
    "gn:feature_code":"PPL",
    "gn:name":"Hamilton",
    "gn:population":0,
    "gn:timezone":"Africa/Freetown",
    "iso:country":"SL",
    "name:und_x_variant":[
        "Kangbe",
        "Hamilton"
    ],
    "wof:name":"Hamilton",
    "wof:placetype":"locality"
},
  "geometry": {"coordinates":[-13.26052,8.38227],"type":"Point"}
}