{
  "type": "Feature",
  "properties": {
    "gn:admin1_code":"01",
    "gn:asciiname":"Sambalu",
    "gn:country_code":"SL",
    "gn:dem":292,
    "gn:feature_class":"P",
    "gn:feature_code":"PPL",
    "gn:name":"Sambalu",
    "gn:population":0,
    "gn:timezone":"Africa/Freetown",
    "iso:country":"SL",
    "name:eng_x_preferred":[
        "Sambalu"
    ],
    "wof:name":"Sambalu",
    "wof:placetype":"locality"
},
  "geometry": {"coordinates":[-10.60998,8.3361],"type":"Point"}
}