{
  "type": "Feature",
  "properties": {
    "gn:admin1_code":"2.0",
    "gn:asciiname":"Lambandi",
    "gn:country_code":"SL",
    "gn:dem":54,
    "gn:feature_class":"P",
    "gn:feature_code":"PPL",
    "gn:name":"Lambandi",
    "gn:population":0,
    "gn:timezone":"Africa/Freetown",
    "iso:country":"SL",
    "name:eng_x_preferred":[
        "Lambandi"
    ],
    "wof:name":"Lambandi",
    "wof:placetype":"locality"
},
  "geometry": {"coordinates":[-12.66626,9.43647],"type":"Point"}
}