{
  "type": "Feature",
  "properties": {
    "gn:admin1_code":"3.0",
    "gn:asciiname":"Mai",
    "gn:country_code":"SL",
    "gn:dem":6,
    "gn:feature_class":"P",
    "gn:feature_code":"PPL",
    "gn:name":"Mai",
    "gn:population":0,
    "gn:timezone":"Africa/Freetown",
    "iso:country":"SL",
    "name:als_x_preferred":[
        "Mai"
    ],
    "name:arg_x_preferred":[
        "Mai"
    ],
    "name:bar_x_preferred":[
        "Mai"
    ],
    "name:ceb_x_preferred":[
        "Mai"
    ],
    "name:deu_x_preferred":[
        "Mai"
    ],
    "name:eng_x_preferred":[
        "Mai"
    ],
    "name:fin_x_preferred":[
        "Mai"
    ],
    "name:fra_x_preferred":[
        "Mai"
    ],
    "name:lin_x_preferred":[
        "Mai"
    ],
    "name:nds_x_preferred":[
        "Mai"
    ],
    "name:nld_x_preferred":[
        "Mai"
    ],
    "name:nor_x_preferred":[
        "Mai"
    ],
    "name:pol_x_preferred":[
        "Mai"
    ],
    "name:spa_x_preferred":[
        "Mai"
    ],
    "name:vie_x_preferred":[
        "Mai"
    ],
    "wof:name":"Mai",
    "wof:placetype":"locality"
},
  "geometry": {"coordinates":[-12.45078,7.68076],"type":"Point"}
}