{
  "type": "Feature",
  "properties": {
    "gn:admin1_code":"3.0",
    "gn:asciiname":"Jomu",
    "gn:country_code":"SL",
    "gn:dem":90,
    "gn:feature_class":"P",
    "gn:feature_code":"PPL",
    "gn:name":"Jomu",
    "gn:population":0,
    "gn:timezone":"Africa/Freetown",
    "iso:country":"SL",
    "name:und_x_variant":[
        "Jumu",
        "Jomu",
        "Juma"
    ],
    "wof:name":"Jomu",
    "wof:placetype":"locality"
},
  "geometry": {"coordinates":[-11.62601,7.8717],"type":"Point"}
}