{
  "type": "Feature",
  "properties": {
    "gn:admin1_code":"02",
    "gn:asciiname":"Robat",
    "gn:country_code":"SL",
    "gn:dem":73,
    "gn:feature_class":"P",
    "gn:feature_code":"PPL",
    "gn:name":"Robat",
    "gn:population":0,
    "gn:timezone":"Africa/Freetown",
    "iso:country":"SL",
    "name:ara_x_preferred":[
        "\u0631\u0628\u0627\u0637"
    ],
    "name:aze_x_preferred":[
        "Rubat"
    ],
    "name:ceb_x_preferred":[
        "Rob\u0101\u0163-e M\u0101h\u012bdasht"
    ],
    "name:ckb_x_preferred":[
        "\u0695\u0628\u0627\u062a"
    ],
    "name:eng_x_preferred":[
        "Robat"
    ],
    "name:fas_x_preferred":[
        "\u0631\u0628\u0627\u0637"
    ],
    "name:fra_x_preferred":[
        "Robat"
    ],
    "name:mlg_x_preferred":[
        "Robat"
    ],
    "name:swe_x_preferred":[
        "Rob\u0101\u0163-e M\u0101h\u012bdasht"
    ],
    "name:tur_x_preferred":[
        "Rubat"
    ],
    "wof:name":"Robat",
    "wof:placetype":"locality"
},
  "geometry": {"coordinates":[-12.37863,9.37763],"type":"Point"}
}