{
  "type": "Feature",
  "properties": {
    "gn:admin1_code":"02",
    "gn:asciiname":"Sokurela",
    "gn:country_code":"SL",
    "gn:dem":505,
    "gn:feature_class":"P",
    "gn:feature_code":"PPL",
    "gn:name":"Sokurela",
    "gn:population":0,
    "gn:timezone":"Africa/Freetown",
    "iso:country":"SL",
    "name:eng_x_preferred":[
        "Sokurela"
    ],
    "wof:name":"Sokurela",
    "wof:placetype":"locality"
},
  "geometry": {"coordinates":[-10.86328,9.47376],"type":"Point"}
}