{
  "type": "Feature",
  "properties": {
    "gn:admin1_code":"02",
    "gn:asciiname":"Robunt",
    "gn:country_code":"SL",
    "gn:dem":54,
    "gn:feature_class":"P",
    "gn:feature_code":"PPL",
    "gn:name":"Robunt",
    "gn:population":0,
    "gn:timezone":"Africa/Freetown",
    "iso:country":"SL",
    "name:eng_x_preferred":[
        "Robunt"
    ],
    "wof:name":"Robunt",
    "wof:placetype":"locality"
},
  "geometry": {"coordinates":[-12.52727,8.53496],"type":"Point"}
}