{
  "type": "Feature",
  "properties": {
    "gn:admin1_code":"01",
    "gn:asciiname":"Sonigiema",
    "gn:country_code":"SL",
    "gn:dem":265,
    "gn:feature_class":"P",
    "gn:feature_code":"PPL",
    "gn:name":"Sonigiema",
    "gn:population":0,
    "gn:timezone":"Africa/Freetown",
    "iso:country":"SL",
    "name:eng_x_preferred":[
        "Sonigiema"
    ],
    "wof:name":"Sonigiema",
    "wof:placetype":"locality"
},
  "geometry": {"coordinates":[-10.92023,7.81407],"type":"Point"}
}