{
  "type": "Feature",
  "properties": {
    "gn:admin1_code":"2.0",
    "gn:asciiname":"Majackson",
    "gn:country_code":"SL",
    "gn:dem":25,
    "gn:feature_class":"P",
    "gn:feature_code":"PPL",
    "gn:name":"Majackson",
    "gn:population":0,
    "gn:timezone":"Africa/Freetown",
    "iso:country":"SL",
    "name:eng_x_preferred":[
        "Majackson"
    ],
    "wof:name":"Majackson",
    "wof:placetype":"locality"
},
  "geometry": {"coordinates":[-12.83965,8.52228],"type":"Point"}
}