{
  "type": "Feature",
  "properties": {
    "gn:admin1_code":"3.0",
    "gn:asciiname":"Mangobu",
    "gn:country_code":"SL",
    "gn:dem":68,
    "gn:feature_class":"P",
    "gn:feature_code":"PPL",
    "gn:name":"Mangobu",
    "gn:population":0,
    "gn:timezone":"Africa/Freetown",
    "iso:country":"SL",
    "name:eng_x_preferred":[
        "Mangobu"
    ],
    "wof:name":"Mangobu",
    "wof:placetype":"locality"
},
  "geometry": {"coordinates":[-12.33926,8.13859],"type":"Point"}
}