{
  "type": "Feature",
  "properties": {
    "gn:admin1_code":"1.0",
    "gn:asciiname":"Kondema",
    "gn:country_code":"SL",
    "gn:dem":252,
    "gn:feature_class":"P",
    "gn:feature_code":"PPL",
    "gn:name":"Kondema",
    "gn:population":0,
    "gn:timezone":"Africa/Freetown",
    "iso:country":"SL",
    "name:eng_x_preferred":[
        "Kondema"
    ],
    "name:und_x_variant":[
        "Kpendema"
    ],
    "wof:name":"Kondema",
    "wof:placetype":"locality"
},
  "geometry": {"coordinates":[-10.84051,8.44269],"type":"Point"}
}