{
  "type": "Feature",
  "properties": {
    "gn:admin1_code":"3.0",
    "gn:asciiname":"Bumpe",
    "gn:country_code":"SL",
    "gn:dem":40,
    "gn:feature_class":"P",
    "gn:feature_code":"PPL",
    "gn:name":"Bumpe",
    "gn:population":0,
    "gn:timezone":"Africa/Freetown",
    "iso:country":"SL",
    "name:ceb_x_preferred":[
        "Bumpe"
    ],
    "name:deu_x_preferred":[
        "Bumpe"
    ],
    "name:fra_x_preferred":[
        "Bumpe"
    ],
    "name:pol_x_preferred":[
        "Bumpe"
    ],
    "name:rus_x_preferred":[
        "\u0411\u0443\u043c\u043f\u0435"
    ],
    "name:ukr_x_preferred":[
        "\u0411\u0443\u043c\u043f\u0435"
    ],
    "name:und_x_variant":[
        "Bumbe"
    ],
    "wof:name":"Bumpe",
    "wof:placetype":"locality"
},
  "geometry": {"coordinates":[-11.56447,7.28389],"type":"Point"}
}