{
  "type": "Feature",
  "properties": {
    "gn:admin1_code":"3.0",
    "gn:asciiname":"Batahol",
    "gn:country_code":"SL",
    "gn:dem":12,
    "gn:feature_class":"P",
    "gn:feature_code":"PPL",
    "gn:name":"Batahol",
    "gn:population":0,
    "gn:timezone":"Africa/Freetown",
    "iso:country":"SL",
    "name:eng_x_preferred":[
        "Batahol"
    ],
    "wof:name":"Batahol",
    "wof:placetype":"locality"
},
  "geometry": {"coordinates":[-12.17603,7.36891],"type":"Point"}
}