{
  "type": "Feature",
  "properties": {
    "gn:admin1_code":"3.0",
    "gn:asciiname":"Baomahun",
    "gn:country_code":"SL",
    "gn:dem":49,
    "gn:feature_class":"P",
    "gn:feature_code":"PPL",
    "gn:name":"Baomahun",
    "gn:population":0,
    "gn:timezone":"Africa/Freetown",
    "iso:country":"SL",
    "name:eng_x_preferred":[
        "Baomahun"
    ],
    "wof:name":"Baomahun",
    "wof:placetype":"locality"
},
  "geometry": {"coordinates":[-11.95488,8.04565],"type":"Point"}
}