{
  "type": "Feature",
  "properties": {
    "gn:admin1_code":"3.0",
    "gn:asciiname":"Buya",
    "gn:country_code":"SL",
    "gn:dem":63,
    "gn:feature_class":"P",
    "gn:feature_code":"PPL",
    "gn:name":"Buya",
    "gn:population":0,
    "gn:timezone":"Africa/Freetown",
    "iso:country":"SL",
    "name:eng_x_preferred":[
        "Buya"
    ],
    "wof:name":"Buya",
    "wof:placetype":"locality"
},
  "geometry": {"coordinates":[-12.2889,8.32126],"type":"Point"}
}