{
  "type": "Feature",
  "properties": {
    "gn:admin1_code":"2.0",
    "gn:asciiname":"Maseka",
    "gn:country_code":"SL",
    "gn:dem":83,
    "gn:feature_class":"P",
    "gn:feature_code":"PPL",
    "gn:name":"Maseka",
    "gn:population":0,
    "gn:timezone":"Africa/Freetown",
    "iso:country":"SL",
    "name:eng_x_preferred":[
        "Maseka"
    ],
    "wof:name":"Maseka",
    "wof:placetype":"locality"
},
  "geometry": {"coordinates":[-12.49258,8.65932],"type":"Point"}
}