{
  "type": "Feature",
  "properties": {
    "gn:admin1_code":"1.0",
    "gn:asciiname":"Pendembu",
    "gn:country_code":"SL",
    "gn:dem":146,
    "gn:feature_class":"P",
    "gn:feature_code":"PPL",
    "gn:name":"Pendembu",
    "gn:population":0,
    "gn:timezone":"Africa/Freetown",
    "iso:country":"SL",
    "name:eng_x_preferred":[
        "Pendembu"
    ],
    "wof:name":"Pendembu",
    "wof:placetype":"locality"
},
  "geometry": {"coordinates":[-11.21773,7.76127],"type":"Point"}
}