{
  "type": "Feature",
  "properties": {
    "gn:admin1_code":"2.0",
    "gn:asciiname":"Kondita",
    "gn:country_code":"SL",
    "gn:dem":147,
    "gn:feature_class":"P",
    "gn:feature_code":"PPL",
    "gn:name":"Kondita",
    "gn:population":0,
    "gn:timezone":"Africa/Freetown",
    "iso:country":"SL",
    "name:eng_x_preferred":[
        "Kondita"
    ],
    "wof:name":"Kondita",
    "wof:placetype":"locality"
},
  "geometry": {"coordinates":[-12.01357,9.87064],"type":"Point"}
}