{
  "type": "Feature",
  "properties": {
    "gn:admin1_code":"02",
    "gn:asciiname":"Timbo",
    "gn:country_code":"SL",
    "gn:dem":88,
    "gn:feature_class":"P",
    "gn:feature_code":"PPL",
    "gn:name":"Timbo",
    "gn:population":0,
    "gn:timezone":"Africa/Freetown",
    "iso:country":"SL",
    "name:ara_x_preferred":[
        "\u062a\u064a\u0645\u0628\u0648"
    ],
    "name:cat_x_preferred":[
        "Timbo"
    ],
    "name:eng_x_preferred":[
        "Timbo"
    ],
    "name:fra_x_preferred":[
        "Timbo"
    ],
    "name:ita_x_preferred":[
        "Timbo"
    ],
    "name:msa_x_preferred":[
        "Timbo"
    ],
    "name:spa_x_preferred":[
        "Timbo"
    ],
    "wof:name":"Timbo",
    "wof:placetype":"locality"
},
  "geometry": {"coordinates":[-12.56135,9.14752],"type":"Point"}
}