{
  "type": "Feature",
  "properties": {
    "gn:admin1_code":"2.0",
    "gn:asciiname":"Mafinka",
    "gn:country_code":"SL",
    "gn:dem":42,
    "gn:feature_class":"P",
    "gn:feature_code":"PPL",
    "gn:name":"Mafinka",
    "gn:population":0,
    "gn:timezone":"Africa/Freetown",
    "iso:country":"SL",
    "name:eng_x_preferred":[
        "Mafinka"
    ],
    "wof:name":"Mafinka",
    "wof:placetype":"locality"
},
  "geometry": {"coordinates":[-12.88155,8.89607],"type":"Point"}
}