{
  "type": "Feature",
  "properties": {
    "gn:admin1_code":"2.0",
    "gn:asciiname":"Shota",
    "gn:country_code":"SL",
    "gn:dem":179,
    "gn:feature_class":"P",
    "gn:feature_code":"PPL",
    "gn:name":"Shota",
    "gn:population":0,
    "gn:timezone":"Africa/Freetown",
    "iso:country":"SL",
    "name:eng_x_preferred":[
        "Shota"
    ],
    "name:ita_x_preferred":[
        "Shota"
    ],
    "name:kat_x_preferred":[
        "\u10e8\u10dd\u10d7\u10d0"
    ],
    "wof:name":"Shota",
    "wof:placetype":"locality"
},
  "geometry": {"coordinates":[-12.235,9.22721],"type":"Point"}
}