{
  "type": "Feature",
  "properties": {
    "gn:admin1_code":"02",
    "gn:asciiname":"Yankone",
    "gn:country_code":"SL",
    "gn:dem":85,
    "gn:feature_class":"P",
    "gn:feature_code":"PPL",
    "gn:name":"Yankone",
    "gn:population":0,
    "gn:timezone":"Africa/Freetown",
    "iso:country":"SL",
    "name:eng_x_preferred":[
        "Yankone"
    ],
    "wof:name":"Yankone",
    "wof:placetype":"locality"
},
  "geometry": {"coordinates":[-12.55479,9.53965],"type":"Point"}
}