{
  "type": "Feature",
  "properties": {
    "gn:admin1_code":"2.0",
    "gn:asciiname":"Fodia",
    "gn:country_code":"SL",
    "gn:dem":85,
    "gn:feature_class":"P",
    "gn:feature_code":"PPL",
    "gn:name":"Fodia",
    "gn:population":0,
    "gn:timezone":"Africa/Freetown",
    "iso:country":"SL",
    "name:eng_x_preferred":[
        "Fodia"
    ],
    "wof:name":"Fodia",
    "wof:placetype":"locality"
},
  "geometry": {"coordinates":[-12.44756,9.71219],"type":"Point"}
}