{
  "type": "Feature",
  "properties": {
    "gn:admin1_code":"2.0",
    "gn:asciiname":"Kasengbe",
    "gn:country_code":"SL",
    "gn:dem":116,
    "gn:feature_class":"P",
    "gn:feature_code":"PPL",
    "gn:name":"Kasengbe",
    "gn:population":0,
    "gn:timezone":"Africa/Freetown",
    "iso:country":"SL",
    "name:eng_x_preferred":[
        "Kasengbe"
    ],
    "wof:name":"Kasengbe",
    "wof:placetype":"locality"
},
  "geometry": {"coordinates":[-11.87871,9.07108],"type":"Point"}
}