{
  "type": "Feature",
  "properties": {
    "gn:admin1_code":"2.0",
    "gn:asciiname":"Magbila",
    "gn:country_code":"SL",
    "gn:dem":65,
    "gn:feature_class":"P",
    "gn:feature_code":"PPL",
    "gn:name":"Magbila",
    "gn:population":0,
    "gn:timezone":"Africa/Freetown",
    "iso:country":"SL",
    "name:eng_x_preferred":[
        "Magbila"
    ],
    "wof:name":"Magbila",
    "wof:placetype":"locality"
},
  "geometry": {"coordinates":[-12.4035,8.33706],"type":"Point"}
}