{
  "type": "Feature",
  "properties": {
    "gn:admin1_code":"2.0",
    "gn:asciiname":"Fotane",
    "gn:country_code":"SL",
    "gn:dem":317,
    "gn:feature_class":"P",
    "gn:feature_code":"PPL",
    "gn:name":"Fotane",
    "gn:population":0,
    "gn:timezone":"Africa/Freetown",
    "iso:country":"SL",
    "name:eng_x_preferred":[
        "Fotane"
    ],
    "wof:name":"Fotane",
    "wof:placetype":"locality"
},
  "geometry": {"coordinates":[-11.64566,8.59525],"type":"Point"}
}