{
  "type": "Feature",
  "properties": {
    "gn:admin1_code":"2.0",
    "gn:asciiname":"Mabingbira",
    "gn:country_code":"SL",
    "gn:dem":32,
    "gn:feature_class":"P",
    "gn:feature_code":"PPL",
    "gn:name":"Mabingbira",
    "gn:population":0,
    "gn:timezone":"Africa/Freetown",
    "iso:country":"SL",
    "name:eng_x_preferred":[
        "Mabingbira"
    ],
    "wof:name":"Mabingbira",
    "wof:placetype":"locality"
},
  "geometry": {"coordinates":[-12.81016,8.59003],"type":"Point"}
}