{
  "type": "Feature",
  "properties": {
    "gn:admin1_code":"2.0",
    "gn:asciiname":"Yiben",
    "gn:country_code":"SL",
    "gn:dem":82,
    "gn:feature_class":"P",
    "gn:feature_code":"PPL",
    "gn:name":"Yiben",
    "gn:population":0,
    "gn:timezone":"Africa/Freetown",
    "iso:country":"SL",
    "name:eng_x_preferred":[
        "Yiben"
    ],
    "wof:name":"Yiben",
    "wof:placetype":"locality"
},
  "geometry": {"coordinates":[-12.42604,8.50706],"type":"Point"}
}