{
  "type": "Feature",
  "properties": {
    "gn:admin1_code":"1.0",
    "gn:asciiname":"Fuyero",
    "gn:country_code":"SL",
    "gn:dem":427,
    "gn:feature_class":"P",
    "gn:feature_code":"PPL",
    "gn:name":"Fuyero",
    "gn:population":0,
    "gn:timezone":"Africa/Freetown",
    "iso:country":"SL",
    "name:eng_x_preferred":[
        "Fuyero"
    ],
    "wof:name":"Fuyero",
    "wof:placetype":"locality"
},
  "geometry": {"coordinates":[-10.92222,8.7628],"type":"Point"}
}