{
  "type": "Feature",
  "properties": {
    "gn:admin1_code":"3.0",
    "gn:asciiname":"Masaila",
    "gn:country_code":"SL",
    "gn:dem":78,
    "gn:feature_class":"P",
    "gn:feature_code":"PPL",
    "gn:name":"Masaila",
    "gn:population":0,
    "gn:timezone":"Africa/Freetown",
    "iso:country":"SL",
    "name:eng_x_preferred":[
        "Masaila"
    ],
    "wof:name":"Masaila",
    "wof:placetype":"locality"
},
  "geometry": {"coordinates":[-11.46528,7.46443],"type":"Point"}
}