{
  "type": "Feature",
  "properties": {
    "gn:admin1_code":"2.0",
    "gn:asciiname":"Masama",
    "gn:country_code":"SL",
    "gn:dem":119,
    "gn:feature_class":"P",
    "gn:feature_code":"PPL",
    "gn:name":"Masama",
    "gn:population":0,
    "gn:timezone":"Africa/Freetown",
    "iso:country":"SL",
    "name:eng_x_preferred":[
        "Masama"
    ],
    "wof:name":"Masama",
    "wof:placetype":"locality"
},
  "geometry": {"coordinates":[-12.20821,9.26558],"type":"Point"}
}