{
  "type": "Feature",
  "properties": {
    "gn:admin1_code":"1.0",
    "gn:asciiname":"Lecrela",
    "gn:country_code":"SL",
    "gn:dem":155,
    "gn:feature_class":"P",
    "gn:feature_code":"PPL",
    "gn:name":"Lecrela",
    "gn:population":0,
    "gn:timezone":"Africa/Freetown",
    "iso:country":"SL",
    "name:eng_x_preferred":[
        "Lecrela"
    ],
    "wof:name":"Lecrela",
    "wof:placetype":"locality"
},
  "geometry": {"coordinates":[-11.20999,7.49098],"type":"Point"}
}