{
  "type": "Feature",
  "properties": {
    "gn:admin1_code":"3.0",
    "gn:asciiname":"Moservice",
    "gn:country_code":"SL",
    "gn:dem":34,
    "gn:feature_class":"P",
    "gn:feature_code":"PPL",
    "gn:name":"Moservice",
    "gn:population":0,
    "gn:timezone":"Africa/Freetown",
    "iso:country":"SL",
    "name:eng_x_preferred":[
        "Moservice"
    ],
    "wof:name":"Moservice",
    "wof:placetype":"locality"
},
  "geometry": {"coordinates":[-12.73006,8.24276],"type":"Point"}
}