{
  "type": "Feature",
  "properties": {
    "gn:admin1_code":"2.0",
    "gn:asciiname":"Masaibu",
    "gn:country_code":"SL",
    "gn:dem":55,
    "gn:feature_class":"P",
    "gn:feature_code":"PPL",
    "gn:name":"Masaibu",
    "gn:population":0,
    "gn:timezone":"Africa/Freetown",
    "iso:country":"SL",
    "name:eng_x_preferred":[
        "Masaibu"
    ],
    "wof:name":"Masaibu",
    "wof:placetype":"locality"
},
  "geometry": {"coordinates":[-12.83674,8.89696],"type":"Point"}
}