{
  "type": "Feature",
  "properties": {
    "gn:admin1_code":"3.0",
    "gn:asciiname":"Mosebua",
    "gn:country_code":"SL",
    "gn:dem":26,
    "gn:feature_class":"P",
    "gn:feature_code":"PPL",
    "gn:name":"Mosebua",
    "gn:population":0,
    "gn:timezone":"Africa/Freetown",
    "iso:country":"SL",
    "name:eng_x_preferred":[
        "Mosebua"
    ],
    "wof:name":"Mosebua",
    "wof:placetype":"locality"
},
  "geometry": {"coordinates":[-12.61346,7.91373],"type":"Point"}
}