{
  "type": "Feature",
  "properties": {
    "gn:admin1_code":"2.0",
    "gn:asciiname":"Masiaka",
    "gn:country_code":"SL",
    "gn:dem":49,
    "gn:feature_class":"P",
    "gn:feature_code":"PPL",
    "gn:name":"Masiaka",
    "gn:population":0,
    "gn:timezone":"Africa/Freetown",
    "iso:country":"SL",
    "wof:name":"Masiaka",
    "wof:placetype":"locality"
},
  "geometry": {"coordinates":[-12.7875,8.76667],"type":"Point"}
}