{
  "type": "Feature",
  "properties": {
    "gn:admin1_code":"02",
    "gn:asciiname":"Rokamp",
    "gn:country_code":"SL",
    "gn:dem":73,
    "gn:feature_class":"P",
    "gn:feature_code":"PPL",
    "gn:name":"Rokamp",
    "gn:population":0,
    "gn:timezone":"Africa/Freetown",
    "iso:country":"SL",
    "name:eng_x_preferred":[
        "Rokamp"
    ],
    "wof:name":"Rokamp",
    "wof:placetype":"locality"
},
  "geometry": {"coordinates":[-12.20058,8.60835],"type":"Point"}
}