{
  "type": "Feature",
  "properties": {
    "gn:admin1_code":"3.0",
    "gn:asciiname":"Nduvuibu",
    "gn:country_code":"SL",
    "gn:dem":55,
    "gn:feature_class":"P",
    "gn:feature_code":"PPL",
    "gn:name":"Nduvuibu",
    "gn:population":0,
    "gn:timezone":"Africa/Freetown",
    "iso:country":"SL",
    "name:eng_x_preferred":[
        "Nduvuibu"
    ],
    "wof:name":"Nduvuibu",
    "wof:placetype":"locality"
},
  "geometry": {"coordinates":[-12.14269,7.95175],"type":"Point"}
}