{
  "type": "Feature",
  "properties": {
    "gn:admin1_code":"2.0",
    "gn:asciiname":"Benikoro",
    "gn:country_code":"SL",
    "gn:dem":482,
    "gn:feature_class":"P",
    "gn:feature_code":"PPL",
    "gn:name":"Benikoro",
    "gn:population":0,
    "gn:timezone":"Africa/Freetown",
    "iso:country":"SL",
    "name:eng_x_preferred":[
        "Benikoro"
    ],
    "wof:name":"Benikoro",
    "wof:placetype":"locality"
},
  "geometry": {"coordinates":[-11.09639,9.46793],"type":"Point"}
}