{
  "type": "Feature",
  "properties": {
    "gn:admin1_code":"3.0",
    "gn:asciiname":"Hagbahun",
    "gn:country_code":"SL",
    "gn:dem":147,
    "gn:feature_class":"P",
    "gn:feature_code":"PPL",
    "gn:name":"Hagbahun",
    "gn:population":0,
    "gn:timezone":"Africa/Freetown",
    "iso:country":"SL",
    "name:eng_x_preferred":[
        "Hagbahun"
    ],
    "wof:name":"Hagbahun",
    "wof:placetype":"locality"
},
  "geometry": {"coordinates":[-11.35105,8.05563],"type":"Point"}
}