{
  "type": "Feature",
  "properties": {
    "gn:admin1_code":"02",
    "gn:asciiname":"Tengeden",
    "gn:country_code":"SL",
    "gn:dem":349,
    "gn:feature_class":"P",
    "gn:feature_code":"PPL",
    "gn:name":"Tengeden",
    "gn:population":0,
    "gn:timezone":"Africa/Freetown",
    "iso:country":"SL",
    "name:eng_x_preferred":[
        "Tengeden"
    ],
    "wof:name":"Tengeden",
    "wof:placetype":"locality"
},
  "geometry": {"coordinates":[-11.84411,9.94674],"type":"Point"}
}