{
  "type": "Feature",
  "properties": {
    "gn:admin1_code":"3.0",
    "gn:asciiname":"Jaiyahun Junction",
    "gn:country_code":"SL",
    "gn:dem":135,
    "gn:feature_class":"P",
    "gn:feature_code":"PPL",
    "gn:name":"Jaiyahun Junction",
    "gn:population":0,
    "gn:timezone":"Africa/Freetown",
    "iso:country":"SL",
    "name:eng_x_preferred":[
        "Jaiyahun Junction"
    ],
    "name:eng_x_variant":[
        "Sieromco Mokanje"
    ],
    "wof:name":"Jaiyahun Junction",
    "wof:placetype":"locality"
},
  "geometry": {"coordinates":[-12.19355,7.90008],"type":"Point"}
}