{
  "type": "Feature",
  "properties": {
    "gn:admin1_code":"1.0",
    "gn:asciiname":"Kongombadu",
    "gn:country_code":"SL",
    "gn:dem":379,
    "gn:feature_class":"P",
    "gn:feature_code":"PPL",
    "gn:name":"Kongombadu",
    "gn:population":0,
    "gn:timezone":"Africa/Freetown",
    "iso:country":"SL",
    "name:eng_x_preferred":[
        "Kongombadu"
    ],
    "name:und_x_variant":[
        "Konkombadu"
    ],
    "wof:name":"Kongombadu",
    "wof:placetype":"locality"
},
  "geometry": {"coordinates":[-11.15273,8.72429],"type":"Point"}
}