{
  "type": "Feature",
  "properties": {
    "gn:admin1_code":"3.0",
    "gn:asciiname":"Jelu",
    "gn:country_code":"SL",
    "gn:dem":258,
    "gn:feature_class":"P",
    "gn:feature_code":"PPL",
    "gn:name":"Jelu",
    "gn:population":0,
    "gn:timezone":"Africa/Freetown",
    "iso:country":"SL",
    "name:eng_x_preferred":[
        "Jelu"
    ],
    "name:und_x_variant":[
        "Jeru"
    ],
    "wof:name":"Jelu",
    "wof:placetype":"locality"
},
  "geometry": {"coordinates":[-11.40962,8.14835],"type":"Point"}
}