{
  "type": "Feature",
  "properties": {
    "gn:admin1_code":"2.0",
    "gn:asciiname":"Dar es Salaam",
    "gn:country_code":"SL",
    "gn:dem":24,
    "gn:feature_class":"P",
    "gn:feature_code":"PPL",
    "gn:name":"Dar es Salaam",
    "gn:population":0,
    "gn:timezone":"Africa/Freetown",
    "iso:country":"SL",
    "name:eng_x_preferred":[
        "Dar es Salaam"
    ],
    "wof:name":"Dar es Salaam",
    "wof:placetype":"locality"
},
  "geometry": {"coordinates":[-13.01263,9.00519],"type":"Point"}
}