{
  "type": "Feature",
  "properties": {
    "gn:admin1_code":"2.0",
    "gn:asciiname":"Kurankoya",
    "gn:country_code":"SL",
    "gn:dem":35,
    "gn:feature_class":"P",
    "gn:feature_code":"PPL",
    "gn:name":"Kurankoya",
    "gn:population":0,
    "gn:timezone":"Africa/Freetown",
    "iso:country":"SL",
    "name:eng_x_preferred":[
        "Kurankoya"
    ],
    "wof:name":"Kurankoya",
    "wof:placetype":"locality"
},
  "geometry": {"coordinates":[-13.19871,8.64401],"type":"Point"}
}