{
  "type": "Feature",
  "properties": {
    "gn:admin1_code":"2.0",
    "gn:asciiname":"Masoko",
    "gn:country_code":"SL",
    "gn:dem":75,
    "gn:feature_class":"P",
    "gn:feature_code":"PPL",
    "gn:name":"Masoko",
    "gn:population":0,
    "gn:timezone":"Africa/Freetown",
    "iso:country":"SL",
    "name:eng_x_preferred":[
        "Masoko"
    ],
    "wof:name":"Masoko",
    "wof:placetype":"locality"
},
  "geometry": {"coordinates":[-12.53208,8.73844],"type":"Point"}
}