{
  "type": "Feature",
  "properties": {
    "gn:admin1_code":"3.0",
    "gn:asciiname":"Kebawana",
    "gn:country_code":"SL",
    "gn:dem":62,
    "gn:feature_class":"P",
    "gn:feature_code":"PPL",
    "gn:name":"Kebawana",
    "gn:population":0,
    "gn:timezone":"Africa/Freetown",
    "iso:country":"SL",
    "name:eng_x_preferred":[
        "Kebawana"
    ],
    "wof:name":"Kebawana",
    "wof:placetype":"locality"
},
  "geometry": {"coordinates":[-11.34721,7.18839],"type":"Point"}
}