{
  "type": "Feature",
  "properties": {
    "gn:admin1_code":"02",
    "gn:asciiname":"Tikump",
    "gn:country_code":"SL",
    "gn:dem":17,
    "gn:feature_class":"P",
    "gn:feature_code":"PPL",
    "gn:name":"Tikump",
    "gn:population":0,
    "gn:timezone":"Africa/Freetown",
    "iso:country":"SL",
    "name:eng_x_preferred":[
        "Tikump"
    ],
    "wof:name":"Tikump",
    "wof:placetype":"locality"
},
  "geometry": {"coordinates":[-12.95616,8.52906],"type":"Point"}
}