{
  "type": "Feature",
  "properties": {
    "gn:admin1_code":"01",
    "gn:asciiname":"Suagolu",
    "gn:country_code":"SL",
    "gn:dem":294,
    "gn:feature_class":"P",
    "gn:feature_code":"PPL",
    "gn:name":"Suagolu",
    "gn:population":0,
    "gn:timezone":"Africa/Freetown",
    "iso:country":"SL",
    "wof:name":"Suagolu",
    "wof:placetype":"locality"
},
  "geometry": {"coordinates":[-10.58333,8.33333],"type":"Point"}
}