{
  "type": "Feature",
  "properties": {
    "gn:admin1_code":"2.0",
    "gn:asciiname":"Wangi",
    "gn:country_code":"SL",
    "gn:dem":136,
    "gn:feature_class":"P",
    "gn:feature_code":"PPL",
    "gn:name":"Wangi",
    "gn:population":0,
    "gn:timezone":"Africa/Freetown",
    "iso:country":"SL",
    "name:eng_x_preferred":[
        "Wangi"
    ],
    "wof:name":"Wangi",
    "wof:placetype":"locality"
},
  "geometry": {"coordinates":[-12.06876,9.25671],"type":"Point"}
}