{
  "type": "Feature",
  "properties": {
    "gn:admin1_code":"2.0",
    "gn:asciiname":"Gbanabe",
    "gn:country_code":"SL",
    "gn:dem":79,
    "gn:feature_class":"P",
    "gn:feature_code":"PPL",
    "gn:name":"Gbanabe",
    "gn:population":0,
    "gn:timezone":"Africa/Freetown",
    "iso:country":"SL",
    "name:eng_x_preferred":[
        "Gbanabe"
    ],
    "wof:name":"Gbanabe",
    "wof:placetype":"locality"
},
  "geometry": {"coordinates":[-12.45971,8.72125],"type":"Point"}
}