{
  "type": "Feature",
  "properties": {
    "gn:admin1_code":"3.0",
    "gn:asciiname":"Nyamaina",
    "gn:country_code":"SL",
    "gn:dem":177,
    "gn:feature_class":"P",
    "gn:feature_code":"PPL",
    "gn:name":"Nyamaina",
    "gn:population":0,
    "gn:timezone":"Africa/Freetown",
    "iso:country":"SL",
    "name:eng_x_preferred":[
        "Nyamaina"
    ],
    "wof:name":"Nyamaina",
    "wof:placetype":"locality"
},
  "geometry": {"coordinates":[-12.44049,8.05956],"type":"Point"}
}