{
  "type": "Feature",
  "properties": {
    "gn:admin1_code":"2.0",
    "gn:asciiname":"Kafukuta",
    "gn:country_code":"SL",
    "gn:dem":194,
    "gn:feature_class":"P",
    "gn:feature_code":"PPL",
    "gn:name":"Kafukuta",
    "gn:population":0,
    "gn:timezone":"Africa/Freetown",
    "iso:country":"SL",
    "name:eng_x_preferred":[
        "Kafukuta"
    ],
    "wof:name":"Kafukuta",
    "wof:placetype":"locality"
},
  "geometry": {"coordinates":[-11.88044,9.21103],"type":"Point"}
}