{
  "type": "Feature",
  "properties": {
    "gn:admin1_code":"2.0",
    "gn:asciiname":"Bura",
    "gn:country_code":"SL",
    "gn:dem":81,
    "gn:feature_class":"P",
    "gn:feature_code":"PPL",
    "gn:name":"Bura",
    "gn:population":0,
    "gn:timezone":"Africa/Freetown",
    "iso:country":"SL",
    "name:ceb_x_preferred":[
        "Bura"
    ],
    "name:deu_x_preferred":[
        "Bura"
    ],
    "name:eng_x_preferred":[
        "Bura"
    ],
    "name:fra_x_preferred":[
        "Bura"
    ],
    "name:hrv_x_preferred":[
        "Bura"
    ],
    "name:rus_x_preferred":[
        "\u0411\u0443\u0440\u0430"
    ],
    "name:srp_x_preferred":[
        "Bura"
    ],
    "name:swe_x_preferred":[
        "Bura"
    ],
    "name:ukr_x_preferred":[
        "\u0411\u0443\u0440\u0430"
    ],
    "name:vie_x_preferred":[
        "Bura"
    ],
    "wof:name":"Bura",
    "wof:placetype":"locality"
},
  "geometry": {"coordinates":[-12.47312,8.80288],"type":"Point"}
}