{
  "type": "Feature",
  "properties": {
    "gn:admin1_code":"3.0",
    "gn:asciiname":"Mafulumu",
    "gn:country_code":"SL",
    "gn:dem":29,
    "gn:feature_class":"P",
    "gn:feature_code":"PPL",
    "gn:name":"Mafulumu",
    "gn:population":0,
    "gn:timezone":"Africa/Freetown",
    "iso:country":"SL",
    "name:eng_x_preferred":[
        "Mafulumu"
    ],
    "wof:name":"Mafulumu",
    "wof:placetype":"locality"
},
  "geometry": {"coordinates":[-12.67922,8.36726],"type":"Point"}
}