{
  "type": "Feature",
  "properties": {
    "gn:admin1_code":"1.0",
    "gn:asciiname":"Jolu",
    "gn:country_code":"SL",
    "gn:dem":158,
    "gn:feature_class":"P",
    "gn:feature_code":"PPL",
    "gn:name":"Jolu",
    "gn:population":0,
    "gn:timezone":"Africa/Freetown",
    "iso:country":"SL",
    "name:und_x_variant":[
        "Joru",
        "Jolu"
    ],
    "wof:name":"Jolu",
    "wof:placetype":"locality"
},
  "geometry": {"coordinates":[-11.25709,7.94461],"type":"Point"}
}