{
  "type": "Feature",
  "properties": {
    "gn:admin1_code":"2.0",
    "gn:asciiname":"Makobolo",
    "gn:country_code":"SL",
    "gn:dem":87,
    "gn:feature_class":"P",
    "gn:feature_code":"PPL",
    "gn:name":"Makobolo",
    "gn:population":0,
    "gn:timezone":"Africa/Freetown",
    "iso:country":"SL",
    "name:eng_x_preferred":[
        "Makobolo"
    ],
    "wof:name":"Makobolo",
    "wof:placetype":"locality"
},
  "geometry": {"coordinates":[-11.93382,8.49501],"type":"Point"}
}