{
  "type": "Feature",
  "properties": {
    "gn:admin1_code":"1.0",
    "gn:asciiname":"Bundobu",
    "gn:country_code":"SL",
    "gn:dem":239,
    "gn:feature_class":"P",
    "gn:feature_code":"PPL",
    "gn:name":"Bundobu",
    "gn:population":0,
    "gn:timezone":"Africa/Freetown",
    "iso:country":"SL",
    "name:eng_x_preferred":[
        "Bundobu"
    ],
    "wof:name":"Bundobu",
    "wof:placetype":"locality"
},
  "geometry": {"coordinates":[-10.81044,8.28858],"type":"Point"}
}