{
  "type": "Feature",
  "properties": {
    "gn:admin1_code":"4.0",
    "gn:asciiname":"Loko Fakai",
    "gn:country_code":"SL",
    "gn:dem":85,
    "gn:feature_class":"P",
    "gn:feature_code":"PPL",
    "gn:name":"Loko Fakai",
    "gn:population":0,
    "gn:timezone":"Africa/Freetown",
    "iso:country":"SL",
    "name:eng_x_preferred":[
        "Loko Fakai"
    ],
    "wof:name":"Loko Fakai",
    "wof:placetype":"locality"
},
  "geometry": {"coordinates":[-13.11025,8.32021],"type":"Point"}
}