{
  "type": "Feature",
  "properties": {
    "gn:admin1_code":"4.0",
    "gn:asciiname":"Joe Town",
    "gn:country_code":"SL",
    "gn:dem":16,
    "gn:feature_class":"P",
    "gn:feature_code":"PPL",
    "gn:name":"Joe Town",
    "gn:population":0,
    "gn:timezone":"Africa/Freetown",
    "iso:country":"SL",
    "name:eng_x_preferred":[
        "Joe Town"
    ],
    "wof:name":"Joe Town",
    "wof:placetype":"locality"
},
  "geometry": {"coordinates":[-13.02957,8.29097],"type":"Point"}
}