{
  "type": "Feature",
  "properties": {
    "gn:admin1_code":"03",
    "gn:asciiname":"Woroma",
    "gn:country_code":"SL",
    "gn:dem":15,
    "gn:feature_class":"P",
    "gn:feature_code":"PPL",
    "gn:name":"Woroma",
    "gn:population":0,
    "gn:timezone":"Africa/Freetown",
    "iso:country":"SL",
    "name:eng_x_preferred":[
        "Woroma"
    ],
    "wof:name":"Woroma",
    "wof:placetype":"locality"
},
  "geometry": {"coordinates":[-11.92967,7.25828],"type":"Point"}
}