{
  "type": "Feature",
  "properties": {
    "gn:admin1_code":"3.0",
    "gn:asciiname":"Mosala",
    "gn:country_code":"SL",
    "gn:dem":44,
    "gn:feature_class":"P",
    "gn:feature_code":"PPL",
    "gn:name":"Mosala",
    "gn:population":0,
    "gn:timezone":"Africa/Freetown",
    "iso:country":"SL",
    "name:eng_x_preferred":[
        "Mosala"
    ],
    "wof:name":"Mosala",
    "wof:placetype":"locality"
},
  "geometry": {"coordinates":[-12.33876,7.91679],"type":"Point"}
}