{
  "type": "Feature",
  "properties": {
    "gn:admin1_code":"3.0",
    "gn:asciiname":"Bumpetok",
    "gn:country_code":"SL",
    "gn:dem":10,
    "gn:feature_class":"P",
    "gn:feature_code":"PPL",
    "gn:name":"Bumpetok",
    "gn:population":0,
    "gn:timezone":"Africa/Freetown",
    "iso:country":"SL",
    "name:eng_x_preferred":[
        "Bumpetok"
    ],
    "wof:name":"Bumpetok",
    "wof:placetype":"locality"
},
  "geometry": {"coordinates":[-12.88333,8.04984],"type":"Point"}
}