{
  "type": "Feature",
  "properties": {
    "gn:admin1_code":"3.0",
    "gn:asciiname":"Bagdad",
    "gn:country_code":"SL",
    "gn:dem":76,
    "gn:feature_class":"P",
    "gn:feature_code":"PPL",
    "gn:name":"Bagdad",
    "gn:population":0,
    "gn:timezone":"Africa/Freetown",
    "iso:country":"SL",
    "name:cat_x_preferred":[
        "Bagdad"
    ],
    "name:ceb_x_preferred":[
        "Bagdad"
    ],
    "name:deu_x_preferred":[
        "Bagdad"
    ],
    "name:eng_x_preferred":[
        "Bagdad"
    ],
    "name:fra_x_preferred":[
        "Bagdad"
    ],
    "name:hun_x_preferred":[
        "Bagdad"
    ],
    "name:nep_x_preferred":[
        "\u092c\u0917\u0926\u093e\u0926"
    ],
    "name:nld_x_preferred":[
        "Bagdad"
    ],
    "name:pol_x_preferred":[
        "Bagdad"
    ],
    "name:ron_x_preferred":[
        "Bagdad"
    ],
    "name:slv_x_preferred":[
        "Bagdad"
    ],
    "name:spa_x_preferred":[
        "Bagdad"
    ],
    "name:srp_x_preferred":[
        "\u0411\u0430\u0433\u0434\u0430\u0434"
    ],
    "name:swe_x_preferred":[
        "Bagdad"
    ],
    "name:vol_x_preferred":[
        "Bagdad"
    ],
    "wof:name":"Bagdad",
    "wof:placetype":"locality"
},
  "geometry": {"coordinates":[-11.55405,7.44398],"type":"Point"}
}