{
  "type": "Feature",
  "properties": {
    "gn:admin1_code":"3.0",
    "gn:asciiname":"Bagdad",
    "gn:country_code":"SL",
    "gn:dem":76,
    "gn:feature_class":"P",
    "gn:feature_code":"PPL",
    "gn:name":"Bagdad",
    "gn:population":0,
    "gn:timezone":"Africa/Freetown",
    "iso:country":"SL",
    "name:eng_x_preferred":[
        "Bagdad"
    ],
    "wof:name":"Bagdad",
    "wof:placetype":"locality"
},
  "geometry": {"coordinates":[-11.55405,7.44398],"type":"Point"}
}