{
  "type": "Feature",
  "properties": {
    "gn:admin1_code":"1.0",
    "gn:asciiname":"Gbokodor",
    "gn:country_code":"SL",
    "gn:dem":356,
    "gn:feature_class":"P",
    "gn:feature_code":"PPL",
    "gn:name":"Gbokodor",
    "gn:population":0,
    "gn:timezone":"Africa/Freetown",
    "iso:country":"SL",
    "name:eng_x_preferred":[
        "Gbokodor"
    ],
    "wof:name":"Gbokodor",
    "wof:placetype":"locality"
},
  "geometry": {"coordinates":[-11.09506,8.7118],"type":"Point"}
}