{
  "type": "Feature",
  "properties": {
    "gn:admin1_code":"2.0",
    "gn:asciiname":"Katankina",
    "gn:country_code":"SL",
    "gn:dem":80,
    "gn:feature_class":"P",
    "gn:feature_code":"PPL",
    "gn:name":"Katankina",
    "gn:population":0,
    "gn:timezone":"Africa/Freetown",
    "iso:country":"SL",
    "wof:name":"Katankina",
    "wof:placetype":"locality"
},
  "geometry": {"coordinates":[-11.96667,9.03333],"type":"Point"}
}