{
  "type": "Feature",
  "properties": {
    "gn:admin1_code":"3.0",
    "gn:asciiname":"Kobu",
    "gn:country_code":"SL",
    "gn:dem":99,
    "gn:feature_class":"P",
    "gn:feature_code":"PPL",
    "gn:name":"Kobu",
    "gn:population":0,
    "gn:timezone":"Africa/Freetown",
    "iso:country":"SL",
    "name:eng_x_preferred":[
        "Kobu"
    ],
    "wof:name":"Kobu",
    "wof:placetype":"locality"
},
  "geometry": {"coordinates":[-11.67583,8.06483],"type":"Point"}
}