{
  "type": "Feature",
  "properties": {
    "gn:admin1_code":"01",
    "gn:asciiname":"Tokpombu",
    "gn:country_code":"SL",
    "gn:dem":457,
    "gn:feature_class":"P",
    "gn:feature_code":"PPL",
    "gn:name":"Tokpombu",
    "gn:population":0,
    "gn:timezone":"Africa/Freetown",
    "iso:country":"SL",
    "wof:name":"Tokpombu",
    "wof:placetype":"locality"
},
  "geometry": {"coordinates":[-11.16667,8.35],"type":"Point"}
}