{
  "type": "Feature",
  "properties": {
    "gn:admin1_code":"2.0",
    "gn:asciiname":"Kasansan",
    "gn:country_code":"SL",
    "gn:dem":91,
    "gn:feature_class":"P",
    "gn:feature_code":"PPL",
    "gn:name":"Kasansan",
    "gn:population":0,
    "gn:timezone":"Africa/Freetown",
    "iso:country":"SL",
    "name:eng_x_preferred":[
        "Kasansan"
    ],
    "wof:name":"Kasansan",
    "wof:placetype":"locality"
},
  "geometry": {"coordinates":[-12.67752,9.27429],"type":"Point"}
}