{
  "type": "Feature",
  "properties": {
    "gn:admin1_code":"1.0",
    "gn:asciiname":"Grima",
    "gn:country_code":"SL",
    "gn:dem":198,
    "gn:feature_class":"P",
    "gn:feature_code":"PPL",
    "gn:name":"Grima",
    "gn:population":0,
    "gn:timezone":"Africa/Freetown",
    "iso:country":"SL",
    "name:ceb_x_preferred":[
        "Grima"
    ],
    "name:deu_x_preferred":[
        "Grima"
    ],
    "name:eng_x_preferred":[
        "Grima"
    ],
    "name:fra_x_preferred":[
        "Grima"
    ],
    "name:nor_x_preferred":[
        "Grima"
    ],
    "name:rus_x_preferred":[
        "\u0413\u0440\u0438\u043c\u0430"
    ],
    "name:swe_x_preferred":[
        "Grima"
    ],
    "wof:name":"Grima",
    "wof:placetype":"locality"
},
  "geometry": {"coordinates":[-11.06977,8.05872],"type":"Point"}
}