{
  "type": "Feature",
  "properties": {
    "gn:admin1_code":"03",
    "gn:asciiname":"Sumbuya",
    "gn:country_code":"SL",
    "gn:dem":15,
    "gn:feature_class":"P",
    "gn:feature_code":"PPL",
    "gn:name":"Sumbuya",
    "gn:population":0,
    "gn:timezone":"Africa/Freetown",
    "iso:country":"SL",
    "name:eng_x_preferred":[
        "Sumbuya"
    ],
    "wof:name":"Sumbuya",
    "wof:placetype":"locality"
},
  "geometry": {"coordinates":[-11.67419,7.18266],"type":"Point"}
}