{
  "type": "Feature",
  "properties": {
    "gn:admin1_code":"01",
    "gn:asciiname":"Yombolu",
    "gn:country_code":"SL",
    "gn:dem":206,
    "gn:feature_class":"P",
    "gn:feature_code":"PPL",
    "gn:name":"Yombolu",
    "gn:population":0,
    "gn:timezone":"Africa/Freetown",
    "iso:country":"SL",
    "name:eng_x_preferred":[
        "Yombolu"
    ],
    "name:und_x_variant":[
        "Yambalu"
    ],
    "wof:name":"Yombolu",
    "wof:placetype":"locality"
},
  "geometry": {"coordinates":[-10.68687,8.25503],"type":"Point"}
}