{
  "type": "Feature",
  "properties": {
    "gn:admin1_code":"01",
    "gn:asciiname":"Waima",
    "gn:country_code":"SL",
    "gn:dem":443,
    "gn:feature_class":"P",
    "gn:feature_code":"PPL",
    "gn:name":"Waima",
    "gn:population":0,
    "gn:timezone":"Africa/Freetown",
    "iso:country":"SL",
    "name:eng_x_preferred":[
        "Waima"
    ],
    "wof:name":"Waima",
    "wof:placetype":"locality"
},
  "geometry": {"coordinates":[-10.78241,8.6352],"type":"Point"}
}