{
  "type": "Feature",
  "properties": {
    "gn:admin1_code":"3.0",
    "gn:asciiname":"Makorewa",
    "gn:country_code":"SL",
    "gn:dem":64,
    "gn:feature_class":"P",
    "gn:feature_code":"PPL",
    "gn:name":"Makorewa",
    "gn:population":0,
    "gn:timezone":"Africa/Freetown",
    "iso:country":"SL",
    "name:eng_x_preferred":[
        "Makorewa"
    ],
    "name:und_x_variant":[
        "Mokore",
        "Makore"
    ],
    "wof:name":"Makorewa",
    "wof:placetype":"locality"
},
  "geometry": {"coordinates":[-12.24692,8.17063],"type":"Point"}
}