{
  "type": "Feature",
  "properties": {
    "gn:admin1_code":"3.0",
    "gn:asciiname":"Fulawahun",
    "gn:country_code":"SL",
    "gn:dem":94,
    "gn:feature_class":"P",
    "gn:feature_code":"PPL",
    "gn:name":"Fulawahun",
    "gn:population":0,
    "gn:timezone":"Africa/Freetown",
    "iso:country":"SL",
    "name:und_x_variant":[
        "Futawahn",
        "Futawahun",
        "Fulawahun"
    ],
    "wof:name":"Fulawahun",
    "wof:placetype":"locality"
},
  "geometry": {"coordinates":[-11.72521,8.05265],"type":"Point"}
}