{
  "type": "Feature",
  "properties": {
    "gn:admin1_code":"02",
    "gn:asciiname":"Sangbamba",
    "gn:country_code":"SL",
    "gn:dem":360,
    "gn:feature_class":"P",
    "gn:feature_code":"PPL",
    "gn:name":"Sangbamba",
    "gn:population":0,
    "gn:timezone":"Africa/Freetown",
    "iso:country":"SL",
    "name:eng_x_preferred":[
        "Sangbamba"
    ],
    "wof:name":"Sangbamba",
    "wof:placetype":"locality"
},
  "geometry": {"coordinates":[-11.76201,9.74587],"type":"Point"}
}