{
  "type": "Feature",
  "properties": {
    "gn:admin1_code":"2.0",
    "gn:asciiname":"Folia",
    "gn:country_code":"SL",
    "gn:dem":402,
    "gn:feature_class":"P",
    "gn:feature_code":"PPL",
    "gn:name":"Folia",
    "gn:population":0,
    "gn:timezone":"Africa/Freetown",
    "iso:country":"SL",
    "name:cat_x_preferred":[
        "Folia"
    ],
    "name:ces_x_preferred":[
        "La Folia"
    ],
    "name:dan_x_preferred":[
        "La Folia"
    ],
    "name:deu_x_preferred":[
        "Folia"
    ],
    "name:eng_x_preferred":[
        "Folia"
    ],
    "name:fin_x_preferred":[
        "Folia"
    ],
    "name:fra_x_preferred":[
        "Folia"
    ],
    "name:jpn_x_preferred":[
        "\u30d5\u30a9\u30ea\u30a2"
    ],
    "name:lat_x_preferred":[
        "Follia"
    ],
    "name:nld_x_preferred":[
        "La Folia"
    ],
    "name:nor_x_preferred":[
        "La folia"
    ],
    "name:oci_x_preferred":[
        "La Folia"
    ],
    "name:pol_x_preferred":[
        "La Fol\u00eda"
    ],
    "name:por_x_preferred":[
        "Folia"
    ],
    "name:rus_x_preferred":[
        "\u0424\u043e\u043b\u0438\u044f"
    ],
    "name:spa_x_preferred":[
        "Fol\u00eda"
    ],
    "name:swe_x_preferred":[
        "La folia"
    ],
    "name:tur_x_preferred":[
        "Follia"
    ],
    "name:zho_x_preferred":[
        "\u798f\u5229\u4e9a\u821e\u66f2"
    ],
    "wof:name":"Folia",
    "wof:placetype":"locality"
},
  "geometry": {"coordinates":[-11.46101,9.09129],"type":"Point"}
}