{
  "type": "Feature",
  "properties": {
    "gn:admin1_code":"2.0",
    "gn:asciiname":"Folia",
    "gn:country_code":"SL",
    "gn:dem":402,
    "gn:feature_class":"P",
    "gn:feature_code":"PPL",
    "gn:name":"Folia",
    "gn:population":0,
    "gn:timezone":"Africa/Freetown",
    "iso:country":"SL",
    "name:eng_x_preferred":[
        "Folia"
    ],
    "wof:name":"Folia",
    "wof:placetype":"locality"
},
  "geometry": {"coordinates":[-11.46101,9.09129],"type":"Point"}
}