{
  "type": "Feature",
  "properties": {
    "gn:admin1_code":"2.0",
    "gn:asciiname":"Matuku",
    "gn:country_code":"SL",
    "gn:dem":57,
    "gn:feature_class":"P",
    "gn:feature_code":"PPL",
    "gn:name":"Matuku",
    "gn:population":0,
    "gn:timezone":"Africa/Freetown",
    "iso:country":"SL",
    "name:ceb_x_preferred":[
        "Matuku"
    ],
    "name:eng_x_preferred":[
        "Matuku"
    ],
    "name:fra_x_preferred":[
        "Matuku"
    ],
    "name:swe_x_preferred":[
        "Matuku"
    ],
    "wof:name":"Matuku",
    "wof:placetype":"locality"
},
  "geometry": {"coordinates":[-12.42112,8.97963],"type":"Point"}
}