{
  "type": "Feature",
  "properties": {
    "gn:admin1_code":"1.0",
    "gn:asciiname":"Lasaru",
    "gn:country_code":"SL",
    "gn:dem":266,
    "gn:feature_class":"P",
    "gn:feature_code":"PPL",
    "gn:name":"Lasaru",
    "gn:population":0,
    "gn:timezone":"Africa/Freetown",
    "iso:country":"SL",
    "name:eng_x_preferred":[
        "Lasaru"
    ],
    "wof:name":"Lasaru",
    "wof:placetype":"locality"
},
  "geometry": {"coordinates":[-10.84671,7.74294],"type":"Point"}
}