{
  "type": "Feature",
  "properties": {
    "gn:admin1_code":"2.0",
    "gn:asciiname":"Bisau",
    "gn:country_code":"SL",
    "gn:dem":3,
    "gn:feature_class":"P",
    "gn:feature_code":"PPL",
    "gn:name":"Bisau",
    "gn:population":0,
    "gn:timezone":"Africa/Freetown",
    "iso:country":"SL",
    "name:eng_x_preferred":[
        "Bisau"
    ],
    "wof:name":"Bisau",
    "wof:placetype":"locality"
},
  "geometry": {"coordinates":[-13.06904,8.83497],"type":"Point"}
}