{
  "type": "Feature",
  "properties": {
    "gn:admin1_code":"1.0",
    "gn:asciiname":"Majehun",
    "gn:country_code":"SL",
    "gn:dem":427,
    "gn:feature_class":"P",
    "gn:feature_code":"PPL",
    "gn:name":"Majehun",
    "gn:population":0,
    "gn:timezone":"Africa/Freetown",
    "iso:country":"SL",
    "name:eng_x_preferred":[
        "Majehun"
    ],
    "name:und_x_variant":[
        "Manjehun"
    ],
    "wof:name":"Majehun",
    "wof:placetype":"locality"
},
  "geometry": {"coordinates":[-11.16865,8.29291],"type":"Point"}
}