{
  "type": "Feature",
  "properties": {
    "gn:admin1_code":"1.0",
    "gn:asciiname":"Bandeining",
    "gn:country_code":"SL",
    "gn:dem":421,
    "gn:feature_class":"P",
    "gn:feature_code":"PPL",
    "gn:name":"Bandeining",
    "gn:population":0,
    "gn:timezone":"Africa/Freetown",
    "iso:country":"SL",
    "name:eng_x_preferred":[
        "Bandeining"
    ],
    "wof:name":"Bandeining",
    "wof:placetype":"locality"
},
  "geometry": {"coordinates":[-10.29548,8.40729],"type":"Point"}
}