{
  "type": "Feature",
  "properties": {
    "gn:admin1_code":"1.0",
    "gn:asciiname":"Garwama",
    "gn:country_code":"SL",
    "gn:dem":148,
    "gn:feature_class":"P",
    "gn:feature_code":"PPL",
    "gn:name":"Garwama",
    "gn:population":0,
    "gn:timezone":"Africa/Freetown",
    "iso:country":"SL",
    "name:eng_x_preferred":[
        "Garwama"
    ],
    "wof:name":"Garwama",
    "wof:placetype":"locality"
},
  "geometry": {"coordinates":[-11.34189,8.23344],"type":"Point"}
}