{
  "type": "Feature",
  "properties": {
    "gn:admin1_code":"1.0",
    "gn:asciiname":"Kisigolahun",
    "gn:country_code":"SL",
    "gn:dem":142,
    "gn:feature_class":"P",
    "gn:feature_code":"PPL",
    "gn:name":"Kisigolahun",
    "gn:population":0,
    "gn:timezone":"Africa/Freetown",
    "iso:country":"SL",
    "name:eng_x_preferred":[
        "Kisigolahun"
    ],
    "name:und_x_variant":[
        "Gorahun"
    ],
    "wof:name":"Kisigolahun",
    "wof:placetype":"locality"
},
  "geometry": {"coordinates":[-11.25247,7.65224],"type":"Point"}
}