{
  "type": "Feature",
  "properties": {
    "gn:admin1_code":"01",
    "gn:asciiname":"Tongoma",
    "gn:country_code":"SL",
    "gn:dem":459,
    "gn:feature_class":"P",
    "gn:feature_code":"PPL",
    "gn:name":"Tongoma",
    "gn:population":0,
    "gn:timezone":"Africa/Freetown",
    "iso:country":"SL",
    "name:und_x_variant":[
        "Tangoma",
        "Tongoma"
    ],
    "wof:name":"Tongoma",
    "wof:placetype":"locality"
},
  "geometry": {"coordinates":[-10.83854,8.60857],"type":"Point"}
}