{
  "type": "Feature",
  "properties": {
    "gn:admin1_code":"3.0",
    "gn:asciiname":"Masanki",
    "gn:country_code":"SL",
    "gn:dem":22,
    "gn:feature_class":"P",
    "gn:feature_code":"PPL",
    "gn:name":"Masanki",
    "gn:population":0,
    "gn:timezone":"Africa/Freetown",
    "iso:country":"SL",
    "name:eng_x_preferred":[
        "Masanki"
    ],
    "wof:name":"Masanki",
    "wof:placetype":"locality"
},
  "geometry": {"coordinates":[-12.80424,8.32023],"type":"Point"}
}