{
  "type": "Feature",
  "properties": {
    "gn:admin1_code":"1.0",
    "gn:asciiname":"Karwaya",
    "gn:country_code":"SL",
    "gn:dem":331,
    "gn:feature_class":"P",
    "gn:feature_code":"PPL",
    "gn:name":"Karwaya",
    "gn:population":0,
    "gn:timezone":"Africa/Freetown",
    "iso:country":"SL",
    "name:eng_x_preferred":[
        "Karwaya"
    ],
    "name:und_x_variant":[
        "Kanwaya"
    ],
    "wof:name":"Karwaya",
    "wof:placetype":"locality"
},
  "geometry": {"coordinates":[-11.35443,8.48214],"type":"Point"}
}