{
  "type": "Feature",
  "properties": {
    "gn:admin1_code":"1.0",
    "gn:asciiname":"Maloma",
    "gn:country_code":"SL",
    "gn:dem":183,
    "gn:feature_class":"P",
    "gn:feature_code":"PPL",
    "gn:name":"Maloma",
    "gn:population":0,
    "gn:timezone":"Africa/Freetown",
    "iso:country":"SL",
    "name:eng_x_preferred":[
        "Maloma"
    ],
    "name:und_x_variant":[
        "Malonta"
    ],
    "wof:name":"Maloma",
    "wof:placetype":"locality"
},
  "geometry": {"coordinates":[-10.84806,7.99587],"type":"Point"}
}