{
  "type": "Feature",
  "properties": {
    "gn:admin1_code":"1.0",
    "gn:asciiname":"Woniyama",
    "gn:country_code":"SL",
    "gn:dem":195,
    "gn:feature_class":"P",
    "gn:feature_code":"PPL",
    "gn:name":"Woniyama",
    "gn:population":0,
    "gn:timezone":"Africa/Freetown",
    "iso:country":"SL",
    "name:eng_x_preferred":[
        "Woniyama"
    ],
    "wof:name":"Woniyama",
    "wof:placetype":"locality"
},
  "geometry": {"coordinates":[-11.30206,8.24916],"type":"Point"}
}