{
  "type": "Feature",
  "properties": {
    "gn:admin1_code":"02",
    "gn:asciiname":"Wari",
    "gn:country_code":"SL",
    "gn:dem":61,
    "gn:feature_class":"P",
    "gn:feature_code":"PPL",
    "gn:name":"Wari",
    "gn:population":0,
    "gn:timezone":"Africa/Freetown",
    "iso:country":"SL",
    "name:ceb_x_preferred":[
        "Wari"
    ],
    "name:deu_x_preferred":[
        "Wari"
    ],
    "name:eng_x_preferred":[
        "Wari"
    ],
    "name:fra_x_preferred":[
        "Wari"
    ],
    "name:jpn_x_preferred":[
        "\u30ef\u30ea"
    ],
    "name:mkd_x_preferred":[
        "\u0412\u0430\u0440\u0438"
    ],
    "name:pol_x_preferred":[
        "Wari"
    ],
    "name:rus_x_preferred":[
        "\u0412\u0430\u0440\u0438"
    ],
    "name:spa_x_preferred":[
        "Wari"
    ],
    "name:swe_x_preferred":[
        "Wari"
    ],
    "wof:name":"Wari",
    "wof:placetype":"locality"
},
  "geometry": {"coordinates":[-12.3776,9.21325],"type":"Point"}
}