{
  "type": "Feature",
  "properties": {
    "gn:admin1_code":"3.0",
    "gn:asciiname":"Wueh",
    "gn:country_code":"SL",
    "gn:dem":16,
    "gn:feature_class":"P",
    "gn:feature_code":"PPL",
    "gn:name":"Wueh",
    "gn:population":0,
    "gn:timezone":"Africa/Freetown",
    "iso:country":"SL",
    "name:eng_x_preferred":[
        "Wueh"
    ],
    "wof:name":"Wueh",
    "wof:placetype":"locality"
},
  "geometry": {"coordinates":[-12.07255,7.47717],"type":"Point"}
}