{
  "type": "Feature",
  "properties": {
    "gn:admin1_code":"1.0",
    "gn:asciiname":"Dugbu",
    "gn:country_code":"SL",
    "gn:dem":310,
    "gn:feature_class":"P",
    "gn:feature_code":"PPL",
    "gn:name":"Dugbu",
    "gn:population":0,
    "gn:timezone":"Africa/Freetown",
    "iso:country":"SL",
    "name:eng_x_preferred":[
        "Dugbu"
    ],
    "name:und_x_variant":[
        "Dagbu"
    ],
    "wof:name":"Dugbu",
    "wof:placetype":"locality"
},
  "geometry": {"coordinates":[-10.6022,8.59173],"type":"Point"}
}