{
  "type": "Feature",
  "properties": {
    "gn:admin1_code":"3.0",
    "gn:asciiname":"Simbaru",
    "gn:country_code":"SL",
    "gn:dem":44,
    "gn:feature_class":"P",
    "gn:feature_code":"PPL",
    "gn:name":"Simbaru",
    "gn:population":0,
    "gn:timezone":"Africa/Freetown",
    "iso:country":"SL",
    "name:eng_x_preferred":[
        "Simbaru"
    ],
    "wof:name":"Simbaru",
    "wof:placetype":"locality"
},
  "geometry": {"coordinates":[-11.4593,7.24039],"type":"Point"}
}