{
  "type": "Feature",
  "properties": {
    "gn:admin1_code":"1.0",
    "gn:asciiname":"Lungai",
    "gn:country_code":"SL",
    "gn:dem":220,
    "gn:feature_class":"P",
    "gn:feature_code":"PPL",
    "gn:name":"Lungai",
    "gn:population":0,
    "gn:timezone":"Africa/Freetown",
    "iso:country":"SL",
    "name:eng_x_preferred":[
        "Lungai"
    ],
    "wof:name":"Lungai",
    "wof:placetype":"locality"
},
  "geometry": {"coordinates":[-10.81202,8.27607],"type":"Point"}
}