{
  "type": "Feature",
  "properties": {
    "gn:admin1_code":"4.0",
    "gn:asciiname":"Campbell Town",
    "gn:country_code":"SL",
    "gn:dem":20,
    "gn:feature_class":"P",
    "gn:feature_code":"PPL",
    "gn:name":"Campbell Town",
    "gn:population":0,
    "gn:timezone":"Africa/Freetown",
    "iso:country":"SL",
    "name:eng_x_preferred":[
        "Campbell Town"
    ],
    "wof:name":"Campbell Town",
    "wof:placetype":"locality"
},
  "geometry": {"coordinates":[-13.0506,8.30705],"type":"Point"}
}