{
  "type": "Feature",
  "properties": {
    "gn:admin1_code":"1.0",
    "gn:asciiname":"Dakadu",
    "gn:country_code":"SL",
    "gn:dem":440,
    "gn:feature_class":"P",
    "gn:feature_code":"PPL",
    "gn:name":"Dakadu",
    "gn:population":0,
    "gn:timezone":"Africa/Freetown",
    "iso:country":"SL",
    "name:eng_x_preferred":[
        "Dakadu"
    ],
    "wof:name":"Dakadu",
    "wof:placetype":"locality"
},
  "geometry": {"coordinates":[-10.79908,8.69044],"type":"Point"}
}