{
  "type": "Feature",
  "properties": {
    "gn:admin1_code":"1.0",
    "gn:asciiname":"Kabalu",
    "gn:country_code":"SL",
    "gn:dem":401,
    "gn:feature_class":"P",
    "gn:feature_code":"PPL",
    "gn:name":"Kabalu",
    "gn:population":0,
    "gn:timezone":"Africa/Freetown",
    "iso:country":"SL",
    "name:eng_x_preferred":[
        "Kabalu"
    ],
    "name:und_x_variant":[
        "Kambalu"
    ],
    "wof:name":"Kabalu",
    "wof:placetype":"locality"
},
  "geometry": {"coordinates":[-10.33102,8.21762],"type":"Point"}
}