{
  "type": "Feature",
  "properties": {
    "gn:admin1_code":"1.0",
    "gn:asciiname":"Bandiworo",
    "gn:country_code":"SL",
    "gn:dem":354,
    "gn:feature_class":"P",
    "gn:feature_code":"PPL",
    "gn:name":"Bandiworo",
    "gn:population":0,
    "gn:timezone":"Africa/Freetown",
    "iso:country":"SL",
    "name:eng_x_preferred":[
        "Bandiworo"
    ],
    "wof:name":"Bandiworo",
    "wof:placetype":"locality"
},
  "geometry": {"coordinates":[-10.37935,8.16711],"type":"Point"}
}