{
  "type": "Feature",
  "properties": {
    "gn:admin1_code":"3.0",
    "gn:asciiname":"Lein",
    "gn:country_code":"SL",
    "gn:dem":78,
    "gn:feature_class":"P",
    "gn:feature_code":"PPL",
    "gn:name":"Lein",
    "gn:population":0,
    "gn:timezone":"Africa/Freetown",
    "iso:country":"SL",
    "name:ceb_x_preferred":[
        "Lein"
    ],
    "name:deu_x_preferred":[
        "Lein"
    ],
    "name:eng_x_preferred":[
        "Lein"
    ],
    "name:fra_x_preferred":[
        "Lein"
    ],
    "name:swe_x_preferred":[
        "Lein"
    ],
    "name:und_x_variant":[
        "Leng"
    ],
    "wof:name":"Lein",
    "wof:placetype":"locality"
},
  "geometry": {"coordinates":[-11.53111,7.58333],"type":"Point"}
}