{
  "type": "Feature",
  "properties": {
    "gn:admin1_code":"01",
    "gn:asciiname":"Teilu",
    "gn:country_code":"SL",
    "gn:dem":372,
    "gn:feature_class":"P",
    "gn:feature_code":"PPL",
    "gn:name":"Teilu",
    "gn:population":0,
    "gn:timezone":"Africa/Freetown",
    "iso:country":"SL",
    "name:eng_x_preferred":[
        "Teilu"
    ],
    "name:und_x_variant":[
        "Teibo"
    ],
    "wof:name":"Teilu",
    "wof:placetype":"locality"
},
  "geometry": {"coordinates":[-10.51582,8.31509],"type":"Point"}
}