{
  "type": "Feature",
  "properties": {
    "gn:admin1_code":"3.0",
    "gn:asciiname":"Titibul",
    "gn:country_code":"SL",
    "gn:dem":5,
    "gn:feature_class":"P",
    "gn:feature_code":"PPL",
    "gn:name":"Titibul",
    "gn:population":0,
    "gn:timezone":"Africa/Freetown",
    "iso:country":"SL",
    "name:eng_x_preferred":[
        "Titibul"
    ],
    "wof:name":"Titibul",
    "wof:placetype":"locality"
},
  "geometry": {"coordinates":[-12.59667,7.74222],"type":"Point"}
}