{
  "type": "Feature",
  "properties": {
    "gn:admin1_code":"3.0",
    "gn:asciiname":"Moyambaworo",
    "gn:country_code":"SL",
    "gn:dem":60,
    "gn:feature_class":"P",
    "gn:feature_code":"PPL",
    "gn:name":"Moyambaworo",
    "gn:population":0,
    "gn:timezone":"Africa/Freetown",
    "iso:country":"SL",
    "name:eng_x_preferred":[
        "Moyambaworo"
    ],
    "wof:name":"Moyambaworo",
    "wof:placetype":"locality"
},
  "geometry": {"coordinates":[-12.03472,8.17469],"type":"Point"}
}