{
  "type": "Feature",
  "properties": {
    "gn:admin1_code":"1.0",
    "gn:asciiname":"Gieumba",
    "gn:country_code":"SL",
    "gn:dem":107,
    "gn:feature_class":"P",
    "gn:feature_code":"PPL",
    "gn:name":"Gieumba",
    "gn:population":0,
    "gn:timezone":"Africa/Freetown",
    "iso:country":"SL",
    "name:und_x_variant":[
        "Gieumbu"
    ],
    "wof:name":"Gieumba",
    "wof:placetype":"locality"
},
  "geometry": {"coordinates":[-11.28381,7.49323],"type":"Point"}
}