{
  "type": "Feature",
  "properties": {
    "gn:admin1_code":"3.0",
    "gn:asciiname":"Nitiworo",
    "gn:country_code":"SL",
    "gn:dem":64,
    "gn:feature_class":"P",
    "gn:feature_code":"PPL",
    "gn:name":"Nitiworo",
    "gn:population":0,
    "gn:timezone":"Africa/Freetown",
    "iso:country":"SL",
    "name:eng_x_preferred":[
        "Nitiworo"
    ],
    "wof:name":"Nitiworo",
    "wof:placetype":"locality"
},
  "geometry": {"coordinates":[-12.11007,7.826],"type":"Point"}
}