{
  "type": "Feature",
  "properties": {
    "gn:admin1_code":"2.0",
    "gn:asciiname":"Duwulema",
    "gn:country_code":"SL",
    "gn:dem":624,
    "gn:feature_class":"P",
    "gn:feature_code":"PPL",
    "gn:name":"Duwulema",
    "gn:population":0,
    "gn:timezone":"Africa/Freetown",
    "iso:country":"SL",
    "name:und_x_variant":[
        "Dawulema",
        "Duwulema"
    ],
    "wof:name":"Duwulema",
    "wof:placetype":"locality"
},
  "geometry": {"coordinates":[-10.64335,9.02336],"type":"Point"}
}