{
  "type": "Feature",
  "properties": {
    "gn:admin1_code":"1.0",
    "gn:asciiname":"Yufondu",
    "gn:country_code":"SL",
    "gn:dem":402,
    "gn:feature_class":"P",
    "gn:feature_code":"PPL",
    "gn:name":"Yufondu",
    "gn:population":0,
    "gn:timezone":"Africa/Freetown",
    "iso:country":"SL",
    "name:eng_x_preferred":[
        "Yufondu"
    ],
    "wof:name":"Yufondu",
    "wof:placetype":"locality"
},
  "geometry": {"coordinates":[-10.41862,8.37405],"type":"Point"}
}