{
  "type": "Feature",
  "properties": {
    "gn:admin1_code":"4.0",
    "gn:asciiname":"Mo-bokari",
    "gn:country_code":"SL",
    "gn:dem":1,
    "gn:feature_class":"P",
    "gn:feature_code":"PPL",
    "gn:name":"Mo-bokari",
    "gn:population":0,
    "gn:timezone":"Africa/Freetown",
    "iso:country":"SL",
    "wof:name":"Mo-bokari",
    "wof:placetype":"locality"
},
  "geometry": {"coordinates":[-13.03333,8.35],"type":"Point"}
}