{
  "type": "Feature",
  "properties": {
    "gn:admin1_code":"2.0",
    "gn:asciiname":"Makeha",
    "gn:country_code":"SL",
    "gn:dem":137,
    "gn:feature_class":"P",
    "gn:feature_code":"PPL",
    "gn:name":"Makeha",
    "gn:population":0,
    "gn:timezone":"Africa/Freetown",
    "iso:country":"SL",
    "name:eng_x_preferred":[
        "Makeha"
    ],
    "wof:name":"Makeha",
    "wof:placetype":"locality"
},
  "geometry": {"coordinates":[-12.04443,9.35424],"type":"Point"}
}