{
  "type": "Feature",
  "properties": {
    "gn:admin1_code":"2.0",
    "gn:asciiname":"Rogbil",
    "gn:country_code":"SL",
    "gn:dem":70,
    "gn:feature_class":"P",
    "gn:feature_code":"PPL",
    "gn:name":"Rogbil",
    "gn:population":0,
    "gn:timezone":"Africa/Freetown",
    "iso:country":"SL",
    "name:eng_x_preferred":[
        "Rogbil"
    ],
    "wof:name":"Rogbil",
    "wof:placetype":"locality"
},
  "geometry": {"coordinates":[-12.32445,8.72873],"type":"Point"}
}