{
  "type": "Feature",
  "properties": {
    "gn:admin1_code":"3.0",
    "gn:asciiname":"Gbewama",
    "gn:country_code":"SL",
    "gn:dem":261,
    "gn:feature_class":"P",
    "gn:feature_code":"PPL",
    "gn:name":"Gbewama",
    "gn:population":0,
    "gn:timezone":"Africa/Freetown",
    "iso:country":"SL",
    "name:eng_x_preferred":[
        "Gbewama"
    ],
    "wof:name":"Gbewama",
    "wof:placetype":"locality"
},
  "geometry": {"coordinates":[-11.552,8.33339],"type":"Point"}
}