{
  "type": "Feature",
  "properties": {
    "gn:admin1_code":"2.0",
    "gn:asciiname":"Magboko",
    "gn:country_code":"SL",
    "gn:dem":36,
    "gn:feature_class":"P",
    "gn:feature_code":"PPL",
    "gn:name":"Magboko",
    "gn:population":0,
    "gn:timezone":"Africa/Freetown",
    "iso:country":"SL",
    "name:eng_x_preferred":[
        "Magboko"
    ],
    "wof:name":"Magboko",
    "wof:placetype":"locality"
},
  "geometry": {"coordinates":[-12.7304,8.54397],"type":"Point"}
}