{
  "type": "Feature",
  "properties": {
    "gn:admin1_code":"1.0",
    "gn:asciiname":"Taninahun",
    "gn:country_code":"SL",
    "gn:dem":224,
    "gn:feature_class":"P",
    "gn:feature_code":"PPL",
    "gn:name":"Taninahun",
    "gn:population":0,
    "gn:timezone":"Africa/Freetown",
    "iso:country":"SL",
    "name:eng_x_preferred":[
        "Taninahun"
    ],
    "wof:name":"Taninahun",
    "wof:placetype":"locality"
},
  "geometry": {"coordinates":[-10.65744,8.1456],"type":"Point"}
}