{
  "type": "Feature",
  "properties": {
    "gn:admin1_code":"2.0",
    "gn:asciiname":"Dania",
    "gn:country_code":"SL",
    "gn:dem":347,
    "gn:feature_class":"P",
    "gn:feature_code":"PPL",
    "gn:name":"Dania",
    "gn:population":0,
    "gn:timezone":"Africa/Freetown",
    "iso:country":"SL",
    "name:eng_x_preferred":[
        "Dania"
    ],
    "wof:name":"Dania",
    "wof:placetype":"locality"
},
  "geometry": {"coordinates":[-11.24265,9.01489],"type":"Point"}
}