{
  "type": "Feature",
  "properties": {
    "gn:admin1_code":"1.0",
    "gn:asciiname":"Bandasuma",
    "gn:country_code":"SL",
    "gn:dem":436,
    "gn:feature_class":"P",
    "gn:feature_code":"PPL",
    "gn:name":"Bandasuma",
    "gn:population":0,
    "gn:timezone":"Africa/Freetown",
    "iso:country":"SL",
    "name:eng_x_preferred":[
        "Bandasuma"
    ],
    "wof:name":"Bandasuma",
    "wof:placetype":"locality"
},
  "geometry": {"coordinates":[-10.78405,8.71712],"type":"Point"}
}