{
  "type": "Feature",
  "properties": {
    "gn:country":"SL",
    "gn:fcode":"PPL",
    "gn:pop":3441,
    "iso:country":"SL",
    "name:unk_x_variant":[
        "Largo"
    ],
    "qs:name":"Lago",
    "qs:photos_9r":0,
    "qs:photos_sr":0,
    "qs:pop_sr":"4",
    "wd:wordcount":125,
    "wof:name":"Lago",
    "wof:placetype":"locality",
    "wof:population":3441
},
  "geometry": {"coordinates":[-12.15,8.26667],"type":"Point"}
}