{
  "type": "Feature",
  "properties": {
    "gn:admin1_code":"01",
    "gn:asciiname":"Tekwiama",
    "gn:country_code":"SL",
    "gn:dem":229,
    "gn:feature_class":"P",
    "gn:feature_code":"PPL",
    "gn:name":"Tekwiama",
    "gn:population":0,
    "gn:timezone":"Africa/Freetown",
    "iso:country":"SL",
    "name:eng_x_preferred":[
        "Tekwiama"
    ],
    "wof:name":"Tekwiama",
    "wof:placetype":"locality"
},
  "geometry": {"coordinates":[-11.2917,8.38145],"type":"Point"}
}