{
  "type": "Feature",
  "properties": {
    "gn:admin1_code":"3.0",
    "gn:asciiname":"Kase",
    "gn:country_code":"SL",
    "gn:dem":7,
    "gn:feature_class":"P",
    "gn:feature_code":"PPL",
    "gn:name":"Kase",
    "gn:population":0,
    "gn:timezone":"Africa/Freetown",
    "iso:country":"SL",
    "name:eng_x_preferred":[
        "Kase"
    ],
    "wof:name":"Kase",
    "wof:placetype":"locality"
},
  "geometry": {"coordinates":[-12.08196,7.32947],"type":"Point"}
}