{
  "type": "Feature",
  "properties": {
    "gn:admin1_code":"3.0",
    "gn:asciiname":"Maninka",
    "gn:country_code":"SL",
    "gn:dem":46,
    "gn:feature_class":"P",
    "gn:feature_code":"PPL",
    "gn:name":"Maninka",
    "gn:population":0,
    "gn:timezone":"Africa/Freetown",
    "iso:country":"SL",
    "name:eng_x_preferred":[
        "Maninka"
    ],
    "wof:name":"Maninka",
    "wof:placetype":"locality"
},
  "geometry": {"coordinates":[-12.62346,8.25118],"type":"Point"}
}