{
  "type": "Feature",
  "properties": {
    "gn:admin1_code":"1.0",
    "gn:asciiname":"Konela",
    "gn:country_code":"SL",
    "gn:dem":205,
    "gn:feature_class":"P",
    "gn:feature_code":"PPL",
    "gn:name":"Konela",
    "gn:population":0,
    "gn:timezone":"Africa/Freetown",
    "iso:country":"SL",
    "name:eng_x_preferred":[
        "Konela"
    ],
    "wof:name":"Konela",
    "wof:placetype":"locality"
},
  "geometry": {"coordinates":[-10.62171,7.98525],"type":"Point"}
}