{
  "type": "Feature",
  "properties": {
    "gn:admin1_code":"03",
    "gn:asciiname":"Waima",
    "gn:country_code":"SL",
    "gn:dem":11,
    "gn:feature_class":"P",
    "gn:feature_code":"PPL",
    "gn:name":"Waima",
    "gn:population":0,
    "gn:timezone":"Africa/Freetown",
    "iso:country":"SL",
    "name:eng_x_preferred":[
        "Waima"
    ],
    "name:nor_x_preferred":[
        "Waima"
    ],
    "wof:name":"Waima",
    "wof:placetype":"locality"
},
  "geometry": {"coordinates":[-12.18537,7.36967],"type":"Point"}
}