{
  "type": "Feature",
  "properties": {
    "gn:admin1_code":"3.0",
    "gn:asciiname":"Mokumbara",
    "gn:country_code":"SL",
    "gn:dem":22,
    "gn:feature_class":"P",
    "gn:feature_code":"PPL",
    "gn:name":"Mokumbara",
    "gn:population":0,
    "gn:timezone":"Africa/Freetown",
    "iso:country":"SL",
    "name:eng_x_preferred":[
        "Mokumbara"
    ],
    "wof:name":"Mokumbara",
    "wof:placetype":"locality"
},
  "geometry": {"coordinates":[-12.54207,7.98663],"type":"Point"}
}