{
  "type": "Feature",
  "properties": {
    "gn:admin1_code":"3.0",
    "gn:asciiname":"Ngiehun",
    "gn:country_code":"SL",
    "gn:dem":30,
    "gn:feature_class":"P",
    "gn:feature_code":"PPL",
    "gn:name":"Ngiehun",
    "gn:population":0,
    "gn:timezone":"Africa/Freetown",
    "iso:country":"SL",
    "name:eng_x_preferred":[
        "Ngiehun"
    ],
    "name:und_x_variant":[
        "Giehun"
    ],
    "wof:name":"Ngiehun",
    "wof:placetype":"locality"
},
  "geometry": {"coordinates":[-12.67495,7.98713],"type":"Point"}
}