{
  "type": "Feature",
  "properties": {
    "gn:admin1_code":"4.0",
    "gn:asciiname":"Mussessi",
    "gn:country_code":"SL",
    "gn:dem":19,
    "gn:feature_class":"P",
    "gn:feature_code":"PPL",
    "gn:name":"Mussessi",
    "gn:population":0,
    "gn:timezone":"Africa/Freetown",
    "iso:country":"SL",
    "name:eng_x_preferred":[
        "Mussessi"
    ],
    "wof:name":"Mussessi",
    "wof:placetype":"locality"
},
  "geometry": {"coordinates":[-13.08156,8.23531],"type":"Point"}
}