{
  "type": "Feature",
  "properties": {
    "gn:admin1_code":"2.0",
    "gn:asciiname":"Fusia",
    "gn:country_code":"SL",
    "gn:dem":403,
    "gn:feature_class":"P",
    "gn:feature_code":"PPL",
    "gn:name":"Fusia",
    "gn:population":0,
    "gn:timezone":"Africa/Freetown",
    "iso:country":"SL",
    "name:eng_x_preferred":[
        "Fusia"
    ],
    "wof:name":"Fusia",
    "wof:placetype":"locality"
},
  "geometry": {"coordinates":[-11.33215,9.89184],"type":"Point"}
}