{
  "type": "Feature",
  "properties": {
    "gn:admin1_code":"2.0",
    "gn:asciiname":"Mindia",
    "gn:country_code":"SL",
    "gn:dem":392,
    "gn:feature_class":"P",
    "gn:feature_code":"PPL",
    "gn:name":"Mindia",
    "gn:population":0,
    "gn:timezone":"Africa/Freetown",
    "iso:country":"SL",
    "name:eng_x_preferred":[
        "Mindia"
    ],
    "wof:name":"Mindia",
    "wof:placetype":"locality"
},
  "geometry": {"coordinates":[-11.55085,9.06103],"type":"Point"}
}