{
  "type": "Feature",
  "properties": {
    "gn:admin1_code":"3.0",
    "gn:asciiname":"Gbapi",
    "gn:country_code":"SL",
    "gn:dem":72,
    "gn:feature_class":"P",
    "gn:feature_code":"PPL",
    "gn:name":"Gbapi",
    "gn:population":0,
    "gn:timezone":"Africa/Freetown",
    "iso:country":"SL",
    "name:eng_x_preferred":[
        "Gbapi"
    ],
    "name:und_x_variant":[
        "Gbap"
    ],
    "wof:name":"Gbapi",
    "wof:placetype":"locality"
},
  "geometry": {"coordinates":[-12.25244,8.23192],"type":"Point"}
}