{
  "type": "Feature",
  "properties": {
    "gn:admin1_code":"02",
    "gn:asciiname":"Rotifunk",
    "gn:country_code":"SL",
    "gn:dem":66,
    "gn:feature_class":"P",
    "gn:feature_code":"PPL",
    "gn:name":"Rotifunk",
    "gn:population":0,
    "gn:timezone":"Africa/Freetown",
    "iso:country":"SL",
    "name:eng_x_preferred":[
        "Rotifunk"
    ],
    "wof:name":"Rotifunk",
    "wof:placetype":"locality"
},
  "geometry": {"coordinates":[-12.59738,9.00838],"type":"Point"}
}