{
  "type": "Feature",
  "properties": {
    "gn:admin1_code":"3.0",
    "gn:asciiname":"Naiagolehun",
    "gn:country_code":"SL",
    "gn:dem":72,
    "gn:feature_class":"P",
    "gn:feature_code":"PPL",
    "gn:name":"Naiagolehun",
    "gn:population":0,
    "gn:timezone":"Africa/Freetown",
    "iso:country":"SL",
    "name:eng_x_preferred":[
        "Naiagolehun"
    ],
    "wof:name":"Naiagolehun",
    "wof:placetype":"locality"
},
  "geometry": {"coordinates":[-11.87161,7.97811],"type":"Point"}
}