{
  "type": "Feature",
  "properties": {
    "gn:admin1_code":"3.0",
    "gn:asciiname":"Gewojahun",
    "gn:country_code":"SL",
    "gn:dem":73,
    "gn:feature_class":"P",
    "gn:feature_code":"PPL",
    "gn:name":"Gewojahun",
    "gn:population":0,
    "gn:timezone":"Africa/Freetown",
    "iso:country":"SL",
    "name:eng_x_preferred":[
        "Gewojahun"
    ],
    "wof:name":"Gewojahun",
    "wof:placetype":"locality"
},
  "geometry": {"coordinates":[-11.32265,7.23847],"type":"Point"}
}