{
  "type": "Feature",
  "properties": {
    "gn:admin1_code":"3.0",
    "gn:asciiname":"Demaboa",
    "gn:country_code":"SL",
    "gn:dem":26,
    "gn:feature_class":"P",
    "gn:feature_code":"PPL",
    "gn:name":"Demaboa",
    "gn:population":0,
    "gn:timezone":"Africa/Freetown",
    "iso:country":"SL",
    "name:eng_x_preferred":[
        "Demaboa"
    ],
    "wof:name":"Demaboa",
    "wof:placetype":"locality"
},
  "geometry": {"coordinates":[-11.99583,7.54919],"type":"Point"}
}