{
  "type": "Feature",
  "properties": {
    "gn:admin1_code":"2.0",
    "gn:asciiname":"Baga",
    "gn:country_code":"SL",
    "gn:dem":199,
    "gn:feature_class":"P",
    "gn:feature_code":"PPL",
    "gn:name":"Baga",
    "gn:population":0,
    "gn:timezone":"Africa/Freetown",
    "iso:country":"SL",
    "wof:name":"Baga",
    "wof:placetype":"locality"
},
  "geometry": {"coordinates":[-11.95,9.26667],"type":"Point"}
}