{
  "type": "Feature",
  "properties": {
    "gn:admin1_code":"2.0",
    "gn:asciiname":"Mangi",
    "gn:country_code":"SL",
    "gn:dem":76,
    "gn:feature_class":"P",
    "gn:feature_code":"PPL",
    "gn:name":"Mangi",
    "gn:population":0,
    "gn:timezone":"Africa/Freetown",
    "iso:country":"SL",
    "name:ceb_x_preferred":[
        "Mangi"
    ],
    "name:eng_x_preferred":[
        "Mangi"
    ],
    "name:snd_x_preferred":[
        "\u0645\u0646\u06af\u064a"
    ],
    "name:swe_x_preferred":[
        "Mangi"
    ],
    "wof:name":"Mangi",
    "wof:placetype":"locality"
},
  "geometry": {"coordinates":[-11.95444,8.58114],"type":"Point"}
}