{
  "type": "Feature",
  "properties": {
    "gn:admin1_code":"2.0",
    "gn:asciiname":"Hankili",
    "gn:country_code":"SL",
    "gn:dem":300,
    "gn:feature_class":"P",
    "gn:feature_code":"PPL",
    "gn:name":"Hankili",
    "gn:population":0,
    "gn:timezone":"Africa/Freetown",
    "iso:country":"SL",
    "name:eng_x_preferred":[
        "Hankili"
    ],
    "wof:name":"Hankili",
    "wof:placetype":"locality"
},
  "geometry": {"coordinates":[-12.14197,9.41693],"type":"Point"}
}