{
  "type": "Feature",
  "properties": {
    "gn:admin1_code":"03",
    "gn:asciiname":"Nyeyama",
    "gn:country_code":"SL",
    "gn:dem":58,
    "gn:feature_class":"P",
    "gn:feature_code":"PPL",
    "gn:name":"Nyeyama",
    "gn:population":0,
    "gn:timezone":"Africa/Freetown",
    "iso:country":"SL",
    "name:eng_x_preferred":[
        "Nyeyama"
    ],
    "wof:name":"Nyeyama",
    "wof:placetype":"locality"
},
  "geometry": {"coordinates":[-11.68811,7.58167],"type":"Point"}
}