{
  "type": "Feature",
  "properties": {
    "gn:admin1_code":"2.0",
    "gn:asciiname":"Makrugbe",
    "gn:country_code":"SL",
    "gn:dem":72,
    "gn:feature_class":"P",
    "gn:feature_code":"PPL",
    "gn:name":"Makrugbe",
    "gn:population":0,
    "gn:timezone":"Africa/Freetown",
    "iso:country":"SL",
    "name:eng_x_preferred":[
        "Makrugbe"
    ],
    "wof:name":"Makrugbe",
    "wof:placetype":"locality"
},
  "geometry": {"coordinates":[-12.43917,8.60503],"type":"Point"}
}