{
  "type": "Feature",
  "properties": {
    "gn:admin1_code":"1.0",
    "gn:asciiname":"Fimbaia",
    "gn:country_code":"SL",
    "gn:dem":382,
    "gn:feature_class":"P",
    "gn:feature_code":"PPL",
    "gn:name":"Fimbaia",
    "gn:population":0,
    "gn:timezone":"Africa/Freetown",
    "iso:country":"SL",
    "name:eng_x_preferred":[
        "Fimbaia"
    ],
    "wof:name":"Fimbaia",
    "wof:placetype":"locality"
},
  "geometry": {"coordinates":[-11.10107,8.67091],"type":"Point"}
}