{
  "type": "Feature",
  "properties": {
    "gn:admin1_code":"3.0",
    "gn:asciiname":"Kondiama",
    "gn:country_code":"SL",
    "gn:dem":124,
    "gn:feature_class":"P",
    "gn:feature_code":"PPL",
    "gn:name":"Kondiama",
    "gn:population":0,
    "gn:timezone":"Africa/Freetown",
    "iso:country":"SL",
    "name:eng_x_preferred":[
        "Kondiama"
    ],
    "wof:name":"Kondiama",
    "wof:placetype":"locality"
},
  "geometry": {"coordinates":[-11.49514,8.05648],"type":"Point"}
}