{
  "type": "Feature",
  "properties": {
    "gn:admin1_code":"01",
    "gn:asciiname":"Sukudu",
    "gn:country_code":"SL",
    "gn:dem":334,
    "gn:feature_class":"P",
    "gn:feature_code":"PPL",
    "gn:name":"Sukudu",
    "gn:population":0,
    "gn:timezone":"Africa/Freetown",
    "iso:country":"SL",
    "name:eng_x_preferred":[
        "Sukudu"
    ],
    "wof:name":"Sukudu",
    "wof:placetype":"locality"
},
  "geometry": {"coordinates":[-10.68011,8.50294],"type":"Point"}
}