{
  "type": "Feature",
  "properties": {
    "gn:admin1_code":"1.0",
    "gn:asciiname":"Moima",
    "gn:country_code":"SL",
    "gn:dem":320,
    "gn:feature_class":"P",
    "gn:feature_code":"PPL",
    "gn:name":"Moima",
    "gn:population":0,
    "gn:timezone":"Africa/Freetown",
    "iso:country":"SL",
    "name:eng_x_preferred":[
        "Moima"
    ],
    "wof:name":"Moima",
    "wof:placetype":"locality"
},
  "geometry": {"coordinates":[-10.52651,8.62909],"type":"Point"}
}