{
  "type": "Feature",
  "properties": {
    "gn:admin1_code":"1.0",
    "gn:asciiname":"Kailahun",
    "gn:country_code":"SL",
    "gn:dem":524,
    "gn:feature_class":"P",
    "gn:feature_code":"PPL",
    "gn:name":"Kailahun",
    "gn:population":0,
    "gn:timezone":"Africa/Freetown",
    "iso:country":"SL",
    "name:bul_x_preferred":[
        "\u041a\u0430\u0439\u043b\u0430\u0445\u0443\u043d"
    ],
    "name:ceb_x_preferred":[
        "Kailahun"
    ],
    "name:dan_x_preferred":[
        "Kailahun"
    ],
    "name:deu_x_preferred":[
        "Kailahun"
    ],
    "name:eng_x_preferred":[
        "Kailahun"
    ],
    "name:fin_x_preferred":[
        "Kailahun"
    ],
    "name:fra_x_preferred":[
        "Kailahun"
    ],
    "name:ita_x_preferred":[
        "Kailahun"
    ],
    "name:lit_x_preferred":[
        "Kailahunas"
    ],
    "name:pol_x_preferred":[
        "Kailahun"
    ],
    "name:por_x_preferred":[
        "Kailahun"
    ],
    "name:rus_x_preferred":[
        "\u041a\u0430\u0439\u043b\u0430\u0445\u0443\u043d"
    ],
    "name:zho_x_preferred":[
        "\u51f1\u62c9\u6d2a"
    ],
    "wof:name":"Kailahun",
    "wof:placetype":"locality"
},
  "geometry": {"coordinates":[-11.0408,8.50607],"type":"Point"}
}