{
  "type": "Feature",
  "properties": {
    "gn:admin1_code":"1.0",
    "gn:asciiname":"Gahun",
    "gn:country_code":"SL",
    "gn:dem":140,
    "gn:feature_class":"P",
    "gn:feature_code":"PPL",
    "gn:name":"Gahun",
    "gn:population":0,
    "gn:timezone":"Africa/Freetown",
    "iso:country":"SL",
    "name:und_x_variant":[
        "Gbuahun"
    ],
    "wof:name":"Gahun",
    "wof:placetype":"locality"
},
  "geometry": {"coordinates":[-11.08116,7.6147],"type":"Point"}
}