{
  "type": "Feature",
  "properties": {
    "gn:admin1_code":"1.0",
    "gn:asciiname":"Koindu",
    "gn:country_code":"SL",
    "gn:dem":438,
    "gn:feature_class":"P",
    "gn:feature_code":"PPL",
    "gn:name":"Koindu",
    "gn:population":0,
    "gn:timezone":"Africa/Freetown",
    "iso:country":"SL",
    "wof:name":"Koindu",
    "wof:placetype":"locality"
},
  "geometry": {"coordinates":[-10.33505,8.46094],"type":"Point"}
}