{
  "type": "Feature",
  "properties": {
    "gn:admin1_code":"3.0",
    "gn:asciiname":"Semabu",
    "gn:country_code":"SL",
    "gn:dem":111,
    "gn:feature_class":"P",
    "gn:feature_code":"PPL",
    "gn:name":"Semabu",
    "gn:population":0,
    "gn:timezone":"Africa/Freetown",
    "iso:country":"SL",
    "name:eng_x_preferred":[
        "Semabu"
    ],
    "wof:name":"Semabu",
    "wof:placetype":"locality"
},
  "geometry": {"coordinates":[-11.52229,7.89646],"type":"Point"}
}