{
  "type": "Feature",
  "properties": {
    "gn:country":"SL",
    "gn:fcode":"PPL",
    "gn:population":2845,
    "iso:country":"SL",
    "name:und_x_variant":[
        "Giehun"
    ],
    "qs_pg:aaroncc":"SL",
    "qs_pg:gn_country":"SL",
    "qs_pg:gn_fcode":"PPL",
    "qs_pg:gn_pop":2845,
    "qs_pg:name":"Ngiehun",
    "qs_pg:photos_9r":0,
    "qs_pg:photos_sr":0,
    "qs_pg:pop_sr":4,
    "qs_pg:qs_pg_placetype":"locality",
    "wof:name":"Ngiehun",
    "wof:placetype":"locality",
    "wof:population":2845
},
  "geometry": {"coordinates":[-11.05,8.55],"type":"Point"}
}