{
  "type": "Feature",
  "properties": {
    "gn:admin1_code":"3.0",
    "gn:asciiname":"Baoma",
    "gn:country_code":"SL",
    "gn:dem":81,
    "gn:feature_class":"P",
    "gn:feature_code":"PPL",
    "gn:name":"Baoma",
    "gn:population":0,
    "gn:timezone":"Africa/Freetown",
    "iso:country":"SL",
    "name:ceb_x_preferred":[
        "Baoma"
    ],
    "name:eng_x_preferred":[
        "Baoma"
    ],
    "name:ron_x_preferred":[
        "Baoma"
    ],
    "wof:name":"Baoma",
    "wof:placetype":"locality"
},
  "geometry": {"coordinates":[-11.5049,7.54261],"type":"Point"}
}