{
  "type": "Feature",
  "properties": {
    "gn:admin1_code":"2.0",
    "gn:asciiname":"Forokoia",
    "gn:country_code":"SL",
    "gn:dem":420,
    "gn:feature_class":"P",
    "gn:feature_code":"PPL",
    "gn:name":"Forokoia",
    "gn:population":0,
    "gn:timezone":"Africa/Freetown",
    "iso:country":"SL",
    "wof:name":"Forokoia",
    "wof:placetype":"locality"
},
  "geometry": {"coordinates":[-11.35,8.88333],"type":"Point"}
}