{
  "type": "Feature",
  "properties": {
    "gn:admin1_code":"01",
    "gn:asciiname":"Siabu",
    "gn:country_code":"SL",
    "gn:dem":426,
    "gn:feature_class":"P",
    "gn:feature_code":"PPL",
    "gn:name":"Siabu",
    "gn:population":0,
    "gn:timezone":"Africa/Freetown",
    "iso:country":"SL",
    "name:eng_x_preferred":[
        "Siabu"
    ],
    "wof:name":"Siabu",
    "wof:placetype":"locality"
},
  "geometry": {"coordinates":[-10.38198,8.41145],"type":"Point"}
}