{
  "type": "Feature",
  "properties": {
    "gn:admin1_code":"1.0",
    "gn:asciiname":"Dorwa",
    "gn:country_code":"SL",
    "gn:dem":377,
    "gn:feature_class":"P",
    "gn:feature_code":"PPL",
    "gn:name":"Dorwa",
    "gn:population":0,
    "gn:timezone":"Africa/Freetown",
    "iso:country":"SL",
    "name:eng_x_preferred":[
        "Dorwa"
    ],
    "name:und_x_variant":[
        "Laowa"
    ],
    "wof:name":"Dorwa",
    "wof:placetype":"locality"
},
  "geometry": {"coordinates":[-10.42442,8.39951],"type":"Point"}
}