{
  "type": "Feature",
  "properties": {
    "gn:admin1_code":"2.0",
    "gn:asciiname":"Makangwi",
    "gn:country_code":"SL",
    "gn:dem":106,
    "gn:feature_class":"P",
    "gn:feature_code":"PPL",
    "gn:name":"Makangwi",
    "gn:population":0,
    "gn:timezone":"Africa/Freetown",
    "iso:country":"SL",
    "name:eng_x_preferred":[
        "Makangwi"
    ],
    "wof:name":"Makangwi",
    "wof:placetype":"locality"
},
  "geometry": {"coordinates":[-12.22114,9.39471],"type":"Point"}
}