{
  "type": "Feature",
  "properties": {
    "gn:admin1_code":"3.0",
    "gn:asciiname":"Motaua",
    "gn:country_code":"SL",
    "gn:dem":25,
    "gn:feature_class":"P",
    "gn:feature_code":"PPL",
    "gn:name":"Motaua",
    "gn:population":0,
    "gn:timezone":"Africa/Freetown",
    "iso:country":"SL",
    "name:eng_x_preferred":[
        "Motaua"
    ],
    "wof:name":"Motaua",
    "wof:placetype":"locality"
},
  "geometry": {"coordinates":[-12.72962,8.24721],"type":"Point"}
}