{
  "type": "Feature",
  "properties": {
    "gn:admin1_code":"2.0",
    "gn:asciiname":"Bambali",
    "gn:country_code":"SL",
    "gn:dem":14,
    "gn:feature_class":"P",
    "gn:feature_code":"PPL",
    "gn:name":"Bambali",
    "gn:population":0,
    "gn:timezone":"Africa/Freetown",
    "iso:country":"SL",
    "name:ceb_x_preferred":[
        "Bambali"
    ],
    "name:deu_x_preferred":[
        "Bambali"
    ],
    "name:swe_x_preferred":[
        "Bambali"
    ],
    "name:und_x_variant":[
        "Bombali",
        "Bambali"
    ],
    "wof:name":"Bambali",
    "wof:placetype":"locality"
},
  "geometry": {"coordinates":[-13.1452,8.98329],"type":"Point"}
}