{
  "type": "Feature",
  "properties": {
    "gn:admin1_code":"1.0",
    "gn:asciiname":"Dunemaro",
    "gn:country_code":"SL",
    "gn:dem":412,
    "gn:feature_class":"P",
    "gn:feature_code":"PPL",
    "gn:name":"Dunemaro",
    "gn:population":0,
    "gn:timezone":"Africa/Freetown",
    "iso:country":"SL",
    "wof:name":"Dunemaro",
    "wof:placetype":"locality"
},
  "geometry": {"coordinates":[-10.88333,8.65],"type":"Point"}
}