{
  "type": "Feature",
  "properties": {
    "gn:admin1_code":"2.0",
    "gn:asciiname":"Mabunguru",
    "gn:country_code":"SL",
    "gn:dem":24,
    "gn:feature_class":"P",
    "gn:feature_code":"PPL",
    "gn:name":"Mabunguru",
    "gn:population":0,
    "gn:timezone":"Africa/Freetown",
    "iso:country":"SL",
    "name:eng_x_preferred":[
        "Mabunguru"
    ],
    "wof:name":"Mabunguru",
    "wof:placetype":"locality"
},
  "geometry": {"coordinates":[-12.88864,8.57608],"type":"Point"}
}