{
  "type": "Feature",
  "properties": {
    "gn:admin1_code":"03",
    "gn:asciiname":"Yoke",
    "gn:country_code":"SL",
    "gn:dem":12,
    "gn:feature_class":"P",
    "gn:feature_code":"PPL",
    "gn:name":"Yoke",
    "gn:population":0,
    "gn:timezone":"Africa/Freetown",
    "iso:country":"SL",
    "name:eng_x_preferred":[
        "Yoke"
    ],
    "wof:name":"Yoke",
    "wof:placetype":"locality"
},
  "geometry": {"coordinates":[-12.48073,7.81636],"type":"Point"}
}