{
  "type": "Feature",
  "properties": {
    "gn:admin1_code":"04",
    "gn:asciiname":"Ro-gberri",
    "gn:country_code":"SL",
    "gn:dem":27,
    "gn:feature_class":"P",
    "gn:feature_code":"PPL",
    "gn:name":"Ro-gberri",
    "gn:population":0,
    "gn:timezone":"Africa/Freetown",
    "iso:country":"SL",
    "name:eng_x_preferred":[
        "Ro-gberri"
    ],
    "wof:name":"Ro-gberri",
    "wof:placetype":"locality"
},
  "geometry": {"coordinates":[-12.9971,8.3086],"type":"Point"}
}