{
  "type": "Feature",
  "properties": {
    "gn:admin1_code":"2.0",
    "gn:asciiname":"Mandaka",
    "gn:country_code":"SL",
    "gn:dem":18,
    "gn:feature_class":"P",
    "gn:feature_code":"PPL",
    "gn:name":"Mandaka",
    "gn:population":0,
    "gn:timezone":"Africa/Freetown",
    "iso:country":"SL",
    "name:eng_x_preferred":[
        "Mandaka"
    ],
    "wof:name":"Mandaka",
    "wof:placetype":"locality"
},
  "geometry": {"coordinates":[-12.91568,8.36655],"type":"Point"}
}