{
  "type": "Feature",
  "properties": {
    "gn:admin1_code":"01",
    "gn:asciiname":"Yabaia",
    "gn:country_code":"SL",
    "gn:dem":457,
    "gn:feature_class":"P",
    "gn:feature_code":"PPL",
    "gn:name":"Yabaia",
    "gn:population":0,
    "gn:timezone":"Africa/Freetown",
    "iso:country":"SL",
    "name:eng_x_preferred":[
        "Yabaia"
    ],
    "wof:name":"Yabaia",
    "wof:placetype":"locality"
},
  "geometry": {"coordinates":[-11.00049,8.82677],"type":"Point"}
}