{
  "type": "Feature",
  "properties": {
    "gn:admin1_code":"2.0",
    "gn:asciiname":"Kambia",
    "gn:country_code":"SL",
    "gn:dem":84,
    "gn:feature_class":"P",
    "gn:feature_code":"PPL",
    "gn:name":"Kambia",
    "gn:population":0,
    "gn:timezone":"Africa/Freetown",
    "iso:country":"SL",
    "name:ceb_x_preferred":[
        "Kambia"
    ],
    "name:eng_x_preferred":[
        "Kambia"
    ],
    "name:ita_x_preferred":[
        "Kambia"
    ],
    "name:nld_x_preferred":[
        "Kambia"
    ],
    "name:swe_x_preferred":[
        "Kambia"
    ],
    "wof:name":"Kambia",
    "wof:placetype":"locality"
},
  "geometry": {"coordinates":[-12.29404,9.33784],"type":"Point"}
}