{
  "type": "Feature",
  "properties": {
    "gn:admin1_code":"3.0",
    "gn:asciiname":"Mambo",
    "gn:country_code":"SL",
    "gn:dem":6,
    "gn:feature_class":"P",
    "gn:feature_code":"PPL",
    "gn:name":"Mambo",
    "gn:population":0,
    "gn:timezone":"Africa/Freetown",
    "iso:country":"SL",
    "name:eng_x_preferred":[
        "Mambo"
    ],
    "wof:name":"Mambo",
    "wof:placetype":"locality"
},
  "geometry": {"coordinates":[-12.56679,7.50372],"type":"Point"}
}