{
  "type": "Feature",
  "properties": {
    "gn:admin1_code":"3.0",
    "gn:asciiname":"Motuama",
    "gn:country_code":"SL",
    "gn:dem":59,
    "gn:feature_class":"P",
    "gn:feature_code":"PPL",
    "gn:name":"Motuama",
    "gn:population":0,
    "gn:timezone":"Africa/Freetown",
    "iso:country":"SL",
    "name:eng_x_preferred":[
        "Motuama"
    ],
    "wof:name":"Motuama",
    "wof:placetype":"locality"
},
  "geometry": {"coordinates":[-11.98981,7.92285],"type":"Point"}
}