{
  "type": "Feature",
  "properties": {
    "gn:admin1_code":"2.0",
    "gn:asciiname":"Bori",
    "gn:country_code":"SL",
    "gn:dem":87,
    "gn:feature_class":"P",
    "gn:feature_code":"PPL",
    "gn:name":"Bori",
    "gn:population":0,
    "gn:timezone":"Africa/Freetown",
    "iso:country":"SL",
    "name:ceb_x_preferred":[
        "Bori"
    ],
    "name:deu_x_preferred":[
        "Bori"
    ],
    "name:eng_x_preferred":[
        "Bori"
    ],
    "name:fra_x_preferred":[
        "Bori"
    ],
    "name:hun_x_preferred":[
        "Bori"
    ],
    "name:ita_x_preferred":[
        "Bori"
    ],
    "name:kor_x_preferred":[
        "\ubcf4\ub9ac"
    ],
    "name:por_x_preferred":[
        "Bori"
    ],
    "name:swe_x_preferred":[
        "Bori"
    ],
    "name:vie_x_preferred":[
        "Bori"
    ],
    "wof:name":"Bori",
    "wof:placetype":"locality"
},
  "geometry": {"coordinates":[-12.7367,9.21226],"type":"Point"}
}