{
  "type": "Feature",
  "properties": {
    "gn:admin1_code":"3.0",
    "gn:asciiname":"Gongohun",
    "gn:country_code":"SL",
    "gn:dem":76,
    "gn:feature_class":"P",
    "gn:feature_code":"PPL",
    "gn:name":"Gongohun",
    "gn:population":0,
    "gn:timezone":"Africa/Freetown",
    "iso:country":"SL",
    "name:eng_x_preferred":[
        "Gongohun"
    ],
    "name:und_x_variant":[
        "Ganguhun"
    ],
    "wof:name":"Gongohun",
    "wof:placetype":"locality"
},
  "geometry": {"coordinates":[-12.20436,8.17886],"type":"Point"}
}