{
  "type": "Feature",
  "properties": {
    "gn:admin1_code":"3.0",
    "gn:asciiname":"Kpakruma",
    "gn:country_code":"SL",
    "gn:dem":77,
    "gn:feature_class":"P",
    "gn:feature_code":"PPL",
    "gn:name":"Kpakruma",
    "gn:population":0,
    "gn:timezone":"Africa/Freetown",
    "iso:country":"SL",
    "name:eng_x_preferred":[
        "Kpakruma"
    ],
    "wof:name":"Kpakruma",
    "wof:placetype":"locality"
},
  "geometry": {"coordinates":[-11.80303,7.82433],"type":"Point"}
}