{
  "type": "Feature",
  "properties": {
    "gn:admin1_code":"2.0",
    "gn:asciiname":"Kadankan",
    "gn:country_code":"SL",
    "gn:dem":441,
    "gn:feature_class":"P",
    "gn:feature_code":"PPL",
    "gn:name":"Kadankan",
    "gn:population":0,
    "gn:timezone":"Africa/Freetown",
    "iso:country":"SL",
    "name:eng_x_preferred":[
        "Kadankan"
    ],
    "wof:name":"Kadankan",
    "wof:placetype":"locality"
},
  "geometry": {"coordinates":[-11.70816,9.59544],"type":"Point"}
}