{
  "type": "Feature",
  "properties": {
    "gn:admin1_code":"1.0",
    "gn:asciiname":"Gehama",
    "gn:country_code":"SL",
    "gn:dem":228,
    "gn:feature_class":"P",
    "gn:feature_code":"PPL",
    "gn:name":"Gehama",
    "gn:population":0,
    "gn:timezone":"Africa/Freetown",
    "iso:country":"SL",
    "name:und_x_variant":[
        "Geliama",
        "Gehama"
    ],
    "wof:name":"Gehama",
    "wof:placetype":"locality"
},
  "geometry": {"coordinates":[-11.03839,8.21803],"type":"Point"}
}