{
  "type": "Feature",
  "properties": {
    "gn:admin1_code":"03",
    "gn:asciiname":"Tormabum",
    "gn:country_code":"SL",
    "gn:dem":15,
    "gn:feature_class":"P",
    "gn:feature_code":"PPL",
    "gn:name":"Tormabum",
    "gn:population":0,
    "gn:timezone":"Africa/Freetown",
    "iso:country":"SL",
    "name:eng_x_preferred":[
        "Tormabum"
    ],
    "wof:name":"Tormabum",
    "wof:placetype":"locality"
},
  "geometry": {"coordinates":[-12.0063,7.41514],"type":"Point"}
}