{
  "type": "Feature",
  "properties": {
    "gn:admin1_code":"2.0",
    "gn:asciiname":"Makola",
    "gn:country_code":"SL",
    "gn:dem":73,
    "gn:feature_class":"P",
    "gn:feature_code":"PPL",
    "gn:name":"Makola",
    "gn:population":0,
    "gn:timezone":"Africa/Freetown",
    "iso:country":"SL",
    "name:ceb_x_preferred":[
        "Makola"
    ],
    "name:eng_x_preferred":[
        "Makola"
    ],
    "name:swe_x_preferred":[
        "Makola"
    ],
    "wof:name":"Makola",
    "wof:placetype":"locality"
},
  "geometry": {"coordinates":[-12.48168,8.8899],"type":"Point"}
}