{
  "type": "Feature",
  "properties": {
    "gn:admin1_code":"3.0",
    "gn:asciiname":"Funkia",
    "gn:country_code":"SL",
    "gn:dem":13,
    "gn:feature_class":"P",
    "gn:feature_code":"PPL",
    "gn:name":"Funkia",
    "gn:population":0,
    "gn:timezone":"Africa/Freetown",
    "iso:country":"SL",
    "name:eng_x_preferred":[
        "Funkia"
    ],
    "wof:name":"Funkia",
    "wof:placetype":"locality"
},
  "geometry": {"coordinates":[-11.84057,7.25399],"type":"Point"}
}