{
  "type": "Feature",
  "properties": {
    "gn:admin1_code":"2.0",
    "gn:asciiname":"Masahe",
    "gn:country_code":"SL",
    "gn:dem":186,
    "gn:feature_class":"P",
    "gn:feature_code":"PPL",
    "gn:name":"Masahe",
    "gn:population":0,
    "gn:timezone":"Africa/Freetown",
    "iso:country":"SL",
    "name:eng_x_preferred":[
        "Masahe"
    ],
    "wof:name":"Masahe",
    "wof:placetype":"locality"
},
  "geometry": {"coordinates":[-11.93344,9.2343],"type":"Point"}
}