{
  "type": "Feature",
  "properties": {
    "gn:admin1_code":"1.0",
    "gn:asciiname":"Jaluahun",
    "gn:country_code":"SL",
    "gn:dem":157,
    "gn:feature_class":"P",
    "gn:feature_code":"PPL",
    "gn:name":"Jaluahun",
    "gn:population":0,
    "gn:timezone":"Africa/Freetown",
    "iso:country":"SL",
    "name:und_x_variant":[
        "Jaluahon"
    ],
    "wof:name":"Jaluahun",
    "wof:placetype":"locality"
},
  "geometry": {"coordinates":[-11.11925,7.78872],"type":"Point"}
}