{
  "type": "Feature",
  "properties": {
    "gn:admin1_code":"1.0",
    "gn:asciiname":"Kajahun",
    "gn:country_code":"SL",
    "gn:dem":188,
    "gn:feature_class":"P",
    "gn:feature_code":"PPL",
    "gn:name":"Kajahun",
    "gn:population":0,
    "gn:timezone":"Africa/Freetown",
    "iso:country":"SL",
    "name:eng_x_preferred":[
        "Kajahun"
    ],
    "name:und_x_variant":[
        "Jagbwema"
    ],
    "wof:name":"Kajahun",
    "wof:placetype":"locality"
},
  "geometry": {"coordinates":[-10.84799,8.29007],"type":"Point"}
}