{
  "type": "Feature",
  "properties": {
    "gn:admin1_code":"01",
    "gn:asciiname":"Walima",
    "gn:country_code":"SL",
    "gn:dem":169,
    "gn:feature_class":"P",
    "gn:feature_code":"PPL",
    "gn:name":"Walima",
    "gn:population":0,
    "gn:timezone":"Africa/Freetown",
    "iso:country":"SL",
    "name:ara_x_preferred":[
        "\u0648\u0644\u064a\u0645\u0629"
    ],
    "name:eng_x_preferred":[
        "Walima"
    ],
    "name:fas_x_preferred":[
        "\u0648\u0644\u06cc\u0645\u0647"
    ],
    "name:ind_x_preferred":[
        "Walimatul 'ursy"
    ],
    "name:kaz_x_preferred":[
        "\u0423\u04d9\u043b\u0438\u043c\u0430"
    ],
    "name:msa_x_preferred":[
        "Walimatulurus"
    ],
    "name:sqi_x_preferred":[
        "Velime"
    ],
    "wof:name":"Walima",
    "wof:placetype":"locality"
},
  "geometry": {"coordinates":[-10.95938,8.06536],"type":"Point"}
}