{
  "type": "Feature",
  "properties": {
    "gn:admin1_code":"03",
    "gn:asciiname":"Yoni",
    "gn:country_code":"SL",
    "gn:dem":14,
    "gn:feature_class":"P",
    "gn:feature_code":"PPL",
    "gn:name":"Yoni",
    "gn:population":0,
    "gn:timezone":"Africa/Freetown",
    "iso:country":"SL",
    "name:bih_x_preferred":[
        "\u092f\u094b\u0928\u0940"
    ],
    "name:cat_x_preferred":[
        "Yoni"
    ],
    "name:dan_x_preferred":[
        "Yoni"
    ],
    "name:deu_x_preferred":[
        "Yoni"
    ],
    "name:ell_x_preferred":[
        "\u0393\u03b9\u03bf\u03bd\u03af"
    ],
    "name:eng_x_preferred":[
        "Yoni"
    ],
    "name:fas_x_preferred":[
        "\u06cc\u0648\u0646\u06cc"
    ],
    "name:fra_x_preferred":[
        "Yoni"
    ],
    "name:heb_x_preferred":[
        "\u05d9\u05d5\u05e0\u05d9"
    ],
    "name:hin_x_preferred":[
        "\u092a\u093f\u0923\u094d\u0921\u093f\u0915\u093e"
    ],
    "name:ind_x_preferred":[
        "Yoni"
    ],
    "name:ita_x_preferred":[
        "Yoni"
    ],
    "name:jav_x_preferred":[
        "Yoni"
    ],
    "name:lit_x_preferred":[
        "Joni"
    ],
    "name:msa_x_preferred":[
        "Yoni"
    ],
    "name:nep_x_preferred":[
        "\u092f\u094b\u0928\u0940"
    ],
    "name:nld_x_preferred":[
        "Yoni"
    ],
    "name:pol_x_preferred":[
        "Joni"
    ],
    "name:por_x_preferred":[
        "Yoni"
    ],
    "name:rus_x_preferred":[
        "\u0419\u043e\u043d\u0438"
    ],
    "name:spa_x_preferred":[
        "Ioni"
    ],
    "name:swe_x_preferred":[
        "Yoni"
    ],
    "name:tam_x_preferred":[
        "\u0baf\u0bcb\u0ba9\u0bbf"
    ],
    "name:tat_x_preferred":[
        "\u0419\u043e\u043d\u0438"
    ],
    "name:tel_x_preferred":[
        "\u0c32\u0c3f\u0c02\u0c17 \u0c2f\u0c4b\u0c28\u0c3f"
    ],
    "name:tha_x_preferred":[
        "\u0e42\u0e22\u0e19\u0e35"
    ],
    "name:tur_x_preferred":[
        "Yoni"
    ],
    "name:ukr_x_preferred":[
        "\u0419\u043e\u043d\u0456"
    ],
    "name:vie_x_preferred":[
        "Yoni"
    ],
    "wof:name":"Yoni",
    "wof:placetype":"locality"
},
  "geometry": {"coordinates":[-11.98806,7.45605],"type":"Point"}
}