{
  "type": "Feature",
  "properties": {
    "gn:admin1_code":"03",
    "gn:asciiname":"Yoni",
    "gn:country_code":"SL",
    "gn:dem":14,
    "gn:feature_class":"P",
    "gn:feature_code":"PPL",
    "gn:name":"Yoni",
    "gn:population":0,
    "gn:timezone":"Africa/Freetown",
    "iso:country":"SL",
    "name:eng_x_preferred":[
        "Yoni"
    ],
    "wof:name":"Yoni",
    "wof:placetype":"locality"
},
  "geometry": {"coordinates":[-11.98806,7.45605],"type":"Point"}
}