{
  "type": "Feature",
  "properties": {
    "gn:admin1_code":"2.0",
    "gn:asciiname":"Bambakalia",
    "gn:country_code":"SL",
    "gn:dem":396,
    "gn:feature_class":"P",
    "gn:feature_code":"PPL",
    "gn:name":"Bambakalia",
    "gn:population":0,
    "gn:timezone":"Africa/Freetown",
    "iso:country":"SL",
    "name:eng_x_preferred":[
        "Bambakalia"
    ],
    "wof:name":"Bambakalia",
    "wof:placetype":"locality"
},
  "geometry": {"coordinates":[-11.32744,9.27544],"type":"Point"}
}