{
  "type": "Feature",
  "properties": {
    "gn:admin1_code":"1.0",
    "gn:asciiname":"Mahoma",
    "gn:country_code":"SL",
    "gn:dem":248,
    "gn:feature_class":"P",
    "gn:feature_code":"PPL",
    "gn:name":"Mahoma",
    "gn:population":0,
    "gn:timezone":"Africa/Freetown",
    "iso:country":"SL",
    "name:eng_x_preferred":[
        "Mahoma"
    ],
    "wof:name":"Mahoma",
    "wof:placetype":"locality"
},
  "geometry": {"coordinates":[-10.97859,7.74365],"type":"Point"}
}