{
  "type": "Feature",
  "properties": {
    "gn:admin1_code":"1.0",
    "gn:asciiname":"Niahun",
    "gn:country_code":"SL",
    "gn:dem":143,
    "gn:feature_class":"P",
    "gn:feature_code":"PPL",
    "gn:name":"Niahun",
    "gn:population":0,
    "gn:timezone":"Africa/Freetown",
    "iso:country":"SL",
    "name:eng_x_preferred":[
        "Niahun"
    ],
    "name:und_x_variant":[
        "Naiahun"
    ],
    "wof:name":"Niahun",
    "wof:placetype":"locality"
},
  "geometry": {"coordinates":[-11.33424,8.16552],"type":"Point"}
}