{
  "type": "Feature",
  "properties": {
    "gn:admin1_code":"1.0",
    "gn:asciiname":"Kalia",
    "gn:country_code":"SL",
    "gn:dem":397,
    "gn:feature_class":"P",
    "gn:feature_code":"PPL",
    "gn:name":"Kalia",
    "gn:population":0,
    "gn:timezone":"Africa/Freetown",
    "iso:country":"SL",
    "wof:name":"Kalia",
    "wof:placetype":"locality"
},
  "geometry": {"coordinates":[-10.58333,8.88333],"type":"Point"}
}