{
  "type": "Feature",
  "properties": {
    "gn:admin1_code":"3.0",
    "gn:asciiname":"Fonkia",
    "gn:country_code":"SL",
    "gn:dem":73,
    "gn:feature_class":"P",
    "gn:feature_code":"PPL",
    "gn:name":"Fonkia",
    "gn:population":0,
    "gn:timezone":"Africa/Freetown",
    "iso:country":"SL",
    "name:eng_x_preferred":[
        "Fonkia"
    ],
    "name:und_x_variant":[
        "Fungia"
    ],
    "wof:name":"Fonkia",
    "wof:placetype":"locality"
},
  "geometry": {"coordinates":[-12.01955,8.10302],"type":"Point"}
}