{
  "type": "Feature",
  "properties": {
    "gn:admin1_code":"3.0",
    "gn:asciiname":"Bunjema",
    "gn:country_code":"SL",
    "gn:dem":144,
    "gn:feature_class":"P",
    "gn:feature_code":"PPL",
    "gn:name":"Bunjema",
    "gn:population":0,
    "gn:timezone":"Africa/Freetown",
    "iso:country":"SL",
    "name:eng_x_preferred":[
        "Bunjema"
    ],
    "wof:name":"Bunjema",
    "wof:placetype":"locality"
},
  "geometry": {"coordinates":[-11.36671,8.16341],"type":"Point"}
}