{
  "type": "Feature",
  "properties": {
    "gn:admin1_code":"1.0",
    "gn:asciiname":"Kombaia",
    "gn:country_code":"SL",
    "gn:dem":367,
    "gn:feature_class":"P",
    "gn:feature_code":"PPL",
    "gn:name":"Kombaia",
    "gn:population":0,
    "gn:timezone":"Africa/Freetown",
    "iso:country":"SL",
    "name:eng_x_preferred":[
        "Kombaia"
    ],
    "wof:name":"Kombaia",
    "wof:placetype":"locality"
},
  "geometry": {"coordinates":[-10.97866,8.7568],"type":"Point"}
}