{
  "type": "Feature",
  "properties": {
    "gn:admin1_code":"2.0",
    "gn:asciiname":"Fasinaia",
    "gn:country_code":"SL",
    "gn:dem":65,
    "gn:feature_class":"P",
    "gn:feature_code":"PPL",
    "gn:name":"Fasinaia",
    "gn:population":0,
    "gn:timezone":"Africa/Freetown",
    "iso:country":"SL",
    "name:eng_x_preferred":[
        "Fasinaia"
    ],
    "wof:name":"Fasinaia",
    "wof:placetype":"locality"
},
  "geometry": {"coordinates":[-12.64011,9.39558],"type":"Point"}
}