{
  "type": "Feature",
  "properties": {
    "gn:admin1_code":"1.0",
    "gn:asciiname":"Faiama",
    "gn:country_code":"SL",
    "gn:dem":415,
    "gn:feature_class":"P",
    "gn:feature_code":"PPL",
    "gn:name":"Faiama",
    "gn:population":0,
    "gn:timezone":"Africa/Freetown",
    "iso:country":"SL",
    "name:eng_x_preferred":[
        "Faiama"
    ],
    "wof:name":"Faiama",
    "wof:placetype":"locality"
},
  "geometry": {"coordinates":[-10.56667,8.83333],"type":"Point"}
}