{
  "type": "Feature",
  "properties": {
    "gn:admin1_code":"3.0",
    "gn:asciiname":"Kabanka",
    "gn:country_code":"SL",
    "gn:dem":25,
    "gn:feature_class":"P",
    "gn:feature_code":"PPL",
    "gn:name":"Kabanka",
    "gn:population":0,
    "gn:timezone":"Africa/Freetown",
    "iso:country":"SL",
    "name:eng_x_preferred":[
        "Kabanka"
    ],
    "wof:name":"Kabanka",
    "wof:placetype":"locality"
},
  "geometry": {"coordinates":[-12.87017,8.21172],"type":"Point"}
}