{
  "type": "Feature",
  "properties": {
    "gn:admin1_code":"2.0",
    "gn:asciiname":"Kamero",
    "gn:country_code":"SL",
    "gn:dem":419,
    "gn:feature_class":"P",
    "gn:feature_code":"PPL",
    "gn:name":"Kamero",
    "gn:population":0,
    "gn:timezone":"Africa/Freetown",
    "iso:country":"SL",
    "name:eng_x_preferred":[
        "Kamero"
    ],
    "wof:name":"Kamero",
    "wof:placetype":"locality"
},
  "geometry": {"coordinates":[-11.61041,9.02228],"type":"Point"}
}