{
  "type": "Feature",
  "properties": {
    "gn:admin1_code":"1.0",
    "gn:asciiname":"Waidala",
    "gn:country_code":"SL",
    "gn:dem":336,
    "gn:feature_class":"P",
    "gn:feature_code":"PPL",
    "gn:name":"Waidala",
    "gn:population":0,
    "gn:timezone":"Africa/Freetown",
    "iso:country":"SL",
    "wof:name":"Waidala",
    "wof:placetype":"locality"
},
  "geometry": {"coordinates":[-11.22765,8.71496],"type":"Point"}
}