{
  "type": "Feature",
  "properties": {
    "gn:admin1_code":"1.0",
    "gn:asciiname":"Gelehun",
    "gn:country_code":"SL",
    "gn:dem":383,
    "gn:feature_class":"P",
    "gn:feature_code":"PPL",
    "gn:name":"Gelehun",
    "gn:population":0,
    "gn:timezone":"Africa/Freetown",
    "iso:country":"SL",
    "name:eng_x_preferred":[
        "Gelehun"
    ],
    "wof:name":"Gelehun",
    "wof:placetype":"locality"
},
  "geometry": {"coordinates":[-10.39978,8.26761],"type":"Point"}
}