{
  "type": "Feature",
  "properties": {
    "gn:admin1_code":"2.0",
    "gn:asciiname":"Fula Town",
    "gn:country_code":"SL",
    "gn:dem":121,
    "gn:feature_class":"P",
    "gn:feature_code":"PPL",
    "gn:name":"Fula Town",
    "gn:population":0,
    "gn:timezone":"Africa/Freetown",
    "iso:country":"SL",
    "name:eng_x_preferred":[
        "Fula Town"
    ],
    "wof:name":"Fula Town",
    "wof:placetype":"locality"
},
  "geometry": {"coordinates":[-11.86737,9.32325],"type":"Point"}
}