{
  "type": "Feature",
  "properties": {
    "gn:admin1_code":"2.0",
    "gn:asciiname":"Kali",
    "gn:country_code":"SL",
    "gn:dem":51,
    "gn:feature_class":"P",
    "gn:feature_code":"PPL",
    "gn:name":"Kali",
    "gn:population":0,
    "gn:timezone":"Africa/Freetown",
    "iso:country":"SL",
    "name:eng_x_preferred":[
        "Kali"
    ],
    "wof:name":"Kali",
    "wof:placetype":"locality"
},
  "geometry": {"coordinates":[-12.65125,9.49786],"type":"Point"}
}