{
  "type": "Feature",
  "properties": {
    "gn:admin1_code":"2.0",
    "gn:asciiname":"Mayali",
    "gn:country_code":"SL",
    "gn:dem":83,
    "gn:feature_class":"P",
    "gn:feature_code":"PPL",
    "gn:name":"Mayali",
    "gn:population":0,
    "gn:timezone":"Africa/Freetown",
    "iso:country":"SL",
    "name:eng_x_preferred":[
        "Mayali"
    ],
    "wof:name":"Mayali",
    "wof:placetype":"locality"
},
  "geometry": {"coordinates":[-12.21367,9.42278],"type":"Point"}
}