{
  "type": "Feature",
  "properties": {
    "gn:admin1_code":"1.0",
    "gn:asciiname":"Njarma",
    "gn:country_code":"SL",
    "gn:dem":203,
    "gn:feature_class":"P",
    "gn:feature_code":"PPL",
    "gn:name":"Njarma",
    "gn:population":0,
    "gn:timezone":"Africa/Freetown",
    "iso:country":"SL",
    "name:eng_x_preferred":[
        "Njarma"
    ],
    "name:und_x_variant":[
        "Njama"
    ],
    "wof:name":"Njarma",
    "wof:placetype":"locality"
},
  "geometry": {"coordinates":[-10.65185,8.1406],"type":"Point"}
}