{
  "type": "Feature",
  "properties": {
    "gn:admin1_code":"2.0",
    "gn:asciiname":"Dintilipan",
    "gn:country_code":"SL",
    "gn:dem":23,
    "gn:feature_class":"P",
    "gn:feature_code":"PPL",
    "gn:name":"Dintilipan",
    "gn:population":0,
    "gn:timezone":"Africa/Freetown",
    "iso:country":"SL",
    "name:eng_x_preferred":[
        "Dintilipan"
    ],
    "wof:name":"Dintilipan",
    "wof:placetype":"locality"
},
  "geometry": {"coordinates":[-13.19882,9.06108],"type":"Point"}
}