{
  "type": "Feature",
  "properties": {
    "gn:admin1_code":"2.0",
    "gn:asciiname":"Mabaine",
    "gn:country_code":"SL",
    "gn:dem":18,
    "gn:feature_class":"P",
    "gn:feature_code":"PPL",
    "gn:name":"Mabaine",
    "gn:population":0,
    "gn:timezone":"Africa/Freetown",
    "iso:country":"SL",
    "name:eng_x_preferred":[
        "Mabaine"
    ],
    "wof:name":"Mabaine",
    "wof:placetype":"locality"
},
  "geometry": {"coordinates":[-12.9791,9.01156],"type":"Point"}
}