{
  "type": "Feature",
  "properties": {
    "gn:admin1_code":"2.0",
    "gn:asciiname":"Mane",
    "gn:country_code":"SL",
    "gn:dem":61,
    "gn:feature_class":"P",
    "gn:feature_code":"PPL",
    "gn:name":"Mane",
    "gn:population":0,
    "gn:timezone":"Africa/Freetown",
    "iso:country":"SL",
    "name:bel_x_preferred":[
        "\u041c\u0430\u043d"
    ],
    "name:bul_x_preferred":[
        "\u041c\u0430\u043d"
    ],
    "name:ceb_x_preferred":[
        "Mane"
    ],
    "name:deu_x_preferred":[
        "Mane"
    ],
    "name:eng_x_preferred":[
        "Mane"
    ],
    "name:fra_x_preferred":[
        "Mane"
    ],
    "name:glg_x_preferred":[
        "Mane"
    ],
    "name:ita_x_preferred":[
        "Mane"
    ],
    "name:nds_x_preferred":[
        "Mane"
    ],
    "name:nld_x_preferred":[
        "Mane"
    ],
    "name:pol_x_preferred":[
        "Mane"
    ],
    "name:rus_x_preferred":[
        "\u041c\u0430\u043d"
    ],
    "name:slk_x_preferred":[
        "Mane"
    ],
    "name:spa_x_preferred":[
        "Mane"
    ],
    "name:srp_x_preferred":[
        "\u041c\u0430\u043d"
    ],
    "name:swe_x_preferred":[
        "Mane"
    ],
    "name:ukr_x_preferred":[
        "\u041c\u0430\u043d"
    ],
    "name:urd_x_preferred":[
        "\u0627\u06cc\u0627\u0644"
    ],
    "wof:name":"Mane",
    "wof:placetype":"locality"
},
  "geometry": {"coordinates":[-12.63845,9.02844],"type":"Point"}
}