{
  "type": "Feature",
  "properties": {
    "gn:admin1_code":"2.0",
    "gn:asciiname":"Batsint",
    "gn:country_code":"SL",
    "gn:dem":27,
    "gn:feature_class":"P",
    "gn:feature_code":"PPL",
    "gn:name":"Batsint",
    "gn:population":0,
    "gn:timezone":"Africa/Freetown",
    "iso:country":"SL",
    "name:eng_x_preferred":[
        "Batsint"
    ],
    "wof:name":"Batsint",
    "wof:placetype":"locality"
},
  "geometry": {"coordinates":[-12.92491,8.78711],"type":"Point"}
}