{
  "type": "Feature",
  "properties": {
    "gn:admin1_code":"3.0",
    "gn:asciiname":"Kotomahun",
    "gn:country_code":"SL",
    "gn:dem":16,
    "gn:feature_class":"P",
    "gn:feature_code":"PPL",
    "gn:name":"Kotomahun",
    "gn:population":0,
    "gn:timezone":"Africa/Freetown",
    "iso:country":"SL",
    "name:eng_x_preferred":[
        "Kotomahun"
    ],
    "wof:name":"Kotomahun",
    "wof:placetype":"locality"
},
  "geometry": {"coordinates":[-11.89385,7.4402],"type":"Point"}
}