{
  "type": "Feature",
  "properties": {
    "gn:admin1_code":"3.0",
    "gn:asciiname":"Dar-es-Salaam",
    "gn:country_code":"SL",
    "gn:dem":15,
    "gn:feature_class":"P",
    "gn:feature_code":"PPL",
    "gn:name":"Dar-es-Salaam",
    "gn:population":0,
    "gn:timezone":"Africa/Freetown",
    "iso:country":"SL",
    "name:eng_x_preferred":[
        "Dar-es-Salaam"
    ],
    "wof:name":"Dar-es-Salaam",
    "wof:placetype":"locality"
},
  "geometry": {"coordinates":[-11.52783,7.09013],"type":"Point"}
}