{
  "type": "Feature",
  "properties": {
    "gn:admin1_code":"3.0",
    "gn:asciiname":"Hogai",
    "gn:country_code":"SL",
    "gn:dem":20,
    "gn:feature_class":"P",
    "gn:feature_code":"PPL",
    "gn:name":"Hogai",
    "gn:population":0,
    "gn:timezone":"Africa/Freetown",
    "iso:country":"SL",
    "name:eng_x_preferred":[
        "Hogai"
    ],
    "name:und_x_variant":[
        "Hunkan"
    ],
    "wof:name":"Hogai",
    "wof:placetype":"locality"
},
  "geometry": {"coordinates":[-11.86748,7.39827],"type":"Point"}
}