{
  "type": "Feature",
  "properties": {
    "gn:admin1_code":"1.0",
    "gn:asciiname":"Konjo",
    "gn:country_code":"SL",
    "gn:dem":463,
    "gn:feature_class":"P",
    "gn:feature_code":"PPL",
    "gn:name":"Konjo",
    "gn:population":0,
    "gn:timezone":"Africa/Freetown",
    "iso:country":"SL",
    "name:eng_x_preferred":[
        "Konjo"
    ],
    "name:und_x_variant":[
        "Naiagolehun"
    ],
    "wof:name":"Konjo",
    "wof:placetype":"locality"
},
  "geometry": {"coordinates":[-10.4063,8.23703],"type":"Point"}
}