{
  "type": "Feature",
  "properties": {
    "gn:admin1_code":"2.0",
    "gn:asciiname":"Tengbe",
    "gn:country_code":"SL",
    "gn:dem":46,
    "gn:feature_class":"P",
    "gn:feature_code":"PPL",
    "gn:name":"Tengbe",
    "gn:population":0,
    "gn:timezone":"Africa/Freetown",
    "iso:country":"SL",
    "name:eng_x_preferred":[
        "Tengbe"
    ],
    "wof:name":"Tengbe",
    "wof:placetype":"locality"
},
  "geometry": {"coordinates":[-12.96537,9.13346],"type":"Point"}
}