{
  "type": "Feature",
  "properties": {
    "gn:admin1_code":"02",
    "gn:asciiname":"Yongaro",
    "gn:country_code":"SL",
    "gn:dem":97,
    "gn:feature_class":"P",
    "gn:feature_code":"PPL",
    "gn:name":"Yongaro",
    "gn:population":0,
    "gn:timezone":"Africa/Freetown",
    "iso:country":"SL",
    "name:eng_x_preferred":[
        "Yongaro"
    ],
    "wof:name":"Yongaro",
    "wof:placetype":"locality"
},
  "geometry": {"coordinates":[-11.92101,9.21332],"type":"Point"}
}