{
  "type": "Feature",
  "properties": {
    "gn:admin1_code":"03",
    "gn:asciiname":"Sahn",
    "gn:country_code":"SL",
    "gn:dem":23,
    "gn:feature_class":"P",
    "gn:feature_code":"PPL",
    "gn:name":"Sahn",
    "gn:population":0,
    "gn:timezone":"Africa/Freetown",
    "iso:country":"SL",
    "name:und_x_variant":[
        "Saha",
        "Sahn",
        "Saba"
    ],
    "wof:name":"Sahn",
    "wof:placetype":"locality"
},
  "geometry": {"coordinates":[-11.84081,7.43277],"type":"Point"}
}