{
  "type": "Feature",
  "properties": {
    "gn:admin1_code":"2.0",
    "gn:asciiname":"Mambui",
    "gn:country_code":"SL",
    "gn:dem":28,
    "gn:feature_class":"P",
    "gn:feature_code":"PPL",
    "gn:name":"Mambui",
    "gn:population":0,
    "gn:timezone":"Africa/Freetown",
    "iso:country":"SL",
    "name:eng_x_preferred":[
        "Mambui"
    ],
    "wof:name":"Mambui",
    "wof:placetype":"locality"
},
  "geometry": {"coordinates":[-12.87156,9.18122],"type":"Point"}
}