{
  "type": "Feature",
  "properties": {
    "gn:admin1_code":"2.0",
    "gn:asciiname":"Matele",
    "gn:country_code":"SL",
    "gn:dem":285,
    "gn:feature_class":"P",
    "gn:feature_code":"PPL",
    "gn:name":"Matele",
    "gn:population":0,
    "gn:timezone":"Africa/Freetown",
    "iso:country":"SL",
    "name:eng_x_preferred":[
        "Matele"
    ],
    "wof:name":"Matele",
    "wof:placetype":"locality"
},
  "geometry": {"coordinates":[-11.75875,8.64543],"type":"Point"}
}