{
  "type": "Feature",
  "properties": {
    "gn:admin1_code":"3.0",
    "gn:asciiname":"Wue",
    "gn:country_code":"SL",
    "gn:dem":9,
    "gn:feature_class":"P",
    "gn:feature_code":"PPL",
    "gn:name":"Wue",
    "gn:population":0,
    "gn:timezone":"Africa/Freetown",
    "iso:country":"SL",
    "name:eng_x_preferred":[
        "Wue"
    ],
    "wof:name":"Wue",
    "wof:placetype":"locality"
},
  "geometry": {"coordinates":[-12.63162,7.77613],"type":"Point"}
}