{
  "type": "Feature",
  "properties": {
    "gn:admin1_code":"3.0",
    "gn:asciiname":"Bohoi",
    "gn:country_code":"SL",
    "gn:dem":77,
    "gn:feature_class":"P",
    "gn:feature_code":"PPL",
    "gn:name":"Bohoi",
    "gn:population":0,
    "gn:timezone":"Africa/Freetown",
    "iso:country":"SL",
    "name:eng_x_preferred":[
        "Bohoi"
    ],
    "wof:name":"Bohoi",
    "wof:placetype":"locality"
},
  "geometry": {"coordinates":[-12.17364,8.13697],"type":"Point"}
}