{
  "type": "Feature",
  "properties": {
    "gn:admin1_code":"01",
    "gn:asciiname":"Tiloma",
    "gn:country_code":"SL",
    "gn:dem":141,
    "gn:feature_class":"P",
    "gn:feature_code":"PPL",
    "gn:name":"Tiloma",
    "gn:population":0,
    "gn:timezone":"Africa/Freetown",
    "iso:country":"SL",
    "name:eng_x_preferred":[
        "Tiloma"
    ],
    "wof:name":"Tiloma",
    "wof:placetype":"locality"
},
  "geometry": {"coordinates":[-11.17661,7.54646],"type":"Point"}
}