{
  "type": "Feature",
  "properties": {
    "gn:admin1_code":"3.0",
    "gn:asciiname":"Bandajuma",
    "gn:country_code":"SL",
    "gn:dem":15,
    "gn:feature_class":"P",
    "gn:feature_code":"PPL",
    "gn:name":"Bandajuma",
    "gn:population":0,
    "gn:timezone":"Africa/Freetown",
    "iso:country":"SL",
    "name:eng_x_preferred":[
        "Bandajuma"
    ],
    "wof:name":"Bandajuma",
    "wof:placetype":"locality"
},
  "geometry": {"coordinates":[-12.32251,7.42074],"type":"Point"}
}