{
  "type": "Feature",
  "properties": {
    "gn:admin1_code":"3.0",
    "gn:asciiname":"Moyani",
    "gn:country_code":"SL",
    "gn:dem":58,
    "gn:feature_class":"P",
    "gn:feature_code":"PPL",
    "gn:name":"Moyani",
    "gn:population":0,
    "gn:timezone":"Africa/Freetown",
    "iso:country":"SL",
    "name:eng_x_preferred":[
        "Moyani"
    ],
    "wof:name":"Moyani",
    "wof:placetype":"locality"
},
  "geometry": {"coordinates":[-12.47091,8.24283],"type":"Point"}
}