{
  "type": "Feature",
  "properties": {
    "gn:admin1_code":"3.0",
    "gn:asciiname":"Bangabu",
    "gn:country_code":"SL",
    "gn:dem":118,
    "gn:feature_class":"P",
    "gn:feature_code":"PPL",
    "gn:name":"Bangabu",
    "gn:population":0,
    "gn:timezone":"Africa/Freetown",
    "iso:country":"SL",
    "name:eng_x_preferred":[
        "Bangabu"
    ],
    "wof:name":"Bangabu",
    "wof:placetype":"locality"
},
  "geometry": {"coordinates":[-11.56605,8.00459],"type":"Point"}
}