{
  "type": "Feature",
  "properties": {
    "gn:admin1_code":"3.0",
    "gn:asciiname":"Sulima",
    "gn:country_code":"SL",
    "gn:dem":86,
    "gn:feature_class":"P",
    "gn:feature_code":"PPL",
    "gn:name":"Sulima",
    "gn:population":0,
    "gn:timezone":"Africa/Freetown",
    "iso:country":"SL",
    "name:ceb_x_preferred":[
        "Sulima"
    ],
    "name:deu_x_preferred":[
        "Sulima"
    ],
    "name:eng_x_preferred":[
        "Sulima"
    ],
    "name:pol_x_preferred":[
        "Sulima"
    ],
    "name:swe_x_preferred":[
        "Sulima"
    ],
    "wof:name":"Sulima",
    "wof:placetype":"locality"
},
  "geometry": {"coordinates":[-11.82607,7.9997],"type":"Point"}
}