{
  "type": "Feature",
  "properties": {
    "gn:admin1_code":"3.0",
    "gn:asciiname":"Upper Mobainchain",
    "gn:country_code":"SL",
    "gn:dem":27,
    "gn:feature_class":"P",
    "gn:feature_code":"PPL",
    "gn:name":"Upper Mobainchain",
    "gn:population":0,
    "gn:timezone":"Africa/Freetown",
    "iso:country":"SL",
    "name:eng_x_preferred":[
        "Upper Mobainchain"
    ],
    "wof:name":"Upper Mobainchain",
    "wof:placetype":"locality"
},
  "geometry": {"coordinates":[-12.6894,8.14227],"type":"Point"}
}