{
  "type": "Feature",
  "properties": {
    "gn:admin1_code":"2.0",
    "gn:asciiname":"Sankolia",
    "gn:country_code":"SL",
    "gn:dem":149,
    "gn:feature_class":"P",
    "gn:feature_code":"PPL",
    "gn:name":"Sankolia",
    "gn:population":0,
    "gn:timezone":"Africa/Freetown",
    "iso:country":"SL",
    "name:eng_x_preferred":[
        "Sankolia"
    ],
    "wof:name":"Sankolia",
    "wof:placetype":"locality"
},
  "geometry": {"coordinates":[-11.74891,8.90581],"type":"Point"}
}