{
  "type": "Feature",
  "properties": {
    "gn:admin1_code":"3.0",
    "gn:asciiname":"Gora Hun",
    "gn:country_code":"SL",
    "gn:dem":171,
    "gn:feature_class":"P",
    "gn:feature_code":"PPL",
    "gn:name":"Gora Hun",
    "gn:population":0,
    "gn:timezone":"Africa/Freetown",
    "iso:country":"SL",
    "name:eng_x_preferred":[
        "Gora Hun"
    ],
    "name:und_x_variant":[
        "Garahun"
    ],
    "wof:name":"Gora Hun",
    "wof:placetype":"locality"
},
  "geometry": {"coordinates":[-11.6146,8.30245],"type":"Point"}
}