{
  "type": "Feature",
  "properties": {
    "gn:admin1_code":"3.0",
    "gn:asciiname":"Jahun",
    "gn:country_code":"SL",
    "gn:dem":24,
    "gn:feature_class":"P",
    "gn:feature_code":"PPL",
    "gn:name":"Jahun",
    "gn:population":0,
    "gn:timezone":"Africa/Freetown",
    "iso:country":"SL",
    "name:ceb_x_preferred":[
        "Jahun"
    ],
    "name:eng_x_preferred":[
        "Jahun"
    ],
    "name:fra_x_preferred":[
        "Jahun"
    ],
    "name:hau_x_preferred":[
        "Jahun"
    ],
    "name:ita_x_preferred":[
        "Jahun"
    ],
    "name:pol_x_preferred":[
        "Jahun"
    ],
    "name:spa_x_preferred":[
        "Jahun"
    ],
    "name:urd_x_preferred":[
        "\u062c\u06c1\u0646"
    ],
    "wof:name":"Jahun",
    "wof:placetype":"locality"
},
  "geometry": {"coordinates":[-12.03745,7.58227],"type":"Point"}
}