{
  "type": "Feature",
  "properties": {
    "gn:admin1_code":"2.0",
    "gn:asciiname":"Bare",
    "gn:country_code":"SL",
    "gn:dem":117,
    "gn:feature_class":"P",
    "gn:feature_code":"PPL",
    "gn:name":"Bare",
    "gn:population":0,
    "gn:timezone":"Africa/Freetown",
    "iso:country":"SL",
    "name:bos_x_preferred":[
        "Bare"
    ],
    "name:ceb_x_preferred":[
        "Bare"
    ],
    "name:deu_x_preferred":[
        "Bare"
    ],
    "name:eng_x_preferred":[
        "Bare"
    ],
    "name:eus_x_preferred":[
        "Bare"
    ],
    "name:fra_x_preferred":[
        "Bare"
    ],
    "name:hrv_x_preferred":[
        "Bare"
    ],
    "name:hun_x_preferred":[
        "Bare"
    ],
    "name:ita_x_preferred":[
        "Bare"
    ],
    "name:nld_x_preferred":[
        "Bare"
    ],
    "name:por_x_preferred":[
        "Bare"
    ],
    "name:slv_x_preferred":[
        "Bare"
    ],
    "name:swe_x_preferred":[
        "Bare"
    ],
    "wof:name":"Bare",
    "wof:placetype":"locality"
},
  "geometry": {"coordinates":[-11.86596,8.99941],"type":"Point"}
}