{
  "type": "Feature",
  "properties": {
    "gn:admin1_code":"3.0",
    "gn:asciiname":"Moyibu",
    "gn:country_code":"SL",
    "gn:dem":23,
    "gn:feature_class":"P",
    "gn:feature_code":"PPL",
    "gn:name":"Moyibu",
    "gn:population":0,
    "gn:timezone":"Africa/Freetown",
    "iso:country":"SL",
    "name:eng_x_preferred":[
        "Moyibu"
    ],
    "wof:name":"Moyibu",
    "wof:placetype":"locality"
},
  "geometry": {"coordinates":[-12.7801,8.01562],"type":"Point"}
}