{
  "type": "Feature",
  "properties": {
    "gn:admin1_code":"2.0",
    "gn:asciiname":"Gemidara",
    "gn:country_code":"SL",
    "gn:dem":61,
    "gn:feature_class":"P",
    "gn:feature_code":"PPL",
    "gn:name":"Gemidara",
    "gn:population":0,
    "gn:timezone":"Africa/Freetown",
    "iso:country":"SL",
    "name:eng_x_preferred":[
        "Gemidara"
    ],
    "wof:name":"Gemidara",
    "wof:placetype":"locality"
},
  "geometry": {"coordinates":[-12.6206,9.45288],"type":"Point"}
}