{
  "type": "Feature",
  "properties": {
    "gn:admin1_code":"3.0",
    "gn:asciiname":"Benyema",
    "gn:country_code":"SL",
    "gn:dem":86,
    "gn:feature_class":"P",
    "gn:feature_code":"PPL",
    "gn:name":"Benyema",
    "gn:population":0,
    "gn:timezone":"Africa/Freetown",
    "iso:country":"SL",
    "name:eng_x_preferred":[
        "Benyema"
    ],
    "name:und_x_variant":[
        "Benyama"
    ],
    "wof:name":"Benyema",
    "wof:placetype":"locality"
},
  "geometry": {"coordinates":[-11.2193,7.2502],"type":"Point"}
}