{
  "type": "Feature",
  "properties": {
    "gn:admin1_code":"3.0",
    "gn:asciiname":"Mokone",
    "gn:country_code":"SL",
    "gn:dem":43,
    "gn:feature_class":"P",
    "gn:feature_code":"PPL",
    "gn:name":"Mokone",
    "gn:population":0,
    "gn:timezone":"Africa/Freetown",
    "iso:country":"SL",
    "name:eng_x_preferred":[
        "Mokone"
    ],
    "wof:name":"Mokone",
    "wof:placetype":"locality"
},
  "geometry": {"coordinates":[-12.15808,7.84401],"type":"Point"}
}