{
  "type": "Feature",
  "properties": {
    "gn:admin1_code":"02",
    "gn:asciiname":"Sangban",
    "gn:country_code":"SL",
    "gn:dem":323,
    "gn:feature_class":"P",
    "gn:feature_code":"PPL",
    "gn:name":"Sangban",
    "gn:population":0,
    "gn:timezone":"Africa/Freetown",
    "iso:country":"SL",
    "name:eng_x_preferred":[
        "Sangban"
    ],
    "wof:name":"Sangban",
    "wof:placetype":"locality"
},
  "geometry": {"coordinates":[-11.96017,9.57902],"type":"Point"}
}