{
  "type": "Feature",
  "properties": {
    "gn:admin1_code":"2.0",
    "gn:asciiname":"Makambri",
    "gn:country_code":"SL",
    "gn:dem":124,
    "gn:feature_class":"P",
    "gn:feature_code":"PPL",
    "gn:name":"Makambri",
    "gn:population":0,
    "gn:timezone":"Africa/Freetown",
    "iso:country":"SL",
    "name:eng_x_preferred":[
        "Makambri"
    ],
    "wof:name":"Makambri",
    "wof:placetype":"locality"
},
  "geometry": {"coordinates":[-11.9255,8.83886],"type":"Point"}
}