{
  "type": "Feature",
  "properties": {
    "gn:admin1_code":"03",
    "gn:asciiname":"Taua",
    "gn:country_code":"SL",
    "gn:dem":71,
    "gn:feature_class":"P",
    "gn:feature_code":"PPL",
    "gn:name":"Taua",
    "gn:population":0,
    "gn:timezone":"Africa/Freetown",
    "iso:country":"SL",
    "name:eng_x_preferred":[
        "Taua"
    ],
    "wof:name":"Taua",
    "wof:placetype":"locality"
},
  "geometry": {"coordinates":[-12.3812,8.32464],"type":"Point"}
}