{
  "type": "Feature",
  "properties": {
    "gn:admin1_code":"2.0",
    "gn:asciiname":"Makali",
    "gn:country_code":"SL",
    "gn:dem":12,
    "gn:feature_class":"P",
    "gn:feature_code":"PPL",
    "gn:name":"Makali",
    "gn:population":0,
    "gn:timezone":"Africa/Freetown",
    "iso:country":"SL",
    "name:eng_x_preferred":[
        "Makali"
    ],
    "wof:name":"Makali",
    "wof:placetype":"locality"
},
  "geometry": {"coordinates":[-13.23091,8.78801],"type":"Point"}
}