{
  "type": "Feature",
  "properties": {
    "gn:admin1_code":"2.0",
    "gn:asciiname":"Magbondi",
    "gn:country_code":"SL",
    "gn:dem":100,
    "gn:feature_class":"P",
    "gn:feature_code":"PPL",
    "gn:name":"Magbondi",
    "gn:population":0,
    "gn:timezone":"Africa/Freetown",
    "iso:country":"SL",
    "name:eng_x_preferred":[
        "Magbondi"
    ],
    "wof:name":"Magbondi",
    "wof:placetype":"locality"
},
  "geometry": {"coordinates":[-12.13436,9.3115],"type":"Point"}
}