{
  "type": "Feature",
  "properties": {
    "gn:admin1_code":"2.0",
    "gn:asciiname":"Lansonabalia",
    "gn:country_code":"SL",
    "gn:dem":482,
    "gn:feature_class":"P",
    "gn:feature_code":"PPL",
    "gn:name":"Lansonabalia",
    "gn:population":0,
    "gn:timezone":"Africa/Freetown",
    "iso:country":"SL",
    "name:eng_x_preferred":[
        "Lansonabalia"
    ],
    "name:und_x_variant":[
        "Lansanabalia"
    ],
    "wof:name":"Lansonabalia",
    "wof:placetype":"locality"
},
  "geometry": {"coordinates":[-10.87799,9.38684],"type":"Point"}
}