{
  "type": "Feature",
  "properties": {
    "gn:admin1_code":"1.0",
    "gn:asciiname":"Kenyema",
    "gn:country_code":"SL",
    "gn:dem":355,
    "gn:feature_class":"P",
    "gn:feature_code":"PPL",
    "gn:name":"Kenyema",
    "gn:population":0,
    "gn:timezone":"Africa/Freetown",
    "iso:country":"SL",
    "name:eng_x_preferred":[
        "Kenyema"
    ],
    "wof:name":"Kenyema",
    "wof:placetype":"locality"
},
  "geometry": {"coordinates":[-11.41305,8.47017],"type":"Point"}
}