{
  "type": "Feature",
  "properties": {
    "gn:admin1_code":"1.0",
    "gn:asciiname":"Kwiko",
    "gn:country_code":"SL",
    "gn:dem":397,
    "gn:feature_class":"P",
    "gn:feature_code":"PPL",
    "gn:name":"Kwiko",
    "gn:population":0,
    "gn:timezone":"Africa/Freetown",
    "iso:country":"SL",
    "name:eng_x_preferred":[
        "Kwiko"
    ],
    "wof:name":"Kwiko",
    "wof:placetype":"locality"
},
  "geometry": {"coordinates":[-10.38133,8.37694],"type":"Point"}
}