{
  "type": "Feature",
  "properties": {
    "gn:admin1_code":"03",
    "gn:asciiname":"Tokoma",
    "gn:country_code":"SL",
    "gn:dem":53,
    "gn:feature_class":"P",
    "gn:feature_code":"PPL",
    "gn:name":"Tokoma",
    "gn:population":0,
    "gn:timezone":"Africa/Freetown",
    "iso:country":"SL",
    "name:eng_x_preferred":[
        "Tokoma"
    ],
    "wof:name":"Tokoma",
    "wof:placetype":"locality"
},
  "geometry": {"coordinates":[-11.39378,7.23687],"type":"Point"}
}