{
  "type": "Feature",
  "properties": {
    "gn:admin1_code":"2.0",
    "gn:asciiname":"Makonkari",
    "gn:country_code":"SL",
    "gn:dem":73,
    "gn:feature_class":"P",
    "gn:feature_code":"PPL",
    "gn:name":"Makonkari",
    "gn:population":0,
    "gn:timezone":"Africa/Freetown",
    "iso:country":"SL",
    "name:eng_x_preferred":[
        "Makonkari"
    ],
    "wof:name":"Makonkari",
    "wof:placetype":"locality"
},
  "geometry": {"coordinates":[-12.41502,8.41587],"type":"Point"}
}