{
  "type": "Feature",
  "properties": {
    "gn:admin1_code":"2.0",
    "gn:asciiname":"Kabunkaw",
    "gn:country_code":"SL",
    "gn:dem":16,
    "gn:feature_class":"P",
    "gn:feature_code":"PPL",
    "gn:name":"Kabunkaw",
    "gn:population":0,
    "gn:timezone":"Africa/Freetown",
    "iso:country":"SL",
    "name:eng_x_preferred":[
        "Kabunkaw"
    ],
    "wof:name":"Kabunkaw",
    "wof:placetype":"locality"
},
  "geometry": {"coordinates":[-12.93041,8.5337],"type":"Point"}
}