{
  "type": "Feature",
  "properties": {
    "gn:admin1_code":"2.0",
    "gn:asciiname":"Kayinda",
    "gn:country_code":"SL",
    "gn:dem":408,
    "gn:feature_class":"P",
    "gn:feature_code":"PPL",
    "gn:name":"Kayinda",
    "gn:population":0,
    "gn:timezone":"Africa/Freetown",
    "iso:country":"SL",
    "name:eng_x_preferred":[
        "Kayinda"
    ],
    "wof:name":"Kayinda",
    "wof:placetype":"locality"
},
  "geometry": {"coordinates":[-11.76667,9.56667],"type":"Point"}
}