{
  "type": "Feature",
  "properties": {
    "gn:admin1_code":"02",
    "gn:asciiname":"Shimbek",
    "gn:country_code":"SL",
    "gn:dem":61,
    "gn:feature_class":"P",
    "gn:feature_code":"PPL",
    "gn:name":"Shimbek",
    "gn:population":0,
    "gn:timezone":"Africa/Freetown",
    "iso:country":"SL",
    "name:eng_x_preferred":[
        "Shimbek"
    ],
    "wof:name":"Shimbek",
    "wof:placetype":"locality"
},
  "geometry": {"coordinates":[-12.45712,8.41031],"type":"Point"}
}