{
  "type": "Feature",
  "properties": {
    "gn:admin1_code":"3.0",
    "gn:asciiname":"Manjama",
    "gn:country_code":"SL",
    "gn:dem":28,
    "gn:feature_class":"P",
    "gn:feature_code":"PPL",
    "gn:name":"Manjama",
    "gn:population":0,
    "gn:timezone":"Africa/Freetown",
    "iso:country":"SL",
    "name:eng_x_preferred":[
        "Manjama"
    ],
    "wof:name":"Manjama",
    "wof:placetype":"locality"
},
  "geometry": {"coordinates":[-11.7287,7.37499],"type":"Point"}
}