{
  "type": "Feature",
  "properties": {
    "gn:admin1_code":"02",
    "gn:asciiname":"Sumata",
    "gn:country_code":"SL",
    "gn:dem":111,
    "gn:feature_class":"P",
    "gn:feature_code":"PPL",
    "gn:name":"Sumata",
    "gn:population":0,
    "gn:timezone":"Africa/Freetown",
    "iso:country":"SL",
    "name:ces_x_preferred":[
        "Sumata"
    ],
    "name:eng_x_preferred":[
        "Sumata"
    ],
    "name:fas_x_preferred":[
        "\u0633\u0648\u0645\u0627\u062a\u0627"
    ],
    "name:fin_x_preferred":[
        "Sumata"
    ],
    "name:fra_x_preferred":[
        "Sumata"
    ],
    "name:ita_x_preferred":[
        "Sumata"
    ],
    "name:kor_x_preferred":[
        "\uc2a4\ub9c8\ud0c0"
    ],
    "name:pol_x_preferred":[
        "Sumata"
    ],
    "name:por_x_preferred":[
        "Sumata"
    ],
    "name:rus_x_preferred":[
        "\u0421\u0443\u043c\u0430\u0442\u0430"
    ],
    "name:spa_x_preferred":[
        "Sumata"
    ],
    "name:tha_x_preferred":[
        "\u0e0b\u0e38\u0e21\u0e30\u0e15\u0e30"
    ],
    "name:ukr_x_preferred":[
        "\u0421\u0443\u043c\u0430\u0442\u0430"
    ],
    "wof:name":"Sumata",
    "wof:placetype":"locality"
},
  "geometry": {"coordinates":[-12.26726,9.69221],"type":"Point"}
}