{
  "type": "Feature",
  "properties": {
    "gn:admin1_code":"3.0",
    "gn:asciiname":"Gonohun",
    "gn:country_code":"SL",
    "gn:dem":54,
    "gn:feature_class":"P",
    "gn:feature_code":"PPL",
    "gn:name":"Gonohun",
    "gn:population":0,
    "gn:timezone":"Africa/Freetown",
    "iso:country":"SL",
    "name:eng_x_preferred":[
        "Gonohun"
    ],
    "wof:name":"Gonohun",
    "wof:placetype":"locality"
},
  "geometry": {"coordinates":[-11.36028,7.18944],"type":"Point"}
}