{
  "type": "Feature",
  "properties": {
    "gn:admin1_code":"2.0",
    "gn:asciiname":"Magbengbe",
    "gn:country_code":"SL",
    "gn:dem":443,
    "gn:feature_class":"P",
    "gn:feature_code":"PPL",
    "gn:name":"Magbengbe",
    "gn:population":0,
    "gn:timezone":"Africa/Freetown",
    "iso:country":"SL",
    "name:eng_x_preferred":[
        "Magbengbe"
    ],
    "wof:name":"Magbengbe",
    "wof:placetype":"locality"
},
  "geometry": {"coordinates":[-11.69659,9.76914],"type":"Point"}
}