{
  "type": "Feature",
  "properties": {
    "gn:admin1_code":"4.0",
    "gn:asciiname":"Barmouth",
    "gn:country_code":"SL",
    "gn:dem":3,
    "gn:feature_class":"P",
    "gn:feature_code":"PPL",
    "gn:name":"Barmouth",
    "gn:population":0,
    "gn:timezone":"Africa/Freetown",
    "iso:country":"SL",
    "name:ast_x_preferred":[
        "Abermaw"
    ],
    "name:bre_x_preferred":[
        "Abermaw"
    ],
    "name:bul_x_preferred":[
        "\u0411\u0430\u0440\u043c\u044a\u0442"
    ],
    "name:cat_x_preferred":[
        "Barmouth"
    ],
    "name:ceb_x_preferred":[
        "Barmouth"
    ],
    "name:cor_x_preferred":[
        "Bermo"
    ],
    "name:cym_x_preferred":[
        "Abermaw"
    ],
    "name:deu_x_preferred":[
        "Barmouth"
    ],
    "name:eng_x_preferred":[
        "Barmouth"
    ],
    "name:epo_x_preferred":[
        "Barmouth"
    ],
    "name:eus_x_preferred":[
        "Barmouth"
    ],
    "name:fas_x_preferred":[
        "\u0628\u0627\u0631\u0645\u0648\u062b"
    ],
    "name:fin_x_preferred":[
        "Barmouth"
    ],
    "name:fra_x_preferred":[
        "Barmouth"
    ],
    "name:gla_x_preferred":[
        "Bermo"
    ],
    "name:gle_x_preferred":[
        "Bermo"
    ],
    "name:ita_x_preferred":[
        "Barmouth"
    ],
    "name:lat_x_preferred":[
        "Barmouth"
    ],
    "name:nld_x_preferred":[
        "Barmouth"
    ],
    "name:nor_x_preferred":[
        "Barmouth"
    ],
    "name:rus_x_preferred":[
        "\u0411\u0430\u0440\u043c\u0443\u0442"
    ],
    "name:sme_x_preferred":[
        "Abermaw"
    ],
    "name:spa_x_preferred":[
        "Barmouth"
    ],
    "name:swe_x_preferred":[
        "Barmouth"
    ],
    "wof:name":"Barmouth",
    "wof:placetype":"locality"
},
  "geometry": {"coordinates":[-12.99365,8.23842],"type":"Point"}
}