{
  "type": "Feature",
  "properties": {
    "gn:admin1_code":"4.0",
    "gn:asciiname":"Barmouth",
    "gn:country_code":"SL",
    "gn:dem":3,
    "gn:feature_class":"P",
    "gn:feature_code":"PPL",
    "gn:name":"Barmouth",
    "gn:population":0,
    "gn:timezone":"Africa/Freetown",
    "iso:country":"SL",
    "name:eng_x_preferred":[
        "Barmouth"
    ],
    "wof:name":"Barmouth",
    "wof:placetype":"locality"
},
  "geometry": {"coordinates":[-12.99365,8.23842],"type":"Point"}
}