{
  "type": "Feature",
  "properties": {
    "gn:admin1_code":"3.0",
    "gn:asciiname":"Kowama",
    "gn:country_code":"SL",
    "gn:dem":66,
    "gn:feature_class":"P",
    "gn:feature_code":"PPL",
    "gn:name":"Kowama",
    "gn:population":0,
    "gn:timezone":"Africa/Freetown",
    "iso:country":"SL",
    "name:eng_x_preferred":[
        "Kowama"
    ],
    "wof:name":"Kowama",
    "wof:placetype":"locality"
},
  "geometry": {"coordinates":[-12.03321,7.88891],"type":"Point"}
}