{
  "type": "Feature",
  "properties": {
    "gn:admin1_code":"1.0",
    "gn:asciiname":"Yokenyambadu",
    "gn:country_code":"SL",
    "gn:dem":334,
    "gn:feature_class":"P",
    "gn:feature_code":"PPL",
    "gn:name":"Yokenyambadu",
    "gn:population":0,
    "gn:timezone":"Africa/Freetown",
    "iso:country":"SL",
    "name:eng_x_preferred":[
        "Yokenyambadu"
    ],
    "wof:name":"Yokenyambadu",
    "wof:placetype":"locality"
},
  "geometry": {"coordinates":[-10.8332,8.58634],"type":"Point"}
}