{
  "type": "Feature",
  "properties": {
    "gn:admin1_code":"2.0",
    "gn:asciiname":"Karainke",
    "gn:country_code":"SL",
    "gn:dem":436,
    "gn:feature_class":"P",
    "gn:feature_code":"PPL",
    "gn:name":"Karainke",
    "gn:population":0,
    "gn:timezone":"Africa/Freetown",
    "iso:country":"SL",
    "name:eng_x_preferred":[
        "Karainke"
    ],
    "wof:name":"Karainke",
    "wof:placetype":"locality"
},
  "geometry": {"coordinates":[-11.57008,9.58161],"type":"Point"}
}