{
  "type": "Feature",
  "properties": {
    "gn:admin1_code":"1.0",
    "gn:asciiname":"Gbongboma",
    "gn:country_code":"SL",
    "gn:dem":153,
    "gn:feature_class":"P",
    "gn:feature_code":"PPL",
    "gn:name":"Gbongboma",
    "gn:population":0,
    "gn:timezone":"Africa/Freetown",
    "iso:country":"SL",
    "name:eng_x_preferred":[
        "Gbongboma"
    ],
    "wof:name":"Gbongboma",
    "wof:placetype":"locality"
},
  "geometry": {"coordinates":[-11.3227,7.96756],"type":"Point"}
}