{
  "type": "Feature",
  "properties": {
    "gn:admin1_code":"3.0",
    "gn:asciiname":"Belebu",
    "gn:country_code":"SL",
    "gn:dem":43,
    "gn:feature_class":"P",
    "gn:feature_code":"PPL",
    "gn:name":"Belebu",
    "gn:population":0,
    "gn:timezone":"Africa/Freetown",
    "iso:country":"SL",
    "name:eng_x_preferred":[
        "Belebu"
    ],
    "wof:name":"Belebu",
    "wof:placetype":"locality"
},
  "geometry": {"coordinates":[-11.67578,7.21533],"type":"Point"}
}