{
  "type": "Feature",
  "properties": {
    "gn:admin1_code":"2.0",
    "gn:asciiname":"Timne",
    "gn:country_code":"SL",
    "gn:dem":74,
    "gn:feature_class":"P",
    "gn:feature_code":"PPL",
    "gn:name":"Timne",
    "gn:population":0,
    "gn:timezone":"Africa/Freetown",
    "iso:country":"SL",
    "name:eng_x_preferred":[
        "Timne"
    ],
    "wof:name":"Timne",
    "wof:placetype":"locality"
},
  "geometry": {"coordinates":[-12.50791,8.90088],"type":"Point"}
}