{
  "type": "Feature",
  "properties": {
    "gn:admin1_code":"3.0",
    "gn:asciiname":"Pinto",
    "gn:country_code":"SL",
    "gn:dem":12,
    "gn:feature_class":"P",
    "gn:feature_code":"PPL",
    "gn:name":"Pinto",
    "gn:population":0,
    "gn:timezone":"Africa/Freetown",
    "iso:country":"SL",
    "name:ces_x_preferred":[
        "Pinto"
    ],
    "name:deu_x_preferred":[
        "Pinto"
    ],
    "name:eng_x_preferred":[
        "Pinto"
    ],
    "name:sco_x_preferred":[
        "Pinto"
    ],
    "wof:name":"Pinto",
    "wof:placetype":"locality"
},
  "geometry": {"coordinates":[-12.67667,7.72333],"type":"Point"}
}