{
  "type": "Feature",
  "properties": {
    "gn:admin1_code":"1.0",
    "gn:asciiname":"Kwuako",
    "gn:country_code":"SL",
    "gn:dem":371,
    "gn:feature_class":"P",
    "gn:feature_code":"PPL",
    "gn:name":"Kwuako",
    "gn:population":0,
    "gn:timezone":"Africa/Freetown",
    "iso:country":"SL",
    "name:eng_x_preferred":[
        "Kwuako"
    ],
    "name:und_x_variant":[
        "Njafoia"
    ],
    "wof:name":"Kwuako",
    "wof:placetype":"locality"
},
  "geometry": {"coordinates":[-11.09755,8.70285],"type":"Point"}
}