{
  "type": "Feature",
  "properties": {
    "gn:admin1_code":"3.0",
    "gn:asciiname":"Yeboya",
    "gn:country_code":"SL",
    "gn:dem":65,
    "gn:feature_class":"P",
    "gn:feature_code":"PPL",
    "gn:name":"Yeboya",
    "gn:population":0,
    "gn:timezone":"Africa/Freetown",
    "iso:country":"SL",
    "name:eng_x_preferred":[
        "Yeboya"
    ],
    "wof:name":"Yeboya",
    "wof:placetype":"locality"
},
  "geometry": {"coordinates":[-12.13299,7.9881],"type":"Point"}
}