{
  "type": "Feature",
  "properties": {
    "gn:admin1_code":"3.0",
    "gn:asciiname":"Kpetemahun",
    "gn:country_code":"SL",
    "gn:dem":56,
    "gn:feature_class":"P",
    "gn:feature_code":"PPL",
    "gn:name":"Kpetemahun",
    "gn:population":0,
    "gn:timezone":"Africa/Freetown",
    "iso:country":"SL",
    "name:eng_x_preferred":[
        "Kpetemahun"
    ],
    "wof:name":"Kpetemahun",
    "wof:placetype":"locality"
},
  "geometry": {"coordinates":[-12.43506,8.14288],"type":"Point"}
}