{
  "type": "Feature",
  "properties": {
    "gn:admin1_code":"3.0",
    "gn:asciiname":"Juluahun",
    "gn:country_code":"SL",
    "gn:dem":61,
    "gn:feature_class":"P",
    "gn:feature_code":"PPL",
    "gn:name":"Juluahun",
    "gn:population":0,
    "gn:timezone":"Africa/Freetown",
    "iso:country":"SL",
    "name:eng_x_preferred":[
        "Juluahun"
    ],
    "name:und_x_variant":[
        "Jaluahun"
    ],
    "wof:name":"Juluahun",
    "wof:placetype":"locality"
},
  "geometry": {"coordinates":[-12.08589,8.18657],"type":"Point"}
}