{
  "type": "Feature",
  "properties": {
    "gn:admin1_code":"1.0",
    "gn:asciiname":"Yendema",
    "gn:country_code":"SL",
    "gn:dem":193,
    "gn:feature_class":"P",
    "gn:feature_code":"PPL",
    "gn:name":"Yendema",
    "gn:population":0,
    "gn:timezone":"Africa/Freetown",
    "iso:country":"SL",
    "name:eng_x_preferred":[
        "Yendema"
    ],
    "wof:name":"Yendema",
    "wof:placetype":"locality"
},
  "geometry": {"coordinates":[-10.91581,8.12362],"type":"Point"}
}