{
  "type": "Feature",
  "properties": {
    "gn:admin1_code":"01",
    "gn:asciiname":"Pendembu",
    "gn:country_code":"SL",
    "gn:dem":182,
    "gn:feature_class":"P",
    "gn:feature_code":"PPL",
    "gn:name":"Pendembu",
    "gn:population":0,
    "gn:timezone":"Africa/Freetown",
    "iso:country":"SL",
    "name:eng_x_preferred":[
        "Pendembu"
    ],
    "wof:name":"Pendembu",
    "wof:placetype":"locality"
},
  "geometry": {"coordinates":[-10.92434,7.94685],"type":"Point"}
}