{
  "type": "Feature",
  "properties": {
    "gn:admin1_code":"02",
    "gn:asciiname":"Royel",
    "gn:country_code":"SL",
    "gn:dem":58,
    "gn:feature_class":"P",
    "gn:feature_code":"PPL",
    "gn:name":"Royel",
    "gn:population":0,
    "gn:timezone":"Africa/Freetown",
    "iso:country":"SL",
    "name:eng_x_preferred":[
        "Royel"
    ],
    "wof:name":"Royel",
    "wof:placetype":"locality"
},
  "geometry": {"coordinates":[-12.55239,8.76298],"type":"Point"}
}