{
  "type": "Feature",
  "properties": {
    "gn:admin1_code":"01",
    "gn:asciiname":"Tawahun",
    "gn:country_code":"SL",
    "gn:dem":177,
    "gn:feature_class":"P",
    "gn:feature_code":"PPL",
    "gn:name":"Tawahun",
    "gn:population":0,
    "gn:timezone":"Africa/Freetown",
    "iso:country":"SL",
    "name:eng_x_preferred":[
        "Tawahun"
    ],
    "wof:name":"Tawahun",
    "wof:placetype":"locality"
},
  "geometry": {"coordinates":[-11.02836,7.86469],"type":"Point"}
}