{
  "type": "Feature",
  "properties": {
    "gn:admin1_code":"3.0",
    "gn:asciiname":"Mokiwo",
    "gn:country_code":"SL",
    "gn:dem":18,
    "gn:feature_class":"P",
    "gn:feature_code":"PPL",
    "gn:name":"Mokiwo",
    "gn:population":0,
    "gn:timezone":"Africa/Freetown",
    "iso:country":"SL",
    "name:eng_x_preferred":[
        "Mokiwo"
    ],
    "wof:name":"Mokiwo",
    "wof:placetype":"locality"
},
  "geometry": {"coordinates":[-12.64568,7.96125],"type":"Point"}
}