{
  "type": "Feature",
  "properties": {
    "gn:admin1_code":"3.0",
    "gn:asciiname":"Makima",
    "gn:country_code":"SL",
    "gn:dem":303,
    "gn:feature_class":"P",
    "gn:feature_code":"PPL",
    "gn:name":"Makima",
    "gn:population":0,
    "gn:timezone":"Africa/Freetown",
    "iso:country":"SL",
    "name:eng_x_preferred":[
        "Makima"
    ],
    "wof:name":"Makima",
    "wof:placetype":"locality"
},
  "geometry": {"coordinates":[-11.75765,8.27142],"type":"Point"}
}