{
  "type": "Feature",
  "properties": {
    "gn:admin1_code":"2.0",
    "gn:asciiname":"Keche",
    "gn:country_code":"SL",
    "gn:dem":80,
    "gn:feature_class":"P",
    "gn:feature_code":"PPL",
    "gn:name":"Keche",
    "gn:population":0,
    "gn:timezone":"Africa/Freetown",
    "iso:country":"SL",
    "name:eng_x_preferred":[
        "Keche"
    ],
    "wof:name":"Keche",
    "wof:placetype":"locality"
},
  "geometry": {"coordinates":[-12.11783,8.85848],"type":"Point"}
}