{
  "type": "Feature",
  "properties": {
    "gn:admin1_code":"2.0",
    "gn:asciiname":"Mafisun",
    "gn:country_code":"SL",
    "gn:dem":22,
    "gn:feature_class":"P",
    "gn:feature_code":"PPL",
    "gn:name":"Mafisun",
    "gn:population":0,
    "gn:timezone":"Africa/Freetown",
    "iso:country":"SL",
    "name:eng_x_preferred":[
        "Mafisun"
    ],
    "wof:name":"Mafisun",
    "wof:placetype":"locality"
},
  "geometry": {"coordinates":[-12.88498,8.82544],"type":"Point"}
}