{
  "type": "Feature",
  "properties": {
    "gn:admin1_code":"1.0",
    "gn:asciiname":"Sami",
    "gn:country_code":"SL",
    "gn:dem":215,
    "gn:feature_class":"P",
    "gn:feature_code":"PPL",
    "gn:name":"Sami",
    "gn:population":0,
    "gn:timezone":"Africa/Freetown",
    "iso:country":"SL",
    "name:ara_x_preferred":[
        "\u0633\u0627\u0645\u064a"
    ],
    "name:cat_x_preferred":[
        "Sami"
    ],
    "name:ceb_x_preferred":[
        "Sami"
    ],
    "name:deu_x_preferred":[
        "Sami"
    ],
    "name:diq_x_preferred":[
        "Sami"
    ],
    "name:eng_x_preferred":[
        "Sami"
    ],
    "name:eus_x_preferred":[
        "Sami"
    ],
    "name:fas_x_preferred":[
        "\u0633\u0627\u0645\u06cc"
    ],
    "name:fra_x_preferred":[
        "Sami"
    ],
    "name:hrv_x_preferred":[
        "Sami"
    ],
    "name:ind_x_preferred":[
        "Sami"
    ],
    "name:ita_x_preferred":[
        "Sami"
    ],
    "name:kor_x_preferred":[
        "\uc0ac\ubbf8"
    ],
    "name:nld_x_preferred":[
        "Sami"
    ],
    "name:nor_x_preferred":[
        "Samisk"
    ],
    "name:pol_x_preferred":[
        "Sami"
    ],
    "name:por_x_preferred":[
        "Sami"
    ],
    "name:ron_x_preferred":[
        "Sami"
    ],
    "name:rus_x_preferred":[
        "\u0421\u0430\u043c\u0438"
    ],
    "name:slv_x_preferred":[
        "Sami"
    ],
    "name:spa_x_preferred":[
        "Sami"
    ],
    "name:srp_x_preferred":[
        "\u0421\u0430\u043c\u0438"
    ],
    "name:swe_x_preferred":[
        "Sami"
    ],
    "name:tam_x_preferred":[
        "\u0b9a\u0bbe\u0bae\u0bbf"
    ],
    "name:tur_x_preferred":[
        "Sami"
    ],
    "wof:name":"Sami",
    "wof:placetype":"locality"
},
  "geometry": {"coordinates":[-10.7126,8.11695],"type":"Point"}
}