{
  "type": "Feature",
  "properties": {
    "gn:admin1_code":"2.0",
    "gn:asciiname":"Mayugurima",
    "gn:country_code":"SL",
    "gn:dem":89,
    "gn:feature_class":"P",
    "gn:feature_code":"PPL",
    "gn:name":"Mayugurima",
    "gn:population":0,
    "gn:timezone":"Africa/Freetown",
    "iso:country":"SL",
    "name:eng_x_preferred":[
        "Mayugurima"
    ],
    "wof:name":"Mayugurima",
    "wof:placetype":"locality"
},
  "geometry": {"coordinates":[-12.04638,9.16627],"type":"Point"}
}