{
  "type": "Feature",
  "properties": {
    "gn:admin1_code":"1.0",
    "gn:asciiname":"Batiyema",
    "gn:country_code":"SL",
    "gn:dem":209,
    "gn:feature_class":"P",
    "gn:feature_code":"PPL",
    "gn:name":"Batiyema",
    "gn:population":0,
    "gn:timezone":"Africa/Freetown",
    "iso:country":"SL",
    "name:eng_x_preferred":[
        "Batiyema"
    ],
    "wof:name":"Batiyema",
    "wof:placetype":"locality"
},
  "geometry": {"coordinates":[-10.81278,8.20596],"type":"Point"}
}