{
  "type": "Feature",
  "properties": {
    "gn:admin1_code":"1.0",
    "gn:asciiname":"Teidu",
    "gn:country_code":"SL",
    "gn:dem":355,
    "gn:feature_class":"P",
    "gn:feature_code":"PPL",
    "gn:name":"Teidu",
    "gn:population":0,
    "gn:timezone":"Africa/Freetown",
    "iso:country":"SL",
    "name:eng_x_preferred":[
        "Teidu"
    ],
    "wof:name":"Teidu",
    "wof:placetype":"locality"
},
  "geometry": {"coordinates":[-11.00631,8.6831],"type":"Point"}
}