{
  "type": "Feature",
  "properties": {
    "gn:admin1_code":"1.0",
    "gn:asciiname":"Koyama",
    "gn:country_code":"SL",
    "gn:dem":197,
    "gn:feature_class":"P",
    "gn:feature_code":"PPL",
    "gn:name":"Koyama",
    "gn:population":0,
    "gn:timezone":"Africa/Freetown",
    "iso:country":"SL",
    "name:eng_x_preferred":[
        "Koyama"
    ],
    "name:und_x_variant":[
        "Kaniva"
    ],
    "wof:name":"Koyama",
    "wof:placetype":"locality"
},
  "geometry": {"coordinates":[-10.89411,8.18287],"type":"Point"}
}