{
  "type": "Feature",
  "properties": {
    "gn:admin1_code":"3.0",
    "gn:asciiname":"Kaina",
    "gn:country_code":"SL",
    "gn:dem":114,
    "gn:feature_class":"P",
    "gn:feature_code":"PPL",
    "gn:name":"Kaina",
    "gn:population":0,
    "gn:timezone":"Africa/Freetown",
    "iso:country":"SL",
    "name:eng_x_preferred":[
        "Kaina"
    ],
    "wof:name":"Kaina",
    "wof:placetype":"locality"
},
  "geometry": {"coordinates":[-11.33402,7.37174],"type":"Point"}
}