{
  "type": "Feature",
  "properties": {
    "gn:admin1_code":"1.0",
    "gn:asciiname":"Golala",
    "gn:country_code":"SL",
    "gn:dem":143,
    "gn:feature_class":"P",
    "gn:feature_code":"PPL",
    "gn:name":"Golala",
    "gn:population":0,
    "gn:timezone":"Africa/Freetown",
    "iso:country":"SL",
    "name:eng_x_preferred":[
        "Golala"
    ],
    "wof:name":"Golala",
    "wof:placetype":"locality"
},
  "geometry": {"coordinates":[-11.20726,7.45125],"type":"Point"}
}