{
  "type": "Feature",
  "properties": {
    "gn:admin1_code":"1.0",
    "gn:asciiname":"Gandorhun",
    "gn:country_code":"SL",
    "gn:dem":319,
    "gn:feature_class":"P",
    "gn:feature_code":"PPL",
    "gn:name":"Gandorhun",
    "gn:population":0,
    "gn:timezone":"Africa/Freetown",
    "iso:country":"SL",
    "name:eng_x_preferred":[
        "Gandorhun"
    ],
    "wof:name":"Gandorhun",
    "wof:placetype":"locality"
},
  "geometry": {"coordinates":[-10.58749,8.28801],"type":"Point"}
}