{
  "type": "Feature",
  "properties": {
    "gn:admin1_code":"2.0",
    "gn:asciiname":"Bangalaia",
    "gn:country_code":"SL",
    "gn:dem":73,
    "gn:feature_class":"P",
    "gn:feature_code":"PPL",
    "gn:name":"Bangalaia",
    "gn:population":0,
    "gn:timezone":"Africa/Freetown",
    "iso:country":"SL",
    "name:ceb_x_preferred":[
        "Bangalaia"
    ],
    "name:eng_x_preferred":[
        "Bangalaia"
    ],
    "name:ind_x_preferred":[
        "Bangalaia"
    ],
    "name:min_x_preferred":[
        "Bangalaia"
    ],
    "name:nld_x_preferred":[
        "Bangalaia"
    ],
    "name:nor_x_preferred":[
        "Bangalaia"
    ],
    "name:swe_x_preferred":[
        "Bangalaia"
    ],
    "name:war_x_preferred":[
        "Bangalaia"
    ],
    "wof:name":"Bangalaia",
    "wof:placetype":"locality"
},
  "geometry": {"coordinates":[-12.63768,9.4184],"type":"Point"}
}