{
  "type": "Feature",
  "properties": {
    "gn:admin1_code":"2.0",
    "gn:asciiname":"Dakaia",
    "gn:cc2":"SL",
    "gn:country_code":"SL",
    "gn:dem":413,
    "gn:feature_class":"P",
    "gn:feature_code":"PPL",
    "gn:name":"Dakaia",
    "gn:population":0,
    "gn:timezone":"Africa/Freetown",
    "iso:country":"SL",
    "name:und_x_variant":[
        "Bakaia",
        "Dakaia"
    ],
    "wof:name":"Dakaia",
    "wof:placetype":"locality"
},
  "geometry": {"coordinates":[-11.25,9.36667],"type":"Point"}
}