{
  "type": "Feature",
  "properties": {
    "gn:admin1_code":"2.0",
    "gn:asciiname":"Mapam",
    "gn:country_code":"SL",
    "gn:dem":78,
    "gn:feature_class":"P",
    "gn:feature_code":"PPL",
    "gn:name":"Mapam",
    "gn:population":0,
    "gn:timezone":"Africa/Freetown",
    "iso:country":"SL",
    "name:bul_x_preferred":[
        "\u041c\u0430\u043f\u0430\u043c"
    ],
    "name:cat_x_preferred":[
        "Mappam"
    ],
    "name:ces_x_preferred":[
        "Mapam"
    ],
    "name:deu_x_preferred":[
        "Mapam"
    ],
    "name:eng_x_preferred":[
        "Mapam"
    ],
    "name:fra_x_preferred":[
        "Mapam"
    ],
    "name:heb_x_preferred":[
        "\u05de\u05e4\"\u05dd"
    ],
    "name:ita_x_preferred":[
        "Mapam"
    ],
    "name:jpn_x_preferred":[
        "\u30de\u30d1\u30e0"
    ],
    "name:nno_x_preferred":[
        "Mapam"
    ],
    "name:pol_x_preferred":[
        "Mapam"
    ],
    "name:por_x_preferred":[
        "Mapam"
    ],
    "name:spa_x_preferred":[
        "Mapam"
    ],
    "name:swe_x_preferred":[
        "Mapam"
    ],
    "wof:name":"Mapam",
    "wof:placetype":"locality"
},
  "geometry": {"coordinates":[-12.29443,9.35477],"type":"Point"}
}