{
  "type": "Feature",
  "properties": {
    "gn:admin1_code":"2.0",
    "gn:asciiname":"Bramah",
    "gn:country_code":"SL",
    "gn:dem":27,
    "gn:feature_class":"P",
    "gn:feature_code":"PPL",
    "gn:name":"Bramah",
    "gn:population":0,
    "gn:timezone":"Africa/Freetown",
    "iso:country":"SL",
    "name:eng_x_preferred":[
        "Bramah"
    ],
    "name:und_x_variant":[
        "Brama"
    ],
    "wof:name":"Bramah",
    "wof:placetype":"locality"
},
  "geometry": {"coordinates":[-12.96135,8.36462],"type":"Point"}
}