{
  "type": "Feature",
  "properties": {
    "gn:admin1_code":"2.0",
    "gn:asciiname":"Matotoka",
    "gn:country_code":"SL",
    "gn:dem":105,
    "gn:feature_class":"P",
    "gn:feature_code":"PPL",
    "gn:name":"Matotoka",
    "gn:population":0,
    "gn:timezone":"Africa/Freetown",
    "iso:country":"SL",
    "name:eng_x_preferred":[
        "Matotoka"
    ],
    "name:und_x_variant":[
        "Matotaka"
    ],
    "wof:name":"Matotoka",
    "wof:placetype":"locality"
},
  "geometry": {"coordinates":[-11.85569,8.65704],"type":"Point"}
}