{
  "type": "Feature",
  "properties": {
    "gn:admin1_code":"3.0",
    "gn:asciiname":"Bahama",
    "gn:country_code":"SL",
    "gn:dem":49,
    "gn:feature_class":"P",
    "gn:feature_code":"PPL",
    "gn:name":"Bahama",
    "gn:population":0,
    "gn:timezone":"Africa/Freetown",
    "iso:country":"SL",
    "name:eng_x_preferred":[
        "Bahama"
    ],
    "wof:name":"Bahama",
    "wof:placetype":"locality"
},
  "geometry": {"coordinates":[-12.33618,7.84174],"type":"Point"}
}