{
  "type": "Feature",
  "properties": {
    "gn:admin1_code":"2.0",
    "gn:asciiname":"Kawlaw",
    "gn:country_code":"SL",
    "gn:dem":99,
    "gn:feature_class":"P",
    "gn:feature_code":"PPL",
    "gn:name":"Kawlaw",
    "gn:population":0,
    "gn:timezone":"Africa/Freetown",
    "iso:country":"SL",
    "name:eng_x_preferred":[
        "Kawlaw"
    ],
    "wof:name":"Kawlaw",
    "wof:placetype":"locality"
},
  "geometry": {"coordinates":[-11.95547,8.75909],"type":"Point"}
}