{
  "type": "Feature",
  "properties": {
    "gn:admin1_code":"01",
    "gn:asciiname":"Wugbadu",
    "gn:country_code":"SL",
    "gn:dem":326,
    "gn:feature_class":"P",
    "gn:feature_code":"PPL",
    "gn:name":"Wugbadu",
    "gn:population":0,
    "gn:timezone":"Africa/Freetown",
    "iso:country":"SL",
    "name:eng_x_preferred":[
        "Wugbadu"
    ],
    "wof:name":"Wugbadu",
    "wof:placetype":"locality"
},
  "geometry": {"coordinates":[-10.86124,8.52959],"type":"Point"}
}