{
  "type": "Feature",
  "properties": {
    "gn:admin1_code":"2.0",
    "gn:asciiname":"Karine",
    "gn:country_code":"SL",
    "gn:dem":71,
    "gn:feature_class":"P",
    "gn:feature_code":"PPL",
    "gn:name":"Karine",
    "gn:population":0,
    "gn:timezone":"Africa/Freetown",
    "iso:country":"SL",
    "name:bre_x_preferred":[
        "Karine"
    ],
    "name:deu_x_preferred":[
        "Karine"
    ],
    "name:eng_x_preferred":[
        "Karine"
    ],
    "name:fra_x_preferred":[
        "Karine"
    ],
    "name:nno_x_preferred":[
        "Karine"
    ],
    "name:nor_x_preferred":[
        "Karine"
    ],
    "wof:name":"Karine",
    "wof:placetype":"locality"
},
  "geometry": {"coordinates":[-12.4723,8.84017],"type":"Point"}
}