{
  "type": "Feature",
  "properties": {
    "gn:admin1_code":"3.0",
    "gn:asciiname":"Bo",
    "gn:country_code":"SL",
    "gn:dem":17,
    "gn:feature_class":"P",
    "gn:feature_code":"PPL",
    "gn:name":"Bo",
    "gn:population":0,
    "gn:timezone":"Africa/Freetown",
    "iso:country":"SL",
    "name:dan_x_preferred":[
        "Bo"
    ],
    "name:eng_x_preferred":[
        "Bo"
    ],
    "name:hye_x_preferred":[
        "\u0532\u0578"
    ],
    "name:lit_x_preferred":[
        "Bo"
    ],
    "wof:name":"Bo",
    "wof:placetype":"locality"
},
  "geometry": {"coordinates":[-12.35111,7.66083],"type":"Point"}
}