{
  "type": "Feature",
  "properties": {
    "gn:admin1_code":"2.0",
    "gn:asciiname":"Mafori",
    "gn:country_code":"SL",
    "gn:dem":108,
    "gn:feature_class":"P",
    "gn:feature_code":"PPL",
    "gn:name":"Mafori",
    "gn:population":0,
    "gn:timezone":"Africa/Freetown",
    "iso:country":"SL",
    "name:eng_x_preferred":[
        "Mafori"
    ],
    "wof:name":"Mafori",
    "wof:placetype":"locality"
},
  "geometry": {"coordinates":[-11.8091,8.75912],"type":"Point"}
}