{
  "type": "Feature",
  "properties": {
    "gn:admin1_code":"2.0",
    "gn:asciiname":"Garya",
    "gn:country_code":"SL",
    "gn:dem":293,
    "gn:feature_class":"P",
    "gn:feature_code":"PPL",
    "gn:name":"Garya",
    "gn:population":0,
    "gn:timezone":"Africa/Freetown",
    "iso:country":"SL",
    "name:eng_x_preferred":[
        "Garya"
    ],
    "wof:name":"Garya",
    "wof:placetype":"locality"
},
  "geometry": {"coordinates":[-11.6693,9.96009],"type":"Point"}
}