{
  "type": "Feature",
  "properties": {
    "gn:admin1_code":"1.0",
    "gn:asciiname":"Goma",
    "gn:country_code":"SL",
    "gn:dem":159,
    "gn:feature_class":"P",
    "gn:feature_code":"PPL",
    "gn:name":"Goma",
    "gn:population":0,
    "gn:timezone":"Africa/Freetown",
    "iso:country":"SL",
    "name:afr_x_preferred":[
        "Goma"
    ],
    "name:ara_x_preferred":[
        "\u063a\u0648\u0645\u0627"
    ],
    "name:bos_x_preferred":[
        "Goma"
    ],
    "name:bre_x_preferred":[
        "Goma"
    ],
    "name:bul_x_preferred":[
        "\u0413\u043e\u043c\u0430"
    ],
    "name:cat_x_preferred":[
        "Goma"
    ],
    "name:ceb_x_preferred":[
        "Goma"
    ],
    "name:ces_x_preferred":[
        "Goma"
    ],
    "name:dan_x_preferred":[
        "Goma"
    ],
    "name:deu_x_preferred":[
        "Goma"
    ],
    "name:ell_x_preferred":[
        "\u0393\u03ba\u03cc\u03bc\u03b1"
    ],
    "name:eng_x_preferred":[
        "Goma"
    ],
    "name:epo_x_preferred":[
        "Goma"
    ],
    "name:est_x_preferred":[
        "Goma"
    ],
    "name:fas_x_preferred":[
        "\u06af\u0648\u0645\u0627"
    ],
    "name:fin_x_preferred":[
        "Goma"
    ],
    "name:fra_x_preferred":[
        "Goma"
    ],
    "name:hau_x_preferred":[
        "Goma"
    ],
    "name:hrv_x_preferred":[
        "Goma"
    ],
    "name:hun_x_preferred":[
        "Goma"
    ],
    "name:ind_x_preferred":[
        "Goma"
    ],
    "name:ita_x_preferred":[
        "Goma"
    ],
    "name:jpn_x_preferred":[
        "\u30b4\u30de"
    ],
    "name:kat_x_preferred":[
        "\u10d2\u10dd\u10db\u10d0"
    ],
    "name:kon_x_preferred":[
        "Goma"
    ],
    "name:kor_x_preferred":[
        "\uace0\ub9c8"
    ],
    "name:lin_x_preferred":[
        "Goma"
    ],
    "name:lit_x_preferred":[
        "Goma"
    ],
    "name:nld_x_preferred":[
        "Goma"
    ],
    "name:nor_x_preferred":[
        "Goma"
    ],
    "name:pms_x_preferred":[
        "Goma"
    ],
    "name:pol_x_preferred":[
        "Goma"
    ],
    "name:ron_x_preferred":[
        "Goma"
    ],
    "name:rus_x_preferred":[
        "\u0413\u043e\u043c\u0430"
    ],
    "name:slk_x_preferred":[
        "Goma"
    ],
    "name:sna_x_preferred":[
        "Goma"
    ],
    "name:spa_x_preferred":[
        "Goma"
    ],
    "name:srp_x_preferred":[
        "\u0413\u043e\u043c\u0430"
    ],
    "name:swa_x_preferred":[
        "Goma"
    ],
    "name:swe_x_preferred":[
        "Goma"
    ],
    "name:tur_x_preferred":[
        "Goma"
    ],
    "name:ukr_x_preferred":[
        "\u0413\u043e\u043c\u0430"
    ],
    "name:urd_x_preferred":[
        "\u06af\u0648\u0645\u0627"
    ],
    "name:war_x_preferred":[
        "Goma"
    ],
    "name:xmf_x_preferred":[
        "\u10d2\u10dd\u10db\u10d0"
    ],
    "name:yor_x_preferred":[
        "Goma"
    ],
    "wof:name":"Goma",
    "wof:placetype":"locality"
},
  "geometry": {"coordinates":[-11.26006,8.15888],"type":"Point"}
}