{
  "type": "Feature",
  "properties": {
    "gn:admin1_code":"01",
    "gn:asciiname":"Sagbe",
    "gn:country_code":"SL",
    "gn:dem":305,
    "gn:feature_class":"P",
    "gn:feature_code":"PPL",
    "gn:name":"Sagbe",
    "gn:population":0,
    "gn:timezone":"Africa/Freetown",
    "iso:country":"SL",
    "name:eng_x_preferred":[
        "Sagbe"
    ],
    "wof:name":"Sagbe",
    "wof:placetype":"locality"
},
  "geometry": {"coordinates":[-11.08108,8.42119],"type":"Point"}
}