{
  "type": "Feature",
  "properties": {
    "gn:admin1_code":"1.0",
    "gn:asciiname":"Teseyima",
    "gn:country_code":"SL",
    "gn:dem":381,
    "gn:feature_class":"P",
    "gn:feature_code":"PPL",
    "gn:name":"Teseyima",
    "gn:population":0,
    "gn:timezone":"Africa/Freetown",
    "iso:country":"SL",
    "name:eng_x_preferred":[
        "Teseyima"
    ],
    "wof:name":"Teseyima",
    "wof:placetype":"locality"
},
  "geometry": {"coordinates":[-11.0488,8.67871],"type":"Point"}
}