{
  "type": "Feature",
  "properties": {
    "gn:admin1_code":"1.0",
    "gn:asciiname":"Bombohun",
    "gn:country_code":"SL",
    "gn:dem":197,
    "gn:feature_class":"P",
    "gn:feature_code":"PPL",
    "gn:name":"Bombohun",
    "gn:population":0,
    "gn:timezone":"Africa/Freetown",
    "iso:country":"SL",
    "name:eng_x_preferred":[
        "Bombohun"
    ],
    "wof:name":"Bombohun",
    "wof:placetype":"locality"
},
  "geometry": {"coordinates":[-10.83508,7.96317],"type":"Point"}
}