{
  "type": "Feature",
  "properties": {
    "gn:admin1_code":"3.0",
    "gn:asciiname":"Mokoibu",
    "gn:country_code":"SL",
    "gn:dem":76,
    "gn:feature_class":"P",
    "gn:feature_code":"PPL",
    "gn:name":"Mokoibu",
    "gn:population":0,
    "gn:timezone":"Africa/Freetown",
    "iso:country":"SL",
    "name:eng_x_preferred":[
        "Mokoibu"
    ],
    "wof:name":"Mokoibu",
    "wof:placetype":"locality"
},
  "geometry": {"coordinates":[-12.13174,8.02883],"type":"Point"}
}