{
  "type": "Feature",
  "properties": {
    "gn:admin1_code":"2.0",
    "gn:asciiname":"Kumba",
    "gn:country_code":"SL",
    "gn:dem":97,
    "gn:feature_class":"P",
    "gn:feature_code":"PPL",
    "gn:name":"Kumba",
    "gn:population":0,
    "gn:timezone":"Africa/Freetown",
    "iso:country":"SL",
    "name:ceb_x_preferred":[
        "Kumba"
    ],
    "name:ces_x_preferred":[
        "Kumba"
    ],
    "name:deu_x_preferred":[
        "Kumba"
    ],
    "name:eng_x_preferred":[
        "Kumba"
    ],
    "name:epo_x_preferred":[
        "Kumba"
    ],
    "name:fas_x_preferred":[
        "\u06a9\u0648\u0645\u0628\u0627"
    ],
    "name:fin_x_preferred":[
        "Kumba"
    ],
    "name:fra_x_preferred":[
        "Kumba"
    ],
    "name:hrv_x_preferred":[
        "Kumba"
    ],
    "name:hun_x_preferred":[
        "Kumba"
    ],
    "name:ita_x_preferred":[
        "Kumba"
    ],
    "name:jpn_x_preferred":[
        "\u30af\u30f3\u30d0"
    ],
    "name:lav_x_preferred":[
        "Kumba"
    ],
    "name:lit_x_preferred":[
        "Kumba"
    ],
    "name:nld_x_preferred":[
        "Kumba"
    ],
    "name:pol_x_preferred":[
        "Kumba"
    ],
    "name:por_x_preferred":[
        "Kumba"
    ],
    "name:ron_x_preferred":[
        "Kumba"
    ],
    "name:rus_x_preferred":[
        "\u041a\u0443\u043c\u0431\u0430"
    ],
    "name:spa_x_preferred":[
        "Kumba"
    ],
    "name:swe_x_preferred":[
        "Kumba"
    ],
    "wof:name":"Kumba",
    "wof:placetype":"locality"
},
  "geometry": {"coordinates":[-12.42345,9.66198],"type":"Point"}
}