{
  "type": "Feature",
  "properties": {
    "gn:admin1_code":"3.0",
    "gn:asciiname":"Mowanga",
    "gn:country_code":"SL",
    "gn:dem":24,
    "gn:feature_class":"P",
    "gn:feature_code":"PPL",
    "gn:name":"Mowanga",
    "gn:population":0,
    "gn:timezone":"Africa/Freetown",
    "iso:country":"SL",
    "name:eng_x_preferred":[
        "Mowanga"
    ],
    "wof:name":"Mowanga",
    "wof:placetype":"locality"
},
  "geometry": {"coordinates":[-12.62705,7.93957],"type":"Point"}
}