{
  "type": "Feature",
  "properties": {
    "gn:admin1_code":"1.0",
    "gn:asciiname":"Keama",
    "gn:country_code":"SL",
    "gn:dem":538,
    "gn:feature_class":"P",
    "gn:feature_code":"PPL",
    "gn:name":"Keama",
    "gn:population":0,
    "gn:timezone":"Africa/Freetown",
    "iso:country":"SL",
    "name:eng_x_preferred":[
        "Keama"
    ],
    "wof:name":"Keama",
    "wof:placetype":"locality"
},
  "geometry": {"coordinates":[-10.68151,8.72094],"type":"Point"}
}