{
  "type": "Feature",
  "properties": {
    "gn:admin1_code":"3.0",
    "gn:asciiname":"Moselolo",
    "gn:country_code":"SL",
    "gn:dem":44,
    "gn:feature_class":"P",
    "gn:feature_code":"PPL",
    "gn:name":"Moselolo",
    "gn:population":0,
    "gn:timezone":"Africa/Freetown",
    "iso:country":"SL",
    "name:eng_x_preferred":[
        "Moselolo"
    ],
    "wof:name":"Moselolo",
    "wof:placetype":"locality"
},
  "geometry": {"coordinates":[-12.4276,7.84773],"type":"Point"}
}