{
  "type": "Feature",
  "properties": {
    "gn:admin1_code":"02",
    "gn:asciiname":"Sokoyo",
    "gn:country_code":"SL",
    "gn:dem":289,
    "gn:feature_class":"P",
    "gn:feature_code":"PPL",
    "gn:name":"Sokoyo",
    "gn:population":0,
    "gn:timezone":"Africa/Freetown",
    "iso:country":"SL",
    "name:eng_x_preferred":[
        "Sokoyo"
    ],
    "name:und_x_variant":[
        "Sokoya"
    ],
    "wof:name":"Sokoyo",
    "wof:placetype":"locality"
},
  "geometry": {"coordinates":[-11.71111,8.93917],"type":"Point"}
}