{
  "type": "Feature",
  "properties": {
    "gn:admin1_code":"01",
    "gn:asciiname":"Shengboma",
    "gn:country_code":"SL",
    "gn:dem":209,
    "gn:feature_class":"P",
    "gn:feature_code":"PPL",
    "gn:name":"Shengboma",
    "gn:population":0,
    "gn:timezone":"Africa/Freetown",
    "iso:country":"SL",
    "name:eng_x_preferred":[
        "Shengboma"
    ],
    "wof:name":"Shengboma",
    "wof:placetype":"locality"
},
  "geometry": {"coordinates":[-10.63575,8.07515],"type":"Point"}
}