{
  "type": "Feature",
  "properties": {
    "gn:admin1_code":"02",
    "gn:asciiname":"Sundulukoro",
    "gn:country_code":"SL",
    "gn:dem":394,
    "gn:feature_class":"P",
    "gn:feature_code":"PPL",
    "gn:name":"Sundulukoro",
    "gn:population":0,
    "gn:timezone":"Africa/Freetown",
    "iso:country":"SL",
    "name:eng_x_preferred":[
        "Sundulukoro"
    ],
    "wof:name":"Sundulukoro",
    "wof:placetype":"locality"
},
  "geometry": {"coordinates":[-11.51295,8.97846],"type":"Point"}
}