{
  "type": "Feature",
  "properties": {
    "gn:admin1_code":"01",
    "gn:asciiname":"Sasahun",
    "gn:country_code":"SL",
    "gn:dem":189,
    "gn:feature_class":"P",
    "gn:feature_code":"PPL",
    "gn:name":"Sasahun",
    "gn:population":0,
    "gn:timezone":"Africa/Freetown",
    "iso:country":"SL",
    "name:eng_x_preferred":[
        "Sasahun"
    ],
    "wof:name":"Sasahun",
    "wof:placetype":"locality"
},
  "geometry": {"coordinates":[-10.90798,7.95615],"type":"Point"}
}