{
  "type": "Feature",
  "properties": {
    "gn:admin1_code":"02",
    "gn:asciiname":"Sinekoro",
    "gn:country_code":"SL",
    "gn:dem":473,
    "gn:feature_class":"P",
    "gn:feature_code":"PPL",
    "gn:name":"Sinekoro",
    "gn:population":0,
    "gn:timezone":"Africa/Freetown",
    "iso:country":"SL",
    "name:eng_x_preferred":[
        "Sinekoro"
    ],
    "wof:name":"Sinekoro",
    "wof:placetype":"locality"
},
  "geometry": {"coordinates":[-11.12098,9.49245],"type":"Point"}
}