{
  "type": "Feature",
  "properties": {
    "gn:admin1_code":"2.0",
    "gn:asciiname":"Kunya",
    "gn:country_code":"SL",
    "gn:dem":435,
    "gn:feature_class":"P",
    "gn:feature_code":"PPL",
    "gn:name":"Kunya",
    "gn:population":0,
    "gn:timezone":"Africa/Freetown",
    "iso:country":"SL",
    "name:ceb_x_preferred":[
        "Kunya"
    ],
    "name:eng_x_preferred":[
        "Kunya"
    ],
    "name:rus_x_preferred":[
        "\u041a\u0443\u043d\u044c\u044f"
    ],
    "name:swe_x_preferred":[
        "Kunya"
    ],
    "wof:name":"Kunya",
    "wof:placetype":"locality"
},
  "geometry": {"coordinates":[-11.51682,9.15579],"type":"Point"}
}