{
  "type": "Feature",
  "properties": {
    "gn:gn_country":"SL",
    "gn:gn_fcode":"PPL",
    "gn:gn_pop":5121,
    "gn:population":5121,
    "iso:country":"SL",
    "name:dut_x_preferred":[
        "Hastings"
    ],
    "name:eng_x_preferred":[
        "Hastings"
    ],
    "name:jpn_x_preferred":[
        "\u30d8\u30a4\u30b9\u30c6\u30a3\u30f3\u30b0\u30ba"
    ],
    "name:rum_x_preferred":[
        "Hastings"
    ],
    "qs_pg:aaroncc":"SL",
    "qs_pg:gn_country":"SL",
    "qs_pg:gn_fcode":"PPL",
    "qs_pg:gn_pop":5121,
    "qs_pg:name":"Hastings",
    "qs_pg:photos_9r":0,
    "qs_pg:photos_sr":0,
    "qs_pg:pop_sr":5,
    "qs_pg:qs_pg_placetype":"locality",
    "wof:name":"Hastings",
    "wof:placetype":"locality",
    "wof:population":5121
},
  "geometry": {"coordinates":[-13.13861,8.37972],"type":"Point"}
}