{
  "type": "Feature",
  "properties": {
    "gn:admin1_code":"1.0",
    "gn:asciiname":"Kongboma",
    "gn:country_code":"SL",
    "gn:dem":406,
    "gn:feature_class":"P",
    "gn:feature_code":"PPL",
    "gn:name":"Kongboma",
    "gn:population":0,
    "gn:timezone":"Africa/Freetown",
    "iso:country":"SL",
    "wof:name":"Kongboma",
    "wof:placetype":"locality"
},
  "geometry": {"coordinates":[-10.35,8.25],"type":"Point"}
}