{
  "type": "Feature",
  "properties": {
    "gn:admin1_code":"1.0",
    "gn:asciiname":"Mansakundu",
    "gn:country_code":"SL",
    "gn:dem":393,
    "gn:feature_class":"P",
    "gn:feature_code":"PPL",
    "gn:name":"Mansakundu",
    "gn:population":0,
    "gn:timezone":"Africa/Conakry",
    "iso:country":"SL",
    "name:eng_x_preferred":[
        "Mansakundu"
    ],
    "name:und_x_variant":[
        "Masakundu"
    ],
    "wof:name":"Mansakundu",
    "wof:placetype":"locality"
},
  "geometry": {"coordinates":[-10.57625,8.84062],"type":"Point"}
}