{
  "type": "Feature",
  "properties": {
    "gn:admin1_code":"1.0",
    "gn:asciiname":"Kongowako",
    "gn:country_code":"SL",
    "gn:dem":401,
    "gn:feature_class":"P",
    "gn:feature_code":"PPL",
    "gn:name":"Kongowako",
    "gn:population":0,
    "gn:timezone":"Africa/Freetown",
    "iso:country":"SL",
    "name:eng_x_preferred":[
        "Kongowako"
    ],
    "name:und_x_variant":[
        "Konkoako"
    ],
    "wof:name":"Kongowako",
    "wof:placetype":"locality"
},
  "geometry": {"coordinates":[-11.06718,8.63408],"type":"Point"}
}