{
  "type": "Feature",
  "properties": {
    "gn:admin1_code":"1.0",
    "gn:asciiname":"Bandajuma",
    "gn:country_code":"SL",
    "gn:dem":197,
    "gn:feature_class":"P",
    "gn:feature_code":"PPL",
    "gn:name":"Bandajuma",
    "gn:population":0,
    "gn:timezone":"Africa/Freetown",
    "iso:country":"SL",
    "name:und_x_variant":[
        "Banoajuma",
        "Bandajuma"
    ],
    "wof:name":"Bandajuma",
    "wof:placetype":"locality"
},
  "geometry": {"coordinates":[-11.01777,8.04506],"type":"Point"}
}