{
  "type": "Feature",
  "properties": {
    "gn:admin1_code":"3.0",
    "gn:asciiname":"Bandahun",
    "gn:country_code":"SL",
    "gn:dem":146,
    "gn:feature_class":"P",
    "gn:feature_code":"PPL",
    "gn:name":"Bandahun",
    "gn:population":0,
    "gn:timezone":"Africa/Freetown",
    "iso:country":"SL",
    "name:eng_x_preferred":[
        "Bandahun"
    ],
    "wof:name":"Bandahun",
    "wof:placetype":"locality"
},
  "geometry": {"coordinates":[-11.79072,8.29942],"type":"Point"}
}