{
  "type": "Feature",
  "properties": {
    "gn:admin1_code":"02",
    "gn:asciiname":"Sumbaria",
    "gn:country_code":"SL",
    "gn:dem":347,
    "gn:feature_class":"P",
    "gn:feature_code":"PPL",
    "gn:name":"Sumbaria",
    "gn:population":0,
    "gn:timezone":"Africa/Freetown",
    "iso:country":"SL",
    "name:und_x_variant":[
        "Sombaria",
        "Sumbaria"
    ],
    "wof:name":"Sumbaria",
    "wof:placetype":"locality"
},
  "geometry": {"coordinates":[-11.33431,8.83173],"type":"Point"}
}