{
  "type": "Feature",
  "properties": {
    "gn:admin1_code":"3.0",
    "gn:asciiname":"Mokolo",
    "gn:country_code":"SL",
    "gn:dem":14,
    "gn:feature_class":"P",
    "gn:feature_code":"PPL",
    "gn:name":"Mokolo",
    "gn:population":0,
    "gn:timezone":"Africa/Freetown",
    "iso:country":"SL",
    "name:ceb_x_preferred":[
        "Mokolo"
    ],
    "name:deu_x_preferred":[
        "Mokolo"
    ],
    "name:eng_x_preferred":[
        "Mokolo"
    ],
    "name:fra_x_preferred":[
        "Mokolo"
    ],
    "name:ita_x_preferred":[
        "Mokolo"
    ],
    "name:msa_x_preferred":[
        "Mokolo"
    ],
    "name:nld_x_preferred":[
        "Mokolo"
    ],
    "name:pol_x_preferred":[
        "Mokolo"
    ],
    "name:por_x_preferred":[
        "Mokolo"
    ],
    "name:ron_x_preferred":[
        "Mokolo"
    ],
    "name:rus_x_preferred":[
        "\u041c\u043e\u043a\u043e\u043b\u043e"
    ],
    "name:spa_x_preferred":[
        "Mokolo"
    ],
    "name:swe_x_preferred":[
        "Mokolo"
    ],
    "name:zho_x_preferred":[
        "\u83ab\u79d1\u6d1b"
    ],
    "wof:name":"Mokolo",
    "wof:placetype":"locality"
},
  "geometry": {"coordinates":[-12.50917,7.48873],"type":"Point"}
}