{
  "type": "Feature",
  "properties": {
    "gn:admin1_code":"2.0",
    "gn:asciiname":"Masanasi",
    "gn:country_code":"SL",
    "gn:dem":65,
    "gn:feature_class":"P",
    "gn:feature_code":"PPL",
    "gn:name":"Masanasi",
    "gn:population":0,
    "gn:timezone":"Africa/Freetown",
    "iso:country":"SL",
    "name:eng_x_preferred":[
        "Masanasi"
    ],
    "wof:name":"Masanasi",
    "wof:placetype":"locality"
},
  "geometry": {"coordinates":[-12.4001,8.88997],"type":"Point"}
}