{
  "type": "Feature",
  "properties": {
    "gn:admin1_code":"2.0",
    "gn:asciiname":"Makuru",
    "gn:country_code":"SL",
    "gn:dem":114,
    "gn:feature_class":"P",
    "gn:feature_code":"PPL",
    "gn:name":"Makuru",
    "gn:population":0,
    "gn:timezone":"Africa/Freetown",
    "iso:country":"SL",
    "name:eng_x_preferred":[
        "Makuru"
    ],
    "name:swa_x_preferred":[
        "Makuru"
    ],
    "wof:name":"Makuru",
    "wof:placetype":"locality"
},
  "geometry": {"coordinates":[-12.18291,9.23044],"type":"Point"}
}