{
  "type": "Feature",
  "properties": {
    "gn:admin1_code":"1.0",
    "gn:asciiname":"Gbasakor",
    "gn:country_code":"SL",
    "gn:dem":416,
    "gn:feature_class":"P",
    "gn:feature_code":"PPL",
    "gn:name":"Gbasakor",
    "gn:population":0,
    "gn:timezone":"Africa/Freetown",
    "iso:country":"SL",
    "name:eng_x_preferred":[
        "Gbasakor"
    ],
    "wof:name":"Gbasakor",
    "wof:placetype":"locality"
},
  "geometry": {"coordinates":[-10.81559,8.75916],"type":"Point"}
}