{
  "type": "Feature",
  "properties": {
    "gn:admin1_code":"2.0",
    "gn:asciiname":"Makondu",
    "gn:country_code":"SL",
    "gn:dem":103,
    "gn:feature_class":"P",
    "gn:feature_code":"PPL",
    "gn:name":"Makondu",
    "gn:population":0,
    "gn:timezone":"Africa/Freetown",
    "iso:country":"SL",
    "name:eng_x_preferred":[
        "Makondu"
    ],
    "wof:name":"Makondu",
    "wof:placetype":"locality"
},
  "geometry": {"coordinates":[-11.94421,8.66312],"type":"Point"}
}