{
  "type": "Feature",
  "properties": {
    "gn:admin1_code":"1.0",
    "gn:asciiname":"Sipayema",
    "gn:country_code":"SL",
    "gn:dem":211,
    "gn:feature_class":"P",
    "gn:feature_code":"PPL",
    "gn:name":"Sipayema",
    "gn:population":0,
    "gn:timezone":"Africa/Freetown",
    "iso:country":"SL",
    "name:eng_x_preferred":[
        "Sipayema"
    ],
    "wof:name":"Sipayema",
    "wof:placetype":"locality"
},
  "geometry": {"coordinates":[-10.69029,7.97253],"type":"Point"}
}