{
  "type": "Feature",
  "properties": {
    "gn:admin1_code":"2.0",
    "gn:asciiname":"Mabai",
    "gn:country_code":"SL",
    "gn:dem":114,
    "gn:feature_class":"P",
    "gn:feature_code":"PPL",
    "gn:name":"Mabai",
    "gn:population":0,
    "gn:timezone":"Africa/Freetown",
    "iso:country":"SL",
    "name:eng_x_preferred":[
        "Mabai"
    ],
    "wof:name":"Mabai",
    "wof:placetype":"locality"
},
  "geometry": {"coordinates":[-11.79246,8.76113],"type":"Point"}
}