{
  "type": "Feature",
  "properties": {
    "gn:admin1_code":"2.0",
    "gn:asciiname":"Mayawlaw",
    "gn:country_code":"SL",
    "gn:dem":98,
    "gn:feature_class":"P",
    "gn:feature_code":"PPL",
    "gn:name":"Mayawlaw",
    "gn:population":0,
    "gn:timezone":"Africa/Freetown",
    "iso:country":"SL",
    "name:eng_x_preferred":[
        "Mayawlaw"
    ],
    "wof:name":"Mayawlaw",
    "wof:placetype":"locality"
},
  "geometry": {"coordinates":[-11.94815,8.74157],"type":"Point"}
}