{
  "type": "Feature",
  "properties": {
    "gn:admin1_code":"1.0",
    "gn:asciiname":"Ngaiagoehun",
    "gn:country_code":"SL",
    "gn:dem":327,
    "gn:feature_class":"P",
    "gn:feature_code":"PPL",
    "gn:name":"Ngaiagoehun",
    "gn:population":0,
    "gn:timezone":"Africa/Freetown",
    "iso:country":"SL",
    "name:eng_x_preferred":[
        "Ngaiagoehun"
    ],
    "wof:name":"Ngaiagoehun",
    "wof:placetype":"locality"
},
  "geometry": {"coordinates":[-11.3871,8.53483],"type":"Point"}
}