{
  "type": "Feature",
  "properties": {
    "gn:admin1_code":"3.0",
    "gn:asciiname":"Banjema",
    "gn:country_code":"SL",
    "gn:dem":114,
    "gn:feature_class":"P",
    "gn:feature_code":"PPL",
    "gn:name":"Banjema",
    "gn:population":0,
    "gn:timezone":"Africa/Freetown",
    "iso:country":"SL",
    "name:eng_x_preferred":[
        "Banjema"
    ],
    "name:und_x_variant":[
        "Bunjema"
    ],
    "wof:name":"Banjema",
    "wof:placetype":"locality"
},
  "geometry": {"coordinates":[-11.70293,8.34842],"type":"Point"}
}