{
  "type": "Feature",
  "properties": {
    "gn:admin1_code":"2.0",
    "gn:asciiname":"Darakuru",
    "gn:country_code":"SL",
    "gn:dem":561,
    "gn:feature_class":"P",
    "gn:feature_code":"PPL",
    "gn:name":"Darakuru",
    "gn:population":0,
    "gn:timezone":"Africa/Freetown",
    "iso:country":"SL",
    "name:eng_x_preferred":[
        "Darakuru"
    ],
    "wof:name":"Darakuru",
    "wof:placetype":"locality"
},
  "geometry": {"coordinates":[-11.53092,9.1916],"type":"Point"}
}