{
  "type": "Feature",
  "properties": {
    "gn:admin1_code":"03",
    "gn:asciiname":"Wubunge",
    "gn:country_code":"SL",
    "gn:dem":46,
    "gn:feature_class":"P",
    "gn:feature_code":"PPL",
    "gn:name":"Wubunge",
    "gn:population":0,
    "gn:timezone":"Africa/Freetown",
    "iso:country":"SL",
    "name:eng_x_preferred":[
        "Wubunge"
    ],
    "wof:name":"Wubunge",
    "wof:placetype":"locality"
},
  "geometry": {"coordinates":[-11.79511,7.81131],"type":"Point"}
}