{
  "type": "Feature",
  "properties": {
    "gn:admin1_code":"2.0",
    "gn:asciiname":"Balentakura",
    "gn:country_code":"SL",
    "gn:dem":104,
    "gn:feature_class":"P",
    "gn:feature_code":"PPL",
    "gn:name":"Balentakura",
    "gn:population":0,
    "gn:timezone":"Africa/Freetown",
    "iso:country":"SL",
    "name:eng_x_preferred":[
        "Balentakura"
    ],
    "wof:name":"Balentakura",
    "wof:placetype":"locality"
},
  "geometry": {"coordinates":[-12.33843,9.79819],"type":"Point"}
}