{
  "type": "Feature",
  "properties": {
    "gn:admin1_code":"3.0",
    "gn:asciiname":"Mojoka",
    "gn:country_code":"SL",
    "gn:dem":41,
    "gn:feature_class":"P",
    "gn:feature_code":"PPL",
    "gn:name":"Mojoka",
    "gn:population":0,
    "gn:timezone":"Africa/Freetown",
    "iso:country":"SL",
    "name:eng_x_preferred":[
        "Mojoka"
    ],
    "wof:name":"Mojoka",
    "wof:placetype":"locality"
},
  "geometry": {"coordinates":[-12.31793,7.90409],"type":"Point"}
}