{
  "type": "Feature",
  "properties": {
    "gn:admin1_code":"4.0",
    "gn:asciiname":"Adonkia",
    "gn:country_code":"SL",
    "gn:dem":43,
    "gn:feature_class":"P",
    "gn:feature_code":"PPL",
    "gn:name":"Adonkia",
    "gn:population":0,
    "gn:timezone":"Africa/Freetown",
    "iso:country":"SL",
    "name:eng_x_preferred":[
        "Adonkia"
    ],
    "wof:name":"Adonkia",
    "wof:placetype":"locality"
},
  "geometry": {"coordinates":[-13.26845,8.41642],"type":"Point"}
}