{
  "type": "Feature",
  "properties": {
    "gn:admin1_code":"2.0",
    "gn:asciiname":"Matanta",
    "gn:country_code":"SL",
    "gn:dem":109,
    "gn:feature_class":"P",
    "gn:feature_code":"PPL",
    "gn:name":"Matanta",
    "gn:population":0,
    "gn:timezone":"Africa/Freetown",
    "iso:country":"SL",
    "name:eng_x_preferred":[
        "Matanta"
    ],
    "wof:name":"Matanta",
    "wof:placetype":"locality"
},
  "geometry": {"coordinates":[-12.16775,9.54682],"type":"Point"}
}