{
  "type": "Feature",
  "properties": {
    "gn:admin1_code":"3.0",
    "gn:asciiname":"Keleh",
    "gn:country_code":"SL",
    "gn:dem":15,
    "gn:feature_class":"P",
    "gn:feature_code":"PPL",
    "gn:name":"Keleh",
    "gn:population":0,
    "gn:timezone":"Africa/Freetown",
    "iso:country":"SL",
    "name:eng_x_preferred":[
        "Keleh"
    ],
    "name:kur_x_preferred":[
        "Keleh"
    ],
    "name:und_x_variant":[
        "Kelei"
    ],
    "wof:name":"Keleh",
    "wof:placetype":"locality"
},
  "geometry": {"coordinates":[-11.98958,7.4315],"type":"Point"}
}