{
  "type": "Feature",
  "properties": {
    "gn:admin1_code":"3.0",
    "gn:asciiname":"Gbangba",
    "gn:country_code":"SL",
    "gn:dem":28,
    "gn:feature_class":"P",
    "gn:feature_code":"PPL",
    "gn:name":"Gbangba",
    "gn:population":0,
    "gn:timezone":"Africa/Freetown",
    "iso:country":"SL",
    "name:eng_x_preferred":[
        "Gbangba"
    ],
    "wof:name":"Gbangba",
    "wof:placetype":"locality"
},
  "geometry": {"coordinates":[-12.62337,8.13714],"type":"Point"}
}