{
  "type": "Feature",
  "properties": {
    "gn:admin1_code":"2.0",
    "gn:asciiname":"Falaba",
    "gn:country_code":"SL",
    "gn:dem":407,
    "gn:feature_class":"P",
    "gn:feature_code":"PPL",
    "gn:name":"Falaba",
    "gn:population":0,
    "gn:timezone":"Africa/Freetown",
    "iso:country":"SL",
    "wof:name":"Falaba",
    "wof:placetype":"locality"
},
  "geometry": {"coordinates":[-11.32151,9.85534],"type":"Point"}
}