{
  "type": "Feature",
  "properties": {
    "gn:admin1_code":"3.0",
    "gn:asciiname":"Tomuihun",
    "gn:country_code":"SL",
    "gn:dem":13,
    "gn:feature_class":"P",
    "gn:feature_code":"PPL",
    "gn:name":"Tomuihun",
    "gn:population":0,
    "gn:timezone":"Africa/Freetown",
    "iso:country":"SL",
    "name:eng_x_preferred":[
        "Tomuihun"
    ],
    "wof:name":"Tomuihun",
    "wof:placetype":"locality"
},
  "geometry": {"coordinates":[-11.59486,7.00675],"type":"Point"}
}