{
  "type": "Feature",
  "properties": {
    "gn:admin1_code":"3.0",
    "gn:asciiname":"Timindi",
    "gn:country_code":"SL",
    "gn:dem":64,
    "gn:feature_class":"P",
    "gn:feature_code":"PPL",
    "gn:name":"Timindi",
    "gn:population":0,
    "gn:timezone":"Africa/Freetown",
    "iso:country":"SL",
    "name:eng_x_preferred":[
        "Timindi"
    ],
    "wof:name":"Timindi",
    "wof:placetype":"locality"
},
  "geometry": {"coordinates":[-12.13605,8.0086],"type":"Point"}
}