{
  "type": "Feature",
  "properties": {
    "gn:admin1_code":"3.0",
    "gn:asciiname":"Ngewobu",
    "gn:country_code":"SL",
    "gn:dem":166,
    "gn:feature_class":"P",
    "gn:feature_code":"PPL",
    "gn:name":"Ngewobu",
    "gn:population":0,
    "gn:timezone":"Africa/Freetown",
    "iso:country":"SL",
    "name:eng_x_preferred":[
        "Ngewobu"
    ],
    "name:und_x_variant":[
        "Giebu"
    ],
    "wof:name":"Ngewobu",
    "wof:placetype":"locality"
},
  "geometry": {"coordinates":[-11.39165,8.02042],"type":"Point"}
}