{
  "type": "Feature",
  "properties": {
    "gn:admin1_code":"2.0",
    "gn:asciiname":"Dandaya",
    "gn:country_code":"SL",
    "gn:dem":411,
    "gn:feature_class":"P",
    "gn:feature_code":"PPL",
    "gn:name":"Dandaya",
    "gn:population":0,
    "gn:timezone":"Africa/Freetown",
    "iso:country":"SL",
    "name:eng_x_preferred":[
        "Dandaya"
    ],
    "wof:name":"Dandaya",
    "wof:placetype":"locality"
},
  "geometry": {"coordinates":[-11.64304,8.88795],"type":"Point"}
}