{
  "type": "Feature",
  "properties": {
    "gn:admin1_code":"3.0",
    "gn:asciiname":"Solima",
    "gn:country_code":"SL",
    "gn:dem":256,
    "gn:feature_class":"P",
    "gn:feature_code":"PPL",
    "gn:name":"Solima",
    "gn:population":0,
    "gn:timezone":"Africa/Freetown",
    "iso:country":"SL",
    "name:eng_x_preferred":[
        "Solima"
    ],
    "wof:name":"Solima",
    "wof:placetype":"locality"
},
  "geometry": {"coordinates":[-11.46219,8.106],"type":"Point"}
}