{
  "type": "Feature",
  "properties": {
    "gn:admin1_code":"01",
    "gn:asciiname":"Senga",
    "gn:country_code":"SL",
    "gn:dem":216,
    "gn:feature_class":"P",
    "gn:feature_code":"PPL",
    "gn:name":"Senga",
    "gn:population":0,
    "gn:timezone":"Africa/Freetown",
    "iso:country":"SL",
    "name:ceb_x_preferred":[
        "Senga"
    ],
    "name:eng_x_preferred":[
        "Senga"
    ],
    "name:ita_x_preferred":[
        "Senga"
    ],
    "name:swa_x_preferred":[
        "Senga"
    ],
    "name:swe_x_preferred":[
        "Senga"
    ],
    "wof:name":"Senga",
    "wof:placetype":"locality"
},
  "geometry": {"coordinates":[-10.62571,7.93674],"type":"Point"}
}