{
  "type": "Feature",
  "properties": {
    "gn:admin1_code":"3.0",
    "gn:asciiname":"Makoma",
    "gn:country_code":"SL",
    "gn:dem":16,
    "gn:feature_class":"P",
    "gn:feature_code":"PPL",
    "gn:name":"Makoma",
    "gn:population":0,
    "gn:timezone":"Africa/Freetown",
    "iso:country":"SL",
    "name:eng_x_preferred":[
        "Makoma"
    ],
    "name:lin_x_preferred":[
        "Makoma"
    ],
    "name:swa_x_preferred":[
        "Makoma"
    ],
    "wof:name":"Makoma",
    "wof:placetype":"locality"
},
  "geometry": {"coordinates":[-12.13323,7.37066],"type":"Point"}
}