{
  "type": "Feature",
  "properties": {
    "gn:admin1_code":"2.0",
    "gn:asciiname":"Gbin",
    "gn:country_code":"SL",
    "gn:dem":113,
    "gn:feature_class":"P",
    "gn:feature_code":"PPL",
    "gn:name":"Gbin",
    "gn:population":0,
    "gn:timezone":"Africa/Freetown",
    "iso:country":"SL",
    "name:eng_x_preferred":[
        "Gbin"
    ],
    "wof:name":"Gbin",
    "wof:placetype":"locality"
},
  "geometry": {"coordinates":[-12.2273,9.21223],"type":"Point"}
}