{
  "type": "Feature",
  "properties": {
    "gn:admin1_code":"3.0",
    "gn:asciiname":"Giawamei",
    "gn:country_code":"SL",
    "gn:dem":37,
    "gn:feature_class":"P",
    "gn:feature_code":"PPL",
    "gn:name":"Giawamei",
    "gn:population":0,
    "gn:timezone":"Africa/Freetown",
    "iso:country":"SL",
    "name:eng_x_preferred":[
        "Giawamei"
    ],
    "wof:name":"Giawamei",
    "wof:placetype":"locality"
},
  "geometry": {"coordinates":[-11.45622,7.21522],"type":"Point"}
}