{
  "type": "Feature",
  "properties": {
    "gn:admin1_code":"2.0",
    "gn:asciiname":"Kabaia",
    "gn:country_code":"SL",
    "gn:dem":56,
    "gn:feature_class":"P",
    "gn:feature_code":"PPL",
    "gn:name":"Kabaia",
    "gn:population":0,
    "gn:timezone":"Africa/Freetown",
    "iso:country":"SL",
    "name:eng_x_preferred":[
        "Kabaia"
    ],
    "wof:name":"Kabaia",
    "wof:placetype":"locality"
},
  "geometry": {"coordinates":[-12.78282,9.29526],"type":"Point"}
}