{
  "type": "Feature",
  "properties": {
    "gn:admin1_code":"3.0",
    "gn:asciiname":"Dambu",
    "gn:country_code":"SL",
    "gn:dem":72,
    "gn:feature_class":"P",
    "gn:feature_code":"PPL",
    "gn:name":"Dambu",
    "gn:population":0,
    "gn:timezone":"Africa/Freetown",
    "iso:country":"SL",
    "name:eng_x_preferred":[
        "Dambu"
    ],
    "wof:name":"Dambu",
    "wof:placetype":"locality"
},
  "geometry": {"coordinates":[-12.45234,8.18279],"type":"Point"}
}