{
  "type": "Feature",
  "properties": {
    "gn:admin1_code":"01",
    "gn:asciiname":"Petema",
    "gn:country_code":"SL",
    "gn:dem":344,
    "gn:feature_class":"P",
    "gn:feature_code":"PPL",
    "gn:name":"Petema",
    "gn:population":0,
    "gn:timezone":"Africa/Freetown",
    "iso:country":"SL",
    "name:eng_x_preferred":[
        "Petema"
    ],
    "wof:name":"Petema",
    "wof:placetype":"locality"
},
  "geometry": {"coordinates":[-11.08005,8.47673],"type":"Point"}
}