{
  "type": "Feature",
  "properties": {
    "gn:admin1_code":"1.0",
    "gn:asciiname":"Kangordu",
    "gn:country_code":"SL",
    "gn:dem":291,
    "gn:feature_class":"P",
    "gn:feature_code":"PPL",
    "gn:name":"Kangordu",
    "gn:population":0,
    "gn:timezone":"Africa/Freetown",
    "iso:country":"SL",
    "name:eng_x_preferred":[
        "Kangordu"
    ],
    "wof:name":"Kangordu",
    "wof:placetype":"locality"
},
  "geometry": {"coordinates":[-10.8346,8.52349],"type":"Point"}
}