{
  "type": "Feature",
  "properties": {
    "gn:admin1_code":"3.0",
    "gn:asciiname":"Komboya",
    "gn:country_code":"SL",
    "gn:dem":406,
    "gn:feature_class":"P",
    "gn:feature_code":"PPL",
    "gn:name":"Komboya",
    "gn:population":0,
    "gn:timezone":"Africa/Freetown",
    "iso:country":"SL",
    "name:eng_x_preferred":[
        "Komboya"
    ],
    "wof:name":"Komboya",
    "wof:placetype":"locality"
},
  "geometry": {"coordinates":[-11.50325,8.2041],"type":"Point"}
}