{
  "type": "Feature",
  "properties": {
    "gn:admin1_code":"2.0",
    "gn:asciiname":"Mabankra",
    "gn:country_code":"SL",
    "gn:dem":69,
    "gn:feature_class":"P",
    "gn:feature_code":"PPL",
    "gn:name":"Mabankra",
    "gn:population":0,
    "gn:timezone":"Africa/Freetown",
    "iso:country":"SL",
    "name:eng_x_preferred":[
        "Mabankra"
    ],
    "wof:name":"Mabankra",
    "wof:placetype":"locality"
},
  "geometry": {"coordinates":[-12.59496,8.56888],"type":"Point"}
}