{
  "type": "Feature",
  "properties": {
    "gn:admin1_code":"01",
    "gn:asciiname":"Sirabu",
    "gn:country_code":"SL",
    "gn:dem":441,
    "gn:feature_class":"P",
    "gn:feature_code":"PPL",
    "gn:name":"Sirabu",
    "gn:population":0,
    "gn:timezone":"Africa/Freetown",
    "iso:country":"SL",
    "wof:name":"Sirabu",
    "wof:placetype":"locality"
},
  "geometry": {"coordinates":[-11.15,8.35],"type":"Point"}
}