{
  "type": "Feature",
  "properties": {
    "gn:admin1_code":"3.0",
    "gn:asciiname":"Jene",
    "gn:country_code":"SL",
    "gn:dem":42,
    "gn:feature_class":"P",
    "gn:feature_code":"PPL",
    "gn:name":"Jene",
    "gn:population":0,
    "gn:timezone":"Africa/Freetown",
    "iso:country":"SL",
    "name:eng_x_preferred":[
        "Jene"
    ],
    "wof:name":"Jene",
    "wof:placetype":"locality"
},
  "geometry": {"coordinates":[-11.39092,7.13383],"type":"Point"}
}