{
  "type": "Feature",
  "properties": {
    "gn:admin1_code":"2.0",
    "gn:asciiname":"Forenorya",
    "gn:country_code":"SL",
    "gn:dem":405,
    "gn:feature_class":"P",
    "gn:feature_code":"PPL",
    "gn:name":"Forenorya",
    "gn:population":0,
    "gn:timezone":"Africa/Freetown",
    "iso:country":"SL",
    "name:eng_x_preferred":[
        "Forenorya"
    ],
    "wof:name":"Forenorya",
    "wof:placetype":"locality"
},
  "geometry": {"coordinates":[-11.46493,9.58672],"type":"Point"}
}