{
  "type": "Feature",
  "properties": {
    "gn:admin1_code":"3.0",
    "gn:asciiname":"Mokaikutu",
    "gn:country_code":"SL",
    "gn:dem":23,
    "gn:feature_class":"P",
    "gn:feature_code":"PPL",
    "gn:name":"Mokaikutu",
    "gn:population":0,
    "gn:timezone":"Africa/Freetown",
    "iso:country":"SL",
    "name:eng_x_preferred":[
        "Mokaikutu"
    ],
    "name:und_x_variant":[
        "Mokalikut"
    ],
    "wof:name":"Mokaikutu",
    "wof:placetype":"locality"
},
  "geometry": {"coordinates":[-12.68534,8.22279],"type":"Point"}
}