{
  "type": "Feature",
  "properties": {
    "gn:admin1_code":"3.0",
    "gn:asciiname":"Fala",
    "gn:country_code":"SL",
    "gn:dem":108,
    "gn:feature_class":"P",
    "gn:feature_code":"PPL",
    "gn:name":"Fala",
    "gn:population":0,
    "gn:timezone":"Africa/Freetown",
    "iso:country":"SL",
    "name:eng_x_preferred":[
        "Fala"
    ],
    "wof:name":"Fala",
    "wof:placetype":"locality"
},
  "geometry": {"coordinates":[-11.5231,7.96589],"type":"Point"}
}