{
  "type": "Feature",
  "properties": {
    "gn:admin1_code":"3.0",
    "gn:asciiname":"Konda",
    "gn:country_code":"SL",
    "gn:dem":84,
    "gn:feature_class":"P",
    "gn:feature_code":"PPL",
    "gn:name":"Konda",
    "gn:population":0,
    "gn:timezone":"Africa/Freetown",
    "iso:country":"SL",
    "name:ceb_x_preferred":[
        "Konda"
    ],
    "name:deu_x_preferred":[
        "Konda"
    ],
    "name:eng_x_preferred":[
        "Konda"
    ],
    "name:fra_x_preferred":[
        "Konda"
    ],
    "name:ita_x_preferred":[
        "Konda"
    ],
    "name:swe_x_preferred":[
        "Konda"
    ],
    "name:und_x_variant":[
        "Kodia",
        "Kondia"
    ],
    "wof:name":"Konda",
    "wof:placetype":"locality"
},
  "geometry": {"coordinates":[-12.19122,8.18814],"type":"Point"}
}