{
  "type": "Feature",
  "properties": {
    "gn:admin1_code":"3.0",
    "gn:asciiname":"Foya",
    "gn:country_code":"SL",
    "gn:dem":33,
    "gn:feature_class":"P",
    "gn:feature_code":"PPL",
    "gn:name":"Foya",
    "gn:population":0,
    "gn:timezone":"Africa/Freetown",
    "iso:country":"SL",
    "name:eng_x_preferred":[
        "Foya"
    ],
    "name:pol_x_preferred":[
        "Foya"
    ],
    "name:rus_x_preferred":[
        "\u0424\u043e\u0439\u0430"
    ],
    "wof:name":"Foya",
    "wof:placetype":"locality"
},
  "geometry": {"coordinates":[-12.16196,7.58337],"type":"Point"}
}