{
  "type": "Feature",
  "properties": {
    "gn:country":"SL",
    "gn:fcode":"PPL",
    "gn:population":14085,
    "iso:country":"SL",
    "name:ast_x_preferred":[
        "Kailahun"
    ],
    "name:bul_x_preferred":[
        "\u041a\u0430\u0439\u043b\u0430\u0445\u0443\u043d"
    ],
    "name:ceb_x_preferred":[
        "Kailahun"
    ],
    "name:dan_x_preferred":[
        "Kailahun"
    ],
    "name:deu_x_preferred":[
        "Kailahun"
    ],
    "name:ell_x_preferred":[
        "\u039a\u03b1\u03ca\u03bb\u03b1\u03c7\u03bf\u03cd\u03bd"
    ],
    "name:eng_x_preferred":[
        "Kailahun"
    ],
    "name:fin_x_preferred":[
        "Kailahun"
    ],
    "name:fra_x_preferred":[
        "Kailahun"
    ],
    "name:ita_x_preferred":[
        "Kailahun"
    ],
    "name:lit_x_preferred":[
        "Kailahunas"
    ],
    "name:nld_x_preferred":[
        "Kailahun"
    ],
    "name:pol_x_preferred":[
        "Kailahun"
    ],
    "name:por_x_preferred":[
        "Kailahun"
    ],
    "name:rus_x_preferred":[
        "\u041a\u0430\u0439\u043b\u0430\u0445\u0443\u043d"
    ],
    "name:zho_x_preferred":[
        "\u51f1\u62c9\u6d2a"
    ],
    "qs:name":"Kailahun",
    "qs:photos_9r":0,
    "qs:photos_sr":0,
    "qs:pop_sr":"6",
    "wd:elevation":303.0,
    "wd:wordcount":553,
    "wof:name":"Kailahun",
    "wof:placetype":"locality",
    "wof:population":14085
},
  "geometry": {"coordinates":[-10.56667,8.28333],"type":"Point"}
}