{
  "type": "Feature",
  "properties": {
    "gn:admin1_code":"03",
    "gn:asciiname":"Tombalu",
    "gn:country_code":"SL",
    "gn:dem":106,
    "gn:feature_class":"P",
    "gn:feature_code":"PPL",
    "gn:name":"Tombalu",
    "gn:population":0,
    "gn:timezone":"Africa/Freetown",
    "iso:country":"SL",
    "wof:name":"Tombalu",
    "wof:placetype":"locality"
},
  "geometry": {"coordinates":[-11.63333,8.16667],"type":"Point"}
}