{
  "type": "Feature",
  "properties": {
    "gn:admin1_code":"2.0",
    "gn:asciiname":"Bambaia",
    "gn:country_code":"SL",
    "gn:dem":66,
    "gn:feature_class":"P",
    "gn:feature_code":"PPL",
    "gn:name":"Bambaia",
    "gn:population":0,
    "gn:timezone":"Africa/Freetown",
    "iso:country":"SL",
    "name:eng_x_preferred":[
        "Bambaia"
    ],
    "wof:name":"Bambaia",
    "wof:placetype":"locality"
},
  "geometry": {"coordinates":[-12.71407,9.36833],"type":"Point"}
}