{
  "type": "Feature",
  "properties": {
    "gn:admin1_code":"3.0",
    "gn:asciiname":"Mochail",
    "gn:country_code":"SL",
    "gn:dem":11,
    "gn:feature_class":"P",
    "gn:feature_code":"PPL",
    "gn:name":"Mochail",
    "gn:population":0,
    "gn:timezone":"Africa/Freetown",
    "iso:country":"SL",
    "name:eng_x_preferred":[
        "Mochail"
    ],
    "name:und_x_variant":[
        "Motail"
    ],
    "wof:name":"Mochail",
    "wof:placetype":"locality"
},
  "geometry": {"coordinates":[-12.93782,8.2256],"type":"Point"}
}