{
  "type": "Feature",
  "properties": {
    "gn:admin1_code":"2.0",
    "gn:asciiname":"Mabali",
    "gn:country_code":"SL",
    "gn:dem":28,
    "gn:feature_class":"P",
    "gn:feature_code":"PPL",
    "gn:name":"Mabali",
    "gn:population":0,
    "gn:timezone":"Africa/Freetown",
    "iso:country":"SL",
    "name:eng_x_preferred":[
        "Mabali"
    ],
    "wof:name":"Mabali",
    "wof:placetype":"locality"
},
  "geometry": {"coordinates":[-12.79805,8.70391],"type":"Point"}
}