{
  "type": "Feature",
  "properties": {
    "gn:admin1_code":"2.0",
    "gn:asciiname":"Matumbu",
    "gn:country_code":"SL",
    "gn:dem":312,
    "gn:feature_class":"P",
    "gn:feature_code":"PPL",
    "gn:name":"Matumbu",
    "gn:population":0,
    "gn:timezone":"Africa/Freetown",
    "iso:country":"SL",
    "name:eng_x_preferred":[
        "Matumbu"
    ],
    "wof:name":"Matumbu",
    "wof:placetype":"locality"
},
  "geometry": {"coordinates":[-11.63997,8.64167],"type":"Point"}
}