{
  "type": "Feature",
  "properties": {
    "gn:admin1_code":"1.0",
    "gn:asciiname":"Bondo",
    "gn:country_code":"SL",
    "gn:dem":393,
    "gn:feature_class":"P",
    "gn:feature_code":"PPL",
    "gn:name":"Bondo",
    "gn:population":0,
    "gn:timezone":"Africa/Freetown",
    "iso:country":"SL",
    "name:cat_x_preferred":[
        "Bondo"
    ],
    "name:ceb_x_preferred":[
        "Bondo"
    ],
    "name:deu_x_preferred":[
        "Bondo"
    ],
    "name:eng_x_preferred":[
        "Bondo"
    ],
    "name:epo_x_preferred":[
        "Bondo"
    ],
    "name:fra_x_preferred":[
        "Bondo"
    ],
    "name:ita_x_preferred":[
        "Bondo"
    ],
    "name:nld_x_preferred":[
        "Bondo"
    ],
    "name:nor_x_preferred":[
        "Bondo"
    ],
    "name:pol_x_preferred":[
        "Bondo"
    ],
    "name:por_x_preferred":[
        "Bondo"
    ],
    "name:rus_x_preferred":[
        "\u0411\u043e\u043d\u0434\u043e"
    ],
    "name:spa_x_preferred":[
        "Bondo"
    ],
    "name:srp_x_preferred":[
        "Bondo"
    ],
    "name:swe_x_preferred":[
        "Bondo"
    ],
    "name:und_x_variant":[
        "Bwedu"
    ],
    "name:vie_x_preferred":[
        "Bondo"
    ],
    "name:vol_x_preferred":[
        "Bondo"
    ],
    "wof:name":"Bondo",
    "wof:placetype":"locality"
},
  "geometry": {"coordinates":[-10.50847,8.29624],"type":"Point"}
}