{
  "type": "Feature",
  "properties": {
    "gn:admin1_code":"1.0",
    "gn:asciiname":"Bondo",
    "gn:country_code":"SL",
    "gn:dem":393,
    "gn:feature_class":"P",
    "gn:feature_code":"PPL",
    "gn:name":"Bondo",
    "gn:population":0,
    "gn:timezone":"Africa/Freetown",
    "iso:country":"SL",
    "name:ben_x_preferred":[
        "\u09ac\u09cb\u09a8\u09cd\u09a1\u09cb"
    ],
    "name:cat_x_preferred":[
        "Bondo"
    ],
    "name:ceb_x_preferred":[
        "Bondo"
    ],
    "name:deu_x_preferred":[
        "Bondo"
    ],
    "name:ell_x_preferred":[
        "\u039c\u03c0\u03cc\u03bd\u03c4\u03bf"
    ],
    "name:eng_x_preferred":[
        "Bondo"
    ],
    "name:epo_x_preferred":[
        "Bondo"
    ],
    "name:fas_x_preferred":[
        "\u0628\u0648\u0646\u062f\u0648"
    ],
    "name:fra_x_preferred":[
        "Bondo"
    ],
    "name:heb_x_preferred":[
        "\u05d1\u05d5\u05e0\u05d3\u05d5"
    ],
    "name:hin_x_preferred":[
        "\u092c\u094b\u0902\u0921\u094b"
    ],
    "name:hun_x_preferred":[
        "Bondo"
    ],
    "name:ind_x_preferred":[
        "Bondo"
    ],
    "name:ita_x_preferred":[
        "Bondo"
    ],
    "name:kor_x_preferred":[
        "\ubcf8\ub3c4"
    ],
    "name:nld_x_preferred":[
        "Bondo"
    ],
    "name:nor_x_preferred":[
        "Bondo"
    ],
    "name:pol_x_preferred":[
        "Bondo"
    ],
    "name:por_x_preferred":[
        "Bondo"
    ],
    "name:rus_x_preferred":[
        "\u0411\u043e\u043d\u0434\u043e"
    ],
    "name:spa_x_preferred":[
        "Bondo"
    ],
    "name:srp_x_preferred":[
        "Bondo"
    ],
    "name:swe_x_preferred":[
        "Bondo"
    ],
    "name:tur_x_preferred":[
        "Bondo"
    ],
    "name:und_x_variant":[
        "Bwedu"
    ],
    "name:urd_x_preferred":[
        "\u0628\u0648\u0646\u0688\u0648"
    ],
    "name:vie_x_preferred":[
        "Bondo"
    ],
    "name:vol_x_preferred":[
        "Bondo"
    ],
    "wof:name":"Bondo",
    "wof:placetype":"locality"
},
  "geometry": {"coordinates":[-10.50847,8.29624],"type":"Point"}
}