{
  "type": "Feature",
  "properties": {
    "gn:admin1_code":"1.0",
    "gn:asciiname":"Boaia",
    "gn:country_code":"SL",
    "gn:dem":358,
    "gn:feature_class":"P",
    "gn:feature_code":"PPL",
    "gn:name":"Boaia",
    "gn:population":0,
    "gn:timezone":"Africa/Freetown",
    "iso:country":"SL",
    "name:eng_x_preferred":[
        "Boaia"
    ],
    "wof:name":"Boaia",
    "wof:placetype":"locality"
},
  "geometry": {"coordinates":[-11.21569,8.6525],"type":"Point"}
}