{
  "type": "Feature",
  "properties": {
    "gn:admin1_code":"3.0",
    "gn:asciiname":"Mokande",
    "gn:country_code":"SL",
    "gn:dem":52,
    "gn:feature_class":"P",
    "gn:feature_code":"PPL",
    "gn:name":"Mokande",
    "gn:population":0,
    "gn:timezone":"Africa/Freetown",
    "iso:country":"SL",
    "name:eng_x_preferred":[
        "Mokande"
    ],
    "wof:name":"Mokande",
    "wof:placetype":"locality"
},
  "geometry": {"coordinates":[-11.89828,7.90033],"type":"Point"}
}