{
  "type": "Feature",
  "properties": {
    "gn:admin1_code":"2.0",
    "gn:asciiname":"Mabin",
    "gn:country_code":"SL",
    "gn:dem":29,
    "gn:feature_class":"P",
    "gn:feature_code":"PPL",
    "gn:name":"Mabin",
    "gn:population":0,
    "gn:timezone":"Africa/Freetown",
    "iso:country":"SL",
    "name:eng_x_preferred":[
        "Mabin"
    ],
    "wof:name":"Mabin",
    "wof:placetype":"locality"
},
  "geometry": {"coordinates":[-12.79712,8.50474],"type":"Point"}
}