{
  "type": "Feature",
  "properties": {
    "gn:admin1_code":"1.0",
    "gn:asciiname":"Bo-Ngieha",
    "gn:country_code":"SL",
    "gn:dem":227,
    "gn:feature_class":"P",
    "gn:feature_code":"PPL",
    "gn:name":"Bo-Ngieha",
    "gn:population":0,
    "gn:timezone":"Africa/Freetown",
    "iso:country":"SL",
    "name:eng_x_preferred":[
        "Bo-Ngieha"
    ],
    "wof:name":"Bo-Ngieha",
    "wof:placetype":"locality"
},
  "geometry": {"coordinates":[-11.05169,8.05861],"type":"Point"}
}