{
  "type": "Feature",
  "properties": {
    "gn:admin1_code":"2.0",
    "gn:asciiname":"Marata",
    "gn:country_code":"SL",
    "gn:dem":55,
    "gn:feature_class":"P",
    "gn:feature_code":"PPL",
    "gn:name":"Marata",
    "gn:population":0,
    "gn:timezone":"Africa/Freetown",
    "iso:country":"SL",
    "name:eng_x_preferred":[
        "Marata"
    ],
    "wof:name":"Marata",
    "wof:placetype":"locality"
},
  "geometry": {"coordinates":[-12.38325,9.24399],"type":"Point"}
}