{
  "type": "Feature",
  "properties": {
    "gn:admin1_code":"2.0",
    "gn:asciiname":"Laia",
    "gn:country_code":"SL",
    "gn:dem":63,
    "gn:feature_class":"P",
    "gn:feature_code":"PPL",
    "gn:name":"Laia",
    "gn:population":0,
    "gn:timezone":"Africa/Freetown",
    "iso:country":"SL",
    "name:eng_x_preferred":[
        "Laia"
    ],
    "wof:name":"Laia",
    "wof:placetype":"locality"
},
  "geometry": {"coordinates":[-12.75153,9.07201],"type":"Point"}
}