{
  "type": "Feature",
  "properties": {
    "gn:admin1_code":"1.0",
    "gn:asciiname":"Gbanahun",
    "gn:country_code":"SL",
    "gn:dem":152,
    "gn:feature_class":"P",
    "gn:feature_code":"PPL",
    "gn:name":"Gbanahun",
    "gn:population":0,
    "gn:timezone":"Africa/Freetown",
    "iso:country":"SL",
    "name:eng_x_preferred":[
        "Gbanahun"
    ],
    "name:und_x_variant":[
        "Banahu"
    ],
    "wof:name":"Gbanahun",
    "wof:placetype":"locality"
},
  "geometry": {"coordinates":[-11.29851,8.10671],"type":"Point"}
}