{
  "type": "Feature",
  "properties": {
    "gn:admin1_code":"03",
    "gn:asciiname":"Samatia",
    "gn:country_code":"SL",
    "gn:dem":103,
    "gn:feature_class":"P",
    "gn:feature_code":"PPL",
    "gn:name":"Samatia",
    "gn:population":0,
    "gn:timezone":"Africa/Freetown",
    "iso:country":"SL",
    "name:eng_x_preferred":[
        "Samatia"
    ],
    "wof:name":"Samatia",
    "wof:placetype":"locality"
},
  "geometry": {"coordinates":[-11.33669,7.41227],"type":"Point"}
}