{
  "type": "Feature",
  "properties": {
    "gn:admin1_code":"3.0",
    "gn:asciiname":"Kambalo",
    "gn:country_code":"SL",
    "gn:dem":25,
    "gn:feature_class":"P",
    "gn:feature_code":"PPL",
    "gn:name":"Kambalo",
    "gn:population":0,
    "gn:timezone":"Africa/Freetown",
    "iso:country":"SL",
    "name:eng_x_preferred":[
        "Kambalo"
    ],
    "wof:name":"Kambalo",
    "wof:placetype":"locality"
},
  "geometry": {"coordinates":[-12.19563,7.57591],"type":"Point"}
}