{
  "type": "Feature",
  "properties": {
    "gn:admin1_code":"3.0",
    "gn:asciiname":"Kuranko",
    "gn:country_code":"SL",
    "gn:dem":17,
    "gn:feature_class":"P",
    "gn:feature_code":"PPL",
    "gn:name":"Kuranko",
    "gn:population":0,
    "gn:timezone":"Africa/Freetown",
    "iso:country":"SL",
    "name:und_x_variant":[
        "Kurako"
    ],
    "wof:name":"Kuranko",
    "wof:placetype":"locality"
},
  "geometry": {"coordinates":[-11.51859,6.99225],"type":"Point"}
}