{
  "type": "Feature",
  "properties": {
    "gn:admin1_code":"02",
    "gn:asciiname":"Sindeya",
    "gn:country_code":"SL",
    "gn:dem":124,
    "gn:feature_class":"P",
    "gn:feature_code":"PPL",
    "gn:name":"Sindeya",
    "gn:population":0,
    "gn:timezone":"Africa/Freetown",
    "iso:country":"SL",
    "name:eng_x_preferred":[
        "Sindeya"
    ],
    "wof:name":"Sindeya",
    "wof:placetype":"locality"
},
  "geometry": {"coordinates":[-12.0716,9.88168],"type":"Point"}
}