{
  "type": "Feature",
  "properties": {
    "gn:admin1_code":"1.0",
    "gn:asciiname":"Kamela",
    "gn:country_code":"SL",
    "gn:dem":447,
    "gn:feature_class":"P",
    "gn:feature_code":"PPL",
    "gn:name":"Kamela",
    "gn:population":0,
    "gn:timezone":"Africa/Freetown",
    "iso:country":"SL",
    "name:azb_x_preferred":[
        "\u06a9\u0627\u0645\u0644\u0627"
    ],
    "name:csb_x_preferred":[
        "Kam\u00e9la"
    ],
    "name:eng_x_preferred":[
        "Kamela"
    ],
    "name:fas_x_preferred":[
        "\u06a9\u0627\u0645\u0644\u0627"
    ],
    "name:nld_x_preferred":[
        "Kamela"
    ],
    "name:pol_x_preferred":[
        "Kamela"
    ],
    "name:ukr_x_preferred":[
        "\u041a\u0430\u043c\u0435\u043b\u044f"
    ],
    "wof:name":"Kamela",
    "wof:placetype":"locality"
},
  "geometry": {"coordinates":[-10.32727,8.18939],"type":"Point"}
}