{
  "type": "Feature",
  "properties": {
    "gn:admin1_code":"3.0",
    "gn:asciiname":"Mokabanda",
    "gn:country_code":"SL",
    "gn:dem":37,
    "gn:feature_class":"P",
    "gn:feature_code":"PPL",
    "gn:name":"Mokabanda",
    "gn:population":0,
    "gn:timezone":"Africa/Freetown",
    "iso:country":"SL",
    "name:eng_x_preferred":[
        "Mokabanda"
    ],
    "wof:name":"Mokabanda",
    "wof:placetype":"locality"
},
  "geometry": {"coordinates":[-12.57957,7.95166],"type":"Point"}
}