{
  "type": "Feature",
  "properties": {
    "gn:admin1_code":"1.0",
    "gn:asciiname":"Kpelobengu",
    "gn:country_code":"SL",
    "gn:dem":445,
    "gn:feature_class":"P",
    "gn:feature_code":"PPL",
    "gn:name":"Kpelobengu",
    "gn:population":0,
    "gn:timezone":"Africa/Freetown",
    "iso:country":"SL",
    "name:eng_x_preferred":[
        "Kpelobengu"
    ],
    "wof:name":"Kpelobengu",
    "wof:placetype":"locality"
},
  "geometry": {"coordinates":[-10.35977,8.3717],"type":"Point"}
}