{
  "type": "Feature",
  "properties": {
    "gn:admin1_code":"3.0",
    "gn:asciiname":"Mobambi",
    "gn:country_code":"SL",
    "gn:dem":5,
    "gn:feature_class":"P",
    "gn:feature_code":"PPL",
    "gn:name":"Mobambi",
    "gn:population":0,
    "gn:timezone":"Africa/Freetown",
    "iso:country":"SL",
    "name:eng_x_preferred":[
        "Mobambi"
    ],
    "wof:name":"Mobambi",
    "wof:placetype":"locality"
},
  "geometry": {"coordinates":[-12.5314,7.50315],"type":"Point"}
}