{
  "type": "Feature",
  "properties": {
    "gn:admin1_code":"3.0",
    "gn:asciiname":"Gondama",
    "gn:country_code":"SL",
    "gn:dem":83,
    "gn:feature_class":"P",
    "gn:feature_code":"PPL",
    "gn:name":"Gondama",
    "gn:population":0,
    "gn:timezone":"Africa/Freetown",
    "iso:country":"SL",
    "name:eng_x_preferred":[
        "Gondama"
    ],
    "wof:name":"Gondama",
    "wof:placetype":"locality"
},
  "geometry": {"coordinates":[-11.87693,8.30007],"type":"Point"}
}