{
  "type": "Feature",
  "properties": {
    "gn:admin1_code":"1.0",
    "gn:asciiname":"Giewabu",
    "gn:country_code":"SL",
    "gn:dem":177,
    "gn:feature_class":"P",
    "gn:feature_code":"PPL",
    "gn:name":"Giewabu",
    "gn:population":0,
    "gn:timezone":"Africa/Freetown",
    "iso:country":"SL",
    "name:eng_x_preferred":[
        "Giewabu"
    ],
    "name:und_x_variant":[
        "Giebu"
    ],
    "wof:name":"Giewabu",
    "wof:placetype":"locality"
},
  "geometry": {"coordinates":[-11.40894,8.25672],"type":"Point"}
}