{
  "type": "Feature",
  "properties": {
    "gn:admin1_code":"4.0",
    "gn:asciiname":"Mokabi",
    "gn:country_code":"SL",
    "gn:dem":31,
    "gn:feature_class":"P",
    "gn:feature_code":"PPL",
    "gn:name":"Mokabi",
    "gn:population":0,
    "gn:timezone":"Africa/Freetown",
    "iso:country":"SL",
    "name:eng_x_preferred":[
        "Mokabi"
    ],
    "wof:name":"Mokabi",
    "wof:placetype":"locality"
},
  "geometry": {"coordinates":[-13.00688,8.31844],"type":"Point"}
}