{
  "type": "Feature",
  "properties": {
    "gn:admin1_code":"2.0",
    "gn:asciiname":"Matale",
    "gn:country_code":"SL",
    "gn:dem":64,
    "gn:feature_class":"P",
    "gn:feature_code":"PPL",
    "gn:name":"Matale",
    "gn:population":0,
    "gn:timezone":"Africa/Freetown",
    "iso:country":"SL",
    "name:cat_x_preferred":[
        "Matale"
    ],
    "name:ceb_x_preferred":[
        "Matale"
    ],
    "name:dan_x_preferred":[
        "Matale"
    ],
    "name:deu_x_preferred":[
        "Matale"
    ],
    "name:eng_x_preferred":[
        "Matale"
    ],
    "name:fas_x_preferred":[
        "\u0645\u062a\u0627\u0644\u0647"
    ],
    "name:fra_x_preferred":[
        "Matale"
    ],
    "name:ind_x_preferred":[
        "Matale"
    ],
    "name:ita_x_preferred":[
        "Matale"
    ],
    "name:jpn_x_preferred":[
        "\u30de\u30fc\u30bf\u30ec\u30fc"
    ],
    "name:nld_x_preferred":[
        "Matale"
    ],
    "name:rus_x_preferred":[
        "\u041c\u0430\u0442\u0430\u043b\u0435"
    ],
    "name:sin_x_preferred":[
        "\u0db8\u0dcf\u0dad\u0dbd\u0dda"
    ],
    "name:spa_x_preferred":[
        "Matale"
    ],
    "name:swe_x_preferred":[
        "Matale"
    ],
    "name:tam_x_preferred":[
        "\u0bae\u0bbe\u0ba4\u0bcd\u0ba4\u0bb3\u0bc8"
    ],
    "name:ukr_x_preferred":[
        "\u041c\u0430\u0442\u0430\u043b\u0435"
    ],
    "name:urd_x_preferred":[
        "\u0645\u0627\u062a\u0627\u0644\u06d2"
    ],
    "name:zho_x_preferred":[
        "\u99ac\u7279\u840a"
    ],
    "wof:name":"Matale",
    "wof:placetype":"locality"
},
  "geometry": {"coordinates":[-12.40211,8.61845],"type":"Point"}
}