{
  "type": "Feature",
  "properties": {
    "gn:admin1_code":"2.0",
    "gn:asciiname":"Surunumia",
    "gn:country_code":"SL",
    "gn:dem":96,
    "gn:feature_class":"P",
    "gn:feature_code":"PPL",
    "gn:name":"Surunumia",
    "gn:population":0,
    "gn:timezone":"Africa/Freetown",
    "iso:country":"SL",
    "name:eng_x_preferred":[
        "Surunumia"
    ],
    "wof:name":"Surunumia",
    "wof:placetype":"locality"
},
  "geometry": {"coordinates":[-11.91944,9.23089],"type":"Point"}
}