{
  "type": "Feature",
  "properties": {
    "gn:admin1_code":"1.0",
    "gn:asciiname":"Njama",
    "gn:country_code":"SL",
    "gn:dem":364,
    "gn:feature_class":"P",
    "gn:feature_code":"PPL",
    "gn:name":"Njama",
    "gn:population":0,
    "gn:timezone":"Africa/Freetown",
    "iso:country":"SL",
    "name:eng_x_preferred":[
        "Njama"
    ],
    "name:und_x_variant":[
        "Jama"
    ],
    "wof:name":"Njama",
    "wof:placetype":"locality"
},
  "geometry": {"coordinates":[-10.75656,8.39294],"type":"Point"}
}