{
  "type": "Feature",
  "properties": {
    "gn:admin1_code":"3.0",
    "gn:asciiname":"Chamahun",
    "gn:country_code":"SL",
    "gn:dem":14,
    "gn:feature_class":"P",
    "gn:feature_code":"PPL",
    "gn:name":"Chamahun",
    "gn:population":0,
    "gn:timezone":"Africa/Freetown",
    "iso:country":"SL",
    "name:eng_x_preferred":[
        "Chamahun"
    ],
    "wof:name":"Chamahun",
    "wof:placetype":"locality"
},
  "geometry": {"coordinates":[-12.37202,7.6147],"type":"Point"}
}