{
  "type": "Feature",
  "properties": {
    "gn:admin1_code":"02",
    "gn:asciiname":"Rosos",
    "gn:country_code":"SL",
    "gn:dem":57,
    "gn:feature_class":"P",
    "gn:feature_code":"PPL",
    "gn:name":"Rosos",
    "gn:population":0,
    "gn:timezone":"Africa/Freetown",
    "iso:country":"SL",
    "name:und_x_variant":[
        "Sos",
        "Rosos"
    ],
    "wof:name":"Rosos",
    "wof:placetype":"locality"
},
  "geometry": {"coordinates":[-12.43491,9.14087],"type":"Point"}
}