{
  "type": "Feature",
  "properties": {
    "gn:admin1_code":"1.0",
    "gn:asciiname":"Gengema",
    "gn:country_code":"SL",
    "gn:dem":296,
    "gn:feature_class":"P",
    "gn:feature_code":"PPL",
    "gn:name":"Gengema",
    "gn:population":0,
    "gn:timezone":"Africa/Freetown",
    "iso:country":"SL",
    "name:eng_x_preferred":[
        "Gengema"
    ],
    "wof:name":"Gengema",
    "wof:placetype":"locality"
},
  "geometry": {"coordinates":[-10.78629,7.81916],"type":"Point"}
}