{
  "type": "Feature",
  "properties": {
    "gn:admin1_code":"2.0",
    "gn:asciiname":"Bonkiri",
    "gn:country_code":"SL",
    "gn:dem":15,
    "gn:feature_class":"P",
    "gn:feature_code":"PPL",
    "gn:name":"Bonkiri",
    "gn:population":0,
    "gn:timezone":"Africa/Freetown",
    "iso:country":"SL",
    "name:eng_x_preferred":[
        "Bonkiri"
    ],
    "wof:name":"Bonkiri",
    "wof:placetype":"locality"
},
  "geometry": {"coordinates":[-12.82836,8.67611],"type":"Point"}
}