{
  "type": "Feature",
  "properties": {
    "gn:admin1_code":"2.0",
    "gn:asciiname":"Yema",
    "gn:country_code":"SL",
    "gn:dem":60,
    "gn:feature_class":"P",
    "gn:feature_code":"PPL",
    "gn:name":"Yema",
    "gn:population":0,
    "gn:timezone":"Africa/Freetown",
    "iso:country":"SL",
    "name:eng_x_preferred":[
        "Yema"
    ],
    "wof:name":"Yema",
    "wof:placetype":"locality"
},
  "geometry": {"coordinates":[-12.85899,9.10906],"type":"Point"}
}