{
  "type": "Feature",
  "properties": {
    "gn:admin1_code":"2.0",
    "gn:asciiname":"Kafuta",
    "gn:country_code":"SL",
    "gn:dem":34,
    "gn:feature_class":"P",
    "gn:feature_code":"PPL",
    "gn:name":"Kafuta",
    "gn:population":0,
    "gn:timezone":"Africa/Freetown",
    "iso:country":"SL",
    "name:eng_x_preferred":[
        "Kafuta"
    ],
    "wof:name":"Kafuta",
    "wof:placetype":"locality"
},
  "geometry": {"coordinates":[-12.79439,9.29905],"type":"Point"}
}