{
  "type": "Feature",
  "properties": {
    "gn:admin1_code":"2.0",
    "gn:asciiname":"Pintekili",
    "gn:country_code":"SL",
    "gn:dem":90,
    "gn:feature_class":"P",
    "gn:feature_code":"PPL",
    "gn:name":"Pintekili",
    "gn:population":0,
    "gn:timezone":"Africa/Freetown",
    "iso:country":"SL",
    "name:eng_x_preferred":[
        "Pintekili"
    ],
    "wof:name":"Pintekili",
    "wof:placetype":"locality"
},
  "geometry": {"coordinates":[-11.84723,8.42663],"type":"Point"}
}