{
  "type": "Feature",
  "properties": {
    "gn:admin1_code":"3.0",
    "gn:asciiname":"Mano-Kpende",
    "gn:country_code":"SL",
    "gn:dem":17,
    "gn:feature_class":"P",
    "gn:feature_code":"PPL",
    "gn:name":"Mano-Kpende",
    "gn:population":0,
    "gn:timezone":"Africa/Freetown",
    "iso:country":"SL",
    "name:und_x_variant":[
        "Mano Pende",
        "Mano-Kpende"
    ],
    "wof:name":"Mano-Kpende",
    "wof:placetype":"locality"
},
  "geometry": {"coordinates":[-11.48065,6.93262],"type":"Point"}
}