{
  "type": "Feature",
  "properties": {
    "gn:admin1_code":"2.0",
    "gn:asciiname":"Makamba",
    "gn:country_code":"SL",
    "gn:dem":60,
    "gn:feature_class":"P",
    "gn:feature_code":"PPL",
    "gn:name":"Makamba",
    "gn:population":0,
    "gn:timezone":"Africa/Freetown",
    "iso:country":"SL",
    "name:eng_x_preferred":[
        "Makamba"
    ],
    "wof:name":"Makamba",
    "wof:placetype":"locality"
},
  "geometry": {"coordinates":[-12.78767,9.17416],"type":"Point"}
}