{
  "type": "Feature",
  "properties": {
    "gn:admin1_code":"2.0",
    "gn:asciiname":"Mange",
    "gn:country_code":"SL",
    "gn:dem":57,
    "gn:feature_class":"P",
    "gn:feature_code":"PPL",
    "gn:name":"Mange",
    "gn:population":0,
    "gn:timezone":"Africa/Freetown",
    "iso:country":"SL",
    "name:eng_x_preferred":[
        "Mange"
    ],
    "wof:name":"Mange",
    "wof:placetype":"locality"
},
  "geometry": {"coordinates":[-12.72627,9.11138],"type":"Point"}
}