{
  "type": "Feature",
  "properties": {
    "gn:admin1_code":"02",
    "gn:asciiname":"Tabuna Tanene",
    "gn:country_code":"SL",
    "gn:dem":96,
    "gn:feature_class":"P",
    "gn:feature_code":"PPL",
    "gn:name":"Tabuna Tanene",
    "gn:population":0,
    "gn:timezone":"Africa/Freetown",
    "iso:country":"SL",
    "name:und_x_variant":[
        "Tabuna",
        "Tabuna Tanene"
    ],
    "wof:name":"Tabuna Tanene",
    "wof:placetype":"locality"
},
  "geometry": {"coordinates":[-12.35022,9.78386],"type":"Point"}
}