{
  "type": "Feature",
  "properties": {
    "gn:admin1_code":"3.0",
    "gn:asciiname":"Kangahun",
    "gn:country_code":"SL",
    "gn:dem":72,
    "gn:feature_class":"P",
    "gn:feature_code":"PPL",
    "gn:name":"Kangahun",
    "gn:population":0,
    "gn:timezone":"Africa/Freetown",
    "iso:country":"SL",
    "name:eng_x_preferred":[
        "Kangahun"
    ],
    "wof:name":"Kangahun",
    "wof:placetype":"locality"
},
  "geometry": {"coordinates":[-12.0242,8.09348],"type":"Point"}
}