{
  "type": "Feature",
  "properties": {
    "gn:admin1_code":"03",
    "gn:asciiname":"Walihun",
    "gn:country_code":"SL",
    "gn:dem":35,
    "gn:feature_class":"P",
    "gn:feature_code":"PPL",
    "gn:name":"Walihun",
    "gn:population":0,
    "gn:timezone":"Africa/Freetown",
    "iso:country":"SL",
    "name:eng_x_preferred":[
        "Walihun"
    ],
    "wof:name":"Walihun",
    "wof:placetype":"locality"
},
  "geometry": {"coordinates":[-11.93135,7.72429],"type":"Point"}
}