{
  "type": "Feature",
  "properties": {
    "gn:admin1_code":"3.0",
    "gn:asciiname":"Sea Pot",
    "gn:country_code":"SL",
    "gn:dem":2,
    "gn:feature_class":"P",
    "gn:feature_code":"PPL",
    "gn:name":"Sea Pot",
    "gn:population":0,
    "gn:timezone":"Africa/Freetown",
    "iso:country":"SL",
    "name:eng_x_preferred":[
        "Sea Pot"
    ],
    "wof:name":"Sea Pot",
    "wof:placetype":"locality"
},
  "geometry": {"coordinates":[-12.93185,8.13664],"type":"Point"}
}