{
  "type": "Feature",
  "properties": {
    "gn:admin1_code":"3.0",
    "gn:asciiname":"Lalewahun",
    "gn:country_code":"SL",
    "gn:dem":107,
    "gn:feature_class":"P",
    "gn:feature_code":"PPL",
    "gn:name":"Lalewahun",
    "gn:population":0,
    "gn:timezone":"Africa/Freetown",
    "iso:country":"SL",
    "name:eng_x_preferred":[
        "Lalewahun"
    ],
    "wof:name":"Lalewahun",
    "wof:placetype":"locality"
},
  "geometry": {"coordinates":[-11.58163,7.82499],"type":"Point"}
}