{
  "type": "Feature",
  "properties": {
    "gn:admin1_code":"2.0",
    "gn:asciiname":"Makasi",
    "gn:country_code":"SL",
    "gn:dem":133,
    "gn:feature_class":"P",
    "gn:feature_code":"PPL",
    "gn:name":"Makasi",
    "gn:population":0,
    "gn:timezone":"Africa/Freetown",
    "iso:country":"SL",
    "name:eng_x_preferred":[
        "Makasi"
    ],
    "wof:name":"Makasi",
    "wof:placetype":"locality"
},
  "geometry": {"coordinates":[-12.15578,9.26248],"type":"Point"}
}