{
  "type": "Feature",
  "properties": {
    "gn:admin1_code":"3.0",
    "gn:asciiname":"Jeoma",
    "gn:country_code":"SL",
    "gn:dem":22,
    "gn:feature_class":"P",
    "gn:feature_code":"PPL",
    "gn:name":"Jeoma",
    "gn:population":0,
    "gn:timezone":"Africa/Freetown",
    "iso:country":"SL",
    "name:eng_x_preferred":[
        "Jeoma"
    ],
    "wof:name":"Jeoma",
    "wof:placetype":"locality"
},
  "geometry": {"coordinates":[-12.28043,7.4644],"type":"Point"}
}