{
  "type": "Feature",
  "properties": {
    "gn:admin1_code":"02",
    "gn:asciiname":"Yamankoro",
    "gn:country_code":"SL",
    "gn:dem":450,
    "gn:feature_class":"P",
    "gn:feature_code":"PPL",
    "gn:name":"Yamankoro",
    "gn:population":0,
    "gn:timezone":"Africa/Freetown",
    "iso:country":"SL",
    "name:und_x_variant":[
        "Yomankoro"
    ],
    "wof:name":"Yamankoro",
    "wof:placetype":"locality"
},
  "geometry": {"coordinates":[-10.88952,8.98222],"type":"Point"}
}