{
  "type": "Feature",
  "properties": {
    "gn:admin1_code":"1.0",
    "gn:asciiname":"Kamengodu",
    "gn:country_code":"SL",
    "gn:dem":380,
    "gn:feature_class":"P",
    "gn:feature_code":"PPL",
    "gn:name":"Kamengodu",
    "gn:population":0,
    "gn:timezone":"Africa/Freetown",
    "iso:country":"SL",
    "name:eng_x_preferred":[
        "Kamengodu"
    ],
    "wof:name":"Kamengodu",
    "wof:placetype":"locality"
},
  "geometry": {"coordinates":[-11.16349,8.86115],"type":"Point"}
}