{
  "type": "Feature",
  "properties": {
    "gn:admin1_code":"3.0",
    "gn:asciiname":"Gombu",
    "gn:country_code":"SL",
    "gn:dem":138,
    "gn:feature_class":"P",
    "gn:feature_code":"PPL",
    "gn:name":"Gombu",
    "gn:population":0,
    "gn:timezone":"Africa/Freetown",
    "iso:country":"SL",
    "name:eng_x_preferred":[
        "Gombu"
    ],
    "wof:name":"Gombu",
    "wof:placetype":"locality"
},
  "geometry": {"coordinates":[-11.38232,7.59252],"type":"Point"}
}