{
  "type": "Feature",
  "properties": {
    "gn:admin1_code":"3.0",
    "gn:asciiname":"Bobobu",
    "gn:country_code":"SL",
    "gn:dem":25,
    "gn:feature_class":"P",
    "gn:feature_code":"PPL",
    "gn:name":"Bobobu",
    "gn:population":0,
    "gn:timezone":"Africa/Freetown",
    "iso:country":"SL",
    "name:eng_x_preferred":[
        "Bobobu"
    ],
    "wof:name":"Bobobu",
    "wof:placetype":"locality"
},
  "geometry": {"coordinates":[-11.78814,7.19761],"type":"Point"}
}