{
  "type": "Feature",
  "properties": {
    "gn:admin1_code":"2.0",
    "gn:asciiname":"Makonte",
    "gn:country_code":"SL",
    "gn:dem":110,
    "gn:feature_class":"P",
    "gn:feature_code":"PPL",
    "gn:name":"Makonte",
    "gn:population":0,
    "gn:timezone":"Africa/Freetown",
    "iso:country":"SL",
    "name:eng_x_preferred":[
        "Makonte"
    ],
    "wof:name":"Makonte",
    "wof:placetype":"locality"
},
  "geometry": {"coordinates":[-11.87089,8.54074],"type":"Point"}
}