{
  "type": "Feature",
  "properties": {
    "gn:admin1_code":"1.0",
    "gn:asciiname":"Langrama",
    "gn:country_code":"SL",
    "gn:dem":252,
    "gn:feature_class":"P",
    "gn:feature_code":"PPL",
    "gn:name":"Langrama",
    "gn:population":0,
    "gn:timezone":"Africa/Freetown",
    "iso:country":"SL",
    "name:eng_x_preferred":[
        "Langrama"
    ],
    "wof:name":"Langrama",
    "wof:placetype":"locality"
},
  "geometry": {"coordinates":[-11.26665,8.38394],"type":"Point"}
}