{
  "type": "Feature",
  "properties": {
    "gn:admin1_code":"2.0",
    "gn:asciiname":"Fodalaminain",
    "gn:country_code":"SL",
    "gn:dem":412,
    "gn:feature_class":"P",
    "gn:feature_code":"PPL",
    "gn:name":"Fodalaminain",
    "gn:population":0,
    "gn:timezone":"Africa/Freetown",
    "iso:country":"SL",
    "name:eng_x_preferred":[
        "Fodalaminain"
    ],
    "wof:name":"Fodalaminain",
    "wof:placetype":"locality"
},
  "geometry": {"coordinates":[-11.60499,9.49343],"type":"Point"}
}